# Comparing `tmp/baopig-0.20.3-py3-none-any.whl.zip` & `tmp/baopig-0.20.4-py3-none-any.whl.zip`

## zipinfo {}

```diff
@@ -1,8 +1,8 @@
-Zip file size: 2847068 bytes, number of entries: 315
+Zip file size: 2848249 bytes, number of entries: 315
 -rw-rw-rw-  2.0 fat      608 b- defN 23-Apr-22 11:51 baopig/__init__.py
 -rw-rw-rw-  2.0 fat     3643 b- defN 22-Jul-12 21:25 baopig/communicative.py
 -rw-rw-rw-  2.0 fat    16525 b- defN 22-Jul-19 15:24 baopig/documentation.py
 -rw-rw-rw-  2.0 fat      548 b- defN 23-Feb-20 13:20 baopig/lines_counter.py
 -rw-rw-rw-  2.0 fat      831 b- defN 22-Jul-12 21:41 baopig/__pycache__/__init__.cpython-310.pyc
 -rw-rw-rw-  2.0 fat     1151 b- defN 23-Apr-22 12:24 baopig/__pycache__/__init__.cpython-311.pyc
 -rw-rw-rw-  2.0 fat      866 b- defN 22-Jun-10 11:59 baopig/__pycache__/__init__.cpython-37.pyc
@@ -62,15 +62,15 @@
 -rw-rw-rw-  2.0 fat      682 b- defN 23-Jan-10 21:21 baopig/googletrans/__pycache__/__init__.cpython-310.pyc
 -rw-rw-rw-  2.0 fat      822 b- defN 23-Apr-14 15:58 baopig/googletrans/__pycache__/__init__.cpython-311.pyc
 -rw-rw-rw-  2.0 fat     9616 b- defN 22-Dec-16 22:54 baopig/googletrans/__pycache__/client.cpython-310.pyc
 -rw-rw-rw-  2.0 fat    13590 b- defN 23-Apr-14 15:58 baopig/googletrans/__pycache__/client.cpython-311.pyc
 -rw-rw-rw-  2.0 fat    10152 b- defN 22-Dec-16 23:02 baopig/googletrans/__pycache__/constants.cpython-310.pyc
 -rw-rw-rw-  2.0 fat    12680 b- defN 23-Apr-14 15:58 baopig/googletrans/__pycache__/constants.cpython-311.pyc
 -rw-rw-rw-  2.0 fat     6220 b- defN 23-Jan-10 21:25 baopig/googletrans/__pycache__/extension.cpython-310.pyc
--rw-rw-rw-  2.0 fat    12787 b- defN 23-Apr-22 13:22 baopig/googletrans/__pycache__/extension.cpython-311.pyc
+-rw-rw-rw-  2.0 fat    12727 b- defN 23-Apr-22 14:10 baopig/googletrans/__pycache__/extension.cpython-311.pyc
 -rw-rw-rw-  2.0 fat     5423 b- defN 22-Dec-15 17:45 baopig/googletrans/__pycache__/gtoken.cpython-310.pyc
 -rw-rw-rw-  2.0 fat     9846 b- defN 23-Apr-14 15:58 baopig/googletrans/__pycache__/gtoken.cpython-311.pyc
 -rw-rw-rw-  2.0 fat     2490 b- defN 22-Dec-15 17:45 baopig/googletrans/__pycache__/models.cpython-310.pyc
 -rw-rw-rw-  2.0 fat     3533 b- defN 23-Apr-14 15:58 baopig/googletrans/__pycache__/models.cpython-311.pyc
 -rw-rw-rw-  2.0 fat     3130 b- defN 23-Jan-10 21:21 baopig/googletrans/__pycache__/translatable.cpython-310.pyc
 -rw-rw-rw-  2.0 fat     5117 b- defN 23-Apr-14 15:58 baopig/googletrans/__pycache__/translatable.cpython-311.pyc
 -rw-rw-rw-  2.0 fat      321 b- defN 22-Dec-15 17:44 baopig/googletrans/__pycache__/urls.cpython-310.pyc
@@ -89,31 +89,31 @@
 -rw-rw-rw-  2.0 fat     7189 b- defN 22-Jun-10 11:59 baopig/io/__pycache__/keyboard.cpython-37.pyc
 -rw-rw-rw-  2.0 fat     3416 b- defN 22-Jul-21 12:50 baopig/io/__pycache__/logging.cpython-310.pyc
 -rw-rw-rw-  2.0 fat     6314 b- defN 23-Apr-14 15:58 baopig/io/__pycache__/logging.cpython-311.pyc
 -rw-rw-rw-  2.0 fat     3376 b- defN 22-Jun-10 11:59 baopig/io/__pycache__/logging.cpython-37.pyc
 -rw-rw-rw-  2.0 fat     7956 b- defN 22-Dec-18 21:13 baopig/io/__pycache__/mouse.cpython-310.pyc
 -rw-rw-rw-  2.0 fat    15307 b- defN 23-Apr-14 15:58 baopig/io/__pycache__/mouse.cpython-311.pyc
 -rw-rw-rw-  2.0 fat     9450 b- defN 22-Jun-10 11:59 baopig/io/__pycache__/mouse.cpython-37.pyc
--rw-rw-rw-  2.0 fat      617 b- defN 22-Jul-20 10:26 baopig/lib/__init__.py
+-rw-rw-rw-  2.0 fat      596 b- defN 23-Apr-22 14:12 baopig/lib/__init__.py
 -rw-rw-rw-  2.0 fat    14075 b- defN 22-Dec-04 18:48 baopig/lib/application.py
 -rw-rw-rw-  2.0 fat    16468 b- defN 23-Apr-21 14:28 baopig/lib/container.py
 -rw-rw-rw-  2.0 fat    18715 b- defN 22-Jul-21 19:32 baopig/lib/gridlayer.py
 -rw-rw-rw-  2.0 fat     2502 b- defN 22-Dec-13 12:20 baopig/lib/imagewidget.py
 -rw-rw-rw-  2.0 fat    10338 b- defN 22-Dec-13 12:16 baopig/lib/layer.py
 -rw-rw-rw-  2.0 fat     4172 b- defN 22-Jul-21 12:50 baopig/lib/layersmanager.py
 -rw-rw-rw-  2.0 fat     7037 b- defN 23-Jan-12 01:33 baopig/lib/scene.py
 -rw-rw-rw-  2.0 fat    10889 b- defN 22-Jul-21 19:31 baopig/lib/selections.py
 -rw-rw-rw-  2.0 fat     7360 b- defN 22-Dec-13 12:28 baopig/lib/shapes.py
 -rw-rw-rw-  2.0 fat    16552 b- defN 22-Jul-21 13:29 baopig/lib/style.py
 -rw-rw-rw-  2.0 fat     4162 b- defN 22-Jul-21 13:07 baopig/lib/utilities.py
 -rw-rw-rw-  2.0 fat    37125 b- defN 23-Jan-10 21:12 baopig/lib/widget.py
--rw-rw-rw-  2.0 fat     8555 b- defN 23-Jan-12 01:33 baopig/lib/widget_supers.py
+-rw-rw-rw-  2.0 fat     9919 b- defN 23-Apr-22 14:10 baopig/lib/widget_supers.py
 -rw-rw-rw-  2.0 fat     3300 b- defN 22-Jul-17 19:47 baopig/lib/zone.py
 -rw-rw-rw-  2.0 fat     1022 b- defN 22-Jul-20 10:26 baopig/lib/__pycache__/__init__.cpython-310.pyc
--rw-rw-rw-  2.0 fat     1378 b- defN 23-Apr-14 15:58 baopig/lib/__pycache__/__init__.cpython-311.pyc
+-rw-rw-rw-  2.0 fat     1418 b- defN 23-Apr-22 14:11 baopig/lib/__pycache__/__init__.cpython-311.pyc
 -rw-rw-rw-  2.0 fat      996 b- defN 22-Jun-10 11:59 baopig/lib/__pycache__/__init__.cpython-37.pyc
 -rw-rw-rw-  2.0 fat    10025 b- defN 22-Dec-04 18:48 baopig/lib/__pycache__/application.cpython-310.pyc
 -rw-rw-rw-  2.0 fat    19363 b- defN 23-Apr-14 15:58 baopig/lib/__pycache__/application.cpython-311.pyc
 -rw-rw-rw-  2.0 fat    11173 b- defN 22-Jun-10 11:59 baopig/lib/__pycache__/application.cpython-37.pyc
 -rw-rw-rw-  2.0 fat    13868 b- defN 22-Dec-18 23:01 baopig/lib/__pycache__/container.cpython-310.pyc
 -rw-rw-rw-  2.0 fat    25435 b- defN 23-Apr-21 15:33 baopig/lib/__pycache__/container.cpython-311.pyc
 -rw-rw-rw-  2.0 fat    17854 b- defN 22-Jun-10 11:59 baopig/lib/__pycache__/container.cpython-37.pyc
@@ -143,15 +143,15 @@
 -rw-rw-rw-  2.0 fat     5742 b- defN 22-Jul-21 13:09 baopig/lib/__pycache__/utilities.cpython-310.pyc
 -rw-rw-rw-  2.0 fat     9424 b- defN 23-Apr-14 15:58 baopig/lib/__pycache__/utilities.cpython-311.pyc
 -rw-rw-rw-  2.0 fat    16139 b- defN 22-Jun-10 11:59 baopig/lib/__pycache__/utilities.cpython-37.pyc
 -rw-rw-rw-  2.0 fat    30683 b- defN 23-Jan-10 21:12 baopig/lib/__pycache__/widget.cpython-310.pyc
 -rw-rw-rw-  2.0 fat    57092 b- defN 23-Apr-14 15:58 baopig/lib/__pycache__/widget.cpython-311.pyc
 -rw-rw-rw-  2.0 fat    36355 b- defN 22-Jun-10 11:59 baopig/lib/__pycache__/widget.cpython-37.pyc
 -rw-rw-rw-  2.0 fat     8647 b- defN 23-Jan-12 01:33 baopig/lib/__pycache__/widget_supers.cpython-310.pyc
--rw-rw-rw-  2.0 fat    13539 b- defN 23-Apr-14 15:58 baopig/lib/__pycache__/widget_supers.cpython-311.pyc
+-rw-rw-rw-  2.0 fat    16061 b- defN 23-Apr-22 14:10 baopig/lib/__pycache__/widget_supers.cpython-311.pyc
 -rw-rw-rw-  2.0 fat     3094 b- defN 22-Jul-17 19:50 baopig/lib/__pycache__/zone.cpython-310.pyc
 -rw-rw-rw-  2.0 fat     6355 b- defN 23-Apr-14 15:58 baopig/lib/__pycache__/zone.cpython-311.pyc
 -rw-rw-rw-  2.0 fat     3722 b- defN 22-Jun-10 11:59 baopig/lib/__pycache__/zone.cpython-37.pyc
 -rw-rw-rw-  2.0 fat     7489 b- defN 22-Jul-21 19:31 baopig/prefabs/colorchooserdialog.py
 -rw-rw-rw-  2.0 fat     5248 b- defN 22-Jul-21 12:53 baopig/prefabs/debugzone.py
 -rw-rw-rw-  2.0 fat     2177 b- defN 22-Dec-19 01:28 baopig/prefabs/presentationscene.py
 -rw-rw-rw-  2.0 fat     4847 b- defN 22-Dec-15 23:15 baopig/prefabs/testerscene.py
@@ -251,17 +251,17 @@
 -rw-rw-rw-  2.0 fat    13507 b- defN 23-Apr-22 11:43 baopig/unit_tests/__pycache__/ut_sleep.cpython-311.pyc
 -rw-rw-rw-  2.0 fat     3621 b- defN 22-Jul-21 20:14 baopig/unit_tests/__pycache__/ut_text.cpython-310.pyc
 -rw-rw-rw-  2.0 fat     6753 b- defN 23-Apr-22 11:43 baopig/unit_tests/__pycache__/ut_text.cpython-311.pyc
 -rw-rw-rw-  2.0 fat     1830 b- defN 22-Jul-21 20:14 baopig/unit_tests/__pycache__/ut_textedit.cpython-310.pyc
 -rw-rw-rw-  2.0 fat     3446 b- defN 23-Apr-22 11:43 baopig/unit_tests/__pycache__/ut_textedit.cpython-311.pyc
 -rw-rw-rw-  2.0 fat     2043 b- defN 22-Jul-21 19:40 baopig/unit_tests/__pycache__/ut_theme.cpython-310.pyc
 -rw-rw-rw-  2.0 fat     3466 b- defN 23-Apr-22 11:43 baopig/unit_tests/__pycache__/ut_theme.cpython-311.pyc
--rw-rw-rw-  2.0 fat      931 b- defN 23-Apr-22 13:23 baopig/version/version.py
+-rw-rw-rw-  2.0 fat      931 b- defN 23-Apr-22 14:15 baopig/version/version.py
 -rw-rw-rw-  2.0 fat     1692 b- defN 22-Dec-18 21:38 baopig/version/__pycache__/version.cpython-310.pyc
--rw-rw-rw-  2.0 fat     2611 b- defN 23-Apr-22 13:24 baopig/version/__pycache__/version.cpython-311.pyc
+-rw-rw-rw-  2.0 fat     2611 b- defN 23-Apr-22 14:17 baopig/version/__pycache__/version.cpython-311.pyc
 -rw-rw-rw-  2.0 fat     1642 b- defN 22-Jun-10 11:59 baopig/version/__pycache__/version.cpython-37.pyc
 -rw-rw-rw-  2.0 fat      767 b- defN 23-Jan-10 20:24 baopig/widgets/__init__.py
 -rw-rw-rw-  2.0 fat     8232 b- defN 23-Jan-10 19:59 baopig/widgets/button.py
 -rw-rw-rw-  2.0 fat     3102 b- defN 22-Jul-21 19:32 baopig/widgets/checkbox.py
 -rw-rw-rw-  2.0 fat     5246 b- defN 22-Jul-21 19:32 baopig/widgets/dialog.py
 -rw-rw-rw-  2.0 fat     1609 b- defN 22-Jul-20 17:43 baopig/widgets/entry.py
 -rw-rw-rw-  2.0 fat     3607 b- defN 23-Jan-10 20:40 baopig/widgets/indicator.py
@@ -305,13 +305,13 @@
 -rw-rw-rw-  2.0 fat     8011 b- defN 22-Jun-10 11:59 baopig/widgets/__pycache__/slider.cpython-37.pyc
 -rw-rw-rw-  2.0 fat    24379 b- defN 22-Jul-21 20:14 baopig/widgets/__pycache__/text.cpython-310.pyc
 -rw-rw-rw-  2.0 fat    43877 b- defN 23-Apr-14 15:58 baopig/widgets/__pycache__/text.cpython-311.pyc
 -rw-rw-rw-  2.0 fat    27867 b- defN 22-Jun-10 11:59 baopig/widgets/__pycache__/text.cpython-37.pyc
 -rw-rw-rw-  2.0 fat    14346 b- defN 22-Jul-21 20:14 baopig/widgets/__pycache__/textedit.cpython-310.pyc
 -rw-rw-rw-  2.0 fat    32458 b- defN 23-Apr-14 15:58 baopig/widgets/__pycache__/textedit.cpython-311.pyc
 -rw-rw-rw-  2.0 fat    13078 b- defN 22-Jun-10 11:59 baopig/widgets/__pycache__/textedit.cpython-37.pyc
--rw-rw-rw-  2.0 fat     1088 b- defN 23-Apr-22 13:24 baopig-0.20.3.dist-info/LICENSE
--rw-rw-rw-  2.0 fat      866 b- defN 23-Apr-22 13:24 baopig-0.20.3.dist-info/METADATA
--rw-rw-rw-  2.0 fat       92 b- defN 23-Apr-22 13:24 baopig-0.20.3.dist-info/WHEEL
--rw-rw-rw-  2.0 fat        7 b- defN 23-Apr-22 13:24 baopig-0.20.3.dist-info/top_level.txt
--rw-rw-r--  2.0 fat    32575 b- defN 23-Apr-22 13:24 baopig-0.20.3.dist-info/RECORD
-315 files, 5114767 bytes uncompressed, 2793890 bytes compressed:  45.4%
+-rw-rw-rw-  2.0 fat     1088 b- defN 23-Apr-22 14:17 baopig-0.20.4.dist-info/LICENSE
+-rw-rw-rw-  2.0 fat      866 b- defN 23-Apr-22 14:17 baopig-0.20.4.dist-info/METADATA
+-rw-rw-rw-  2.0 fat       92 b- defN 23-Apr-22 14:17 baopig-0.20.4.dist-info/WHEEL
+-rw-rw-rw-  2.0 fat        7 b- defN 23-Apr-22 14:17 baopig-0.20.4.dist-info/top_level.txt
+-rw-rw-r--  2.0 fat    32575 b- defN 23-Apr-22 14:17 baopig-0.20.4.dist-info/RECORD
+315 files, 5118612 bytes uncompressed, 2795071 bytes compressed:  45.4%
```

## zipnote {}

```diff
@@ -924,23 +924,23 @@
 
 Filename: baopig/widgets/__pycache__/textedit.cpython-311.pyc
 Comment: 
 
 Filename: baopig/widgets/__pycache__/textedit.cpython-37.pyc
 Comment: 
 
-Filename: baopig-0.20.3.dist-info/LICENSE
+Filename: baopig-0.20.4.dist-info/LICENSE
 Comment: 
 
-Filename: baopig-0.20.3.dist-info/METADATA
+Filename: baopig-0.20.4.dist-info/METADATA
 Comment: 
 
-Filename: baopig-0.20.3.dist-info/WHEEL
+Filename: baopig-0.20.4.dist-info/WHEEL
 Comment: 
 
-Filename: baopig-0.20.3.dist-info/top_level.txt
+Filename: baopig-0.20.4.dist-info/top_level.txt
 Comment: 
 
-Filename: baopig-0.20.3.dist-info/RECORD
+Filename: baopig-0.20.4.dist-info/RECORD
 Comment: 
 
 Zip file comment:
```

## baopig/googletrans/__pycache__/extension.cpython-311.pyc

### Python bytecode

```diff
@@ -1,10 +1,10 @@
 magic:    0xa70d0d0a
-moddate:  0x90df4364 (Sat Apr 22 13:22:24 2023 UTC)
-files sz: 6811
+moddate:  0xcedf4364 (Sat Apr 22 13:23:26 2023 UTC)
+files sz: 6781
 code
    argcount  : 0
    nlocals   : 0
    stacksize : 5
    flags     : 0
    code
       0x9700640064016c005a00640064016c015a01640064016c025a02640064
@@ -56,45 +56,45 @@
                 64 MAKE_FUNCTION            0
                 66 LOAD_CONST               6 ('Dictionnary')
                 68 LOAD_NAME                9 (dict)
                 70 PRECALL                  3
                 74 CALL                     3
                 84 STORE_NAME              10 (Dictionnary)
    
-    75          86 PUSH_NULL
+    74          86 PUSH_NULL
                 88 LOAD_BUILD_CLASS
-                90 LOAD_CONST               7 (<code object LangManager, file "C:\Users\symrb\Documents\dev\python\baopig\baopig\googletrans\extension.py", line 75>)
+                90 LOAD_CONST               7 (<code object LangManager, file "C:\Users\symrb\Documents\dev\python\baopig\baopig\googletrans\extension.py", line 74>)
                 92 MAKE_FUNCTION            0
                 94 LOAD_CONST               8 ('LangManager')
                 96 LOAD_NAME                6 (bp)
                 98 LOAD_ATTR               11 (Communicative)
                108 PRECALL                  3
                112 CALL                     3
                122 STORE_NAME              12 (LangManager)
    
-   164         124 PUSH_NULL
+   163         124 PUSH_NULL
                126 LOAD_BUILD_CLASS
-               128 LOAD_CONST               9 (<code object OptimizedTranslator, file "C:\Users\symrb\Documents\dev\python\baopig\baopig\googletrans\extension.py", line 164>)
+               128 LOAD_CONST               9 (<code object OptimizedTranslator, file "C:\Users\symrb\Documents\dev\python\baopig\baopig\googletrans\extension.py", line 163>)
                130 MAKE_FUNCTION            0
                132 LOAD_CONST              10 ('OptimizedTranslator')
                134 LOAD_NAME                8 (Translator)
                136 PRECALL                  3
                140 CALL                     3
                150 STORE_NAME              13 (OptimizedTranslator)
    
-   211         152 BUILD_MAP                0
+   210         152 BUILD_MAP                0
                154 STORE_NAME              14 (dicts)
    
-   212         156 PUSH_NULL
+   211         156 PUSH_NULL
                158 LOAD_NAME               12 (LangManager)
                160 PRECALL                  0
                164 CALL                     0
                174 STORE_NAME              15 (lang_manager)
    
-   213         176 PUSH_NULL
+   212         176 PUSH_NULL
                178 LOAD_NAME               13 (OptimizedTranslator)
                180 PRECALL                  0
                184 CALL                     0
                194 STORE_NAME              16 (translator)
                196 LOAD_CONST               1 (None)
                198 RETURN_VALUE
    consts
@@ -115,15 +115,15 @@
                        6 LOAD_CONST               0 ('Dictionnary')
                        8 STORE_NAME               2 (__qualname__)
          
           11          10 LOAD_CONST               1 (<code object __init__, file "C:\Users\symrb\Documents\dev\python\baopig\baopig\googletrans\extension.py", line 11>)
                       12 MAKE_FUNCTION            0
                       14 STORE_NAME               3 (__init__)
          
-          58          16 LOAD_CONST               2 (<code object save, file "C:\Users\symrb\Documents\dev\python\baopig\baopig\googletrans\extension.py", line 58>)
+          57          16 LOAD_CONST               2 (<code object save, file "C:\Users\symrb\Documents\dev\python\baopig\baopig\googletrans\extension.py", line 57>)
                       18 MAKE_FUNCTION            0
                       20 STORE_NAME               4 (save)
                       22 LOAD_CONST               3 (None)
                       24 RETURN_VALUE
          consts
             'Dictionnary'
             code
@@ -140,50 +140,49 @@
                   00000000007408000000000000000000006a050000000000000000a00700
                   000000000000000000000000000000000000007408000000000000000000
                   006a050000000000000000a0080000000000000000000000000000000000
                   0000007412000000000000000000006a0a00000000000000006401190000
                   00000000000000a6010000ab010000000000000000a6010000ab01000000
                   00000000009b007408000000000000000000006a0b00000000000000009b
                   0064027408000000000000000000006a0b00000000000000009b0064037c
-                  019b0064049d07a6010000ab01000000000000000072ca640164006c0c7d
+                  019b0064049d07a6010000ab01000000000000000072bb640164006c0c7d
                   027c026a0d0000000000000000a00e000000000000000000000000000000
                   0000000000a6000000ab0000000000000000009b00740800000000000000
                   0000006a0b00000000000000009b0064027408000000000000000000006a
                   0b00000000000000009b0064037c019b0064049d077d0364037c019b009d
                   027d04741e000000000000000000006a100000000000000000a011000000
                   00000000000000000000000000000000007c047c03a6020000ab02000000
                   00000000007d05741e000000000000000000006a100000000000000000a0
                   1200000000000000000000000000000000000000007c05a6010000ab0100
                   000000000000007d067c056a130000000000000000a01400000000000000
                   000000000000000000000000007c06a6010000ab01000000000000000001
-                  00742b000000000000000000006405a6010000ab01000000000000000001
-                  00742d000000000000000000007c066a170000000000000000a6010000ab
+                  00742b000000000000000000007c066a160000000000000000a6010000ab
                   01000000000000000044005d0a5c0200007d077d087c087c007c073c0000
-                  008c0b640053007c006a0200000000000000007430000000000000000000
-                  006a1900000000000000006b0200000000720f7435000000000000000000
-                  006406a6010000ab01000000000000000082017430000000000000000000
-                  006a1b0000000000000000730f7439000000000000000000006407a60100
-                  00ab01000000000000000082010900640164006c1d7d097c09a01d000000
+                  008c0b640053007c006a020000000000000000742e000000000000000000
+                  006a1800000000000000006b0200000000720f7433000000000000000000
+                  006405a6010000ab0100000000000000008201742e000000000000000000
+                  006a1a0000000000000000730f7437000000000000000000006406a60100
+                  00ab01000000000000000082010900640164006c1c7d097c09a01c000000
                   0000000000000000000000000000000000a6000000ab0000000000000000
-                  007d0a743c00000000000000000000a01f00000000000000000000000000
-                  000000000000007441000000000000000000007406000000000000000000
-                  007430000000000000000000006a19000000000000000019000000000000
-                  000000a0210000000000000000000000000000000000000000a6000000ab
-                  000000000000000000a6010000ab01000000000000000074300000000000
-                  00000000006a1900000000000000007c01ac08a6030000ab030000000000
-                  0000007d0b7c09a01d0000000000000000000000000000000000000000a6
-                  000000ab0000000000000000007d0c7444000000000000000000006a2300
-                  00000000000000a024000000000000000000000000000000000000000064
-                  097c0c7c0a7a0a00009b009d02a6010000ab01000000000000000001006e
-                  332300744a00000000000000000000240072267d0d744400000000000000
-                  0000006a230000000000000000a026000000000000000000000000000000
+                  007d0a743a00000000000000000000a01e00000000000000000000000000
+                  00000000000000743f000000000000000000007406000000000000000000
+                  00742e000000000000000000006a18000000000000000019000000000000
+                  000000a0200000000000000000000000000000000000000000a6000000ab
+                  000000000000000000a6010000ab010000000000000000742e0000000000
+                  00000000006a1800000000000000007c01ac07a6030000ab030000000000
+                  0000007d0b7c09a01c0000000000000000000000000000000000000000a6
+                  000000ab0000000000000000007d0c7442000000000000000000006a2200
+                  00000000000000a023000000000000000000000000000000000000000064
+                  087c0c7c0a7a0a00009b009d02a6010000ab01000000000000000001006e
+                  332300744800000000000000000000240072267d0d744200000000000000
+                  0000006a220000000000000000a025000000000000000000000000000000
                   00000000007c0da6010000ab01000000000000000001007c0d820164007d
-                  0d7e0d77017700780359007701744f000000000000000000007406000000
-                  000000000000007430000000000000000000006a19000000000000000019
-                  000000000000000000a02800000000000000000000000000000000000000
+                  0d7e0d77017700780359007701744d000000000000000000007406000000
+                  00000000000000742e000000000000000000006a18000000000000000019
+                  000000000000000000a02700000000000000000000000000000000000000
                   00a6000000ab0000000000000000007c0ba6020000ab0200000000000000
                   0044005d0a5c0200007d077d0e7c0e7c007c073c0000008c0b64005300
                 11           0 RESUME                   0
                
                 13           2 LOAD_GLOBAL              0 (dict)
                             14 LOAD_METHOD              1 (__init__)
                             36 LOAD_FAST                0 (self)
@@ -235,15 +234,15 @@
                            356 LOAD_CONST               3 ('dict_')
                            358 LOAD_FAST                1 (lang_id)
                            360 FORMAT_VALUE             0
                            362 LOAD_CONST               4 ('.py')
                            364 BUILD_STRING             7
                            366 PRECALL                  1
                            370 CALL                     1
-                           380 POP_JUMP_FORWARD_IF_FALSE   202 (to 786)
+                           380 POP_JUMP_FORWARD_IF_FALSE   187 (to 756)
                
                 22         382 LOAD_CONST               1 (0)
                            384 LOAD_CONST               0 (None)
                            386 IMPORT_NAME             12 (pathlib)
                            388 STORE_FAST               2 (pathlib)
                
                 23         390 LOAD_FAST                2 (pathlib)
@@ -293,196 +292,189 @@
                            640 LOAD_ATTR               19 (loader)
                            650 LOAD_METHOD             20 (exec_module)
                            672 LOAD_FAST                6 (module)
                            674 PRECALL                  1
                            678 CALL                     1
                            688 POP_TOP
                
-                28         690 LOAD_GLOBAL             43 (NULL + print)
-                           702 LOAD_CONST               5 ('zfdegeb')
-                           704 PRECALL                  1
-                           708 CALL                     1
-                           718 POP_TOP
-               
-                30         720 LOAD_GLOBAL             45 (NULL + enumerate)
-                           732 LOAD_FAST                6 (module)
-                           734 LOAD_ATTR               23 (texts)
-                           744 PRECALL                  1
-                           748 CALL                     1
-                           758 GET_ITER
-                       >>  760 FOR_ITER                10 (to 782)
-                           762 UNPACK_SEQUENCE          2
-                           766 STORE_FAST               7 (text_id)
-                           768 STORE_FAST               8 (text)
-               
-                31         770 LOAD_FAST                8 (text)
-                           772 LOAD_FAST                0 (self)
-                           774 LOAD_FAST                7 (text_id)
-                           776 STORE_SUBSCR
-                           780 JUMP_BACKWARD           11 (to 760)
-               
-                30     >>  782 LOAD_CONST               0 (None)
-                           784 RETURN_VALUE
-               
-                34     >>  786 LOAD_FAST                0 (self)
-                           788 LOAD_ATTR                2 (lang_id)
-                           798 LOAD_GLOBAL             48 (lang_manager)
-                           810 LOAD_ATTR               25 (ref_language)
-                           820 COMPARE_OP               2 (==)
-                           826 POP_JUMP_FORWARD_IF_FALSE    15 (to 858)
-               
-                35         828 LOAD_GLOBAL             53 (NULL + FileNotFoundError)
-                           840 LOAD_CONST               6 ('The dictionnary for the ref language has not been found')
-                           842 PRECALL                  1
-                           846 CALL                     1
-                           856 RAISE_VARARGS            1
-               
-                37     >>  858 LOAD_GLOBAL             48 (lang_manager)
-                           870 LOAD_ATTR               27 (is_connected_to_network)
-                           880 POP_JUMP_FORWARD_IF_TRUE    15 (to 912)
-               
-                38         882 LOAD_GLOBAL             57 (NULL + ConnectionError)
-                           894 LOAD_CONST               7 ('Translation impossible : baopig.googletrans.lang_manager is not connected to internet')
-                           896 PRECALL                  1
-                           900 CALL                     1
-                           910 RAISE_VARARGS            1
-               
-                41     >>  912 NOP
-               
-                42         914 LOAD_CONST               1 (0)
-                           916 LOAD_CONST               0 (None)
-                           918 IMPORT_NAME             29 (time)
-                           920 STORE_FAST               9 (time)
-               
-                43         922 LOAD_FAST                9 (time)
-                           924 LOAD_METHOD             29 (time)
-                           946 PRECALL                  0
-                           950 CALL                     0
-                           960 STORE_FAST              10 (start_time)
-               
-                45         962 LOAD_GLOBAL             60 (translator)
-                           974 LOAD_METHOD             31 (optimized_translate)
-                           996 LOAD_GLOBAL             65 (NULL + list)
-                          1008 LOAD_GLOBAL              6 (dicts)
-                          1020 LOAD_GLOBAL             48 (lang_manager)
-                          1032 LOAD_ATTR               25 (ref_language)
-                          1042 BINARY_SUBSCR
-                          1052 LOAD_METHOD             33 (values)
-                          1074 PRECALL                  0
-                          1078 CALL                     0
-                          1088 PRECALL                  1
-                          1092 CALL                     1
-               
-                46        1102 LOAD_GLOBAL             48 (lang_manager)
-                          1114 LOAD_ATTR               25 (ref_language)
-                          1124 LOAD_FAST                1 (lang_id)
-               
-                45        1126 KW_NAMES                 8
-                          1128 PRECALL                  3
-                          1132 CALL                     3
-                          1142 STORE_FAST              11 (translations)
-               
-                48        1144 LOAD_FAST                9 (time)
-                          1146 LOAD_METHOD             29 (time)
-                          1168 PRECALL                  0
-                          1172 CALL                     0
-                          1182 STORE_FAST              12 (end_time)
-               
-                49        1184 LOAD_GLOBAL             68 (bp)
-                          1196 LOAD_ATTR               35 (LOGGER)
-                          1206 LOAD_METHOD             36 (fine)
-                          1228 LOAD_CONST               9 ('Language loading time : ')
-                          1230 LOAD_FAST               12 (end_time)
-                          1232 LOAD_FAST               10 (start_time)
-                          1234 BINARY_OP               10 (-)
-                          1238 FORMAT_VALUE             0
-                          1240 BUILD_STRING             2
-                          1242 PRECALL                  1
-                          1246 CALL                     1
-                          1256 POP_TOP
-                          1258 JUMP_FORWARD            51 (to 1362)
-                       >> 1260 PUSH_EXC_INFO
-               
-                51        1262 LOAD_GLOBAL             74 (Exception)
-                          1274 CHECK_EXC_MATCH
-                          1276 POP_JUMP_FORWARD_IF_FALSE    38 (to 1354)
-                          1278 STORE_FAST              13 (e)
-               
-                52        1280 LOAD_GLOBAL             68 (bp)
-                          1292 LOAD_ATTR               35 (LOGGER)
-                          1302 LOAD_METHOD             38 (warning)
-                          1324 LOAD_FAST               13 (e)
-                          1326 PRECALL                  1
-                          1330 CALL                     1
-                          1340 POP_TOP
-               
-                53        1342 LOAD_FAST               13 (e)
-                          1344 RAISE_VARARGS            1
-                       >> 1346 LOAD_CONST               0 (None)
-                          1348 STORE_FAST              13 (e)
-                          1350 DELETE_FAST             13 (e)
-                          1352 RERAISE                  1
-               
-                51     >> 1354 RERAISE                  0
-                       >> 1356 COPY                     3
-                          1358 POP_EXCEPT
-                          1360 RERAISE                  1
-               
-                55     >> 1362 LOAD_GLOBAL             79 (NULL + zip)
-                          1374 LOAD_GLOBAL              6 (dicts)
-                          1386 LOAD_GLOBAL             48 (lang_manager)
-                          1398 LOAD_ATTR               25 (ref_language)
-                          1408 BINARY_SUBSCR
-                          1418 LOAD_METHOD             40 (keys)
-                          1440 PRECALL                  0
-                          1444 CALL                     0
-                          1454 LOAD_FAST               11 (translations)
-                          1456 PRECALL                  2
-                          1460 CALL                     2
-                          1470 GET_ITER
-                       >> 1472 FOR_ITER                10 (to 1494)
-                          1474 UNPACK_SEQUENCE          2
-                          1478 STORE_FAST               7 (text_id)
-                          1480 STORE_FAST              14 (translation)
-               
-                56        1482 LOAD_FAST               14 (translation)
-                          1484 LOAD_FAST                0 (self)
-                          1486 LOAD_FAST                7 (text_id)
-                          1488 STORE_SUBSCR
-                          1492 JUMP_BACKWARD           11 (to 1472)
+                29         690 LOAD_GLOBAL             43 (NULL + enumerate)
+                           702 LOAD_FAST                6 (module)
+                           704 LOAD_ATTR               22 (texts)
+                           714 PRECALL                  1
+                           718 CALL                     1
+                           728 GET_ITER
+                       >>  730 FOR_ITER                10 (to 752)
+                           732 UNPACK_SEQUENCE          2
+                           736 STORE_FAST               7 (text_id)
+                           738 STORE_FAST               8 (text)
+               
+                30         740 LOAD_FAST                8 (text)
+                           742 LOAD_FAST                0 (self)
+                           744 LOAD_FAST                7 (text_id)
+                           746 STORE_SUBSCR
+                           750 JUMP_BACKWARD           11 (to 730)
+               
+                29     >>  752 LOAD_CONST               0 (None)
+                           754 RETURN_VALUE
+               
+                33     >>  756 LOAD_FAST                0 (self)
+                           758 LOAD_ATTR                2 (lang_id)
+                           768 LOAD_GLOBAL             46 (lang_manager)
+                           780 LOAD_ATTR               24 (ref_language)
+                           790 COMPARE_OP               2 (==)
+                           796 POP_JUMP_FORWARD_IF_FALSE    15 (to 828)
+               
+                34         798 LOAD_GLOBAL             51 (NULL + FileNotFoundError)
+                           810 LOAD_CONST               5 ('The dictionnary for the ref language has not been found')
+                           812 PRECALL                  1
+                           816 CALL                     1
+                           826 RAISE_VARARGS            1
+               
+                36     >>  828 LOAD_GLOBAL             46 (lang_manager)
+                           840 LOAD_ATTR               26 (is_connected_to_network)
+                           850 POP_JUMP_FORWARD_IF_TRUE    15 (to 882)
+               
+                37         852 LOAD_GLOBAL             55 (NULL + ConnectionError)
+                           864 LOAD_CONST               6 ('Translation impossible : baopig.googletrans.lang_manager is not connected to internet')
+                           866 PRECALL                  1
+                           870 CALL                     1
+                           880 RAISE_VARARGS            1
+               
+                40     >>  882 NOP
+               
+                41         884 LOAD_CONST               1 (0)
+                           886 LOAD_CONST               0 (None)
+                           888 IMPORT_NAME             28 (time)
+                           890 STORE_FAST               9 (time)
+               
+                42         892 LOAD_FAST                9 (time)
+                           894 LOAD_METHOD             28 (time)
+                           916 PRECALL                  0
+                           920 CALL                     0
+                           930 STORE_FAST              10 (start_time)
+               
+                44         932 LOAD_GLOBAL             58 (translator)
+                           944 LOAD_METHOD             30 (optimized_translate)
+                           966 LOAD_GLOBAL             63 (NULL + list)
+                           978 LOAD_GLOBAL              6 (dicts)
+                           990 LOAD_GLOBAL             46 (lang_manager)
+                          1002 LOAD_ATTR               24 (ref_language)
+                          1012 BINARY_SUBSCR
+                          1022 LOAD_METHOD             32 (values)
+                          1044 PRECALL                  0
+                          1048 CALL                     0
+                          1058 PRECALL                  1
+                          1062 CALL                     1
+               
+                45        1072 LOAD_GLOBAL             46 (lang_manager)
+                          1084 LOAD_ATTR               24 (ref_language)
+                          1094 LOAD_FAST                1 (lang_id)
+               
+                44        1096 KW_NAMES                 7
+                          1098 PRECALL                  3
+                          1102 CALL                     3
+                          1112 STORE_FAST              11 (translations)
+               
+                47        1114 LOAD_FAST                9 (time)
+                          1116 LOAD_METHOD             28 (time)
+                          1138 PRECALL                  0
+                          1142 CALL                     0
+                          1152 STORE_FAST              12 (end_time)
+               
+                48        1154 LOAD_GLOBAL             66 (bp)
+                          1166 LOAD_ATTR               34 (LOGGER)
+                          1176 LOAD_METHOD             35 (fine)
+                          1198 LOAD_CONST               8 ('Language loading time : ')
+                          1200 LOAD_FAST               12 (end_time)
+                          1202 LOAD_FAST               10 (start_time)
+                          1204 BINARY_OP               10 (-)
+                          1208 FORMAT_VALUE             0
+                          1210 BUILD_STRING             2
+                          1212 PRECALL                  1
+                          1216 CALL                     1
+                          1226 POP_TOP
+                          1228 JUMP_FORWARD            51 (to 1332)
+                       >> 1230 PUSH_EXC_INFO
+               
+                50        1232 LOAD_GLOBAL             72 (Exception)
+                          1244 CHECK_EXC_MATCH
+                          1246 POP_JUMP_FORWARD_IF_FALSE    38 (to 1324)
+                          1248 STORE_FAST              13 (e)
+               
+                51        1250 LOAD_GLOBAL             66 (bp)
+                          1262 LOAD_ATTR               34 (LOGGER)
+                          1272 LOAD_METHOD             37 (warning)
+                          1294 LOAD_FAST               13 (e)
+                          1296 PRECALL                  1
+                          1300 CALL                     1
+                          1310 POP_TOP
+               
+                52        1312 LOAD_FAST               13 (e)
+                          1314 RAISE_VARARGS            1
+                       >> 1316 LOAD_CONST               0 (None)
+                          1318 STORE_FAST              13 (e)
+                          1320 DELETE_FAST             13 (e)
+                          1322 RERAISE                  1
+               
+                50     >> 1324 RERAISE                  0
+                       >> 1326 COPY                     3
+                          1328 POP_EXCEPT
+                          1330 RERAISE                  1
+               
+                54     >> 1332 LOAD_GLOBAL             77 (NULL + zip)
+                          1344 LOAD_GLOBAL              6 (dicts)
+                          1356 LOAD_GLOBAL             46 (lang_manager)
+                          1368 LOAD_ATTR               24 (ref_language)
+                          1378 BINARY_SUBSCR
+                          1388 LOAD_METHOD             39 (keys)
+                          1410 PRECALL                  0
+                          1414 CALL                     0
+                          1424 LOAD_FAST               11 (translations)
+                          1426 PRECALL                  2
+                          1430 CALL                     2
+                          1440 GET_ITER
+                       >> 1442 FOR_ITER                10 (to 1464)
+                          1444 UNPACK_SEQUENCE          2
+                          1448 STORE_FAST               7 (text_id)
+                          1450 STORE_FAST              14 (translation)
+               
+                55        1452 LOAD_FAST               14 (translation)
+                          1454 LOAD_FAST                0 (self)
+                          1456 LOAD_FAST                7 (text_id)
+                          1458 STORE_SUBSCR
+                          1462 JUMP_BACKWARD           11 (to 1442)
                
-                55     >> 1494 LOAD_CONST               0 (None)
-                          1496 RETURN_VALUE
+                54     >> 1464 LOAD_CONST               0 (None)
+                          1466 RETURN_VALUE
                ExceptionTable:
-                 914 to 1256 -> 1260 [0]
-                 1260 to 1278 -> 1356 [1] lasti
-                 1280 to 1344 -> 1346 [1] lasti
-                 1346 to 1354 -> 1356 [1] lasti
+                 884 to 1226 -> 1230 [0]
+                 1230 to 1248 -> 1326 [1] lasti
+                 1250 to 1314 -> 1316 [1] lasti
+                 1316 to 1324 -> 1326 [1] lasti
                consts
                   None
                   0
                   'lang'
                   'dict_'
                   '.py'
-                  'zfdegeb'
                   'The dictionnary for the ref language has not been found'
                   'Translation impossible : baopig.googletrans.lang_manager is not connected to internet'
                   ('src', 'dest')
                   'Language loading time : '
-               names      ('dict', '__init__', 'lang_id', 'dicts', 'os', 'path', 'exists', 'abspath', 'dirname', 'sys', 'argv', 'sep', 'pathlib', 'Path', 'cwd', 'importlib', 'util', 'spec_from_file_location', 'module_from_spec', 'loader', 'exec_module', 'print', 'enumerate', 'texts', 'lang_manager', 'ref_language', 'FileNotFoundError', 'is_connected_to_network', 'ConnectionError', 'time', 'translator', 'optimized_translate', 'list', 'values', 'bp', 'LOGGER', 'fine', 'Exception', 'warning', 'zip', 'keys')
+               names      ('dict', '__init__', 'lang_id', 'dicts', 'os', 'path', 'exists', 'abspath', 'dirname', 'sys', 'argv', 'sep', 'pathlib', 'Path', 'cwd', 'importlib', 'util', 'spec_from_file_location', 'module_from_spec', 'loader', 'exec_module', 'enumerate', 'texts', 'lang_manager', 'ref_language', 'FileNotFoundError', 'is_connected_to_network', 'ConnectionError', 'time', 'translator', 'optimized_translate', 'list', 'values', 'bp', 'LOGGER', 'fine', 'Exception', 'warning', 'zip', 'keys')
                varnames   ('self', 'lang_id', 'pathlib', 'file_path', 'file_name', 'spec', 'module', 'text_id', 'text', 'time', 'start_time', 'translations', 'end_time', 'e', 'translation')
                freevars   ()
                cellvars   ()
                filename   'C:\\Users\\symrb\\Documents\\dev\\python\\baopig\\baopig\\googletrans\\extension.py'
                name       '__init__'
                firstlineno 11
                lnotab
-                  0x020234020e0216011402ff001102080170010a0140013e0134011e0232
-                  010cff04042a011e0218011e030201080128028c0118ff120328014e0212
-                  013e010cfe080478010cff
+                  0x020234020e0216011402ff001102080170010a0140013e01340232010c
+                  ff04042a011e0218011e030201080128028c0118ff120328014e0212013e
+                  010cfe080478010cff
             code
                argcount  : 1
                nlocals   : 5
                stacksize : 10
                flags     : 3
                code
                   0x97007400000000000000000000006a010000000000000000a002000000
@@ -503,17 +495,17 @@
                   007d037d047c03640c6b0400000000722f7c04a00b000000000000000000
                   0000000000000000000000640e640fa6020000ab0200000000000000007d
                   047c02a009000000000000000000000000000000000000000064097c049b
                   00640d9d03a6010000ab01000000000000000001008c3b7c02a009000000
                   00000000000000000000000000000000006410a6010000ab010000000000
                   0000000100640064006400a6020000ab0200000000000000000100640053
                   002300310073047702780359007701010059000100010064005300
-                58           0 RESUME                   0
+                57           0 RESUME                   0
                
-                60           2 LOAD_GLOBAL              0 (os)
+                59           2 LOAD_GLOBAL              0 (os)
                             14 LOAD_ATTR                1 (path)
                             24 LOAD_METHOD              2 (abspath)
                             46 LOAD_GLOBAL              0 (os)
                             58 LOAD_ATTR                1 (path)
                             68 LOAD_METHOD              3 (dirname)
                             90 LOAD_GLOBAL              8 (sys)
                            102 LOAD_ATTR                5 (argv)
@@ -535,32 +527,32 @@
                            206 LOAD_FAST                0 (self)
                            208 LOAD_ATTR                7 (lang_id)
                            218 FORMAT_VALUE             0
                            220 LOAD_CONST               4 ('.py')
                            222 BUILD_STRING             7
                            224 STORE_FAST               1 (absfilename)
                
-                62         226 LOAD_GLOBAL             17 (NULL + open)
+                61         226 LOAD_GLOBAL             17 (NULL + open)
                            238 LOAD_FAST                1 (absfilename)
                            240 LOAD_CONST               5 ('w')
                            242 LOAD_CONST               6 ('utf8')
                            244 KW_NAMES                 7
                            246 PRECALL                  3
                            250 CALL                     3
                            260 BEFORE_WITH
                            262 STORE_FAST               2 (writer)
                
-                64         264 LOAD_FAST                2 (writer)
+                63         264 LOAD_FAST                2 (writer)
                            266 LOAD_METHOD              9 (write)
                            288 LOAD_CONST               8 ('texts = [\n')
                            290 PRECALL                  1
                            294 CALL                     1
                            304 POP_TOP
                
-                65         306 LOAD_FAST                2 (writer)
+                64         306 LOAD_FAST                2 (writer)
                            308 LOAD_METHOD              9 (write)
                            330 LOAD_CONST               9 ('    "')
                            332 LOAD_FAST                0 (self)
                            334 LOAD_CONST               1 (0)
                            336 BINARY_SUBSCR
                            346 FORMAT_VALUE             0
                            348 LOAD_CONST              10 ('", "')
@@ -575,57 +567,57 @@
                            382 FORMAT_VALUE             0
                            384 LOAD_CONST              13 ('",\n')
                            386 BUILD_STRING             7
                            388 PRECALL                  1
                            392 CALL                     1
                            402 POP_TOP
                
-                67         404 LOAD_FAST                0 (self)
+                66         404 LOAD_FAST                0 (self)
                            406 LOAD_METHOD             10 (items)
                            428 PRECALL                  0
                            432 CALL                     0
                            442 GET_ITER
                        >>  444 FOR_ITER                58 (to 562)
                            446 UNPACK_SEQUENCE          2
                            450 STORE_FAST               3 (i)
                            452 STORE_FAST               4 (text)
                
-                68         454 LOAD_FAST                3 (i)
+                67         454 LOAD_FAST                3 (i)
                            456 LOAD_CONST              12 (2)
                            458 COMPARE_OP               4 (>)
                            464 POP_JUMP_FORWARD_IF_FALSE    47 (to 560)
                
-                69         466 LOAD_FAST                4 (text)
+                68         466 LOAD_FAST                4 (text)
                            468 LOAD_METHOD             11 (replace)
                            490 LOAD_CONST              14 ('\n')
                            492 LOAD_CONST              15 ('\\n')
                            494 PRECALL                  2
                            498 CALL                     2
                            508 STORE_FAST               4 (text)
                
-                70         510 LOAD_FAST                2 (writer)
+                69         510 LOAD_FAST                2 (writer)
                            512 LOAD_METHOD              9 (write)
                            534 LOAD_CONST               9 ('    "')
                            536 LOAD_FAST                4 (text)
                            538 FORMAT_VALUE             0
                            540 LOAD_CONST              13 ('",\n')
                            542 BUILD_STRING             3
                            544 PRECALL                  1
                            548 CALL                     1
                            558 POP_TOP
                        >>  560 JUMP_BACKWARD           59 (to 444)
                
-                72     >>  562 LOAD_FAST                2 (writer)
+                71     >>  562 LOAD_FAST                2 (writer)
                            564 LOAD_METHOD              9 (write)
                            586 LOAD_CONST              16 (']')
                            588 PRECALL                  1
                            592 CALL                     1
                            602 POP_TOP
                
-                62         604 LOAD_CONST               0 (None)
+                61         604 LOAD_CONST               0 (None)
                            606 LOAD_CONST               0 (None)
                            608 LOAD_CONST               0 (None)
                            610 PRECALL                  2
                            614 CALL                     2
                            624 POP_TOP
                            626 LOAD_CONST               0 (None)
                            628 RETURN_VALUE
@@ -666,92 +658,92 @@
                   ']'
                names      ('os', 'path', 'abspath', 'dirname', 'sys', 'argv', 'sep', 'lang_id', 'open', 'write', 'items', 'replace')
                varnames   ('self', 'absfilename', 'writer', 'i', 'text')
                freevars   ()
                cellvars   ()
                filename   'C:\\Users\\symrb\\Documents\\dev\\python\\baopig\\baopig\\googletrans\\extension.py'
                name       'save'
-               firstlineno 58
+               firstlineno 57
                lnotab 0x0202e00226022a01620232010c012c0134022af6
             None
          names      ('__name__', '__module__', '__qualname__', '__init__', 'save')
          varnames   ()
          freevars   ()
          cellvars   ()
          filename   'C:\\Users\\symrb\\Documents\\dev\\python\\baopig\\baopig\\googletrans\\extension.py'
          name       'Dictionnary'
          firstlineno 9
-         lnotab 0x0a02062f
+         lnotab 0x0a02062e
       'Dictionnary'
       code
          argcount  : 0
          nlocals   : 0
          stacksize : 3
          flags     : 0
          code
             0x970065005a0164005a02640184005a030200650464028400a6010000ab
             0100000000000000005a050200650464038400a6010000ab010000000000
             0000005a060200650464048400a6010000ab0100000000000000005a0764
             0584005a08640684005a09640784005a0a640884005a0b640984005a0c64
             0a84005a0d640b5300
-          75           0 RESUME                   0
+          74           0 RESUME                   0
                        2 LOAD_NAME                0 (__name__)
                        4 STORE_NAME               1 (__module__)
                        6 LOAD_CONST               0 ('LangManager')
                        8 STORE_NAME               2 (__qualname__)
          
-          77          10 LOAD_CONST               1 (<code object __init__, file "C:\Users\symrb\Documents\dev\python\baopig\baopig\googletrans\extension.py", line 77>)
+          76          10 LOAD_CONST               1 (<code object __init__, file "C:\Users\symrb\Documents\dev\python\baopig\baopig\googletrans\extension.py", line 76>)
                       12 MAKE_FUNCTION            0
                       14 STORE_NAME               3 (__init__)
          
-          90          16 PUSH_NULL
+          89          16 PUSH_NULL
                       18 LOAD_NAME                4 (property)
-                      20 LOAD_CONST               2 (<code object <lambda>, file "C:\Users\symrb\Documents\dev\python\baopig\baopig\googletrans\extension.py", line 90>)
+                      20 LOAD_CONST               2 (<code object <lambda>, file "C:\Users\symrb\Documents\dev\python\baopig\baopig\googletrans\extension.py", line 89>)
                       22 MAKE_FUNCTION            0
                       24 PRECALL                  1
                       28 CALL                     1
                       38 STORE_NAME               5 (is_connected_to_network)
          
-          91          40 PUSH_NULL
+          90          40 PUSH_NULL
                       42 LOAD_NAME                4 (property)
-                      44 LOAD_CONST               3 (<code object <lambda>, file "C:\Users\symrb\Documents\dev\python\baopig\baopig\googletrans\extension.py", line 91>)
+                      44 LOAD_CONST               3 (<code object <lambda>, file "C:\Users\symrb\Documents\dev\python\baopig\baopig\googletrans\extension.py", line 90>)
                       46 MAKE_FUNCTION            0
                       48 PRECALL                  1
                       52 CALL                     1
                       62 STORE_NAME               6 (language)
          
-          92          64 PUSH_NULL
+          91          64 PUSH_NULL
                       66 LOAD_NAME                4 (property)
-                      68 LOAD_CONST               4 (<code object <lambda>, file "C:\Users\symrb\Documents\dev\python\baopig\baopig\googletrans\extension.py", line 92>)
+                      68 LOAD_CONST               4 (<code object <lambda>, file "C:\Users\symrb\Documents\dev\python\baopig\baopig\googletrans\extension.py", line 91>)
                       70 MAKE_FUNCTION            0
                       72 PRECALL                  1
                       76 CALL                     1
                       86 STORE_NAME               7 (ref_language)
          
-          94          88 LOAD_CONST               5 (<code object get_text_from_id, file "C:\Users\symrb\Documents\dev\python\baopig\baopig\googletrans\extension.py", line 94>)
+          93          88 LOAD_CONST               5 (<code object get_text_from_id, file "C:\Users\symrb\Documents\dev\python\baopig\baopig\googletrans\extension.py", line 93>)
                       90 MAKE_FUNCTION            0
                       92 STORE_NAME               8 (get_text_from_id)
          
-         100          94 LOAD_CONST               6 (<code object remove_widget, file "C:\Users\symrb\Documents\dev\python\baopig\baopig\googletrans\extension.py", line 100>)
+          99          94 LOAD_CONST               6 (<code object remove_widget, file "C:\Users\symrb\Documents\dev\python\baopig\baopig\googletrans\extension.py", line 99>)
                       96 MAKE_FUNCTION            0
                       98 STORE_NAME               9 (remove_widget)
          
-         104         100 LOAD_CONST               7 (<code object set_connected, file "C:\Users\symrb\Documents\dev\python\baopig\baopig\googletrans\extension.py", line 104>)
+         103         100 LOAD_CONST               7 (<code object set_connected, file "C:\Users\symrb\Documents\dev\python\baopig\baopig\googletrans\extension.py", line 103>)
                      102 MAKE_FUNCTION            0
                      104 STORE_NAME              10 (set_connected)
          
-         120         106 LOAD_CONST               8 (<code object set_language, file "C:\Users\symrb\Documents\dev\python\baopig\baopig\googletrans\extension.py", line 120>)
+         119         106 LOAD_CONST               8 (<code object set_language, file "C:\Users\symrb\Documents\dev\python\baopig\baopig\googletrans\extension.py", line 119>)
                      108 MAKE_FUNCTION            0
                      110 STORE_NAME              11 (set_language)
          
-         144         112 LOAD_CONST               9 (<code object set_ref_language, file "C:\Users\symrb\Documents\dev\python\baopig\baopig\googletrans\extension.py", line 144>)
+         143         112 LOAD_CONST               9 (<code object set_ref_language, file "C:\Users\symrb\Documents\dev\python\baopig\baopig\googletrans\extension.py", line 143>)
                      114 MAKE_FUNCTION            0
                      116 STORE_NAME              12 (set_ref_language)
          
-         154         118 LOAD_CONST              10 (<code object set_ref_text, file "C:\Users\symrb\Documents\dev\python\baopig\baopig\googletrans\extension.py", line 154>)
+         153         118 LOAD_CONST              10 (<code object set_ref_text, file "C:\Users\symrb\Documents\dev\python\baopig\baopig\googletrans\extension.py", line 153>)
                      120 MAKE_FUNCTION            0
                      122 STORE_NAME              13 (set_ref_text)
                      124 LOAD_CONST              11 (None)
                      126 RETURN_VALUE
          consts
             'LangManager'
             code
@@ -764,51 +756,51 @@
                   00000000000000000000000000000000007c00a6010000ab010000000000
                   000000010069007c005f03000000000000000069007c005f040000000000
                   000000640078017c005f0500000000000000007c005f0600000000000000
                   0064017c005f0700000000000000007c00a0080000000000000000000000
                   0000000000000000006402a6010000ab01000000000000000001007c00a0
                   0800000000000000000000000000000000000000006403a6010000ab0100
                   00000000000000010064005300
-                77           0 RESUME                   0
+                76           0 RESUME                   0
                
-                79           2 LOAD_GLOBAL              0 (bp)
+                78           2 LOAD_GLOBAL              0 (bp)
                             14 LOAD_ATTR                1 (Communicative)
                             24 LOAD_METHOD              2 (__init__)
                             46 LOAD_FAST                0 (self)
                             48 PRECALL                  1
                             52 CALL                     1
                             62 POP_TOP
                
-                81          64 BUILD_MAP                0
+                80          64 BUILD_MAP                0
                             66 LOAD_FAST                0 (self)
                             68 STORE_ATTR               3 (_ref_texts)
                
-                82          78 BUILD_MAP                0
+                81          78 BUILD_MAP                0
                             80 LOAD_FAST                0 (self)
                             82 STORE_ATTR               4 (_textid_by_widget)
                
-                83          92 LOAD_CONST               0 (None)
+                82          92 LOAD_CONST               0 (None)
                             94 COPY                     1
                             96 LOAD_FAST                0 (self)
                             98 STORE_ATTR               5 (_ref_language)
                            108 LOAD_FAST                0 (self)
                            110 STORE_ATTR               6 (_language)
                
-                85         120 LOAD_CONST               1 (True)
+                84         120 LOAD_CONST               1 (True)
                            122 LOAD_FAST                0 (self)
                            124 STORE_ATTR               7 (_is_connected_to_network)
                
-                87         134 LOAD_FAST                0 (self)
+                86         134 LOAD_FAST                0 (self)
                            136 LOAD_METHOD              8 (create_signal)
                            158 LOAD_CONST               2 ('UPDATE_LANGUAGE')
                            160 PRECALL                  1
                            164 CALL                     1
                            174 POP_TOP
                
-                88         176 LOAD_FAST                0 (self)
+                87         176 LOAD_FAST                0 (self)
                            178 LOAD_METHOD              8 (create_signal)
                            200 LOAD_CONST               3 ('NEW_CONNECTION_STATE')
                            202 PRECALL                  1
                            206 CALL                     1
                            216 POP_TOP
                            218 LOAD_CONST               0 (None)
                            220 RETURN_VALUE
@@ -819,116 +811,116 @@
                   'NEW_CONNECTION_STATE'
                names      ('bp', 'Communicative', '__init__', '_ref_texts', '_textid_by_widget', '_ref_language', '_language', '_is_connected_to_network', 'create_signal')
                varnames   ('self',)
                freevars   ()
                cellvars   ()
                filename   'C:\\Users\\symrb\\Documents\\dev\\python\\baopig\\baopig\\googletrans\\extension.py'
                name       '__init__'
-               firstlineno 77
+               firstlineno 76
                lnotab 0x02023e020e010e011c020e022a01
             code
                argcount  : 1
                nlocals   : 1
                stacksize : 1
                flags     : 3
                code 0x97007c006a0000000000000000005300
-                90           0 RESUME                   0
+                89           0 RESUME                   0
                              2 LOAD_FAST                0 (self)
                              4 LOAD_ATTR                0 (_is_connected_to_network)
                             14 RETURN_VALUE
                consts
                   None
                names      ('_is_connected_to_network',)
                varnames   ('self',)
                freevars   ()
                cellvars   ()
                filename   'C:\\Users\\symrb\\Documents\\dev\\python\\baopig\\baopig\\googletrans\\extension.py'
                name       '<lambda>'
-               firstlineno 90
+               firstlineno 89
                lnotab 0x
             code
                argcount  : 1
                nlocals   : 1
                stacksize : 1
                flags     : 3
                code 0x97007c006a0000000000000000005300
-                91           0 RESUME                   0
+                90           0 RESUME                   0
                              2 LOAD_FAST                0 (self)
                              4 LOAD_ATTR                0 (_language)
                             14 RETURN_VALUE
                consts
                   None
                names      ('_language',)
                varnames   ('self',)
                freevars   ()
                cellvars   ()
                filename   'C:\\Users\\symrb\\Documents\\dev\\python\\baopig\\baopig\\googletrans\\extension.py'
                name       '<lambda>'
-               firstlineno 91
+               firstlineno 90
                lnotab 0x
             code
                argcount  : 1
                nlocals   : 1
                stacksize : 1
                flags     : 3
                code 0x97007c006a0000000000000000005300
-                92           0 RESUME                   0
+                91           0 RESUME                   0
                              2 LOAD_FAST                0 (self)
                              4 LOAD_ATTR                0 (_ref_language)
                             14 RETURN_VALUE
                consts
                   None
                names      ('_ref_language',)
                varnames   ('self',)
                freevars   ()
                cellvars   ()
                filename   'C:\\Users\\symrb\\Documents\\dev\\python\\baopig\\baopig\\googletrans\\extension.py'
                name       '<lambda>'
-               firstlineno 92
+               firstlineno 91
                lnotab 0x
             code
                argcount  : 2
                nlocals   : 2
                stacksize : 4
                flags     : 3
                code
                   0x970009007400000000000000000000007c006a01000000000000000019
                   0000000000000000007c0119000000000000000000530023007404000000
                   000000000000002400721b01007400000000000000000000007c006a0300
                   00000000000000190000000000000000007c011900000000000000000063
                   02590053007700780359007701
-                94           0 RESUME                   0
+                93           0 RESUME                   0
                
-                95           2 NOP
+                94           2 NOP
                
-                96           4 LOAD_GLOBAL              0 (dicts)
+                95           4 LOAD_GLOBAL              0 (dicts)
                             16 LOAD_FAST                0 (self)
                             18 LOAD_ATTR                1 (_language)
                             28 BINARY_SUBSCR
                             38 LOAD_FAST                1 (text_id)
                             40 BINARY_SUBSCR
                             50 RETURN_VALUE
                        >>   52 PUSH_EXC_INFO
                
-                97          54 LOAD_GLOBAL              4 (KeyError)
+                96          54 LOAD_GLOBAL              4 (KeyError)
                             66 CHECK_EXC_MATCH
                             68 POP_JUMP_FORWARD_IF_FALSE    27 (to 124)
                             70 POP_TOP
                
-                98          72 LOAD_GLOBAL              0 (dicts)
+                97          72 LOAD_GLOBAL              0 (dicts)
                             84 LOAD_FAST                0 (self)
                             86 LOAD_ATTR                3 (_ref_language)
                             96 BINARY_SUBSCR
                            106 LOAD_FAST                1 (text_id)
                            108 BINARY_SUBSCR
                            118 SWAP                     2
                            120 POP_EXCEPT
                            122 RETURN_VALUE
                
-                97     >>  124 RERAISE                  0
+                96     >>  124 RERAISE                  0
                        >>  126 COPY                     3
                            128 POP_EXCEPT
                            130 RERAISE                  1
                ExceptionTable:
                  4 to 48 -> 52 [0]
                  52 to 118 -> 126 [1] lasti
                  124 to 124 -> 126 [1] lasti
@@ -936,37 +928,37 @@
                   None
                names      ('dicts', '_language', 'KeyError', '_ref_language')
                varnames   ('self', 'text_id')
                freevars   ()
                cellvars   ()
                filename   'C:\\Users\\symrb\\Documents\\dev\\python\\baopig\\baopig\\googletrans\\extension.py'
                name       'get_text_from_id'
-               firstlineno 94
+               firstlineno 93
                lnotab 0x020102013201120134ff
             code
                argcount  : 2
                nlocals   : 2
                stacksize : 3
                flags     : 3
                code
                   0x97007c006a000000000000000000a00100000000000000000000000000
                   000000000000007c01a6010000ab01000000000000000001007c006a0200
                   00000000000000a00100000000000000000000000000000000000000007c
                   01a6010000ab010000000000000000010064005300
-               100           0 RESUME                   0
+                99           0 RESUME                   0
                
-               101           2 LOAD_FAST                0 (self)
+               100           2 LOAD_FAST                0 (self)
                              4 LOAD_ATTR                0 (_ref_texts)
                             14 LOAD_METHOD              1 (pop)
                             36 LOAD_FAST                1 (widget)
                             38 PRECALL                  1
                             42 CALL                     1
                             52 POP_TOP
                
-               102          54 LOAD_FAST                0 (self)
+               101          54 LOAD_FAST                0 (self)
                             56 LOAD_ATTR                2 (_textid_by_widget)
                             66 LOAD_METHOD              1 (pop)
                             88 LOAD_FAST                1 (widget)
                             90 PRECALL                  1
                             94 CALL                     1
                            104 POP_TOP
                            106 LOAD_CONST               0 (None)
@@ -975,65 +967,65 @@
                   None
                names      ('_ref_texts', 'pop', '_textid_by_widget')
                varnames   ('self', 'widget')
                freevars   ()
                cellvars   ()
                filename   'C:\\Users\\symrb\\Documents\\dev\\python\\baopig\\baopig\\googletrans\\extension.py'
                name       'remove_widget'
-               firstlineno 100
+               firstlineno 99
                lnotab 0x02013401
             code
                argcount  : 2
                nlocals   : 2
                stacksize : 3
                flags     : 3
                code
                   0x97007401000000000000000000007c01a6010000ab0100000000000000
                   007c006a0100000000000000006b02000000007202640053007c01722374
                   0400000000000000000000a0030000000000000000000000000000000000
                   000000a6000000ab000000000000000000720864017c005f040000000000
                   0000006e096400530064027c005f0400000000000000007c006a05000000
                   00000000006a060000000000000000a00700000000000000000000000000
                   00000000000000a6000000ab000000000000000000010064005300
-               104           0 RESUME                   0
+               103           0 RESUME                   0
                
-               106           2 LOAD_GLOBAL              1 (NULL + bool)
+               105           2 LOAD_GLOBAL              1 (NULL + bool)
                             14 LOAD_FAST                1 (connected)
                             16 PRECALL                  1
                             20 CALL                     1
                             30 LOAD_FAST                0 (self)
                             32 LOAD_ATTR                1 (is_connected_to_network)
                             42 COMPARE_OP               2 (==)
                             48 POP_JUMP_FORWARD_IF_FALSE     2 (to 54)
                
-               107          50 LOAD_CONST               0 (None)
+               106          50 LOAD_CONST               0 (None)
                             52 RETURN_VALUE
                
-               109     >>   54 LOAD_FAST                1 (connected)
+               108     >>   54 LOAD_FAST                1 (connected)
                             56 POP_JUMP_FORWARD_IF_FALSE    35 (to 128)
                
-               110          58 LOAD_GLOBAL              4 (translator)
+               109          58 LOAD_GLOBAL              4 (translator)
                             70 LOAD_METHOD              3 (test_connection)
                             92 PRECALL                  0
                             96 CALL                     0
                            106 POP_JUMP_FORWARD_IF_FALSE     8 (to 124)
                
-               111         108 LOAD_CONST               1 (True)
+               110         108 LOAD_CONST               1 (True)
                            110 LOAD_FAST                0 (self)
                            112 STORE_ATTR               4 (_is_connected_to_network)
                            122 JUMP_FORWARD             9 (to 142)
                
-               113     >>  124 LOAD_CONST               0 (None)
+               112     >>  124 LOAD_CONST               0 (None)
                            126 RETURN_VALUE
                
-               116     >>  128 LOAD_CONST               2 (False)
+               115     >>  128 LOAD_CONST               2 (False)
                            130 LOAD_FAST                0 (self)
                            132 STORE_ATTR               4 (_is_connected_to_network)
                
-               118     >>  142 LOAD_FAST                0 (self)
+               117     >>  142 LOAD_FAST                0 (self)
                            144 LOAD_ATTR                5 (signal)
                            154 LOAD_ATTR                6 (NEW_CONNECTION_STATE)
                            164 LOAD_METHOD              7 (emit)
                            186 PRECALL                  0
                            190 CALL                     0
                            200 POP_TOP
                            202 LOAD_CONST               0 (None)
@@ -1044,15 +1036,15 @@
                   False
                names      ('bool', 'is_connected_to_network', 'translator', 'test_connection', '_is_connected_to_network', 'signal', 'NEW_CONNECTION_STATE', 'emit')
                varnames   ('self', 'connected')
                freevars   ()
                cellvars   ()
                filename   'C:\\Users\\symrb\\Documents\\dev\\python\\baopig\\baopig\\googletrans\\extension.py'
                name       'set_connected'
-               firstlineno 104
+               firstlineno 103
                lnotab 0x02023001040204013201100204030e02
             code
                argcount  : 2
                nlocals   : 4
                stacksize : 6
                flags     : 3
                code
@@ -1069,100 +1061,100 @@
                   00000000000000000000007c00a008000000000000000000000000000000
                   00000000007c026a090000000000000000a6010000ab0100000000000000
                   00a6010000ab01000000000000000001007c02a007000000000000000000
                   0000000000000000000000a6000000ab00000000000000000001008c447c
                   006a0a00000000000000006a0b0000000000000000a00c00000000000000
                   00000000000000000000000000a6000000ab000000000000000000010064
                   005300
-               120           0 RESUME                   0
+               119           0 RESUME                   0
                
-               122           2 LOAD_FAST                1 (lang_id)
+               121           2 LOAD_FAST                1 (lang_id)
                              4 LOAD_FAST                0 (self)
                              6 LOAD_ATTR                0 (_language)
                             16 COMPARE_OP               2 (==)
                             22 POP_JUMP_FORWARD_IF_FALSE     2 (to 28)
                
-               123          24 LOAD_CONST               0 (None)
+               122          24 LOAD_CONST               0 (None)
                             26 RETURN_VALUE
                
-               125     >>   28 LOAD_FAST                1 (lang_id)
+               124     >>   28 LOAD_FAST                1 (lang_id)
                             30 LOAD_GLOBAL              2 (dicts)
                             42 CONTAINS_OP              1
                             44 POP_JUMP_FORWARD_IF_FALSE    15 (to 76)
                
-               126          46 LOAD_GLOBAL              5 (NULL + Dictionnary)
+               125          46 LOAD_GLOBAL              5 (NULL + Dictionnary)
                             58 LOAD_FAST                1 (lang_id)
                             60 PRECALL                  1
                             64 CALL                     1
                             74 POP_TOP
                
-               128     >>   76 LOAD_FAST                1 (lang_id)
+               127     >>   76 LOAD_FAST                1 (lang_id)
                             78 LOAD_FAST                0 (self)
                             80 STORE_ATTR               0 (_language)
                
-               130          90 LOAD_FAST                0 (self)
+               129          90 LOAD_FAST                0 (self)
                             92 LOAD_ATTR                0 (_language)
                            102 LOAD_FAST                0 (self)
                            104 LOAD_ATTR                3 (_ref_language)
                            114 COMPARE_OP               2 (==)
                            120 POP_JUMP_FORWARD_IF_FALSE    73 (to 268)
                
-               132         122 LOAD_FAST                0 (self)
+               131         122 LOAD_FAST                0 (self)
                            124 LOAD_ATTR                4 (_ref_texts)
                            134 LOAD_METHOD              5 (items)
                            156 PRECALL                  0
                            160 CALL                     0
                            170 GET_ITER
                        >>  172 FOR_ITER                46 (to 266)
                            174 UNPACK_SEQUENCE          2
                            178 STORE_FAST               2 (widget)
                            180 STORE_FAST               3 (text)
                
-               133         182 LOAD_FAST                2 (widget)
+               132         182 LOAD_FAST                2 (widget)
                            184 LOAD_METHOD              6 (set_text)
                            206 LOAD_FAST                3 (text)
                            208 PRECALL                  1
                            212 CALL                     1
                            222 POP_TOP
                
-               134         224 LOAD_FAST                2 (widget)
+               133         224 LOAD_FAST                2 (widget)
                            226 LOAD_METHOD              7 (fit)
                            248 PRECALL                  0
                            252 CALL                     0
                            262 POP_TOP
                            264 JUMP_BACKWARD           47 (to 172)
                
-               132     >>  266 JUMP_FORWARD            75 (to 418)
+               131     >>  266 JUMP_FORWARD            75 (to 418)
                
-               138     >>  268 LOAD_FAST                0 (self)
+               137     >>  268 LOAD_FAST                0 (self)
                            270 LOAD_ATTR                4 (_ref_texts)
                            280 GET_ITER
                        >>  282 FOR_ITER                67 (to 418)
                            284 STORE_FAST               2 (widget)
                
-               139         286 LOAD_FAST                2 (widget)
+               138         286 LOAD_FAST                2 (widget)
                            288 LOAD_METHOD              6 (set_text)
                            310 LOAD_FAST                0 (self)
                            312 LOAD_METHOD              8 (get_text_from_id)
                            334 LOAD_FAST                2 (widget)
                            336 LOAD_ATTR                9 (text_id)
                            346 PRECALL                  1
                            350 CALL                     1
                            360 PRECALL                  1
                            364 CALL                     1
                            374 POP_TOP
                
-               140         376 LOAD_FAST                2 (widget)
+               139         376 LOAD_FAST                2 (widget)
                            378 LOAD_METHOD              7 (fit)
                            400 PRECALL                  0
                            404 CALL                     0
                            414 POP_TOP
                            416 JUMP_BACKWARD           68 (to 282)
                
-               142     >>  418 LOAD_FAST                0 (self)
+               141     >>  418 LOAD_FAST                0 (self)
                            420 LOAD_ATTR               10 (signal)
                            430 LOAD_ATTR               11 (UPDATE_LANGUAGE)
                            440 LOAD_METHOD             12 (emit)
                            462 PRECALL                  0
                            466 CALL                     0
                            476 POP_TOP
                            478 LOAD_CONST               0 (None)
@@ -1171,15 +1163,15 @@
                   None
                names      ('_language', 'dicts', 'Dictionnary', '_ref_language', '_ref_texts', 'items', 'set_text', 'fit', 'get_text_from_id', 'text_id', 'signal', 'UPDATE_LANGUAGE', 'emit')
                varnames   ('self', 'lang_id', 'widget', 'text')
                freevars   ()
                cellvars   ()
                filename   'C:\\Users\\symrb\\Documents\\dev\\python\\baopig\\baopig\\googletrans\\extension.py'
                name       'set_language'
-               firstlineno 120
+               firstlineno 119
                lnotab 0x02021601040212011e020e0220023c012a012afe020612015a012a02
             code
                argcount  : 2
                nlocals   : 2
                stacksize : 4
                flags     : 3
                code
@@ -1187,30 +1179,30 @@
                   0000009b009d02a6000000ab000000000000000000820174030000000000
                   00000000007c01740400000000000000000000a6020000ab020000000000
                   00000072137407000000000000000000007c01a6010000ab010000000000
                   00000064026b020000000073024a0082017c0178017c005f000000000000
                   0000007c005f0400000000000000007c01740a0000000000000000000076
                   017211740d000000000000000000007c01a6010000ab0100000000000000
                   0001006400530064005300
-               144           0 RESUME                   0
+               143           0 RESUME                   0
                
-               146           2 LOAD_FAST                0 (self)
+               145           2 LOAD_FAST                0 (self)
                              4 LOAD_ATTR                0 (_ref_language)
                             14 POP_JUMP_FORWARD_IF_NONE    18 (to 52)
                             16 LOAD_ASSERTION_ERROR
                             18 LOAD_CONST               1 ('The reference language is already set to ')
                             20 LOAD_FAST                0 (self)
                             22 LOAD_ATTR                0 (_ref_language)
                             32 FORMAT_VALUE             0
                             34 BUILD_STRING             2
                             36 PRECALL                  0
                             40 CALL                     0
                             50 RAISE_VARARGS            1
                
-               147     >>   52 LOAD_GLOBAL              3 (NULL + isinstance)
+               146     >>   52 LOAD_GLOBAL              3 (NULL + isinstance)
                             64 LOAD_FAST                1 (ref_lang_id)
                             66 LOAD_GLOBAL              4 (str)
                             78 PRECALL                  2
                             82 CALL                     2
                             92 POP_JUMP_FORWARD_IF_FALSE    19 (to 132)
                             94 LOAD_GLOBAL              7 (NULL + len)
                            106 LOAD_FAST                1 (ref_lang_id)
@@ -1218,47 +1210,47 @@
                            112 CALL                     1
                            122 LOAD_CONST               2 (2)
                            124 COMPARE_OP               2 (==)
                            130 POP_JUMP_FORWARD_IF_TRUE     2 (to 136)
                        >>  132 LOAD_ASSERTION_ERROR
                            134 RAISE_VARARGS            1
                
-               149     >>  136 LOAD_FAST                1 (ref_lang_id)
+               148     >>  136 LOAD_FAST                1 (ref_lang_id)
                            138 COPY                     1
                            140 LOAD_FAST                0 (self)
                            142 STORE_ATTR               0 (_ref_language)
                            152 LOAD_FAST                0 (self)
                            154 STORE_ATTR               4 (_language)
                
-               151         164 LOAD_FAST                1 (ref_lang_id)
+               150         164 LOAD_FAST                1 (ref_lang_id)
                            166 LOAD_GLOBAL             10 (dicts)
                            178 CONTAINS_OP              1
                            180 POP_JUMP_FORWARD_IF_FALSE    17 (to 216)
                
-               152         182 LOAD_GLOBAL             13 (NULL + Dictionnary)
+               151         182 LOAD_GLOBAL             13 (NULL + Dictionnary)
                            194 LOAD_FAST                1 (ref_lang_id)
                            196 PRECALL                  1
                            200 CALL                     1
                            210 POP_TOP
                            212 LOAD_CONST               0 (None)
                            214 RETURN_VALUE
                
-               151     >>  216 LOAD_CONST               0 (None)
+               150     >>  216 LOAD_CONST               0 (None)
                            218 RETURN_VALUE
                consts
                   None
                   'The reference language is already set to '
                   2
                names      ('_ref_language', 'isinstance', 'str', 'len', '_language', 'dicts', 'Dictionnary')
                varnames   ('self', 'ref_lang_id')
                freevars   ()
                cellvars   ()
                filename   'C:\\Users\\symrb\\Documents\\dev\\python\\baopig\\baopig\\googletrans\\extension.py'
                name       'set_ref_language'
-               firstlineno 144
+               firstlineno 143
                lnotab 0x0202320154021c02120122ff
             code
                argcount  : 3
                nlocals   : 4
                stacksize : 5
                flags     : 3
                code
@@ -1266,52 +1258,52 @@
                   0000000000000000007d037c037c006a0100000000000000007c013c0000
                   007c027c006a0200000000000000007c013c0000007c027c015f03000000
                   00000000007c01a00400000000000000000000000000000000000000007c
                   00a00500000000000000000000000000000000000000007c016a03000000
                   0000000000a6010000ab010000000000000000a6010000ab010000000000
                   00000001007c01a0060000000000000000000000000000000000000000a6
                   000000ab000000000000000000010064005300
-               154           0 RESUME                   0
+               153           0 RESUME                   0
                
-               156           2 LOAD_GLOBAL              0 (dicts)
+               155           2 LOAD_GLOBAL              0 (dicts)
                             14 LOAD_CONST               1 ('fr')
                             16 BINARY_SUBSCR
                             26 LOAD_FAST                2 (text_id)
                             28 BINARY_SUBSCR
                             38 STORE_FAST               3 (text)
                
-               157          40 LOAD_FAST                3 (text)
+               156          40 LOAD_FAST                3 (text)
                             42 LOAD_FAST                0 (self)
                             44 LOAD_ATTR                1 (_ref_texts)
                             54 LOAD_FAST                1 (widget)
                             56 STORE_SUBSCR
                
-               158          60 LOAD_FAST                2 (text_id)
+               157          60 LOAD_FAST                2 (text_id)
                             62 LOAD_FAST                0 (self)
                             64 LOAD_ATTR                2 (_textid_by_widget)
                             74 LOAD_FAST                1 (widget)
                             76 STORE_SUBSCR
                
-               159          80 LOAD_FAST                2 (text_id)
+               158          80 LOAD_FAST                2 (text_id)
                             82 LOAD_FAST                1 (widget)
                             84 STORE_ATTR               3 (text_id)
                
-               160          94 LOAD_FAST                1 (widget)
+               159          94 LOAD_FAST                1 (widget)
                             96 LOAD_METHOD              4 (set_text)
                            118 LOAD_FAST                0 (self)
                            120 LOAD_METHOD              5 (get_text_from_id)
                            142 LOAD_FAST                1 (widget)
                            144 LOAD_ATTR                3 (text_id)
                            154 PRECALL                  1
                            158 CALL                     1
                            168 PRECALL                  1
                            172 CALL                     1
                            182 POP_TOP
                
-               161         184 LOAD_FAST                1 (widget)
+               160         184 LOAD_FAST                1 (widget)
                            186 LOAD_METHOD              6 (fit)
                            208 PRECALL                  0
                            212 CALL                     0
                            222 POP_TOP
                            224 LOAD_CONST               0 (None)
                            226 RETURN_VALUE
                consts
@@ -1319,49 +1311,49 @@
                   'fr'
                names      ('dicts', '_ref_texts', '_textid_by_widget', 'text_id', 'set_text', 'get_text_from_id', 'fit')
                varnames   ('self', 'widget', 'text_id', 'text')
                freevars   ()
                cellvars   ()
                filename   'C:\\Users\\symrb\\Documents\\dev\\python\\baopig\\baopig\\googletrans\\extension.py'
                name       'set_ref_text'
-               firstlineno 154
+               firstlineno 153
                lnotab 0x02022601140114010e015a01
             None
          names      ('__name__', '__module__', '__qualname__', '__init__', 'property', 'is_connected_to_network', 'language', 'ref_language', 'get_text_from_id', 'remove_widget', 'set_connected', 'set_language', 'set_ref_language', 'set_ref_text')
          varnames   ()
          freevars   ()
          cellvars   ()
          filename   'C:\\Users\\symrb\\Documents\\dev\\python\\baopig\\baopig\\googletrans\\extension.py'
          name       'LangManager'
-         firstlineno 75
+         firstlineno 74
          lnotab 0x0a02060d1801180118020606060406100618060a
       'LangManager'
       code
          argcount  : 0
          nlocals   : 0
          stacksize : 2
          flags     : 0
          code
             0x8700970065005a0164005a02640184005a0388006601640284085a0488
             0078015a055300
                        0 MAKE_CELL                0 (__class__)
          
-         164           2 RESUME                   0
+         163           2 RESUME                   0
                        4 LOAD_NAME                0 (__name__)
                        6 STORE_NAME               1 (__module__)
                        8 LOAD_CONST               0 ('OptimizedTranslator')
                       10 STORE_NAME               2 (__qualname__)
          
-         166          12 LOAD_CONST               1 (<code object optimized_translate, file "C:\Users\symrb\Documents\dev\python\baopig\baopig\googletrans\extension.py", line 166>)
+         165          12 LOAD_CONST               1 (<code object optimized_translate, file "C:\Users\symrb\Documents\dev\python\baopig\baopig\googletrans\extension.py", line 165>)
                       14 MAKE_FUNCTION            0
                       16 STORE_NAME               3 (optimized_translate)
          
-         201          18 LOAD_CLOSURE             0 (__class__)
+         200          18 LOAD_CLOSURE             0 (__class__)
                       20 BUILD_TUPLE              1
-                      22 LOAD_CONST               2 (<code object test_connection, file "C:\Users\symrb\Documents\dev\python\baopig\baopig\googletrans\extension.py", line 201>)
+                      22 LOAD_CONST               2 (<code object test_connection, file "C:\Users\symrb\Documents\dev\python\baopig\baopig\googletrans\extension.py", line 200>)
                       24 MAKE_FUNCTION            8 (closure)
                       26 STORE_NAME               4 (test_connection)
                       28 LOAD_CLOSURE             0 (__class__)
                       30 COPY                     1
                       32 STORE_NAME               5 (__classcell__)
                       34 RETURN_VALUE
          consts
@@ -1400,157 +1392,157 @@
                   00000000000000000000000000000000000000640b84007c0b640c190000
                   000000000000004400a6000000ab000000000000000000a6010000ab0100
                   000000000000005300
                              0 MAKE_CELL                0 (self)
                              2 MAKE_CELL                2 (src)
                              4 MAKE_CELL                3 (dest)
                
-               166           6 RESUME                   0
+               165           6 RESUME                   0
                
-               168           8 LOAD_GLOBAL              1 (NULL + isinstance)
+               167           8 LOAD_GLOBAL              1 (NULL + isinstance)
                             20 LOAD_FAST                1 (text)
                             22 LOAD_GLOBAL              2 (list)
                             34 PRECALL                  2
                             38 CALL                     2
                             48 EXTENDED_ARG             1
                             50 POP_JUMP_FORWARD_IF_FALSE   256 (to 564)
                
-               170          52 LOAD_CONST               1 ('\n')
+               169          52 LOAD_CONST               1 ('\n')
                             54 STORE_FAST               4 (sep)
                
-               171          56 LOAD_CONST               2 ('')
+               170          56 LOAD_CONST               2 ('')
                             58 STORE_FAST               5 (sep_transition)
                
-               172          60 LOAD_CONST               3 ('')
+               171          60 LOAD_CONST               3 ('')
                             62 STORE_FAST               6 (sep_encoded)
                
-               173          64 LOAD_GLOBAL              5 (NULL + len)
+               172          64 LOAD_GLOBAL              5 (NULL + len)
                             76 LOAD_FAST                1 (text)
                             78 PRECALL                  1
                             82 CALL                     1
                             92 STORE_FAST               7 (ln)
                
-               174          94 LOAD_FAST                5 (sep_transition)
+               173          94 LOAD_FAST                5 (sep_transition)
                             96 LOAD_METHOD              3 (join)
                            118 LOAD_FAST                1 (text)
                            120 PRECALL                  1
                            124 CALL                     1
                            134 STORE_FAST               8 (joined)
                
-               175         136 LOAD_FAST                8 (joined)
+               174         136 LOAD_FAST                8 (joined)
                            138 LOAD_METHOD              4 (replace)
                            160 LOAD_FAST                4 (sep)
                            162 LOAD_FAST                6 (sep_encoded)
                            164 PRECALL                  2
                            168 CALL                     2
                            178 STORE_FAST               8 (joined)
                
-               176         180 LOAD_FAST                8 (joined)
+               175         180 LOAD_FAST                8 (joined)
                            182 LOAD_METHOD              4 (replace)
                            204 LOAD_FAST                5 (sep_transition)
                            206 LOAD_FAST                4 (sep)
                            208 PRECALL                  2
                            212 CALL                     2
                            222 STORE_FAST               8 (joined)
                
-               177         224 LOAD_DEREF               0 (self)
+               176         224 LOAD_DEREF               0 (self)
                            226 LOAD_METHOD              5 (optimized_translate)
                            248 LOAD_FAST                8 (joined)
                            250 LOAD_DEREF               3 (dest)
                            252 LOAD_DEREF               2 (src)
                            254 KW_NAMES                 4
                            256 PRECALL                  3
                            260 CALL                     3
                            270 STORE_FAST               9 (joined_translated)
                
-               178         272 LOAD_FAST                9 (joined_translated)
+               177         272 LOAD_FAST                9 (joined_translated)
                            274 LOAD_METHOD              4 (replace)
                            296 LOAD_FAST                4 (sep)
                            298 LOAD_FAST                5 (sep_transition)
                            300 PRECALL                  2
                            304 CALL                     2
                            314 STORE_FAST               9 (joined_translated)
                
-               179         316 LOAD_FAST                9 (joined_translated)
+               178         316 LOAD_FAST                9 (joined_translated)
                            318 LOAD_METHOD              4 (replace)
                            340 LOAD_FAST                6 (sep_encoded)
                            342 LOAD_FAST                4 (sep)
                            344 PRECALL                  2
                            348 CALL                     2
                            358 STORE_FAST               9 (joined_translated)
                
-               180         360 LOAD_FAST                9 (joined_translated)
+               179         360 LOAD_FAST                9 (joined_translated)
                            362 LOAD_METHOD              6 (split)
                            384 LOAD_FAST                5 (sep_transition)
                            386 PRECALL                  1
                            390 CALL                     1
                            400 STORE_FAST              10 (result)
                
-               181         402 LOAD_FAST                7 (ln)
+               180         402 LOAD_FAST                7 (ln)
                            404 LOAD_GLOBAL              5 (NULL + len)
                            416 LOAD_FAST               10 (result)
                            418 PRECALL                  1
                            422 CALL                     1
                            432 COMPARE_OP               2 (==)
                            438 POP_JUMP_FORWARD_IF_FALSE     2 (to 444)
                
-               182         440 LOAD_FAST               10 (result)
+               181         440 LOAD_FAST               10 (result)
                            442 RETURN_VALUE
                
-               184     >>  444 LOAD_GLOBAL             14 (bp)
+               183     >>  444 LOAD_GLOBAL             14 (bp)
                            456 LOAD_ATTR                8 (LOGGER)
                            466 LOAD_METHOD              9 (info)
                            488 LOAD_CONST               5 ('Translation optimization has failed')
                            490 PRECALL                  1
                            494 CALL                     1
                            504 POP_TOP
                
-               186         506 LOAD_GLOBAL             21 (NULL + tuple)
+               185         506 LOAD_GLOBAL             21 (NULL + tuple)
                            518 LOAD_CLOSURE             3 (dest)
                            520 LOAD_CLOSURE             0 (self)
                            522 LOAD_CLOSURE             2 (src)
                            524 BUILD_TUPLE              3
-                           526 LOAD_CONST               6 (<code object <genexpr>, file "C:\Users\symrb\Documents\dev\python\baopig\baopig\googletrans\extension.py", line 186>)
+                           526 LOAD_CONST               6 (<code object <genexpr>, file "C:\Users\symrb\Documents\dev\python\baopig\baopig\googletrans\extension.py", line 185>)
                            528 MAKE_FUNCTION            8 (closure)
                            530 LOAD_FAST                1 (text)
                            532 GET_ITER
                            534 PRECALL                  0
                            538 CALL                     0
                            548 PRECALL                  1
                            552 CALL                     1
                            562 RETURN_VALUE
                
-               188     >>  564 LOAD_FAST                1 (text)
+               187     >>  564 LOAD_FAST                1 (text)
                            566 POP_JUMP_FORWARD_IF_TRUE     2 (to 572)
                
-               189         568 LOAD_CONST               7 ('')
+               188         568 LOAD_CONST               7 ('')
                            570 RETURN_VALUE
                
-               191     >>  572 NOP
+               190     >>  572 NOP
                
-               192         574 LOAD_DEREF               0 (self)
+               191         574 LOAD_DEREF               0 (self)
                            576 LOAD_METHOD             11 (_translate)
                            598 LOAD_FAST                1 (text)
                            600 LOAD_DEREF               3 (dest)
                            602 LOAD_DEREF               2 (src)
                            604 LOAD_CONST               0 (None)
                            606 PRECALL                  4
                            610 CALL                     4
                            620 UNPACK_SEQUENCE          2
                            624 STORE_FAST              11 (data)
                            626 STORE_FAST              12 (response)
                            628 JUMP_FORWARD            57 (to 744)
                        >>  630 PUSH_EXC_INFO
                
-               194         632 LOAD_GLOBAL             24 (ConnectError)
+               193         632 LOAD_GLOBAL             24 (ConnectError)
                            644 CHECK_EXC_MATCH
                            646 POP_JUMP_FORWARD_IF_FALSE    44 (to 736)
                            648 POP_TOP
                
-               195         650 LOAD_GLOBAL             14 (bp)
+               194         650 LOAD_GLOBAL             14 (bp)
                            662 LOAD_ATTR                8 (LOGGER)
                            672 LOAD_METHOD             13 (warning)
                            694 LOAD_CONST               8 ("Couldn't translate ")
                            696 LOAD_FAST                1 (text)
                            698 FORMAT_VALUE             0
                            700 LOAD_CONST               9 (' from ')
                            702 LOAD_DEREF               2 (src)
@@ -1559,26 +1551,26 @@
                            708 LOAD_DEREF               3 (dest)
                            710 FORMAT_VALUE             0
                            712 BUILD_STRING             6
                            714 PRECALL                  1
                            718 CALL                     1
                            728 POP_TOP
                
-               196         730 POP_EXCEPT
+               195         730 POP_EXCEPT
                            732 LOAD_CONST               7 ('')
                            734 RETURN_VALUE
                
-               194     >>  736 RERAISE                  0
+               193     >>  736 RERAISE                  0
                        >>  738 COPY                     3
                            740 POP_EXCEPT
                            742 RERAISE                  1
                
-               199     >>  744 LOAD_CONST               7 ('')
+               198     >>  744 LOAD_CONST               7 ('')
                            746 LOAD_METHOD              3 (join)
-                           768 LOAD_CONST              11 (<code object <listcomp>, file "C:\Users\symrb\Documents\dev\python\baopig\baopig\googletrans\extension.py", line 199>)
+                           768 LOAD_CONST              11 (<code object <listcomp>, file "C:\Users\symrb\Documents\dev\python\baopig\baopig\googletrans\extension.py", line 198>)
                            770 MAKE_FUNCTION            0
                            772 LOAD_FAST               11 (data)
                            774 LOAD_CONST              12 (0)
                            776 BINARY_SUBSCR
                            786 GET_ITER
                            788 PRECALL                  0
                            792 CALL                     0
@@ -1603,15 +1595,15 @@
                      flags     : 51
                      code
                         0x95034b00010097007c005d1c7d018903a0000000000000000000000000
                         0000000000000000007c0189048902ac00a6030000ab0300000000000000
                         005600970101008c1d64015300
                                    0 COPY_FREE_VARS           3
                      
-                     186           2 RETURN_GENERATOR
+                     185           2 RETURN_GENERATOR
                                    4 POP_TOP
                                    6 RESUME                   0
                                    8 LOAD_FAST                0 (.0)
                              >>   10 FOR_ITER                28 (to 68)
                                   12 STORE_FAST               1 (t)
                                   14 LOAD_DEREF               3 (self)
                                   16 LOAD_METHOD              0 (optimized_translate)
@@ -1632,29 +1624,29 @@
                         None
                      names      ('optimized_translate',)
                      varnames   ('.0', 't')
                      freevars   ('dest', 'self', 'src')
                      cellvars   ()
                      filename   'C:\\Users\\symrb\\Documents\\dev\\python\\baopig\\baopig\\googletrans\\extension.py'
                      name       '<genexpr>'
-                     firstlineno 186
+                     firstlineno 185
                      lnotab 0x
                   ''
                   "Couldn't translate "
                   ' from '
                   ' to '
                   code
                      argcount  : 1
                      nlocals   : 2
                      stacksize : 4
                      flags     : 19
                      code
                         0x970067007c005d147d017c0164001900000000000000000072087c0164
                         00190000000000000000006e01640191028c155300
-                     199           0 RESUME                   0
+                     198           0 RESUME                   0
                                    2 BUILD_LIST               0
                                    4 LOAD_FAST                0 (.0)
                              >>    6 FOR_ITER                20 (to 48)
                                    8 STORE_FAST               1 (d)
                                   10 LOAD_FAST                1 (d)
                                   12 LOAD_CONST               0 (0)
                                   14 BINARY_SUBSCR
@@ -1672,24 +1664,24 @@
                         ''
                      names      ()
                      varnames   ('.0', 'd')
                      freevars   ()
                      cellvars   ()
                      filename   'C:\\Users\\symrb\\Documents\\dev\\python\\baopig\\baopig\\googletrans\\extension.py'
                      name       '<listcomp>'
-                     firstlineno 199
+                     firstlineno 198
                      lnotab 0x
                   0
                names      ('isinstance', 'list', 'len', 'join', 'replace', 'optimized_translate', 'split', 'bp', 'LOGGER', 'info', 'tuple', '_translate', 'ConnectError', 'warning')
                varnames   ('self', 'text', 'src', 'dest', 'sep', 'sep_transition', 'sep_encoded', 'ln', 'joined', 'joined_translated', 'result', 'data', 'response')
                freevars   ()
                cellvars   ('self', 'src', 'dest')
                filename   'C:\\Users\\symrb\\Documents\\dev\\python\\baopig\\baopig\\googletrans\\extension.py'
                name       'optimized_translate'
-               firstlineno 166
+               firstlineno 165
                lnotab
                   0x08022c020401040104011e012a012c012c0130012c012c012a01260104
                   023e023a020401040202013a021201500106fe0805
             code
                argcount  : 1
                nlocals   : 1
                stacksize : 6
@@ -1697,45 +1689,45 @@
                code
                   0x950197000900740100000000000000000000a6000000ab000000000000
                   000000a00100000000000000000000000000000000000000006401640264
                   036400ac04a6040000ab0400000000000000000100640553002300740400
                   0000000000000000002400720401005900640653007700780359007701
                              0 COPY_FREE_VARS           1
                
-               201           2 RESUME                   0
+               200           2 RESUME                   0
                
-               203           4 NOP
+               202           4 NOP
                
-               204           6 LOAD_GLOBAL              1 (NULL + super)
+               203           6 LOAD_GLOBAL              1 (NULL + super)
                             18 PRECALL                  0
                             22 CALL                     0
                             32 LOAD_METHOD              1 (_translate)
                             54 LOAD_CONST               1 ('Bonjour')
                             56 LOAD_CONST               2 ('fr')
                             58 LOAD_CONST               3 ('en')
                             60 LOAD_CONST               0 (None)
                             62 KW_NAMES                 4
                             64 PRECALL                  4
                             68 CALL                     4
                             78 POP_TOP
                
-               208          80 LOAD_CONST               5 (True)
+               207          80 LOAD_CONST               5 (True)
                             82 RETURN_VALUE
                        >>   84 PUSH_EXC_INFO
                
-               205          86 LOAD_GLOBAL              4 (ConnectError)
+               204          86 LOAD_GLOBAL              4 (ConnectError)
                             98 CHECK_EXC_MATCH
                            100 POP_JUMP_FORWARD_IF_FALSE     4 (to 110)
                            102 POP_TOP
                
-               206         104 POP_EXCEPT
+               205         104 POP_EXCEPT
                            106 LOAD_CONST               6 (False)
                            108 RETURN_VALUE
                
-               205     >>  110 RERAISE                  0
+               204     >>  110 RERAISE                  0
                        >>  112 COPY                     3
                            114 POP_EXCEPT
                            116 RERAISE                  1
                ExceptionTable:
                  6 to 78 -> 84 [0]
                  84 to 102 -> 112 [1] lasti
                  110 to 110 -> 112 [1] lasti
@@ -1749,26 +1741,26 @@
                   False
                names      ('super', '_translate', 'ConnectError')
                varnames   ('self',)
                freevars   ('__class__',)
                cellvars   ()
                filename   'C:\\Users\\symrb\\Documents\\dev\\python\\baopig\\baopig\\googletrans\\extension.py'
                name       'test_connection'
-               firstlineno 201
+               firstlineno 200
                lnotab 0x040202014a0406fd120106ff
          names      ('__name__', '__module__', '__qualname__', 'optimized_translate', 'test_connection', '__classcell__')
          varnames   ()
          freevars   ()
          cellvars   ('__class__',)
          filename   'C:\\Users\\symrb\\Documents\\dev\\python\\baopig\\baopig\\googletrans\\extension.py'
          name       'OptimizedTranslator'
-         firstlineno 164
+         firstlineno 163
          lnotab 0x0c020623
       'OptimizedTranslator'
    names      ('os', 'sys', 'importlib', 'httpcore', 'ConnectError', 'baopig', 'bp', 'client', 'Translator', 'dict', 'Dictionnary', 'Communicative', 'LangManager', 'OptimizedTranslator', 'dicts', 'lang_manager', 'translator')
    varnames   ()
    freevars   ()
    cellvars   ()
    filename   'C:\\Users\\symrb\\Documents\\dev\\python\\baopig\\baopig\\googletrans\\extension.py'
    name       '<module>'
    firstlineno 1
-   lnotab 0x00ff02010801080108010c0108010c031c4226591c2f04011401
+   lnotab 0x00ff02010801080108010c0108010c031c4126591c2f04011401
```

## baopig/lib/__init__.py

```diff
@@ -1,11 +1,10 @@
 from .style import Theme
 from .utilities import *
-from .widget import Widget, Communicative
-from .widget_supers import DraggableByMouse, Focusable, HoverableByMouse, LinkableByMouse, \
+from .widget_supers import DraggableByMouse, Focusable, HoverableByMouse, LinkableByMouse, MaintainableByFocus, \
     RepetivelyAnimated, Runable, Validable
 from .imagewidget import Image
 from .shapes import Rectangle, Highlighter, Polygon, Line, Circle
 from .layer import Layer
 from .gridlayer import GridLayer
 from .layersmanager import LayersManager
 from .container import Container
```

## baopig/lib/widget_supers.py

```diff
@@ -186,14 +186,53 @@
         d = 1 if keyboard.mod.maj == 0 else -1
 
         if len(all_focs) > 1:
             all_focs.sort(key=lambda c: (c.rect.top, c.rect.left))
             self.scene.focus(all_focs[(all_focs.index(self) + d) % len(all_focs)])
 
 
+class MaintainableByFocus(Widget):
+    """ Class for widgets who need to be open as long as they have a focused maintainer """
+
+    def __init__(self, parent, is_valid_maintainer):
+
+        Widget.__init__(self, parent)
+
+        self._maintainer_ref = lambda: None  # this is the child that is focused
+        self.is_valid_maintainer = is_valid_maintainer
+
+    maintainer = property(lambda self: self._maintainer_ref())
+
+    def _handle_maintainer_defocus(self):
+
+        self.maintainer.signal.DEFOCUS.disconnect(self._handle_maintainer_defocus)
+
+        focused_widget = self.scene.focused_widget
+        if focused_widget is None:
+            return self.close()
+
+        if self.is_valid_maintainer(focused_widget):
+            self._maintainer_ref = focused_widget.get_weakref()
+            self.maintainer.signal.DEFOCUS.connect(self._handle_maintainer_defocus, owner=self)
+
+        else:
+            self.close()
+
+    def close(self):
+        """ Stuff to do when there is no focused maintainer anymore """
+
+    def open(self, maintainer):
+
+        if not self.is_valid_maintainer(maintainer):
+            raise PermissionError(f"Invalid maintainer : {maintainer}")
+
+        self._maintainer_ref = maintainer.get_weakref()
+        self.maintainer.signal.DEFOCUS.connect(self._handle_maintainer_defocus, owner=self)
+
+
 class DraggableByMouse(LinkableByMouse):
     """
     Class for widgets who want to be moved by mouse
     """
 
     def handle_link_motion(self, rel):
         self.move(*rel)
```

## baopig/lib/__pycache__/__init__.cpython-311.pyc

### Python bytecode

```diff
@@ -1,24 +1,24 @@
 magic:    0xa70d0d0a
-moddate:  0x4dd8d762 (Wed Jul 20 10:26:21 2022 UTC)
-files sz: 617
+moddate:  0x03eb4364 (Sat Apr 22 14:11:15 2023 UTC)
+files sz: 638
 code
    argcount  : 0
    nlocals   : 0
    stacksize : 2
    flags     : 0
    code
       0x9700640064016c006d015a010100640064026c025400640064036c036d
       045a046d055a050100640064046c066d075a076d085a086d095a096d0a5a
-      0a6d0b5a0b6d0c5a0c6d0d5a0d0100640064056c0e6d0f5a0f0100640064
-      066c106d115a116d125a126d135a136d145a146d155a150100640064076c
-      166d175a170100640064086c186d195a190100640064096c1a6d1b5a1b01
-      006400640a6c1c6d1d5a1d01006400640b6c1e6d1f5a1f6d205a20010064
-      00640c6c216d225a226d235a236d245a2401006400640d6c256d265a2601
-      006400640e6c276d285a280100640f5300
+      0a6d0b5a0b6d0c5a0c6d0d5a0d6d0e5a0e0100640064056c0f6d105a1001
+      00640064066c116d125a126d135a136d145a146d155a156d165a16010064
+      0064076c176d185a180100640064086c196d1a5a1a0100640064096c1b6d
+      1c5a1c01006400640a6c1d6d1e5a1e01006400640b6c1f6d205a206d215a
+      2101006400640c6c226d235a236d245a246d255a2501006400640d6c266d
+      275a2701006400640e6c286d295a290100640f5300
      0           0 RESUME                   0
    
      1           2 LOAD_CONST               0 (1)
                  4 LOAD_CONST               1 (('Theme',))
                  6 IMPORT_NAME              0 (style)
                  8 IMPORT_FROM              1 (Theme)
                 10 STORE_NAME               1 (Theme)
@@ -35,137 +35,139 @@
                 28 IMPORT_FROM              4 (Widget)
                 30 STORE_NAME               4 (Widget)
                 32 IMPORT_FROM              5 (Communicative)
                 34 STORE_NAME               5 (Communicative)
                 36 POP_TOP
    
      4          38 LOAD_CONST               0 (1)
-                40 LOAD_CONST               4 (('DraggableByMouse', 'Focusable', 'HoverableByMouse', 'LinkableByMouse', 'RepetivelyAnimated', 'Runable', 'Validable'))
+                40 LOAD_CONST               4 (('DraggableByMouse', 'Focusable', 'HoverableByMouse', 'LinkableByMouse', 'MaintainableByFocus', 'RepetivelyAnimated', 'Runable', 'Validable'))
                 42 IMPORT_NAME              6 (widget_supers)
                 44 IMPORT_FROM              7 (DraggableByMouse)
                 46 STORE_NAME               7 (DraggableByMouse)
                 48 IMPORT_FROM              8 (Focusable)
                 50 STORE_NAME               8 (Focusable)
                 52 IMPORT_FROM              9 (HoverableByMouse)
                 54 STORE_NAME               9 (HoverableByMouse)
                 56 IMPORT_FROM             10 (LinkableByMouse)
                 58 STORE_NAME              10 (LinkableByMouse)
-                60 IMPORT_FROM             11 (RepetivelyAnimated)
-                62 STORE_NAME              11 (RepetivelyAnimated)
-                64 IMPORT_FROM             12 (Runable)
-                66 STORE_NAME              12 (Runable)
-                68 IMPORT_FROM             13 (Validable)
-                70 STORE_NAME              13 (Validable)
-                72 POP_TOP
-   
-     6          74 LOAD_CONST               0 (1)
-                76 LOAD_CONST               5 (('Image',))
-                78 IMPORT_NAME             14 (imagewidget)
-                80 IMPORT_FROM             15 (Image)
-                82 STORE_NAME              15 (Image)
-                84 POP_TOP
-   
-     7          86 LOAD_CONST               0 (1)
-                88 LOAD_CONST               6 (('Rectangle', 'Highlighter', 'Polygon', 'Line', 'Circle'))
-                90 IMPORT_NAME             16 (shapes)
-                92 IMPORT_FROM             17 (Rectangle)
-                94 STORE_NAME              17 (Rectangle)
-                96 IMPORT_FROM             18 (Highlighter)
-                98 STORE_NAME              18 (Highlighter)
-               100 IMPORT_FROM             19 (Polygon)
-               102 STORE_NAME              19 (Polygon)
-               104 IMPORT_FROM             20 (Line)
-               106 STORE_NAME              20 (Line)
-               108 IMPORT_FROM             21 (Circle)
-               110 STORE_NAME              21 (Circle)
-               112 POP_TOP
-   
-     8         114 LOAD_CONST               0 (1)
-               116 LOAD_CONST               7 (('Layer',))
-               118 IMPORT_NAME             22 (layer)
-               120 IMPORT_FROM             23 (Layer)
-               122 STORE_NAME              23 (Layer)
-               124 POP_TOP
-   
-     9         126 LOAD_CONST               0 (1)
-               128 LOAD_CONST               8 (('GridLayer',))
-               130 IMPORT_NAME             24 (gridlayer)
-               132 IMPORT_FROM             25 (GridLayer)
-               134 STORE_NAME              25 (GridLayer)
-               136 POP_TOP
-   
-    10         138 LOAD_CONST               0 (1)
-               140 LOAD_CONST               9 (('LayersManager',))
-               142 IMPORT_NAME             26 (layersmanager)
-               144 IMPORT_FROM             27 (LayersManager)
-               146 STORE_NAME              27 (LayersManager)
-               148 POP_TOP
-   
-    11         150 LOAD_CONST               0 (1)
-               152 LOAD_CONST              10 (('Container',))
-               154 IMPORT_NAME             28 (container)
-               156 IMPORT_FROM             29 (Container)
-               158 STORE_NAME              29 (Container)
-               160 POP_TOP
-   
-    12         162 LOAD_CONST               0 (1)
-               164 LOAD_CONST              11 (('Zone', 'SubZone'))
-               166 IMPORT_NAME             30 (zone)
-               168 IMPORT_FROM             31 (Zone)
-               170 STORE_NAME              31 (Zone)
-               172 IMPORT_FROM             32 (SubZone)
-               174 STORE_NAME              32 (SubZone)
-               176 POP_TOP
-   
-    13         178 LOAD_CONST               0 (1)
-               180 LOAD_CONST              12 (('SelectableWidget', 'Selector', 'SelectionRect'))
-               182 IMPORT_NAME             33 (selections)
-               184 IMPORT_FROM             34 (SelectableWidget)
-               186 STORE_NAME              34 (SelectableWidget)
-               188 IMPORT_FROM             35 (Selector)
-               190 STORE_NAME              35 (Selector)
-               192 IMPORT_FROM             36 (SelectionRect)
-               194 STORE_NAME              36 (SelectionRect)
-               196 POP_TOP
-   
-    14         198 LOAD_CONST               0 (1)
-               200 LOAD_CONST              13 (('Scene',))
-               202 IMPORT_NAME             37 (scene)
-               204 IMPORT_FROM             38 (Scene)
-               206 STORE_NAME              38 (Scene)
-               208 POP_TOP
-   
-    15         210 LOAD_CONST               0 (1)
-               212 LOAD_CONST              14 (('Application',))
-               214 IMPORT_NAME             39 (application)
-               216 IMPORT_FROM             40 (Application)
-               218 STORE_NAME              40 (Application)
-               220 POP_TOP
-               222 LOAD_CONST              15 (None)
-               224 RETURN_VALUE
+                60 IMPORT_FROM             11 (MaintainableByFocus)
+                62 STORE_NAME              11 (MaintainableByFocus)
+                64 IMPORT_FROM             12 (RepetivelyAnimated)
+                66 STORE_NAME              12 (RepetivelyAnimated)
+                68 IMPORT_FROM             13 (Runable)
+                70 STORE_NAME              13 (Runable)
+                72 IMPORT_FROM             14 (Validable)
+                74 STORE_NAME              14 (Validable)
+                76 POP_TOP
+   
+     6          78 LOAD_CONST               0 (1)
+                80 LOAD_CONST               5 (('Image',))
+                82 IMPORT_NAME             15 (imagewidget)
+                84 IMPORT_FROM             16 (Image)
+                86 STORE_NAME              16 (Image)
+                88 POP_TOP
+   
+     7          90 LOAD_CONST               0 (1)
+                92 LOAD_CONST               6 (('Rectangle', 'Highlighter', 'Polygon', 'Line', 'Circle'))
+                94 IMPORT_NAME             17 (shapes)
+                96 IMPORT_FROM             18 (Rectangle)
+                98 STORE_NAME              18 (Rectangle)
+               100 IMPORT_FROM             19 (Highlighter)
+               102 STORE_NAME              19 (Highlighter)
+               104 IMPORT_FROM             20 (Polygon)
+               106 STORE_NAME              20 (Polygon)
+               108 IMPORT_FROM             21 (Line)
+               110 STORE_NAME              21 (Line)
+               112 IMPORT_FROM             22 (Circle)
+               114 STORE_NAME              22 (Circle)
+               116 POP_TOP
+   
+     8         118 LOAD_CONST               0 (1)
+               120 LOAD_CONST               7 (('Layer',))
+               122 IMPORT_NAME             23 (layer)
+               124 IMPORT_FROM             24 (Layer)
+               126 STORE_NAME              24 (Layer)
+               128 POP_TOP
+   
+     9         130 LOAD_CONST               0 (1)
+               132 LOAD_CONST               8 (('GridLayer',))
+               134 IMPORT_NAME             25 (gridlayer)
+               136 IMPORT_FROM             26 (GridLayer)
+               138 STORE_NAME              26 (GridLayer)
+               140 POP_TOP
+   
+    10         142 LOAD_CONST               0 (1)
+               144 LOAD_CONST               9 (('LayersManager',))
+               146 IMPORT_NAME             27 (layersmanager)
+               148 IMPORT_FROM             28 (LayersManager)
+               150 STORE_NAME              28 (LayersManager)
+               152 POP_TOP
+   
+    11         154 LOAD_CONST               0 (1)
+               156 LOAD_CONST              10 (('Container',))
+               158 IMPORT_NAME             29 (container)
+               160 IMPORT_FROM             30 (Container)
+               162 STORE_NAME              30 (Container)
+               164 POP_TOP
+   
+    12         166 LOAD_CONST               0 (1)
+               168 LOAD_CONST              11 (('Zone', 'SubZone'))
+               170 IMPORT_NAME             31 (zone)
+               172 IMPORT_FROM             32 (Zone)
+               174 STORE_NAME              32 (Zone)
+               176 IMPORT_FROM             33 (SubZone)
+               178 STORE_NAME              33 (SubZone)
+               180 POP_TOP
+   
+    13         182 LOAD_CONST               0 (1)
+               184 LOAD_CONST              12 (('SelectableWidget', 'Selector', 'SelectionRect'))
+               186 IMPORT_NAME             34 (selections)
+               188 IMPORT_FROM             35 (SelectableWidget)
+               190 STORE_NAME              35 (SelectableWidget)
+               192 IMPORT_FROM             36 (Selector)
+               194 STORE_NAME              36 (Selector)
+               196 IMPORT_FROM             37 (SelectionRect)
+               198 STORE_NAME              37 (SelectionRect)
+               200 POP_TOP
+   
+    14         202 LOAD_CONST               0 (1)
+               204 LOAD_CONST              13 (('Scene',))
+               206 IMPORT_NAME             38 (scene)
+               208 IMPORT_FROM             39 (Scene)
+               210 STORE_NAME              39 (Scene)
+               212 POP_TOP
+   
+    15         214 LOAD_CONST               0 (1)
+               216 LOAD_CONST              14 (('Application',))
+               218 IMPORT_NAME             40 (application)
+               220 IMPORT_FROM             41 (Application)
+               222 STORE_NAME              41 (Application)
+               224 POP_TOP
+               226 LOAD_CONST              15 (None)
+               228 RETURN_VALUE
    consts
       1
       ('Theme',)
       ('*',)
       ('Widget', 'Communicative')
-      ('DraggableByMouse', 'Focusable', 'HoverableByMouse', 'LinkableByMouse', 'RepetivelyAnimated', 'Runable', 'Validable')
+      ('DraggableByMouse', 'Focusable', 'HoverableByMouse', 'LinkableByMouse', 'MaintainableByFocus', 'RepetivelyAnimated', 'Runable', 'Validable')
       ('Image',)
       ('Rectangle', 'Highlighter', 'Polygon', 'Line', 'Circle')
       ('Layer',)
       ('GridLayer',)
       ('LayersManager',)
       ('Container',)
       ('Zone', 'SubZone')
       ('SelectableWidget', 'Selector', 'SelectionRect')
       ('Scene',)
       ('Application',)
       None
-   names      ('style', 'Theme', 'utilities', 'widget', 'Widget', 'Communicative', 'widget_supers', 'DraggableByMouse', 'Focusable', 'HoverableByMouse', 'LinkableByMouse', 'RepetivelyAnimated', 'Runable', 'Validable', 'imagewidget', 'Image', 'shapes', 'Rectangle', 'Highlighter', 'Polygon', 'Line', 'Circle', 'layer', 'Layer', 'gridlayer', 'GridLayer', 'layersmanager', 'LayersManager', 'container', 'Container', 'zone', 'Zone', 'SubZone', 'selections', 'SelectableWidget', 'Selector', 'SelectionRect', 'scene', 'Scene', 'application', 'Application')
+   names      ('style', 'Theme', 'utilities', 'widget', 'Widget', 'Communicative', 'widget_supers', 'DraggableByMouse', 'Focusable', 'HoverableByMouse', 'LinkableByMouse', 'MaintainableByFocus', 'RepetivelyAnimated', 'Runable', 'Validable', 'imagewidget', 'Image', 'shapes', 'Rectangle', 'Highlighter', 'Polygon', 'Line', 'Circle', 'layer', 'Layer', 'gridlayer', 'GridLayer', 'layersmanager', 'LayersManager', 'container', 'Container', 'zone', 'Zone', 'SubZone', 'selections', 'SelectableWidget', 'Selector', 'SelectionRect', 'scene', 'Scene', 'application', 'Application')
    varnames   ()
    freevars   ()
    cellvars   ()
    filename   'C:\\Users\\symrb\\Documents\\dev\\python\\baopig\\baopig\\lib\\__init__.py'
    name       '<module>'
    firstlineno 1
    lnotab
-      0x00ff02010c010801100124020c011c010c010c010c010c01100114010c
+      0x00ff02010c010801100128020c011c010c010c010c010c01100114010c
       01
```

## baopig/lib/__pycache__/widget_supers.cpython-311.pyc

### Python bytecode

```diff
@@ -1,10 +1,10 @@
 magic:    0xa70d0d0a
-moddate:  0x7363bf63 (Thu Jan 12 01:33:39 2023 UTC)
-files sz: 8555
+moddate:  0xddea4364 (Sat Apr 22 14:10:37 2023 UTC)
+files sz: 9919
 code
    argcount  : 0
    nlocals   : 0
    stacksize : 6
    flags     : 0
    code
       0x9700640064016c005a00640064026c016d025a026d035a036d045a0401
@@ -12,17 +12,18 @@
       0064056c056d0a5a0b0100640064066c056d0c5a0d0100640064076c056d
       0e5a0f0100640064086c056d105a110100640064096c126d135a13010064
       0a640b6c146d155a15010002004700640c8400640d6511a6030000ab0300
       000000000000005a1002004700640e8400640f650f6515a6040000ab0400
       000000000000005a0e02004700641084006411650b6515a6040000ab0400
       000000000000005a0a02004700641284006413650d650aa6040000ab0400
       000000000000005a0c020047006414840064156509650ca6040000ab0400
-      000000000000005a0802004700641684006417650ca6030000ab03000000
-      00000000005a16020047006418840064196515a6030000ab030000000000
-      0000005a1764015300
+      000000000000005a08020047006416840064176515a6030000ab03000000
+      00000000005a1602004700641884006419650ca6030000ab030000000000
+      0000005a1702004700641a8400641b6515a6030000ab0300000000000000
+      005a1864015300
      0           0 RESUME                   0
    
      1           2 LOAD_CONST               0 (0)
                  4 LOAD_CONST               1 (None)
                  6 IMPORT_NAME              0 (pygame)
                  8 STORE_NAME               0 (pygame)
    
@@ -147,33 +148,43 @@
                260 LOAD_NAME               12 (LinkableByMouse)
                262 PRECALL                  4
                266 CALL                     4
                276 STORE_NAME               8 (Focusable)
    
    193         278 PUSH_NULL
                280 LOAD_BUILD_CLASS
-               282 LOAD_CONST              22 (<code object DraggableByMouse, file "C:\Users\symrb\Documents\dev\python\baopig\baopig\lib\widget_supers.py", line 193>)
+               282 LOAD_CONST              22 (<code object MaintainableByFocus, file "C:\Users\symrb\Documents\dev\python\baopig\baopig\lib\widget_supers.py", line 193>)
                284 MAKE_FUNCTION            0
-               286 LOAD_CONST              23 ('DraggableByMouse')
-               288 LOAD_NAME               12 (LinkableByMouse)
+               286 LOAD_CONST              23 ('MaintainableByFocus')
+               288 LOAD_NAME               21 (Widget)
                290 PRECALL                  3
                294 CALL                     3
-               304 STORE_NAME              22 (DraggableByMouse)
+               304 STORE_NAME              22 (MaintainableByFocus)
    
-   202         306 PUSH_NULL
+   232         306 PUSH_NULL
                308 LOAD_BUILD_CLASS
-               310 LOAD_CONST              24 (<code object RepetivelyAnimated, file "C:\Users\symrb\Documents\dev\python\baopig\baopig\lib\widget_supers.py", line 202>)
+               310 LOAD_CONST              24 (<code object DraggableByMouse, file "C:\Users\symrb\Documents\dev\python\baopig\baopig\lib\widget_supers.py", line 232>)
                312 MAKE_FUNCTION            0
-               314 LOAD_CONST              25 ('RepetivelyAnimated')
-               316 LOAD_NAME               21 (Widget)
+               314 LOAD_CONST              25 ('DraggableByMouse')
+               316 LOAD_NAME               12 (LinkableByMouse)
                318 PRECALL                  3
                322 CALL                     3
-               332 STORE_NAME              23 (RepetivelyAnimated)
-               334 LOAD_CONST               1 (None)
-               336 RETURN_VALUE
+               332 STORE_NAME              23 (DraggableByMouse)
+   
+   241         334 PUSH_NULL
+               336 LOAD_BUILD_CLASS
+               338 LOAD_CONST              26 (<code object RepetivelyAnimated, file "C:\Users\symrb\Documents\dev\python\baopig\baopig\lib\widget_supers.py", line 241>)
+               340 MAKE_FUNCTION            0
+               342 LOAD_CONST              27 ('RepetivelyAnimated')
+               344 LOAD_NAME               21 (Widget)
+               346 PRECALL                  3
+               350 CALL                     3
+               360 STORE_NAME              24 (RepetivelyAnimated)
+               362 LOAD_CONST               1 (None)
+               364 RETURN_VALUE
    consts
       0
       None
       ('LOGGER', 'mouse', 'keyboard')
       ('ApplicationExit', 'Selector')
       ('Focusable',)
       ('HoverableByMouse',)
@@ -1430,43 +1441,359 @@
          name       'Focusable'
          firstlineno 128
          lnotab 0x0a02060c18020605060306051802060e
       'Focusable'
       code
          argcount  : 0
          nlocals   : 0
+         stacksize : 3
+         flags     : 0
+         code
+            0x970065005a0164005a0264015a03640284005a040200650564038400a6
+            010000ab0100000000000000005a06640484005a07640584005a08640684
+            005a0964075300
+         193           0 RESUME                   0
+                       2 LOAD_NAME                0 (__name__)
+                       4 STORE_NAME               1 (__module__)
+                       6 LOAD_CONST               0 ('MaintainableByFocus')
+                       8 STORE_NAME               2 (__qualname__)
+         
+         194          10 LOAD_CONST               1 (' Class for widgets who need to be open as long as they have a focused maintainer ')
+                      12 STORE_NAME               3 (__doc__)
+         
+         196          14 LOAD_CONST               2 (<code object __init__, file "C:\Users\symrb\Documents\dev\python\baopig\baopig\lib\widget_supers.py", line 196>)
+                      16 MAKE_FUNCTION            0
+                      18 STORE_NAME               4 (__init__)
+         
+         203          20 PUSH_NULL
+                      22 LOAD_NAME                5 (property)
+                      24 LOAD_CONST               3 (<code object <lambda>, file "C:\Users\symrb\Documents\dev\python\baopig\baopig\lib\widget_supers.py", line 203>)
+                      26 MAKE_FUNCTION            0
+                      28 PRECALL                  1
+                      32 CALL                     1
+                      42 STORE_NAME               6 (maintainer)
+         
+         205          44 LOAD_CONST               4 (<code object _handle_maintainer_defocus, file "C:\Users\symrb\Documents\dev\python\baopig\baopig\lib\widget_supers.py", line 205>)
+                      46 MAKE_FUNCTION            0
+                      48 STORE_NAME               7 (_handle_maintainer_defocus)
+         
+         220          50 LOAD_CONST               5 (<code object close, file "C:\Users\symrb\Documents\dev\python\baopig\baopig\lib\widget_supers.py", line 220>)
+                      52 MAKE_FUNCTION            0
+                      54 STORE_NAME               8 (close)
+         
+         223          56 LOAD_CONST               6 (<code object open, file "C:\Users\symrb\Documents\dev\python\baopig\baopig\lib\widget_supers.py", line 223>)
+                      58 MAKE_FUNCTION            0
+                      60 STORE_NAME               9 (open)
+                      62 LOAD_CONST               7 (None)
+                      64 RETURN_VALUE
+         consts
+            'MaintainableByFocus'
+            ' Class for widgets who need to be open as long as they have a focused maintainer '
+            code
+               argcount  : 3
+               nlocals   : 3
+               stacksize : 4
+               flags     : 3
+               code
+                  0x97007401000000000000000000006a0100000000000000007c007c01a6
+                  020000ab0200000000000000000100640184007c005f0200000000000000
+                  007c027c005f03000000000000000064005300
+               196           0 RESUME                   0
+               
+               198           2 LOAD_GLOBAL              1 (NULL + Widget)
+                            14 LOAD_ATTR                1 (__init__)
+                            24 LOAD_FAST                0 (self)
+                            26 LOAD_FAST                1 (parent)
+                            28 PRECALL                  2
+                            32 CALL                     2
+                            42 POP_TOP
+               
+               200          44 LOAD_CONST               1 (<code object <lambda>, file "C:\Users\symrb\Documents\dev\python\baopig\baopig\lib\widget_supers.py", line 200>)
+                            46 MAKE_FUNCTION            0
+                            48 LOAD_FAST                0 (self)
+                            50 STORE_ATTR               2 (_maintainer_ref)
+               
+               201          60 LOAD_FAST                2 (is_valid_maintainer)
+                            62 LOAD_FAST                0 (self)
+                            64 STORE_ATTR               3 (is_valid_maintainer)
+                            74 LOAD_CONST               0 (None)
+                            76 RETURN_VALUE
+               consts
+                  None
+                  code
+                     argcount  : 0
+                     nlocals   : 0
+                     stacksize : 1
+                     flags     : 19
+                     code 0x970064005300
+                     200           0 RESUME                   0
+                                   2 LOAD_CONST               0 (None)
+                                   4 RETURN_VALUE
+                     consts
+                        None
+                     names      ()
+                     varnames   ()
+                     freevars   ()
+                     cellvars   ()
+                     filename   'C:\\Users\\symrb\\Documents\\dev\\python\\baopig\\baopig\\lib\\widget_supers.py'
+                     name       '<lambda>'
+                     firstlineno 200
+                     lnotab 0x
+               names      ('Widget', '__init__', '_maintainer_ref', 'is_valid_maintainer')
+               varnames   ('self', 'parent', 'is_valid_maintainer')
+               freevars   ()
+               cellvars   ()
+               filename   'C:\\Users\\symrb\\Documents\\dev\\python\\baopig\\baopig\\lib\\widget_supers.py'
+               name       '__init__'
+               firstlineno 196
+               lnotab 0x02022a021001
+            code
+               argcount  : 1
+               nlocals   : 1
+               stacksize : 2
+               flags     : 3
+               code
+                  0x97007c00a0000000000000000000000000000000000000000000a60000
+                  00ab0000000000000000005300
+               203           0 RESUME                   0
+                             2 LOAD_FAST                0 (self)
+                             4 LOAD_METHOD              0 (_maintainer_ref)
+                            26 PRECALL                  0
+                            30 CALL                     0
+                            40 RETURN_VALUE
+               consts
+                  None
+               names      ('_maintainer_ref',)
+               varnames   ('self',)
+               freevars   ()
+               cellvars   ()
+               filename   'C:\\Users\\symrb\\Documents\\dev\\python\\baopig\\baopig\\lib\\widget_supers.py'
+               name       '<lambda>'
+               firstlineno 203
+               lnotab 0x
+            code
+               argcount  : 1
+               nlocals   : 2
+               stacksize : 4
+               flags     : 3
+               code
+                  0x97007c006a0000000000000000006a0100000000000000006a02000000
+                  0000000000a00300000000000000000000000000000000000000007c006a
+                  040000000000000000a6010000ab01000000000000000001007c006a0500
+                  000000000000006a0600000000000000007d017c0180147c00a007000000
+                  0000000000000000000000000000000000a6000000ab0000000000000000
+                  0053007c00a00800000000000000000000000000000000000000007c01a6
+                  010000ab01000000000000000072467c01a0090000000000000000000000
+                  000000000000000000a6000000ab0000000000000000007c005f0a000000
+                  00000000007c006a0000000000000000006a0100000000000000006a0200
+                  00000000000000a00b00000000000000000000000000000000000000007c
+                  006a0400000000000000007c00ac01a6020000ab02000000000000000001
+                  00640053007c00a0070000000000000000000000000000000000000000a6
+                  000000ab000000000000000000010064005300
+               205           0 RESUME                   0
+               
+               207           2 LOAD_FAST                0 (self)
+                             4 LOAD_ATTR                0 (maintainer)
+                            14 LOAD_ATTR                1 (signal)
+                            24 LOAD_ATTR                2 (DEFOCUS)
+                            34 LOAD_METHOD              3 (disconnect)
+                            56 LOAD_FAST                0 (self)
+                            58 LOAD_ATTR                4 (_handle_maintainer_defocus)
+                            68 PRECALL                  1
+                            72 CALL                     1
+                            82 POP_TOP
+               
+               209          84 LOAD_FAST                0 (self)
+                            86 LOAD_ATTR                5 (scene)
+                            96 LOAD_ATTR                6 (focused_widget)
+                           106 STORE_FAST               1 (focused_widget)
+               
+               210         108 LOAD_FAST                1 (focused_widget)
+                           110 POP_JUMP_FORWARD_IF_NOT_NONE    20 (to 152)
+               
+               211         112 LOAD_FAST                0 (self)
+                           114 LOAD_METHOD              7 (close)
+                           136 PRECALL                  0
+                           140 CALL                     0
+                           150 RETURN_VALUE
+               
+               213     >>  152 LOAD_FAST                0 (self)
+                           154 LOAD_METHOD              8 (is_valid_maintainer)
+                           176 LOAD_FAST                1 (focused_widget)
+                           178 PRECALL                  1
+                           182 CALL                     1
+                           192 POP_JUMP_FORWARD_IF_FALSE    70 (to 334)
+               
+               214         194 LOAD_FAST                1 (focused_widget)
+                           196 LOAD_METHOD              9 (get_weakref)
+                           218 PRECALL                  0
+                           222 CALL                     0
+                           232 LOAD_FAST                0 (self)
+                           234 STORE_ATTR              10 (_maintainer_ref)
+               
+               215         244 LOAD_FAST                0 (self)
+                           246 LOAD_ATTR                0 (maintainer)
+                           256 LOAD_ATTR                1 (signal)
+                           266 LOAD_ATTR                2 (DEFOCUS)
+                           276 LOAD_METHOD             11 (connect)
+                           298 LOAD_FAST                0 (self)
+                           300 LOAD_ATTR                4 (_handle_maintainer_defocus)
+                           310 LOAD_FAST                0 (self)
+                           312 KW_NAMES                 1
+                           314 PRECALL                  2
+                           318 CALL                     2
+                           328 POP_TOP
+                           330 LOAD_CONST               0 (None)
+                           332 RETURN_VALUE
+               
+               218     >>  334 LOAD_FAST                0 (self)
+                           336 LOAD_METHOD              7 (close)
+                           358 PRECALL                  0
+                           362 CALL                     0
+                           372 POP_TOP
+                           374 LOAD_CONST               0 (None)
+                           376 RETURN_VALUE
+               consts
+                  None
+                  ('owner',)
+               names      ('maintainer', 'signal', 'DEFOCUS', 'disconnect', '_handle_maintainer_defocus', 'scene', 'focused_widget', 'close', 'is_valid_maintainer', 'get_weakref', '_maintainer_ref', 'connect')
+               varnames   ('self', 'focused_widget')
+               freevars   ()
+               cellvars   ()
+               filename   'C:\\Users\\symrb\\Documents\\dev\\python\\baopig\\baopig\\lib\\widget_supers.py'
+               name       '_handle_maintainer_defocus'
+               firstlineno 205
+               lnotab 0x020252021801040128022a0132015a03
+            code
+               argcount  : 1
+               nlocals   : 1
+               stacksize : 1
+               flags     : 3
+               code 0x970064015300
+               220           0 RESUME                   0
+                             2 LOAD_CONST               1 (None)
+                             4 RETURN_VALUE
+               consts
+                  ' Stuff to do when there is no focused maintainer anymore '
+                  None
+               names      ()
+               varnames   ('self',)
+               freevars   ()
+               cellvars   ()
+               filename   'C:\\Users\\symrb\\Documents\\dev\\python\\baopig\\baopig\\lib\\widget_supers.py'
+               name       'close'
+               firstlineno 220
+               lnotab 0x
+            code
+               argcount  : 2
+               nlocals   : 2
+               stacksize : 4
+               flags     : 3
+               code
+                  0x97007c00a00000000000000000000000000000000000000000007c01a6
+                  010000ab010000000000000000731274030000000000000000000064017c
+                  019b009d02a6010000ab01000000000000000082017c01a0020000000000
+                  000000000000000000000000000000a6000000ab0000000000000000007c
+                  005f0300000000000000007c006a0400000000000000006a050000000000
+                  0000006a060000000000000000a007000000000000000000000000000000
+                  00000000007c006a0800000000000000007c00ac02a6020000ab02000000
+                  0000000000010064005300
+               223           0 RESUME                   0
+               
+               225           2 LOAD_FAST                0 (self)
+                             4 LOAD_METHOD              0 (is_valid_maintainer)
+                            26 LOAD_FAST                1 (maintainer)
+                            28 PRECALL                  1
+                            32 CALL                     1
+                            42 POP_JUMP_FORWARD_IF_TRUE    18 (to 80)
+               
+               226          44 LOAD_GLOBAL              3 (NULL + PermissionError)
+                            56 LOAD_CONST               1 ('Invalid maintainer : ')
+                            58 LOAD_FAST                1 (maintainer)
+                            60 FORMAT_VALUE             0
+                            62 BUILD_STRING             2
+                            64 PRECALL                  1
+                            68 CALL                     1
+                            78 RAISE_VARARGS            1
+               
+               228     >>   80 LOAD_FAST                1 (maintainer)
+                            82 LOAD_METHOD              2 (get_weakref)
+                           104 PRECALL                  0
+                           108 CALL                     0
+                           118 LOAD_FAST                0 (self)
+                           120 STORE_ATTR               3 (_maintainer_ref)
+               
+               229         130 LOAD_FAST                0 (self)
+                           132 LOAD_ATTR                4 (maintainer)
+                           142 LOAD_ATTR                5 (signal)
+                           152 LOAD_ATTR                6 (DEFOCUS)
+                           162 LOAD_METHOD              7 (connect)
+                           184 LOAD_FAST                0 (self)
+                           186 LOAD_ATTR                8 (_handle_maintainer_defocus)
+                           196 LOAD_FAST                0 (self)
+                           198 KW_NAMES                 2
+                           200 PRECALL                  2
+                           204 CALL                     2
+                           214 POP_TOP
+                           216 LOAD_CONST               0 (None)
+                           218 RETURN_VALUE
+               consts
+                  None
+                  'Invalid maintainer : '
+                  ('owner',)
+               names      ('is_valid_maintainer', 'PermissionError', 'get_weakref', '_maintainer_ref', 'maintainer', 'signal', 'DEFOCUS', 'connect', '_handle_maintainer_defocus')
+               varnames   ('self', 'maintainer')
+               freevars   ()
+               cellvars   ()
+               filename   'C:\\Users\\symrb\\Documents\\dev\\python\\baopig\\baopig\\lib\\widget_supers.py'
+               name       'open'
+               firstlineno 223
+               lnotab 0x02022a0124023201
+            None
+         names      ('__name__', '__module__', '__qualname__', '__doc__', '__init__', 'property', 'maintainer', '_handle_maintainer_defocus', 'close', 'open')
+         varnames   ()
+         freevars   ()
+         cellvars   ()
+         filename   'C:\\Users\\symrb\\Documents\\dev\\python\\baopig\\baopig\\lib\\widget_supers.py'
+         name       'MaintainableByFocus'
+         firstlineno 193
+         lnotab 0x0a01040206071802060f0603
+      'MaintainableByFocus'
+      code
+         argcount  : 0
+         nlocals   : 0
          stacksize : 1
          flags     : 0
          code 0x970065005a0164005a0264015a03640284005a0464035300
-         193           0 RESUME                   0
+         232           0 RESUME                   0
                        2 LOAD_NAME                0 (__name__)
                        4 STORE_NAME               1 (__module__)
                        6 LOAD_CONST               0 ('DraggableByMouse')
                        8 STORE_NAME               2 (__qualname__)
          
-         194          10 LOAD_CONST               1 ('\n    Class for widgets who want to be moved by mouse\n    ')
+         233          10 LOAD_CONST               1 ('\n    Class for widgets who want to be moved by mouse\n    ')
                       12 STORE_NAME               3 (__doc__)
          
-         198          14 LOAD_CONST               2 (<code object handle_link_motion, file "C:\Users\symrb\Documents\dev\python\baopig\baopig\lib\widget_supers.py", line 198>)
+         237          14 LOAD_CONST               2 (<code object handle_link_motion, file "C:\Users\symrb\Documents\dev\python\baopig\baopig\lib\widget_supers.py", line 237>)
                       16 MAKE_FUNCTION            0
                       18 STORE_NAME               4 (handle_link_motion)
                       20 LOAD_CONST               3 (None)
                       22 RETURN_VALUE
          consts
             'DraggableByMouse'
             '\n    Class for widgets who want to be moved by mouse\n    '
             code
                argcount  : 2
                nlocals   : 2
                stacksize : 3
                flags     : 3
                code 0x970002007c006a0000000000000000007c018e00010064005300
-               198           0 RESUME                   0
+               237           0 RESUME                   0
                
-               199           2 PUSH_NULL
+               238           2 PUSH_NULL
                              4 LOAD_FAST                0 (self)
                              6 LOAD_ATTR                0 (move)
                             16 LOAD_FAST                1 (rel)
                             18 CALL_FUNCTION_EX         0
                             20 POP_TOP
                             22 LOAD_CONST               0 (None)
                             24 RETURN_VALUE
@@ -1474,60 +1801,60 @@
                   None
                names      ('move',)
                varnames   ('self', 'rel')
                freevars   ()
                cellvars   ()
                filename   'C:\\Users\\symrb\\Documents\\dev\\python\\baopig\\baopig\\lib\\widget_supers.py'
                name       'handle_link_motion'
-               firstlineno 198
+               firstlineno 237
                lnotab 0x0201
             None
          names      ('__name__', '__module__', '__qualname__', '__doc__', 'handle_link_motion')
          varnames   ()
          freevars   ()
          cellvars   ()
          filename   'C:\\Users\\symrb\\Documents\\dev\\python\\baopig\\baopig\\lib\\widget_supers.py'
          name       'DraggableByMouse'
-         firstlineno 193
+         firstlineno 232
          lnotab 0x0a010404
       'DraggableByMouse'
       code
          argcount  : 0
          nlocals   : 0
          stacksize : 1
          flags     : 0
          code
             0x970065005a0164005a0264015a03640284005a04640384005a05640484
             005a06640584005a07640684005a0864075300
-         202           0 RESUME                   0
+         241           0 RESUME                   0
                        2 LOAD_NAME                0 (__name__)
                        4 STORE_NAME               1 (__module__)
                        6 LOAD_CONST               0 ('RepetivelyAnimated')
                        8 STORE_NAME               2 (__qualname__)
          
-         203          10 LOAD_CONST               1 ('\n    A RepetivelyAnimated is a widget who blinks every interval seconds\n\n    Exemple :\n\n        class Lighthouse(RepetivelyAnimated):\n\n    ')
+         242          10 LOAD_CONST               1 ('\n    A RepetivelyAnimated is a widget who blinks every interval seconds\n\n    Exemple :\n\n        class Lighthouse(RepetivelyAnimated):\n\n    ')
                       12 STORE_NAME               3 (__doc__)
          
-         212          14 LOAD_CONST               2 (<code object __init__, file "C:\Users\symrb\Documents\dev\python\baopig\baopig\lib\widget_supers.py", line 212>)
+         251          14 LOAD_CONST               2 (<code object __init__, file "C:\Users\symrb\Documents\dev\python\baopig\baopig\lib\widget_supers.py", line 251>)
                       16 MAKE_FUNCTION            0
                       18 STORE_NAME               4 (__init__)
          
-         236          20 LOAD_CONST               3 (<code object handle_sleep, file "C:\Users\symrb\Documents\dev\python\baopig\baopig\lib\widget_supers.py", line 236>)
+         275          20 LOAD_CONST               3 (<code object handle_sleep, file "C:\Users\symrb\Documents\dev\python\baopig\baopig\lib\widget_supers.py", line 275>)
                       22 MAKE_FUNCTION            0
                       24 STORE_NAME               5 (handle_sleep)
          
-         241          26 LOAD_CONST               4 (<code object start_animation, file "C:\Users\symrb\Documents\dev\python\baopig\baopig\lib\widget_supers.py", line 241>)
+         280          26 LOAD_CONST               4 (<code object start_animation, file "C:\Users\symrb\Documents\dev\python\baopig\baopig\lib\widget_supers.py", line 280>)
                       28 MAKE_FUNCTION            0
                       30 STORE_NAME               6 (start_animation)
          
-         251          32 LOAD_CONST               5 (<code object stop_animation, file "C:\Users\symrb\Documents\dev\python\baopig\baopig\lib\widget_supers.py", line 251>)
+         290          32 LOAD_CONST               5 (<code object stop_animation, file "C:\Users\symrb\Documents\dev\python\baopig\baopig\lib\widget_supers.py", line 290>)
                       34 MAKE_FUNCTION            0
                       36 STORE_NAME               7 (stop_animation)
          
-         259          38 LOAD_CONST               6 (<code object handle_wake, file "C:\Users\symrb\Documents\dev\python\baopig\baopig\lib\widget_supers.py", line 259>)
+         298          38 LOAD_CONST               6 (<code object handle_wake, file "C:\Users\symrb\Documents\dev\python\baopig\baopig\lib\widget_supers.py", line 298>)
                       40 MAKE_FUNCTION            0
                       42 STORE_NAME               8 (handle_wake)
                       44 LOAD_CONST               7 (None)
                       46 RETURN_VALUE
          consts
             'RepetivelyAnimated'
             '\n    A RepetivelyAnimated is a widget who blinks every interval seconds\n\n    Exemple :\n\n        class Lighthouse(RepetivelyAnimated):\n\n    '
@@ -1550,88 +1877,88 @@
                   0000000000000000000000000000000000000089006a0e00000000000000
                   006404ac05a6020000ab020000000000000000010089006a090000000000
                   0000006a0f0000000000000000a00b000000000000000000000000000000
                   000000000089006a0700000000000000006a1000000000000000006404ac
                   05a6020000ab020000000000000000010064045300
                              0 MAKE_CELL                0 (self)
                
-               212           2 RESUME                   0
+               251           2 RESUME                   0
                
-               218           4 LOAD_GLOBAL              1 (NULL + Widget)
+               257           4 LOAD_GLOBAL              1 (NULL + Widget)
                             16 LOAD_ATTR                1 (__init__)
                             26 LOAD_DEREF               0 (self)
                             28 LOAD_FAST                1 (parent)
                             30 BUILD_TUPLE              2
                             32 BUILD_MAP                0
                             34 LOAD_FAST                3 (kwargs)
                             36 DICT_MERGE               1
                             38 CALL_FUNCTION_EX         1
                             40 POP_TOP
                
-               220          42 LOAD_GLOBAL              5 (NULL + isinstance)
+               259          42 LOAD_GLOBAL              5 (NULL + isinstance)
                             54 LOAD_FAST                2 (interval)
                             56 LOAD_GLOBAL              6 (int)
                             68 LOAD_GLOBAL              8 (float)
                             80 BUILD_TUPLE              2
                             82 PRECALL                  2
                             86 CALL                     2
                             96 POP_JUMP_FORWARD_IF_TRUE    10 (to 118)
                             98 LOAD_ASSERTION_ERROR
                            100 LOAD_CONST               1 ('interval must be a float or an integer')
                            102 PRECALL                  0
                            106 CALL                     0
                            116 RAISE_VARARGS            1
                
-               222     >>  118 LOAD_FAST                2 (interval)
+               261     >>  118 LOAD_FAST                2 (interval)
                            120 LOAD_DEREF               0 (self)
                            122 STORE_ATTR               5 (interval)
                
-               224         132 LOAD_CLOSURE             0 (self)
+               263         132 LOAD_CLOSURE             0 (self)
                            134 BUILD_TUPLE              1
-                           136 LOAD_CONST               2 (<code object blink, file "C:\Users\symrb\Documents\dev\python\baopig\baopig\lib\widget_supers.py", line 224>)
+                           136 LOAD_CONST               2 (<code object blink, file "C:\Users\symrb\Documents\dev\python\baopig\baopig\lib\widget_supers.py", line 263>)
                            138 MAKE_FUNCTION            8 (closure)
                            140 STORE_FAST               4 (blink)
                
-               230         142 LOAD_GLOBAL             13 (NULL + RepeatingTimer)
+               269         142 LOAD_GLOBAL             13 (NULL + RepeatingTimer)
                            154 LOAD_FAST                2 (interval)
                            156 LOAD_FAST                4 (blink)
                            158 PRECALL                  2
                            162 CALL                     2
                            172 LOAD_DEREF               0 (self)
                            174 STORE_ATTR               7 (_countdown_before_blink)
                
-               231         184 LOAD_CONST               3 (False)
+               270         184 LOAD_CONST               3 (False)
                            186 LOAD_DEREF               0 (self)
                            188 STORE_ATTR               8 (_need_start_animation)
                
-               232         198 LOAD_DEREF               0 (self)
+               271         198 LOAD_DEREF               0 (self)
                            200 LOAD_ATTR                9 (signal)
                            210 LOAD_ATTR               10 (SLEEP)
                            220 LOAD_METHOD             11 (connect)
                            242 LOAD_DEREF               0 (self)
                            244 LOAD_ATTR               12 (handle_sleep)
                            254 LOAD_CONST               4 (None)
                            256 KW_NAMES                 5
                            258 PRECALL                  2
                            262 CALL                     2
                            272 POP_TOP
                
-               233         274 LOAD_DEREF               0 (self)
+               272         274 LOAD_DEREF               0 (self)
                            276 LOAD_ATTR                9 (signal)
                            286 LOAD_ATTR               13 (WAKE)
                            296 LOAD_METHOD             11 (connect)
                            318 LOAD_DEREF               0 (self)
                            320 LOAD_ATTR               14 (handle_wake)
                            330 LOAD_CONST               4 (None)
                            332 KW_NAMES                 5
                            334 PRECALL                  2
                            338 CALL                     2
                            348 POP_TOP
                
-               234         350 LOAD_DEREF               0 (self)
+               273         350 LOAD_DEREF               0 (self)
                            352 LOAD_ATTR                9 (signal)
                            362 LOAD_ATTR               15 (KILL)
                            372 LOAD_METHOD             11 (connect)
                            394 LOAD_DEREF               0 (self)
                            396 LOAD_ATTR                7 (_countdown_before_blink)
                            406 LOAD_ATTR               16 (cancel)
                            416 LOAD_CONST               4 (None)
@@ -1652,75 +1979,75 @@
                      code
                         0x9501970089006a00000000000000000072168900a00100000000000000
                         00000000000000000000000000a6000000ab000000000000000000010064
                         0053008900a0020000000000000000000000000000000000000000a60000
                         00ab000000000000000000010064005300
                                    0 COPY_FREE_VARS           1
                      
-                     224           2 RESUME                   0
+                     263           2 RESUME                   0
                      
-                     225           4 LOAD_DEREF               0 (self)
+                     264           4 LOAD_DEREF               0 (self)
                                    6 LOAD_ATTR                0 (is_visible)
                                   16 POP_JUMP_FORWARD_IF_FALSE    22 (to 62)
                      
-                     226          18 LOAD_DEREF               0 (self)
+                     265          18 LOAD_DEREF               0 (self)
                                   20 LOAD_METHOD              1 (hide)
                                   42 PRECALL                  0
                                   46 CALL                     0
                                   56 POP_TOP
                                   58 LOAD_CONST               0 (None)
                                   60 RETURN_VALUE
                      
-                     228     >>   62 LOAD_DEREF               0 (self)
+                     267     >>   62 LOAD_DEREF               0 (self)
                                   64 LOAD_METHOD              2 (show)
                                   86 PRECALL                  0
                                   90 CALL                     0
                                  100 POP_TOP
                                  102 LOAD_CONST               0 (None)
                                  104 RETURN_VALUE
                      consts
                         None
                      names      ('is_visible', 'hide', 'show')
                      varnames   ()
                      freevars   ('self',)
                      cellvars   ()
                      filename   'C:\\Users\\symrb\\Documents\\dev\\python\\baopig\\baopig\\lib\\widget_supers.py'
                      name       'blink'
-                     firstlineno 224
+                     firstlineno 263
                      lnotab 0x04010e012c02
                   False
                   None
                   ('owner',)
                names      ('Widget', '__init__', 'isinstance', 'int', 'float', 'interval', 'RepeatingTimer', '_countdown_before_blink', '_need_start_animation', 'signal', 'SLEEP', 'connect', 'handle_sleep', 'WAKE', 'handle_wake', 'KILL', 'cancel')
                varnames   ('self', 'parent', 'interval', 'kwargs', 'blink')
                freevars   ()
                cellvars   ('self',)
                filename   'C:\\Users\\symrb\\Documents\\dev\\python\\baopig\\baopig\\lib\\widget_supers.py'
                name       '__init__'
-               firstlineno 212
+               firstlineno 251
                lnotab 0x040626024c020e020a062a010e014c014c01
             code
                argcount  : 1
                nlocals   : 1
                stacksize : 2
                flags     : 3
                code
                   0x97007c006a0000000000000000006a0100000000000000007c005f0200
                   000000000000007c006a000000000000000000a003000000000000000000
                   0000000000000000000000a6000000ab0000000000000000000100640053
                   00
-               236           0 RESUME                   0
+               275           0 RESUME                   0
                
-               238           2 LOAD_FAST                0 (self)
+               277           2 LOAD_FAST                0 (self)
                              4 LOAD_ATTR                0 (_countdown_before_blink)
                             14 LOAD_ATTR                1 (is_running)
                             24 LOAD_FAST                0 (self)
                             26 STORE_ATTR               2 (_need_start_animation)
                
-               239          36 LOAD_FAST                0 (self)
+               278          36 LOAD_FAST                0 (self)
                             38 LOAD_ATTR                0 (_countdown_before_blink)
                             48 LOAD_METHOD              3 (cancel)
                             70 PRECALL                  0
                             74 CALL                     0
                             84 POP_TOP
                             86 LOAD_CONST               0 (None)
                             88 RETURN_VALUE
@@ -1728,54 +2055,54 @@
                   None
                names      ('_countdown_before_blink', 'is_running', '_need_start_animation', 'cancel')
                varnames   ('self',)
                freevars   ()
                cellvars   ()
                filename   'C:\\Users\\symrb\\Documents\\dev\\python\\baopig\\baopig\\lib\\widget_supers.py'
                name       'handle_sleep'
-               firstlineno 236
+               firstlineno 275
                lnotab 0x02022201
             code
                argcount  : 1
                nlocals   : 1
                stacksize : 2
                flags     : 3
                code
                   0x97007c006a000000000000000000720964017c005f0100000000000000
                   00640053007c006a0200000000000000006a03000000000000000072197c
                   006a020000000000000000a0040000000000000000000000000000000000
                   000000a6000000ab00000000000000000001007c006a0200000000000000
                   00a0050000000000000000000000000000000000000000a6000000ab0000
                   00000000000000010064005300
-               241           0 RESUME                   0
+               280           0 RESUME                   0
                
-               243           2 LOAD_FAST                0 (self)
+               282           2 LOAD_FAST                0 (self)
                              4 LOAD_ATTR                0 (is_asleep)
                             14 POP_JUMP_FORWARD_IF_FALSE     9 (to 34)
                
-               244          16 LOAD_CONST               1 (True)
+               283          16 LOAD_CONST               1 (True)
                             18 LOAD_FAST                0 (self)
                             20 STORE_ATTR               1 (_need_start_animation)
                
-               245          30 LOAD_CONST               0 (None)
+               284          30 LOAD_CONST               0 (None)
                             32 RETURN_VALUE
                
-               247     >>   34 LOAD_FAST                0 (self)
+               286     >>   34 LOAD_FAST                0 (self)
                             36 LOAD_ATTR                2 (_countdown_before_blink)
                             46 LOAD_ATTR                3 (is_running)
                             56 POP_JUMP_FORWARD_IF_FALSE    25 (to 108)
                
-               248          58 LOAD_FAST                0 (self)
+               287          58 LOAD_FAST                0 (self)
                             60 LOAD_ATTR                2 (_countdown_before_blink)
                             70 LOAD_METHOD              4 (cancel)
                             92 PRECALL                  0
                             96 CALL                     0
                            106 POP_TOP
                
-               249     >>  108 LOAD_FAST                0 (self)
+               288     >>  108 LOAD_FAST                0 (self)
                            110 LOAD_ATTR                2 (_countdown_before_blink)
                            120 LOAD_METHOD              5 (start)
                            142 PRECALL                  0
                            146 CALL                     0
                            156 POP_TOP
                            158 LOAD_CONST               0 (None)
                            160 RETURN_VALUE
@@ -1784,39 +2111,39 @@
                   True
                names      ('is_asleep', '_need_start_animation', '_countdown_before_blink', 'is_running', 'cancel', 'start')
                varnames   ('self',)
                freevars   ()
                cellvars   ()
                filename   'C:\\Users\\symrb\\Documents\\dev\\python\\baopig\\baopig\\lib\\widget_supers.py'
                name       'start_animation'
-               firstlineno 241
+               firstlineno 280
                lnotab 0x02020e010e01040218013201
             code
                argcount  : 1
                nlocals   : 1
                stacksize : 2
                flags     : 3
                code
                   0x97007c006a000000000000000000720964017c005f0100000000000000
                   00640053007c006a020000000000000000a0030000000000000000000000
                   000000000000000000a6000000ab000000000000000000010064005300
-               251           0 RESUME                   0
+               290           0 RESUME                   0
                
-               253           2 LOAD_FAST                0 (self)
+               292           2 LOAD_FAST                0 (self)
                              4 LOAD_ATTR                0 (is_asleep)
                             14 POP_JUMP_FORWARD_IF_FALSE     9 (to 34)
                
-               254          16 LOAD_CONST               1 (False)
+               293          16 LOAD_CONST               1 (False)
                             18 LOAD_FAST                0 (self)
                             20 STORE_ATTR               1 (_need_start_animation)
                
-               255          30 LOAD_CONST               0 (None)
+               294          30 LOAD_CONST               0 (None)
                             32 RETURN_VALUE
                
-               257     >>   34 LOAD_FAST                0 (self)
+               296     >>   34 LOAD_FAST                0 (self)
                             36 LOAD_ATTR                2 (_countdown_before_blink)
                             46 LOAD_METHOD              3 (cancel)
                             68 PRECALL                  0
                             72 CALL                     0
                             82 POP_TOP
                             84 LOAD_CONST               0 (None)
                             86 RETURN_VALUE
@@ -1825,67 +2152,67 @@
                   False
                names      ('is_asleep', '_need_start_animation', '_countdown_before_blink', 'cancel')
                varnames   ('self',)
                freevars   ()
                cellvars   ()
                filename   'C:\\Users\\symrb\\Documents\\dev\\python\\baopig\\baopig\\lib\\widget_supers.py'
                name       'stop_animation'
-               firstlineno 251
+               firstlineno 290
                lnotab 0x02020e010e010402
             code
                argcount  : 1
                nlocals   : 1
                stacksize : 2
                flags     : 3
                code
                   0x97007c006a00000000000000000072197c006a010000000000000000a0
                   020000000000000000000000000000000000000000a6000000ab00000000
                   0000000000010064017c005f00000000000000000064005300
-               259           0 RESUME                   0
+               298           0 RESUME                   0
                
-               261           2 LOAD_FAST                0 (self)
+               300           2 LOAD_FAST                0 (self)
                              4 LOAD_ATTR                0 (_need_start_animation)
                             14 POP_JUMP_FORWARD_IF_FALSE    25 (to 66)
                
-               262          16 LOAD_FAST                0 (self)
+               301          16 LOAD_FAST                0 (self)
                             18 LOAD_ATTR                1 (_countdown_before_blink)
                             28 LOAD_METHOD              2 (start)
                             50 PRECALL                  0
                             54 CALL                     0
                             64 POP_TOP
                
-               263     >>   66 LOAD_CONST               1 (False)
+               302     >>   66 LOAD_CONST               1 (False)
                             68 LOAD_FAST                0 (self)
                             70 STORE_ATTR               0 (_need_start_animation)
                             80 LOAD_CONST               0 (None)
                             82 RETURN_VALUE
                consts
                   None
                   False
                names      ('_need_start_animation', '_countdown_before_blink', 'start')
                varnames   ('self',)
                freevars   ()
                cellvars   ()
                filename   'C:\\Users\\symrb\\Documents\\dev\\python\\baopig\\baopig\\lib\\widget_supers.py'
                name       'handle_wake'
-               firstlineno 259
+               firstlineno 298
                lnotab 0x02020e013201
             None
          names      ('__name__', '__module__', '__qualname__', '__doc__', '__init__', 'handle_sleep', 'start_animation', 'stop_animation', 'handle_wake')
          varnames   ()
          freevars   ()
          cellvars   ()
          filename   'C:\\Users\\symrb\\Documents\\dev\\python\\baopig\\baopig\\lib\\widget_supers.py'
          name       'RepetivelyAnimated'
-         firstlineno 202
+         firstlineno 241
          lnotab 0x0a01040906180605060a0608
       'RepetivelyAnimated'
-   names      ('pygame', 'baopig.io', 'LOGGER', 'mouse', 'keyboard', 'baopig.documentation', 'ApplicationExit', 'Selector', 'Focusable', 'FocusableDoc', 'HoverableByMouse', 'HoverableByMouseDoc', 'LinkableByMouse', 'LinkableByMouseDoc', 'Runable', 'RunableDoc', 'Validable', 'ValidableDoc', 'baopig.time.timer', 'RepeatingTimer', 'widget', 'Widget', 'DraggableByMouse', 'RepetivelyAnimated')
+   names      ('pygame', 'baopig.io', 'LOGGER', 'mouse', 'keyboard', 'baopig.documentation', 'ApplicationExit', 'Selector', 'Focusable', 'FocusableDoc', 'HoverableByMouse', 'HoverableByMouseDoc', 'LinkableByMouse', 'LinkableByMouseDoc', 'Runable', 'RunableDoc', 'Validable', 'ValidableDoc', 'baopig.time.timer', 'RepeatingTimer', 'widget', 'Widget', 'MaintainableByFocus', 'DraggableByMouse', 'RepetivelyAnimated')
    varnames   ()
    freevars   ()
    cellvars   ()
    filename   'C:\\Users\\symrb\\Documents\\dev\\python\\baopig\\baopig\\lib\\widget_supers.py'
    name       '<module>'
    firstlineno 1
    lnotab
       0x00ff02010801140110010c010c010c010c010c010c010c031c171e0d1e
-      361e191e411c09
+      361e191e411c271c09
```

## baopig/version/version.py

```diff
@@ -16,12 +16,12 @@
         return '{}.{}.{}'.format(*self) if len(self) == 3 else '{}.{}.{} - {}'.format(*self)
 
     major = property(lambda self: self[0])
     minor = property(lambda self: self[1])
     patch = property(lambda self: self[2])
 
 
-version = BaopigVersion(0, 20, 3)
+version = BaopigVersion(0, 20, 4)
 
 if __name__ == "__main__":
     # TODO : try to access baopig.version without creating application, threads...
     print("Hello, this is baopig version", version)
```

## baopig/version/__pycache__/version.cpython-311.pyc

### Python bytecode

```diff
@@ -1,9 +1,9 @@
 magic:    0xa70d0d0a
-moddate:  0xdcdf4364 (Sat Apr 22 13:23:40 2023 UTC)
+moddate:  0xf2eb4364 (Sat Apr 22 14:15:14 2023 UTC)
 files sz: 931
 code
    argcount  : 0
    nlocals   : 0
    stacksize : 5
    flags     : 0
    code
@@ -23,15 +23,15 @@
                 18 CALL                     3
                 28 STORE_NAME               1 (BaopigVersion)
    
     23          30 PUSH_NULL
                 32 LOAD_NAME                1 (BaopigVersion)
                 34 LOAD_CONST               2 (0)
                 36 LOAD_CONST               3 (20)
-                38 LOAD_CONST               4 (3)
+                38 LOAD_CONST               4 (4)
                 40 PRECALL                  3
                 44 CALL                     3
                 54 STORE_NAME               2 (version)
    
     25          56 LOAD_NAME                3 (__name__)
                 58 LOAD_CONST               5 ('__main__')
                 60 COMPARE_OP               2 (==)
@@ -375,15 +375,15 @@
          filename   'C:\\Users\\symrb\\Documents\\dev\\python\\baopig\\.\\baopig\\version\\version.py'
          name       'BaopigVersion'
          firstlineno 3
          lnotab 0x0a0104010401040208030604060318011801
       'BaopigVersion'
       0
       20
-      3
+      4
       '__main__'
       'Hello, this is baopig version'
       None
    names      ('tuple', 'BaopigVersion', 'version', '__name__', 'print')
    varnames   ()
    freevars   ()
    cellvars   ()
```

## Comparing `baopig-0.20.3.dist-info/LICENSE` & `baopig-0.20.4.dist-info/LICENSE`

 * *Files identical despite different names*

## Comparing `baopig-0.20.3.dist-info/METADATA` & `baopig-0.20.4.dist-info/METADATA`

 * *Files 1% similar despite different names*

```diff
@@ -1,10 +1,10 @@
 Metadata-Version: 2.1
 Name: baopig
-Version: 0.20.3
+Version: 0.20.4
 Summary: pygame gui
 Home-page: https://baopig.readthedocs.io/
 Author: Symeon Rougevin-Baville
 Author-email: dev.chresyr@gmail.com
 License: MIT
 Classifier: Intended Audience :: Developers
 Classifier: License :: OSI Approved :: MIT License
```

## Comparing `baopig-0.20.3.dist-info/RECORD` & `baopig-0.20.4.dist-info/RECORD`

 * *Files 1% similar despite different names*

```diff
@@ -61,15 +61,15 @@
 baopig/googletrans/__pycache__/__init__.cpython-310.pyc,sha256=5S7AaS6hhCLTTqdU0pI7ds52zXzRlIakSFhqsPvftNs,682
 baopig/googletrans/__pycache__/__init__.cpython-311.pyc,sha256=UBXO3UkfAaHte6HsOpx5O1WmqkvEvEGctR9F_zkUUGw,822
 baopig/googletrans/__pycache__/client.cpython-310.pyc,sha256=jgV72J9DnB7taX3kGl02uNkm4aZ5fGvEYQBAAXa71gw,9616
 baopig/googletrans/__pycache__/client.cpython-311.pyc,sha256=xJ9l2nbZkybNvcWul7M-OZTViNMf2-KkS_d6DIQixEc,13590
 baopig/googletrans/__pycache__/constants.cpython-310.pyc,sha256=n439gXFLNNT7nB2xMNajtac07Y4DQl5Vsplqj3lOHUM,10152
 baopig/googletrans/__pycache__/constants.cpython-311.pyc,sha256=G0mUpARZYXcoNOqIOIZrvZ_wpxstIn1vmulGobJpCpk,12680
 baopig/googletrans/__pycache__/extension.cpython-310.pyc,sha256=14fWjNd-5jr8NhyRCwkLIEYkqlSCm6Nzaves8dptV_w,6220
-baopig/googletrans/__pycache__/extension.cpython-311.pyc,sha256=kPbPx0rvGXUHIEWSzojG_0B_wmNjLQj973NJJAy175s,12787
+baopig/googletrans/__pycache__/extension.cpython-311.pyc,sha256=N-xfjI9FLmhZAT0Ey8ITjV3apn-wPnKYOU0saLW6z64,12727
 baopig/googletrans/__pycache__/gtoken.cpython-310.pyc,sha256=ibpTNCxdLT7hFQ9xGzv5JVRP-pK19Wy5dxsx6N_kIL0,5423
 baopig/googletrans/__pycache__/gtoken.cpython-311.pyc,sha256=26xyLwfQFecfNTvpsn-3zRV8mNhbuDs9QYgysQ3T6TM,9846
 baopig/googletrans/__pycache__/models.cpython-310.pyc,sha256=ga4xpDoQlpMcpliKNIj_DjOo7bD1oSpi2sPA8AS_EEo,2490
 baopig/googletrans/__pycache__/models.cpython-311.pyc,sha256=jJRiOQ99qkVe6kSxizR-XleMpE5Xk1ycTWeb5pY-pu4,3533
 baopig/googletrans/__pycache__/translatable.cpython-310.pyc,sha256=GOrBHKcx3nkSPsD10GyGA3K7G7a5wK4DkQEe3eVHah0,3130
 baopig/googletrans/__pycache__/translatable.cpython-311.pyc,sha256=wSlNKkdjtL1SmaPe45HICHIxdYdGwzi9698BU5rj_8Y,5117
 baopig/googletrans/__pycache__/urls.cpython-310.pyc,sha256=XsAlhs9gUGH7GZGZVSQUJgj8whiTlNS5K3CfXV5kofo,321
@@ -88,31 +88,31 @@
 baopig/io/__pycache__/keyboard.cpython-37.pyc,sha256=DLpaiZhujZ9G_DtjRX6YfryVep-5ccc5Hk7ImMK-Dks,7189
 baopig/io/__pycache__/logging.cpython-310.pyc,sha256=79S-YGeUaXu81fCAZr4UUA8dy8-okGNl1ycB30crxtM,3416
 baopig/io/__pycache__/logging.cpython-311.pyc,sha256=INAkhL5VZWsMAsU_zOcy2niifIlvkBHvozwtgHi8ldA,6314
 baopig/io/__pycache__/logging.cpython-37.pyc,sha256=0apV2UPLFBH1OkNU7kWYnAY-2tW3rShDpRSFlDj6UtQ,3376
 baopig/io/__pycache__/mouse.cpython-310.pyc,sha256=OMkB7t88yMt4ku6J0VXpRYsknY6JslUEi5unWG7GhF0,7956
 baopig/io/__pycache__/mouse.cpython-311.pyc,sha256=gP9aEEbscsyzy7BA2G7V19hbx5ke86uhU8tAxbKg99U,15307
 baopig/io/__pycache__/mouse.cpython-37.pyc,sha256=6QybLrsrImVBpnh9YCb1dapDUNhz4y9Lf_4LvfJrhQA,9450
-baopig/lib/__init__.py,sha256=EDwBTVVsP5t13T8uLpCFsmMxzbPmjvXZp-U6iNw7Aoo,617
+baopig/lib/__init__.py,sha256=lPf5jSg4gxGecm44nfUOomrdJipEu2C8UHX5jGZ7GLc,596
 baopig/lib/application.py,sha256=prGTgjq4OJ1H2JcAx42Gnz_QZ-f8i7zaqW-mlTtp29A,14075
 baopig/lib/container.py,sha256=VwHW6C6p4RohLPHH1YD_OdIe7sukT1_tZa4vCz-j3Es,16468
 baopig/lib/gridlayer.py,sha256=A5YqZtz56i-9AGJjIU-1ukhbRqvTjzfa86pIxu5u04Q,18715
 baopig/lib/imagewidget.py,sha256=QKfSJo4R3fsYgNgnenGYlsBnX8JvxiiaapYhLmmzCfk,2502
 baopig/lib/layer.py,sha256=mx_gcQjZ_4uFQu9w6k8M55zYIJVPIiV8SKSmWcM9AQY,10338
 baopig/lib/layersmanager.py,sha256=qmZxVn5_0Sj1OJ8JmDJfDi7FM4ydNA4kcwqCoHHyxcQ,4172
 baopig/lib/scene.py,sha256=uYybMC2uNh-6cXlQd3yP0SsqFTCEsUWJpK0V6AHEFLM,7037
 baopig/lib/selections.py,sha256=5orInDZ4vWj7LLodlqgyfhXqtwvwLxcoauZNTfoT6s0,10889
 baopig/lib/shapes.py,sha256=wMVdMoWu6vQ1hxJ2HH9JO9tHBWemNeBLbAbFGchrbeQ,7360
 baopig/lib/style.py,sha256=keDYALWSKO2D3wdPDOmgQMwIb0tpNYboCfMs49kNhfU,16552
 baopig/lib/utilities.py,sha256=t6hq2G8BVL4e2ml9YkrmiFT1MkNaZc2ioGhJ9_BzpAI,4162
 baopig/lib/widget.py,sha256=rCdIzMaRrQXQh_w-C3-crC-iXt_uhcd2sTKlvoDafxk,37125
-baopig/lib/widget_supers.py,sha256=HIpOszOUsbY7G2fedwFIUbuh_Cm7DG03v1WpzBOKv1M,8555
+baopig/lib/widget_supers.py,sha256=HGtkyeeG07N0Ux0hx-dD4WZJy3zHV8pp0eRqNfLd23A,9919
 baopig/lib/zone.py,sha256=i3m_-5JbdRkQ_zOwHUoCfZv5TeBMUC_5yIdyfgNV2j8,3300
 baopig/lib/__pycache__/__init__.cpython-310.pyc,sha256=bwkBpR3K5cQLEtjcxWvn7Eo4Gpq8fwgofGC1Nz2bCAo,1022
-baopig/lib/__pycache__/__init__.cpython-311.pyc,sha256=RlZFVzeMdGODdSuudmoR0O_YQv2Mmjj4mkmLLFYObxY,1378
+baopig/lib/__pycache__/__init__.cpython-311.pyc,sha256=Rt6FQVsfBsAfRMsokRy8Rhqy3n-e7t7Zr09Kc7LI4H0,1418
 baopig/lib/__pycache__/__init__.cpython-37.pyc,sha256=UFHkDz3gqx-YZr_AgX4fU5o2v0qmcYNRDS8hQvvDwKw,996
 baopig/lib/__pycache__/application.cpython-310.pyc,sha256=mUYtq9moPq3csEQi--t_mRBW-MbUiBXA7sbG62hW8Nk,10025
 baopig/lib/__pycache__/application.cpython-311.pyc,sha256=joewM1eHUVcYq6vdkknkMjGNMIzQOI4MLY8ipuiYGa8,19363
 baopig/lib/__pycache__/application.cpython-37.pyc,sha256=FaFtKhczKjVQzmpMQ8Wa1R2FmCzx0d1s60Vds2bCMtE,11173
 baopig/lib/__pycache__/container.cpython-310.pyc,sha256=LzNkbl_-VqPBC4J93ElOqIdJ_DRWjvHE10cRQPBLwzI,13868
 baopig/lib/__pycache__/container.cpython-311.pyc,sha256=KoyYLzWiPlsefuDZUHg3dHgANU9uuxXP_GHc6GbFjXw,25435
 baopig/lib/__pycache__/container.cpython-37.pyc,sha256=RAPlBe9JL_uJwDwxMT2zl4VrJZKACWHwKt9-PJG6tTQ,17854
@@ -142,15 +142,15 @@
 baopig/lib/__pycache__/utilities.cpython-310.pyc,sha256=j0bvx6suEs1ceYNLpAKWOY4gQn_oyhb_iUFnQl8PgoE,5742
 baopig/lib/__pycache__/utilities.cpython-311.pyc,sha256=N7n4BBzh0Id9Wlrx1_I84icS2p5kcJio5HO3j6aSXm0,9424
 baopig/lib/__pycache__/utilities.cpython-37.pyc,sha256=RBVbBPfYzj1Uzp-yYvd09e1dOQ4BsDKFDt9_o_Ok9sk,16139
 baopig/lib/__pycache__/widget.cpython-310.pyc,sha256=tczMn_oQc5MK-fizAxEZBvxgOMfVb3S1JZC5KII56LM,30683
 baopig/lib/__pycache__/widget.cpython-311.pyc,sha256=61x2zKTwxmOjClMrYoR5eKnIB7YLTGBB4psLl4k2Z6Q,57092
 baopig/lib/__pycache__/widget.cpython-37.pyc,sha256=UGGfvYZWBzLeytZm86HGJ3mxjFtaCD5brN9SlduELa0,36355
 baopig/lib/__pycache__/widget_supers.cpython-310.pyc,sha256=WGm9nZbLBU1IVNJAyCvE-yBkpTrFLFTlPudgJjdCVa4,8647
-baopig/lib/__pycache__/widget_supers.cpython-311.pyc,sha256=gkVKJUNEOTM_vPNvJb4n1MptclZLSbNT1-2Q5ye-dpw,13539
+baopig/lib/__pycache__/widget_supers.cpython-311.pyc,sha256=NVOuwFoX43B05Cq49Rz06R3Aat1TyEOd5qFi9fmDwQ4,16061
 baopig/lib/__pycache__/zone.cpython-310.pyc,sha256=scAXcJVqrQ3c-lOH7Oq38GKwYTa47c7769mICY2Wuus,3094
 baopig/lib/__pycache__/zone.cpython-311.pyc,sha256=eN3yp7eYkP9JVs46ORv3yQMF8c32AbjUjyNhmDXXMx0,6355
 baopig/lib/__pycache__/zone.cpython-37.pyc,sha256=M31S58SrSbqqrvHzRK6KztFemUXO8UBi-36Kriy9qAQ,3722
 baopig/prefabs/colorchooserdialog.py,sha256=FpSzWUNOS1lRiwT-7S3K-w8BDVq5FUPKAiozmO1j57Y,7489
 baopig/prefabs/debugzone.py,sha256=pWuJnPSPH7iFf-2wvULBZfnOhvJS6cfYzW6rj7HVTx8,5248
 baopig/prefabs/presentationscene.py,sha256=iZZeGOGjV-Ii4JrrrYEtpIABly3ay6G9KtHgSt2K7WU,2177
 baopig/prefabs/testerscene.py,sha256=nznLRxlND-vlBEUVhr2vC1peOTPVDsLdnVoJR7I-q4Y,4847
@@ -250,17 +250,17 @@
 baopig/unit_tests/__pycache__/ut_sleep.cpython-311.pyc,sha256=9IsK69xKVmkyAR2CbTXopWWC0Vj7SRIndg1cQfi-5Ac,13507
 baopig/unit_tests/__pycache__/ut_text.cpython-310.pyc,sha256=Izd3N6trwDF_1o0O3msWBUUDBbfjphQ7Bh9DiROS-qI,3621
 baopig/unit_tests/__pycache__/ut_text.cpython-311.pyc,sha256=YOfvIZAZSaEmcCb4qxOybmWye-89s_lEVKR4Y8G6NFI,6753
 baopig/unit_tests/__pycache__/ut_textedit.cpython-310.pyc,sha256=Kb5XYTUGs1yP69qXaFwgbLqjXqI8V5AVtfiowqy4Mwo,1830
 baopig/unit_tests/__pycache__/ut_textedit.cpython-311.pyc,sha256=QGoRJDpfOUhFxL5d55cKdltmZp-r4zreIgYHWvhBU3M,3446
 baopig/unit_tests/__pycache__/ut_theme.cpython-310.pyc,sha256=Jd822wGf32M0nTwWRCSecbXojL_-Sk-Y-jt4qNKJFDU,2043
 baopig/unit_tests/__pycache__/ut_theme.cpython-311.pyc,sha256=5uTVze6gUU95lFO99ZXU6dvGquVDL5Xe8gIQqkFUYBE,3466
-baopig/version/version.py,sha256=-8ODaQKDaHDoPUvKzSaxj9QoixyE78DzERESr05RLLU,931
+baopig/version/version.py,sha256=RRxaDsx2M9VMGh2CEKs0W03_iC9x_cS-FdJxiJDKa7E,931
 baopig/version/__pycache__/version.cpython-310.pyc,sha256=Rp0XTLPGzphYoaYVQXoqP_pfEh2wLtNCsS3tVJN1Lbk,1692
-baopig/version/__pycache__/version.cpython-311.pyc,sha256=siG7KXxNTYu7dx5o8oEM4JrhqSQgRn4yf4snp14EJMc,2611
+baopig/version/__pycache__/version.cpython-311.pyc,sha256=1DUdeaVxWFQH58-laGK_9UTYt4M1-aaBbU8ykWACZCI,2611
 baopig/version/__pycache__/version.cpython-37.pyc,sha256=g23o3EB_00N3g1jhY4M6TwBov_bzg3MnZhZ2JPMLYHM,1642
 baopig/widgets/__init__.py,sha256=PeQrRjeytaGx2rd_C6ygb6wjiKoOQbDWtaHr9LvPtZg,767
 baopig/widgets/button.py,sha256=D7Q3wskW1gdq09Mj9EIuxYAtNbn3C9ejjnn-pN3-dFU,8232
 baopig/widgets/checkbox.py,sha256=VMsW42qIdGLCcD4KjPE3ytzqJvYs-ETzF1Y1Ku8Isfc,3102
 baopig/widgets/dialog.py,sha256=uJCa-Pr2dqaGhsHCuYIB03Dp8oaixFUmjapDfJuJRNk,5246
 baopig/widgets/entry.py,sha256=UODsZ2hPYKBY8QMPzOmiWGhTeF_p6bdsxJeRiTXRcuU,1609
 baopig/widgets/indicator.py,sha256=sEkysKLVNEQQPZgdnXd5KexBPDzUjQbKCYWT5Jiuuc8,3607
@@ -304,12 +304,12 @@
 baopig/widgets/__pycache__/slider.cpython-37.pyc,sha256=NhB3ncvsXTPaRXNm43xwc2DLV23RCaN6r1swBDjzwec,8011
 baopig/widgets/__pycache__/text.cpython-310.pyc,sha256=OhRohkmN_-EC-JXQsNr-WcCoeXSeOe-YxtdFBvnxdf4,24379
 baopig/widgets/__pycache__/text.cpython-311.pyc,sha256=y08KoLK9bQFsBECor7dDImLOvTLmYv06sG-1J5V9oC0,43877
 baopig/widgets/__pycache__/text.cpython-37.pyc,sha256=FIM-g85PDkaLQAHpojF_M88lkFpXG2kS_fwbvCsKCyo,27867
 baopig/widgets/__pycache__/textedit.cpython-310.pyc,sha256=D7KcLsLSPxQpLyaRf_BNHd7Px_jfPJVYcIXazq8FJHs,14346
 baopig/widgets/__pycache__/textedit.cpython-311.pyc,sha256=ACqhG1VRq7Ff_87p3QWyRZlx0IO8PNPLzqlNQEwa3Y4,32458
 baopig/widgets/__pycache__/textedit.cpython-37.pyc,sha256=Cia7Ci-9PVR2oUo4ObWEX7o5v3kULv-ZiTxbuH38JSA,13078
-baopig-0.20.3.dist-info/LICENSE,sha256=G6lZz1IZuCNLDTIxvk6dJWPWwozp2altzGHlF4NWUz4,1088
-baopig-0.20.3.dist-info/METADATA,sha256=fI3B5hwxarqB9_pYPonl-TtQku30fD5zzbOS7Ojb_iY,866
-baopig-0.20.3.dist-info/WHEEL,sha256=pkctZYzUS4AYVn6dJ-7367OJZivF2e8RA9b_ZBjif18,92
-baopig-0.20.3.dist-info/top_level.txt,sha256=soVidPUY0es6t4CoXpPdWPTwz8Y_4-NGZYPsvyET458,7
-baopig-0.20.3.dist-info/RECORD,,
+baopig-0.20.4.dist-info/LICENSE,sha256=G6lZz1IZuCNLDTIxvk6dJWPWwozp2altzGHlF4NWUz4,1088
+baopig-0.20.4.dist-info/METADATA,sha256=ug_SKuum0rxMLo6KeAhhJ-E5o8aJ8FLwjph_eNygO_M,866
+baopig-0.20.4.dist-info/WHEEL,sha256=pkctZYzUS4AYVn6dJ-7367OJZivF2e8RA9b_ZBjif18,92
+baopig-0.20.4.dist-info/top_level.txt,sha256=soVidPUY0es6t4CoXpPdWPTwz8Y_4-NGZYPsvyET458,7
+baopig-0.20.4.dist-info/RECORD,,
```

