# Comparing `tmp/baopig-0.20.2-py3-none-any.whl.zip` & `tmp/baopig-0.20.3-py3-none-any.whl.zip`

## zipinfo {}

```diff
@@ -1,14 +1,14 @@
-Zip file size: 2846748 bytes, number of entries: 315
+Zip file size: 2847068 bytes, number of entries: 315
 -rw-rw-rw-  2.0 fat      608 b- defN 23-Apr-22 11:51 baopig/__init__.py
 -rw-rw-rw-  2.0 fat     3643 b- defN 22-Jul-12 21:25 baopig/communicative.py
 -rw-rw-rw-  2.0 fat    16525 b- defN 22-Jul-19 15:24 baopig/documentation.py
 -rw-rw-rw-  2.0 fat      548 b- defN 23-Feb-20 13:20 baopig/lines_counter.py
 -rw-rw-rw-  2.0 fat      831 b- defN 22-Jul-12 21:41 baopig/__pycache__/__init__.cpython-310.pyc
--rw-rw-rw-  2.0 fat     1151 b- defN 23-Apr-22 11:47 baopig/__pycache__/__init__.cpython-311.pyc
+-rw-rw-rw-  2.0 fat     1151 b- defN 23-Apr-22 12:24 baopig/__pycache__/__init__.cpython-311.pyc
 -rw-rw-rw-  2.0 fat      866 b- defN 22-Jun-10 11:59 baopig/__pycache__/__init__.cpython-37.pyc
 -rw-rw-rw-  2.0 fat     4334 b- defN 22-Jul-12 21:25 baopig/__pycache__/communicative.cpython-310.pyc
 -rw-rw-rw-  2.0 fat     6953 b- defN 23-Apr-14 15:58 baopig/__pycache__/communicative.cpython-311.pyc
 -rw-rw-rw-  2.0 fat     6055 b- defN 22-Jun-10 11:59 baopig/__pycache__/communicative.cpython-37.pyc
 -rw-rw-rw-  2.0 fat    16336 b- defN 22-Jul-19 15:24 baopig/__pycache__/documentation.cpython-310.pyc
 -rw-rw-rw-  2.0 fat    18292 b- defN 23-Apr-14 15:58 baopig/__pycache__/documentation.cpython-311.pyc
 -rw-rw-rw-  2.0 fat       24 b- defN 22-Jul-20 11:07 baopig/font/__init__.py
@@ -49,28 +49,28 @@
 -rw-rw-rw-  2.0 fat    50936 b- defN 22-Jun-10 11:59 baopig/font/lib/JetBrainsMono-1.0.2/web/woff2/JetBrainsMono-Italic.woff2
 -rw-rw-rw-  2.0 fat    52928 b- defN 22-Jun-10 11:59 baopig/font/lib/JetBrainsMono-1.0.2/web/woff2/JetBrainsMono-Medium-Italic.woff2
 -rw-rw-rw-  2.0 fat    49592 b- defN 22-Jun-10 11:59 baopig/font/lib/JetBrainsMono-1.0.2/web/woff2/JetBrainsMono-Medium.woff2
 -rw-rw-rw-  2.0 fat    48700 b- defN 22-Jun-10 11:59 baopig/font/lib/JetBrainsMono-1.0.2/web/woff2/JetBrainsMono-Regular.woff2
 -rw-rw-rw-  2.0 fat      413 b- defN 23-Jan-10 21:21 baopig/googletrans/__init__.py
 -rw-rw-rw-  2.0 fat    11622 b- defN 22-Dec-15 23:45 baopig/googletrans/client.py
 -rw-rw-rw-  2.0 fat    11881 b- defN 22-Dec-16 23:00 baopig/googletrans/constants.py
--rw-rw-rw-  2.0 fat     6508 b- defN 23-Jan-10 21:25 baopig/googletrans/extension.py
+-rw-rw-rw-  2.0 fat     6781 b- defN 23-Apr-22 13:23 baopig/googletrans/extension.py
 -rw-rw-rw-  2.0 fat     7240 b- defN 22-Dec-15 17:45 baopig/googletrans/gtoken.py
 -rw-rw-rw-  2.0 fat     1797 b- defN 22-Dec-01 21:58 baopig/googletrans/models.py
 -rw-rw-rw-  2.0 fat     2163 b- defN 23-Jan-10 21:21 baopig/googletrans/translatable.py
 -rw-rw-rw-  2.0 fat      174 b- defN 22-Dec-01 21:58 baopig/googletrans/urls.py
 -rw-rw-rw-  2.0 fat     1951 b- defN 22-Dec-15 17:33 baopig/googletrans/utils.py
 -rw-rw-rw-  2.0 fat      682 b- defN 23-Jan-10 21:21 baopig/googletrans/__pycache__/__init__.cpython-310.pyc
 -rw-rw-rw-  2.0 fat      822 b- defN 23-Apr-14 15:58 baopig/googletrans/__pycache__/__init__.cpython-311.pyc
 -rw-rw-rw-  2.0 fat     9616 b- defN 22-Dec-16 22:54 baopig/googletrans/__pycache__/client.cpython-310.pyc
 -rw-rw-rw-  2.0 fat    13590 b- defN 23-Apr-14 15:58 baopig/googletrans/__pycache__/client.cpython-311.pyc
 -rw-rw-rw-  2.0 fat    10152 b- defN 22-Dec-16 23:02 baopig/googletrans/__pycache__/constants.cpython-310.pyc
 -rw-rw-rw-  2.0 fat    12680 b- defN 23-Apr-14 15:58 baopig/googletrans/__pycache__/constants.cpython-311.pyc
 -rw-rw-rw-  2.0 fat     6220 b- defN 23-Jan-10 21:25 baopig/googletrans/__pycache__/extension.cpython-310.pyc
--rw-rw-rw-  2.0 fat    12270 b- defN 23-Apr-14 15:58 baopig/googletrans/__pycache__/extension.cpython-311.pyc
+-rw-rw-rw-  2.0 fat    12787 b- defN 23-Apr-22 13:22 baopig/googletrans/__pycache__/extension.cpython-311.pyc
 -rw-rw-rw-  2.0 fat     5423 b- defN 22-Dec-15 17:45 baopig/googletrans/__pycache__/gtoken.cpython-310.pyc
 -rw-rw-rw-  2.0 fat     9846 b- defN 23-Apr-14 15:58 baopig/googletrans/__pycache__/gtoken.cpython-311.pyc
 -rw-rw-rw-  2.0 fat     2490 b- defN 22-Dec-15 17:45 baopig/googletrans/__pycache__/models.cpython-310.pyc
 -rw-rw-rw-  2.0 fat     3533 b- defN 23-Apr-14 15:58 baopig/googletrans/__pycache__/models.cpython-311.pyc
 -rw-rw-rw-  2.0 fat     3130 b- defN 23-Jan-10 21:21 baopig/googletrans/__pycache__/translatable.cpython-310.pyc
 -rw-rw-rw-  2.0 fat     5117 b- defN 23-Apr-14 15:58 baopig/googletrans/__pycache__/translatable.cpython-311.pyc
 -rw-rw-rw-  2.0 fat      321 b- defN 22-Dec-15 17:44 baopig/googletrans/__pycache__/urls.cpython-310.pyc
@@ -251,17 +251,17 @@
 -rw-rw-rw-  2.0 fat    13507 b- defN 23-Apr-22 11:43 baopig/unit_tests/__pycache__/ut_sleep.cpython-311.pyc
 -rw-rw-rw-  2.0 fat     3621 b- defN 22-Jul-21 20:14 baopig/unit_tests/__pycache__/ut_text.cpython-310.pyc
 -rw-rw-rw-  2.0 fat     6753 b- defN 23-Apr-22 11:43 baopig/unit_tests/__pycache__/ut_text.cpython-311.pyc
 -rw-rw-rw-  2.0 fat     1830 b- defN 22-Jul-21 20:14 baopig/unit_tests/__pycache__/ut_textedit.cpython-310.pyc
 -rw-rw-rw-  2.0 fat     3446 b- defN 23-Apr-22 11:43 baopig/unit_tests/__pycache__/ut_textedit.cpython-311.pyc
 -rw-rw-rw-  2.0 fat     2043 b- defN 22-Jul-21 19:40 baopig/unit_tests/__pycache__/ut_theme.cpython-310.pyc
 -rw-rw-rw-  2.0 fat     3466 b- defN 23-Apr-22 11:43 baopig/unit_tests/__pycache__/ut_theme.cpython-311.pyc
--rw-rw-rw-  2.0 fat      931 b- defN 23-Apr-22 11:45 baopig/version/version.py
+-rw-rw-rw-  2.0 fat      931 b- defN 23-Apr-22 13:23 baopig/version/version.py
 -rw-rw-rw-  2.0 fat     1692 b- defN 22-Dec-18 21:38 baopig/version/__pycache__/version.cpython-310.pyc
--rw-rw-rw-  2.0 fat     2609 b- defN 23-Apr-22 11:45 baopig/version/__pycache__/version.cpython-311.pyc
+-rw-rw-rw-  2.0 fat     2611 b- defN 23-Apr-22 13:24 baopig/version/__pycache__/version.cpython-311.pyc
 -rw-rw-rw-  2.0 fat     1642 b- defN 22-Jun-10 11:59 baopig/version/__pycache__/version.cpython-37.pyc
 -rw-rw-rw-  2.0 fat      767 b- defN 23-Jan-10 20:24 baopig/widgets/__init__.py
 -rw-rw-rw-  2.0 fat     8232 b- defN 23-Jan-10 19:59 baopig/widgets/button.py
 -rw-rw-rw-  2.0 fat     3102 b- defN 22-Jul-21 19:32 baopig/widgets/checkbox.py
 -rw-rw-rw-  2.0 fat     5246 b- defN 22-Jul-21 19:32 baopig/widgets/dialog.py
 -rw-rw-rw-  2.0 fat     1609 b- defN 22-Jul-20 17:43 baopig/widgets/entry.py
 -rw-rw-rw-  2.0 fat     3607 b- defN 23-Jan-10 20:40 baopig/widgets/indicator.py
@@ -305,13 +305,13 @@
 -rw-rw-rw-  2.0 fat     8011 b- defN 22-Jun-10 11:59 baopig/widgets/__pycache__/slider.cpython-37.pyc
 -rw-rw-rw-  2.0 fat    24379 b- defN 22-Jul-21 20:14 baopig/widgets/__pycache__/text.cpython-310.pyc
 -rw-rw-rw-  2.0 fat    43877 b- defN 23-Apr-14 15:58 baopig/widgets/__pycache__/text.cpython-311.pyc
 -rw-rw-rw-  2.0 fat    27867 b- defN 22-Jun-10 11:59 baopig/widgets/__pycache__/text.cpython-37.pyc
 -rw-rw-rw-  2.0 fat    14346 b- defN 22-Jul-21 20:14 baopig/widgets/__pycache__/textedit.cpython-310.pyc
 -rw-rw-rw-  2.0 fat    32458 b- defN 23-Apr-14 15:58 baopig/widgets/__pycache__/textedit.cpython-311.pyc
 -rw-rw-rw-  2.0 fat    13078 b- defN 22-Jun-10 11:59 baopig/widgets/__pycache__/textedit.cpython-37.pyc
--rw-rw-rw-  2.0 fat     1088 b- defN 23-Apr-22 11:53 baopig-0.20.2.dist-info/LICENSE
--rw-rw-rw-  2.0 fat      866 b- defN 23-Apr-22 11:53 baopig-0.20.2.dist-info/METADATA
--rw-rw-rw-  2.0 fat       92 b- defN 23-Apr-22 11:53 baopig-0.20.2.dist-info/WHEEL
--rw-rw-rw-  2.0 fat        7 b- defN 23-Apr-22 11:53 baopig-0.20.2.dist-info/top_level.txt
--rw-rw-r--  2.0 fat    32575 b- defN 23-Apr-22 11:53 baopig-0.20.2.dist-info/RECORD
-315 files, 5113975 bytes uncompressed, 2793570 bytes compressed:  45.4%
+-rw-rw-rw-  2.0 fat     1088 b- defN 23-Apr-22 13:24 baopig-0.20.3.dist-info/LICENSE
+-rw-rw-rw-  2.0 fat      866 b- defN 23-Apr-22 13:24 baopig-0.20.3.dist-info/METADATA
+-rw-rw-rw-  2.0 fat       92 b- defN 23-Apr-22 13:24 baopig-0.20.3.dist-info/WHEEL
+-rw-rw-rw-  2.0 fat        7 b- defN 23-Apr-22 13:24 baopig-0.20.3.dist-info/top_level.txt
+-rw-rw-r--  2.0 fat    32575 b- defN 23-Apr-22 13:24 baopig-0.20.3.dist-info/RECORD
+315 files, 5114767 bytes uncompressed, 2793890 bytes compressed:  45.4%
```

## zipnote {}

```diff
@@ -924,23 +924,23 @@
 
 Filename: baopig/widgets/__pycache__/textedit.cpython-311.pyc
 Comment: 
 
 Filename: baopig/widgets/__pycache__/textedit.cpython-37.pyc
 Comment: 
 
-Filename: baopig-0.20.2.dist-info/LICENSE
+Filename: baopig-0.20.3.dist-info/LICENSE
 Comment: 
 
-Filename: baopig-0.20.2.dist-info/METADATA
+Filename: baopig-0.20.3.dist-info/METADATA
 Comment: 
 
-Filename: baopig-0.20.2.dist-info/WHEEL
+Filename: baopig-0.20.3.dist-info/WHEEL
 Comment: 
 
-Filename: baopig-0.20.2.dist-info/top_level.txt
+Filename: baopig-0.20.3.dist-info/top_level.txt
 Comment: 
 
-Filename: baopig-0.20.2.dist-info/RECORD
+Filename: baopig-0.20.3.dist-info/RECORD
 Comment: 
 
 Zip file comment:
```

## baopig/__pycache__/__init__.cpython-311.pyc

### Python bytecode

```diff
@@ -1,10 +1,10 @@
 magic:    0xa70d0d0a
-moddate:  0x3dc94364 (Sat Apr 22 11:47:09 2023 UTC)
-files sz: 607
+moddate:  0x5eca4364 (Sat Apr 22 11:51:58 2023 UTC)
+files sz: 608
 code
    argcount  : 0
    nlocals   : 0
    stacksize : 4
    flags     : 0
    code
       0x970064005a00640164026c016d025a02010002006503640365029b009d
@@ -21,76 +21,76 @@
     12           6 LOAD_CONST               1 (1)
                  8 LOAD_CONST               2 (('version',))
                 10 IMPORT_NAME              1 (version.version)
                 12 IMPORT_FROM              2 (version)
                 14 STORE_NAME               2 (version)
                 16 POP_TOP
    
-    13          18 PUSH_NULL
+    14          18 PUSH_NULL
                 20 LOAD_NAME                3 (print)
                 22 LOAD_CONST               3 ('baopig ')
                 24 LOAD_NAME                2 (version)
                 26 FORMAT_VALUE             0
                 28 BUILD_STRING             2
                 30 PRECALL                  1
                 34 CALL                     1
                 44 POP_TOP
    
-    14          46 LOAD_CONST               4 (0)
+    15          46 LOAD_CONST               4 (0)
                 48 LOAD_CONST               5 (('*',))
                 50 IMPORT_NAME              4 (pygame)
                 52 IMPORT_STAR
    
-    15          54 LOAD_CONST               1 (1)
+    16          54 LOAD_CONST               1 (1)
                 56 LOAD_CONST               5 (('*',))
                 58 IMPORT_NAME              5 (pybao.issomething)
                 60 IMPORT_STAR
    
-    16          62 LOAD_CONST               1 (1)
+    17          62 LOAD_CONST               1 (1)
                 64 LOAD_CONST               6 (('Object', 'PrefilledFunction', 'PackedFunctions'))
                 66 IMPORT_NAME              6 (pybao.objectutilities)
                 68 IMPORT_FROM              7 (Object)
                 70 STORE_NAME               7 (Object)
                 72 IMPORT_FROM              8 (PrefilledFunction)
                 74 STORE_NAME               8 (PrefilledFunction)
                 76 IMPORT_FROM              9 (PackedFunctions)
                 78 STORE_NAME               9 (PackedFunctions)
                 80 POP_TOP
    
-    18          82 LOAD_CONST               1 (1)
+    19          82 LOAD_CONST               1 (1)
                 84 LOAD_CONST               5 (('*',))
                 86 IMPORT_NAME             10 (io)
                 88 IMPORT_STAR
    
-    19          90 LOAD_CONST               1 (1)
+    20          90 LOAD_CONST               1 (1)
                 92 LOAD_CONST               5 (('*',))
                 94 IMPORT_NAME             11 (time)
                 96 IMPORT_STAR
    
-    20          98 LOAD_CONST               1 (1)
+    21          98 LOAD_CONST               1 (1)
                100 LOAD_CONST               5 (('*',))
                102 IMPORT_NAME             12 (lib)
                104 IMPORT_STAR
    
-    21         106 LOAD_CONST               1 (1)
+    22         106 LOAD_CONST               1 (1)
                108 LOAD_CONST               5 (('*',))
                110 IMPORT_NAME             13 (widgets)
                112 IMPORT_STAR
    
-    23         114 LOAD_CONST               7 (None)
+    24         114 LOAD_CONST               7 (None)
                116 STORE_NAME              14 (display)
    
-    25         118 PUSH_NULL
+    26         118 PUSH_NULL
                120 LOAD_NAME               15 (str)
                122 LOAD_NAME                2 (version)
                124 PRECALL                  1
                128 CALL                     1
                138 STORE_NAME              16 (__version__)
    
-    28         140 LOAD_CONST               8 (<code object debug_with_logging, file "C:\Users\symrb\Documents\dev\python\baopig\baopig\__init__.py", line 28>)
+    29         140 LOAD_CONST               8 (<code object debug_with_logging, file "C:\Users\symrb\Documents\dev\python\baopig\baopig\__init__.py", line 29>)
                142 MAKE_FUNCTION            0
                144 STORE_NAME              17 (debug_with_logging)
                146 LOAD_CONST               7 (None)
                148 RETURN_VALUE
    consts
       '\nWelcome to BaoPig\n\nBAOPIG : Boite A Outils Pour Interfaces Graphiques\n\n'
       1
@@ -107,23 +107,23 @@
          flags     : 3
          code
             0x9700740000000000000000000000a00100000000000000000000000000
             00000000000000a6000000ab000000000000000000010074000000000000
             00000000006a020000000000000000a00300000000000000000000000000
             000000000000007400000000000000000000006a040000000000000000a6
             010000ab010000000000000000010064005300
-          28           0 RESUME                   0
+          29           0 RESUME                   0
          
-          30           2 LOAD_GLOBAL              0 (LOGGER)
+          31           2 LOAD_GLOBAL              0 (LOGGER)
                       14 LOAD_METHOD              1 (add_debug_filehandler)
                       36 PRECALL                  0
                       40 CALL                     0
                       50 POP_TOP
          
-          31          52 LOAD_GLOBAL              0 (LOGGER)
+          32          52 LOAD_GLOBAL              0 (LOGGER)
                       64 LOAD_ATTR                2 (cons_handler)
                       74 LOAD_METHOD              3 (setLevel)
                       96 LOAD_GLOBAL              0 (LOGGER)
                      108 LOAD_ATTR                4 (DEBUG)
                      118 PRECALL                  1
                      122 CALL                     1
                      132 POP_TOP
@@ -133,17 +133,17 @@
             None
          names      ('LOGGER', 'add_debug_filehandler', 'cons_handler', 'setLevel', 'DEBUG')
          varnames   ()
          freevars   ()
          cellvars   ()
          filename   'C:\\Users\\symrb\\Documents\\dev\\python\\baopig\\baopig\\__init__.py'
          name       'debug_with_logging'
-         firstlineno 28
+         firstlineno 29
          lnotab 0x02023201
    names      ('__doc__', 'version.version', 'version', 'print', 'pygame', 'pybao.issomething', 'pybao.objectutilities', 'Object', 'PrefilledFunction', 'PackedFunctions', 'io', 'time', 'lib', 'widgets', 'display', 'str', '__version__', 'debug_with_logging')
    varnames   ()
    freevars   ()
    cellvars   ()
    filename   'C:\\Users\\symrb\\Documents\\dev\\python\\baopig\\baopig\\__init__.py'
    name       '<module>'
    firstlineno 1
-   lnotab 0x00ff0202040a0c011c01080108011402080108010801080204021603
+   lnotab 0x00ff0202040a0c021c01080108011402080108010801080204021603
```

## baopig/googletrans/extension.py

```diff
@@ -15,15 +15,20 @@
         self.lang_id = lang_id
 
         assert lang_id not in dicts
         dicts[lang_id] = self
 
         if os.path.exists(f"{os.path.abspath(os.path.dirname(sys.argv[0]))}{os.sep}lang{os.sep}dict_{lang_id}.py"):
 
-            module = importlib.import_module(f"lang.dict_{lang_id}")
+            import pathlib
+            file_path = f"{pathlib.Path.cwd()}{os.sep}lang{os.sep}dict_{lang_id}.py"
+            file_name = f"dict_{lang_id}"
+            spec = importlib.util.spec_from_file_location(file_name, file_path)
+            module = importlib.util.module_from_spec(spec)
+            spec.loader.exec_module(module)
 
             for text_id, text in enumerate(module.texts):
                 self[text_id] = text
 
         else:
             if self.lang_id == lang_manager.ref_language:
                 raise FileNotFoundError("The dictionnary for the ref language has not been found")
```

## baopig/googletrans/__pycache__/extension.cpython-311.pyc

### Python bytecode

```diff
@@ -1,10 +1,10 @@
 magic:    0xa70d0d0a
-moddate:  0xacd7bd63 (Tue Jan 10 21:25:00 2023 UTC)
-files sz: 6508
+moddate:  0x90df4364 (Sat Apr 22 13:22:24 2023 UTC)
+files sz: 6811
 code
    argcount  : 0
    nlocals   : 0
    stacksize : 5
    flags     : 0
    code
       0x9700640064016c005a00640064016c015a01640064016c025a02640064
@@ -56,45 +56,45 @@
                 64 MAKE_FUNCTION            0
                 66 LOAD_CONST               6 ('Dictionnary')
                 68 LOAD_NAME                9 (dict)
                 70 PRECALL                  3
                 74 CALL                     3
                 84 STORE_NAME              10 (Dictionnary)
    
-    69          86 PUSH_NULL
+    75          86 PUSH_NULL
                 88 LOAD_BUILD_CLASS
-                90 LOAD_CONST               7 (<code object LangManager, file "C:\Users\symrb\Documents\dev\python\baopig\baopig\googletrans\extension.py", line 69>)
+                90 LOAD_CONST               7 (<code object LangManager, file "C:\Users\symrb\Documents\dev\python\baopig\baopig\googletrans\extension.py", line 75>)
                 92 MAKE_FUNCTION            0
                 94 LOAD_CONST               8 ('LangManager')
                 96 LOAD_NAME                6 (bp)
                 98 LOAD_ATTR               11 (Communicative)
                108 PRECALL                  3
                112 CALL                     3
                122 STORE_NAME              12 (LangManager)
    
-   158         124 PUSH_NULL
+   164         124 PUSH_NULL
                126 LOAD_BUILD_CLASS
-               128 LOAD_CONST               9 (<code object OptimizedTranslator, file "C:\Users\symrb\Documents\dev\python\baopig\baopig\googletrans\extension.py", line 158>)
+               128 LOAD_CONST               9 (<code object OptimizedTranslator, file "C:\Users\symrb\Documents\dev\python\baopig\baopig\googletrans\extension.py", line 164>)
                130 MAKE_FUNCTION            0
                132 LOAD_CONST              10 ('OptimizedTranslator')
                134 LOAD_NAME                8 (Translator)
                136 PRECALL                  3
                140 CALL                     3
                150 STORE_NAME              13 (OptimizedTranslator)
    
-   205         152 BUILD_MAP                0
+   211         152 BUILD_MAP                0
                154 STORE_NAME              14 (dicts)
    
-   206         156 PUSH_NULL
+   212         156 PUSH_NULL
                158 LOAD_NAME               12 (LangManager)
                160 PRECALL                  0
                164 CALL                     0
                174 STORE_NAME              15 (lang_manager)
    
-   207         176 PUSH_NULL
+   213         176 PUSH_NULL
                178 LOAD_NAME               13 (OptimizedTranslator)
                180 PRECALL                  0
                184 CALL                     0
                194 STORE_NAME              16 (translator)
                196 LOAD_CONST               1 (None)
                198 RETURN_VALUE
    consts
@@ -115,24 +115,24 @@
                        6 LOAD_CONST               0 ('Dictionnary')
                        8 STORE_NAME               2 (__qualname__)
          
           11          10 LOAD_CONST               1 (<code object __init__, file "C:\Users\symrb\Documents\dev\python\baopig\baopig\googletrans\extension.py", line 11>)
                       12 MAKE_FUNCTION            0
                       14 STORE_NAME               3 (__init__)
          
-          52          16 LOAD_CONST               2 (<code object save, file "C:\Users\symrb\Documents\dev\python\baopig\baopig\googletrans\extension.py", line 52>)
+          58          16 LOAD_CONST               2 (<code object save, file "C:\Users\symrb\Documents\dev\python\baopig\baopig\googletrans\extension.py", line 58>)
                       18 MAKE_FUNCTION            0
                       20 STORE_NAME               4 (save)
                       22 LOAD_CONST               3 (None)
                       24 RETURN_VALUE
          consts
             'Dictionnary'
             code
                argcount  : 2
-               nlocals   : 11
+               nlocals   : 15
                stacksize : 9
                flags     : 3
                code
                   0x9700740000000000000000000000a00100000000000000000000000000
                   000000000000007c00a6010000ab01000000000000000001007c017c005f
                   0200000000000000007c01740600000000000000000000760173024a0082
                   017c007406000000000000000000007c013c000000740800000000000000
@@ -140,43 +140,52 @@
                   00000000007408000000000000000000006a050000000000000000a00700
                   000000000000000000000000000000000000007408000000000000000000
                   006a050000000000000000a0080000000000000000000000000000000000
                   0000007412000000000000000000006a0a00000000000000006401190000
                   00000000000000a6010000ab010000000000000000a6010000ab01000000
                   00000000009b007408000000000000000000006a0b00000000000000009b
                   0064027408000000000000000000006a0b00000000000000009b0064037c
-                  019b0064049d07a6010000ab010000000000000000723874190000000000
-                  00000000006a0d000000000000000064057c019b009d02a6010000ab0100
-                  000000000000007d02741d000000000000000000007c026a0f0000000000
-                  000000a6010000ab01000000000000000044005d0a5c0200007d037d047c
-                  047c007c033c0000008c0b640053007c006a020000000000000000742000
-                  0000000000000000006a1100000000000000006b0200000000720f742500
-                  0000000000000000006406a6010000ab0100000000000000008201742000
-                  0000000000000000006a130000000000000000730f742900000000000000
-                  0000006407a6010000ab01000000000000000082010900640164006c157d
-                  057c05a0150000000000000000000000000000000000000000a6000000ab
-                  0000000000000000007d06742c00000000000000000000a0170000000000
-                  000000000000000000000000000000743100000000000000000000740600
-                  0000000000000000007420000000000000000000006a1100000000000000
-                  0019000000000000000000a0190000000000000000000000000000000000
-                  000000a6000000ab000000000000000000a6010000ab0100000000000000
-                  007420000000000000000000006a1100000000000000007c01ac08a60300
-                  00ab0300000000000000007d077c05a01500000000000000000000000000
-                  00000000000000a6000000ab0000000000000000007d0874340000000000
-                  00000000006a1b0000000000000000a01c00000000000000000000000000
-                  0000000000000064097c087c067a0a00009b009d02a6010000ab01000000
-                  000000000001006e332300743a00000000000000000000240072267d0974
-                  34000000000000000000006a1b0000000000000000a01e00000000000000
-                  000000000000000000000000007c09a6010000ab01000000000000000001
-                  007c09820164007d097e0977017700780359007701743f00000000000000
-                  0000007406000000000000000000007420000000000000000000006a1100
-                  0000000000000019000000000000000000a0200000000000000000000000
-                  000000000000000000a6000000ab0000000000000000007c07a6020000ab
-                  02000000000000000044005d0a5c0200007d037d0a7c0a7c007c033c0000
-                  008c0b64005300
+                  019b0064049d07a6010000ab01000000000000000072ca640164006c0c7d
+                  027c026a0d0000000000000000a00e000000000000000000000000000000
+                  0000000000a6000000ab0000000000000000009b00740800000000000000
+                  0000006a0b00000000000000009b0064027408000000000000000000006a
+                  0b00000000000000009b0064037c019b0064049d077d0364037c019b009d
+                  027d04741e000000000000000000006a100000000000000000a011000000
+                  00000000000000000000000000000000007c047c03a6020000ab02000000
+                  00000000007d05741e000000000000000000006a100000000000000000a0
+                  1200000000000000000000000000000000000000007c05a6010000ab0100
+                  000000000000007d067c056a130000000000000000a01400000000000000
+                  000000000000000000000000007c06a6010000ab01000000000000000001
+                  00742b000000000000000000006405a6010000ab01000000000000000001
+                  00742d000000000000000000007c066a170000000000000000a6010000ab
+                  01000000000000000044005d0a5c0200007d077d087c087c007c073c0000
+                  008c0b640053007c006a0200000000000000007430000000000000000000
+                  006a1900000000000000006b0200000000720f7435000000000000000000
+                  006406a6010000ab01000000000000000082017430000000000000000000
+                  006a1b0000000000000000730f7439000000000000000000006407a60100
+                  00ab01000000000000000082010900640164006c1d7d097c09a01d000000
+                  0000000000000000000000000000000000a6000000ab0000000000000000
+                  007d0a743c00000000000000000000a01f00000000000000000000000000
+                  000000000000007441000000000000000000007406000000000000000000
+                  007430000000000000000000006a19000000000000000019000000000000
+                  000000a0210000000000000000000000000000000000000000a6000000ab
+                  000000000000000000a6010000ab01000000000000000074300000000000
+                  00000000006a1900000000000000007c01ac08a6030000ab030000000000
+                  0000007d0b7c09a01d0000000000000000000000000000000000000000a6
+                  000000ab0000000000000000007d0c7444000000000000000000006a2300
+                  00000000000000a024000000000000000000000000000000000000000064
+                  097c0c7c0a7a0a00009b009d02a6010000ab01000000000000000001006e
+                  332300744a00000000000000000000240072267d0d744400000000000000
+                  0000006a230000000000000000a026000000000000000000000000000000
+                  00000000007c0da6010000ab01000000000000000001007c0d820164007d
+                  0d7e0d77017700780359007701744f000000000000000000007406000000
+                  000000000000007430000000000000000000006a19000000000000000019
+                  000000000000000000a02800000000000000000000000000000000000000
+                  00a6000000ab0000000000000000007c0ba6020000ab0200000000000000
+                  0044005d0a5c0200007d077d0e7c0e7c007c073c0000008c0b64005300
                 11           0 RESUME                   0
                
                 13           2 LOAD_GLOBAL              0 (dict)
                             14 LOAD_METHOD              1 (__init__)
                             36 LOAD_FAST                0 (self)
                             38 PRECALL                  1
                             42 CALL                     1
@@ -226,201 +235,254 @@
                            356 LOAD_CONST               3 ('dict_')
                            358 LOAD_FAST                1 (lang_id)
                            360 FORMAT_VALUE             0
                            362 LOAD_CONST               4 ('.py')
                            364 BUILD_STRING             7
                            366 PRECALL                  1
                            370 CALL                     1
-                           380 POP_JUMP_FORWARD_IF_FALSE    56 (to 494)
+                           380 POP_JUMP_FORWARD_IF_FALSE   202 (to 786)
                
-                22         382 LOAD_GLOBAL             25 (NULL + importlib)
-                           394 LOAD_ATTR               13 (import_module)
-                           404 LOAD_CONST               5 ('lang.dict_')
-                           406 LOAD_FAST                1 (lang_id)
-                           408 FORMAT_VALUE             0
-                           410 BUILD_STRING             2
-                           412 PRECALL                  1
-                           416 CALL                     1
-                           426 STORE_FAST               2 (module)
-               
-                24         428 LOAD_GLOBAL             29 (NULL + enumerate)
-                           440 LOAD_FAST                2 (module)
-                           442 LOAD_ATTR               15 (texts)
-                           452 PRECALL                  1
-                           456 CALL                     1
-                           466 GET_ITER
-                       >>  468 FOR_ITER                10 (to 490)
-                           470 UNPACK_SEQUENCE          2
-                           474 STORE_FAST               3 (text_id)
-                           476 STORE_FAST               4 (text)
-               
-                25         478 LOAD_FAST                4 (text)
-                           480 LOAD_FAST                0 (self)
-                           482 LOAD_FAST                3 (text_id)
-                           484 STORE_SUBSCR
-                           488 JUMP_BACKWARD           11 (to 468)
-               
-                24     >>  490 LOAD_CONST               0 (None)
-                           492 RETURN_VALUE
-               
-                28     >>  494 LOAD_FAST                0 (self)
-                           496 LOAD_ATTR                2 (lang_id)
-                           506 LOAD_GLOBAL             32 (lang_manager)
-                           518 LOAD_ATTR               17 (ref_language)
-                           528 COMPARE_OP               2 (==)
-                           534 POP_JUMP_FORWARD_IF_FALSE    15 (to 566)
-               
-                29         536 LOAD_GLOBAL             37 (NULL + FileNotFoundError)
-                           548 LOAD_CONST               6 ('The dictionnary for the ref language has not been found')
-                           550 PRECALL                  1
-                           554 CALL                     1
-                           564 RAISE_VARARGS            1
-               
-                31     >>  566 LOAD_GLOBAL             32 (lang_manager)
-                           578 LOAD_ATTR               19 (is_connected_to_network)
-                           588 POP_JUMP_FORWARD_IF_TRUE    15 (to 620)
-               
-                32         590 LOAD_GLOBAL             41 (NULL + ConnectionError)
-                           602 LOAD_CONST               7 ('Translation impossible : baopig.googletrans.lang_manager is not connected to internet')
-                           604 PRECALL                  1
-                           608 CALL                     1
-                           618 RAISE_VARARGS            1
-               
-                35     >>  620 NOP
-               
-                36         622 LOAD_CONST               1 (0)
-                           624 LOAD_CONST               0 (None)
-                           626 IMPORT_NAME             21 (time)
-                           628 STORE_FAST               5 (time)
-               
-                37         630 LOAD_FAST                5 (time)
-                           632 LOAD_METHOD             21 (time)
-                           654 PRECALL                  0
-                           658 CALL                     0
-                           668 STORE_FAST               6 (start_time)
-               
-                39         670 LOAD_GLOBAL             44 (translator)
-                           682 LOAD_METHOD             23 (optimized_translate)
-                           704 LOAD_GLOBAL             49 (NULL + list)
-                           716 LOAD_GLOBAL              6 (dicts)
-                           728 LOAD_GLOBAL             32 (lang_manager)
-                           740 LOAD_ATTR               17 (ref_language)
-                           750 BINARY_SUBSCR
-                           760 LOAD_METHOD             25 (values)
-                           782 PRECALL                  0
-                           786 CALL                     0
-                           796 PRECALL                  1
-                           800 CALL                     1
-               
-                40         810 LOAD_GLOBAL             32 (lang_manager)
-                           822 LOAD_ATTR               17 (ref_language)
-                           832 LOAD_FAST                1 (lang_id)
-               
-                39         834 KW_NAMES                 8
-                           836 PRECALL                  3
-                           840 CALL                     3
-                           850 STORE_FAST               7 (translations)
-               
-                42         852 LOAD_FAST                5 (time)
-                           854 LOAD_METHOD             21 (time)
-                           876 PRECALL                  0
-                           880 CALL                     0
-                           890 STORE_FAST               8 (end_time)
-               
-                43         892 LOAD_GLOBAL             52 (bp)
-                           904 LOAD_ATTR               27 (LOGGER)
-                           914 LOAD_METHOD             28 (fine)
-                           936 LOAD_CONST               9 ('Language loading time : ')
-                           938 LOAD_FAST                8 (end_time)
-                           940 LOAD_FAST                6 (start_time)
-                           942 BINARY_OP               10 (-)
-                           946 FORMAT_VALUE             0
-                           948 BUILD_STRING             2
-                           950 PRECALL                  1
-                           954 CALL                     1
-                           964 POP_TOP
-                           966 JUMP_FORWARD            51 (to 1070)
-                       >>  968 PUSH_EXC_INFO
-               
-                45         970 LOAD_GLOBAL             58 (Exception)
-                           982 CHECK_EXC_MATCH
-                           984 POP_JUMP_FORWARD_IF_FALSE    38 (to 1062)
-                           986 STORE_FAST               9 (e)
-               
-                46         988 LOAD_GLOBAL             52 (bp)
-                          1000 LOAD_ATTR               27 (LOGGER)
-                          1010 LOAD_METHOD             30 (warning)
-                          1032 LOAD_FAST                9 (e)
-                          1034 PRECALL                  1
-                          1038 CALL                     1
-                          1048 POP_TOP
-               
-                47        1050 LOAD_FAST                9 (e)
-                          1052 RAISE_VARARGS            1
-                       >> 1054 LOAD_CONST               0 (None)
-                          1056 STORE_FAST               9 (e)
-                          1058 DELETE_FAST              9 (e)
-                          1060 RERAISE                  1
-               
-                45     >> 1062 RERAISE                  0
-                       >> 1064 COPY                     3
-                          1066 POP_EXCEPT
-                          1068 RERAISE                  1
-               
-                49     >> 1070 LOAD_GLOBAL             63 (NULL + zip)
-                          1082 LOAD_GLOBAL              6 (dicts)
-                          1094 LOAD_GLOBAL             32 (lang_manager)
-                          1106 LOAD_ATTR               17 (ref_language)
-                          1116 BINARY_SUBSCR
-                          1126 LOAD_METHOD             32 (keys)
-                          1148 PRECALL                  0
-                          1152 CALL                     0
-                          1162 LOAD_FAST                7 (translations)
-                          1164 PRECALL                  2
-                          1168 CALL                     2
-                          1178 GET_ITER
-                       >> 1180 FOR_ITER                10 (to 1202)
-                          1182 UNPACK_SEQUENCE          2
-                          1186 STORE_FAST               3 (text_id)
-                          1188 STORE_FAST              10 (translation)
-               
-                50        1190 LOAD_FAST               10 (translation)
-                          1192 LOAD_FAST                0 (self)
-                          1194 LOAD_FAST                3 (text_id)
-                          1196 STORE_SUBSCR
-                          1200 JUMP_BACKWARD           11 (to 1180)
+                22         382 LOAD_CONST               1 (0)
+                           384 LOAD_CONST               0 (None)
+                           386 IMPORT_NAME             12 (pathlib)
+                           388 STORE_FAST               2 (pathlib)
+               
+                23         390 LOAD_FAST                2 (pathlib)
+                           392 LOAD_ATTR               13 (Path)
+                           402 LOAD_METHOD             14 (cwd)
+                           424 PRECALL                  0
+                           428 CALL                     0
+                           438 FORMAT_VALUE             0
+                           440 LOAD_GLOBAL              8 (os)
+                           452 LOAD_ATTR               11 (sep)
+                           462 FORMAT_VALUE             0
+                           464 LOAD_CONST               2 ('lang')
+                           466 LOAD_GLOBAL              8 (os)
+                           478 LOAD_ATTR               11 (sep)
+                           488 FORMAT_VALUE             0
+                           490 LOAD_CONST               3 ('dict_')
+                           492 LOAD_FAST                1 (lang_id)
+                           494 FORMAT_VALUE             0
+                           496 LOAD_CONST               4 ('.py')
+                           498 BUILD_STRING             7
+                           500 STORE_FAST               3 (file_path)
+               
+                24         502 LOAD_CONST               3 ('dict_')
+                           504 LOAD_FAST                1 (lang_id)
+                           506 FORMAT_VALUE             0
+                           508 BUILD_STRING             2
+                           510 STORE_FAST               4 (file_name)
+               
+                25         512 LOAD_GLOBAL             30 (importlib)
+                           524 LOAD_ATTR               16 (util)
+                           534 LOAD_METHOD             17 (spec_from_file_location)
+                           556 LOAD_FAST                4 (file_name)
+                           558 LOAD_FAST                3 (file_path)
+                           560 PRECALL                  2
+                           564 CALL                     2
+                           574 STORE_FAST               5 (spec)
+               
+                26         576 LOAD_GLOBAL             30 (importlib)
+                           588 LOAD_ATTR               16 (util)
+                           598 LOAD_METHOD             18 (module_from_spec)
+                           620 LOAD_FAST                5 (spec)
+                           622 PRECALL                  1
+                           626 CALL                     1
+                           636 STORE_FAST               6 (module)
+               
+                27         638 LOAD_FAST                5 (spec)
+                           640 LOAD_ATTR               19 (loader)
+                           650 LOAD_METHOD             20 (exec_module)
+                           672 LOAD_FAST                6 (module)
+                           674 PRECALL                  1
+                           678 CALL                     1
+                           688 POP_TOP
+               
+                28         690 LOAD_GLOBAL             43 (NULL + print)
+                           702 LOAD_CONST               5 ('zfdegeb')
+                           704 PRECALL                  1
+                           708 CALL                     1
+                           718 POP_TOP
+               
+                30         720 LOAD_GLOBAL             45 (NULL + enumerate)
+                           732 LOAD_FAST                6 (module)
+                           734 LOAD_ATTR               23 (texts)
+                           744 PRECALL                  1
+                           748 CALL                     1
+                           758 GET_ITER
+                       >>  760 FOR_ITER                10 (to 782)
+                           762 UNPACK_SEQUENCE          2
+                           766 STORE_FAST               7 (text_id)
+                           768 STORE_FAST               8 (text)
+               
+                31         770 LOAD_FAST                8 (text)
+                           772 LOAD_FAST                0 (self)
+                           774 LOAD_FAST                7 (text_id)
+                           776 STORE_SUBSCR
+                           780 JUMP_BACKWARD           11 (to 760)
+               
+                30     >>  782 LOAD_CONST               0 (None)
+                           784 RETURN_VALUE
+               
+                34     >>  786 LOAD_FAST                0 (self)
+                           788 LOAD_ATTR                2 (lang_id)
+                           798 LOAD_GLOBAL             48 (lang_manager)
+                           810 LOAD_ATTR               25 (ref_language)
+                           820 COMPARE_OP               2 (==)
+                           826 POP_JUMP_FORWARD_IF_FALSE    15 (to 858)
+               
+                35         828 LOAD_GLOBAL             53 (NULL + FileNotFoundError)
+                           840 LOAD_CONST               6 ('The dictionnary for the ref language has not been found')
+                           842 PRECALL                  1
+                           846 CALL                     1
+                           856 RAISE_VARARGS            1
+               
+                37     >>  858 LOAD_GLOBAL             48 (lang_manager)
+                           870 LOAD_ATTR               27 (is_connected_to_network)
+                           880 POP_JUMP_FORWARD_IF_TRUE    15 (to 912)
+               
+                38         882 LOAD_GLOBAL             57 (NULL + ConnectionError)
+                           894 LOAD_CONST               7 ('Translation impossible : baopig.googletrans.lang_manager is not connected to internet')
+                           896 PRECALL                  1
+                           900 CALL                     1
+                           910 RAISE_VARARGS            1
+               
+                41     >>  912 NOP
+               
+                42         914 LOAD_CONST               1 (0)
+                           916 LOAD_CONST               0 (None)
+                           918 IMPORT_NAME             29 (time)
+                           920 STORE_FAST               9 (time)
+               
+                43         922 LOAD_FAST                9 (time)
+                           924 LOAD_METHOD             29 (time)
+                           946 PRECALL                  0
+                           950 CALL                     0
+                           960 STORE_FAST              10 (start_time)
+               
+                45         962 LOAD_GLOBAL             60 (translator)
+                           974 LOAD_METHOD             31 (optimized_translate)
+                           996 LOAD_GLOBAL             65 (NULL + list)
+                          1008 LOAD_GLOBAL              6 (dicts)
+                          1020 LOAD_GLOBAL             48 (lang_manager)
+                          1032 LOAD_ATTR               25 (ref_language)
+                          1042 BINARY_SUBSCR
+                          1052 LOAD_METHOD             33 (values)
+                          1074 PRECALL                  0
+                          1078 CALL                     0
+                          1088 PRECALL                  1
+                          1092 CALL                     1
+               
+                46        1102 LOAD_GLOBAL             48 (lang_manager)
+                          1114 LOAD_ATTR               25 (ref_language)
+                          1124 LOAD_FAST                1 (lang_id)
+               
+                45        1126 KW_NAMES                 8
+                          1128 PRECALL                  3
+                          1132 CALL                     3
+                          1142 STORE_FAST              11 (translations)
+               
+                48        1144 LOAD_FAST                9 (time)
+                          1146 LOAD_METHOD             29 (time)
+                          1168 PRECALL                  0
+                          1172 CALL                     0
+                          1182 STORE_FAST              12 (end_time)
+               
+                49        1184 LOAD_GLOBAL             68 (bp)
+                          1196 LOAD_ATTR               35 (LOGGER)
+                          1206 LOAD_METHOD             36 (fine)
+                          1228 LOAD_CONST               9 ('Language loading time : ')
+                          1230 LOAD_FAST               12 (end_time)
+                          1232 LOAD_FAST               10 (start_time)
+                          1234 BINARY_OP               10 (-)
+                          1238 FORMAT_VALUE             0
+                          1240 BUILD_STRING             2
+                          1242 PRECALL                  1
+                          1246 CALL                     1
+                          1256 POP_TOP
+                          1258 JUMP_FORWARD            51 (to 1362)
+                       >> 1260 PUSH_EXC_INFO
+               
+                51        1262 LOAD_GLOBAL             74 (Exception)
+                          1274 CHECK_EXC_MATCH
+                          1276 POP_JUMP_FORWARD_IF_FALSE    38 (to 1354)
+                          1278 STORE_FAST              13 (e)
+               
+                52        1280 LOAD_GLOBAL             68 (bp)
+                          1292 LOAD_ATTR               35 (LOGGER)
+                          1302 LOAD_METHOD             38 (warning)
+                          1324 LOAD_FAST               13 (e)
+                          1326 PRECALL                  1
+                          1330 CALL                     1
+                          1340 POP_TOP
+               
+                53        1342 LOAD_FAST               13 (e)
+                          1344 RAISE_VARARGS            1
+                       >> 1346 LOAD_CONST               0 (None)
+                          1348 STORE_FAST              13 (e)
+                          1350 DELETE_FAST             13 (e)
+                          1352 RERAISE                  1
+               
+                51     >> 1354 RERAISE                  0
+                       >> 1356 COPY                     3
+                          1358 POP_EXCEPT
+                          1360 RERAISE                  1
+               
+                55     >> 1362 LOAD_GLOBAL             79 (NULL + zip)
+                          1374 LOAD_GLOBAL              6 (dicts)
+                          1386 LOAD_GLOBAL             48 (lang_manager)
+                          1398 LOAD_ATTR               25 (ref_language)
+                          1408 BINARY_SUBSCR
+                          1418 LOAD_METHOD             40 (keys)
+                          1440 PRECALL                  0
+                          1444 CALL                     0
+                          1454 LOAD_FAST               11 (translations)
+                          1456 PRECALL                  2
+                          1460 CALL                     2
+                          1470 GET_ITER
+                       >> 1472 FOR_ITER                10 (to 1494)
+                          1474 UNPACK_SEQUENCE          2
+                          1478 STORE_FAST               7 (text_id)
+                          1480 STORE_FAST              14 (translation)
+               
+                56        1482 LOAD_FAST               14 (translation)
+                          1484 LOAD_FAST                0 (self)
+                          1486 LOAD_FAST                7 (text_id)
+                          1488 STORE_SUBSCR
+                          1492 JUMP_BACKWARD           11 (to 1472)
                
-                49     >> 1202 LOAD_CONST               0 (None)
-                          1204 RETURN_VALUE
+                55     >> 1494 LOAD_CONST               0 (None)
+                          1496 RETURN_VALUE
                ExceptionTable:
-                 622 to 964 -> 968 [0]
-                 968 to 986 -> 1064 [1] lasti
-                 988 to 1052 -> 1054 [1] lasti
-                 1054 to 1062 -> 1064 [1] lasti
+                 914 to 1256 -> 1260 [0]
+                 1260 to 1278 -> 1356 [1] lasti
+                 1280 to 1344 -> 1346 [1] lasti
+                 1346 to 1354 -> 1356 [1] lasti
                consts
                   None
                   0
                   'lang'
                   'dict_'
                   '.py'
-                  'lang.dict_'
+                  'zfdegeb'
                   'The dictionnary for the ref language has not been found'
                   'Translation impossible : baopig.googletrans.lang_manager is not connected to internet'
                   ('src', 'dest')
                   'Language loading time : '
-               names      ('dict', '__init__', 'lang_id', 'dicts', 'os', 'path', 'exists', 'abspath', 'dirname', 'sys', 'argv', 'sep', 'importlib', 'import_module', 'enumerate', 'texts', 'lang_manager', 'ref_language', 'FileNotFoundError', 'is_connected_to_network', 'ConnectionError', 'time', 'translator', 'optimized_translate', 'list', 'values', 'bp', 'LOGGER', 'fine', 'Exception', 'warning', 'zip', 'keys')
-               varnames   ('self', 'lang_id', 'module', 'text_id', 'text', 'time', 'start_time', 'translations', 'end_time', 'e', 'translation')
+               names      ('dict', '__init__', 'lang_id', 'dicts', 'os', 'path', 'exists', 'abspath', 'dirname', 'sys', 'argv', 'sep', 'pathlib', 'Path', 'cwd', 'importlib', 'util', 'spec_from_file_location', 'module_from_spec', 'loader', 'exec_module', 'print', 'enumerate', 'texts', 'lang_manager', 'ref_language', 'FileNotFoundError', 'is_connected_to_network', 'ConnectionError', 'time', 'translator', 'optimized_translate', 'list', 'values', 'bp', 'LOGGER', 'fine', 'Exception', 'warning', 'zip', 'keys')
+               varnames   ('self', 'lang_id', 'pathlib', 'file_path', 'file_name', 'spec', 'module', 'text_id', 'text', 'time', 'start_time', 'translations', 'end_time', 'e', 'translation')
                freevars   ()
                cellvars   ()
                filename   'C:\\Users\\symrb\\Documents\\dev\\python\\baopig\\baopig\\googletrans\\extension.py'
                name       '__init__'
                firstlineno 11
                lnotab
-                  0x020234020e0216011402ff0011022e0232010cff04042a011e0218011e
-                  030201080128028c0118ff120328014e0212013e010cfe080478010cff
+                  0x020234020e0216011402ff001102080170010a0140013e0134011e0232
+                  010cff04042a011e0218011e030201080128028c0118ff120328014e0212
+                  013e010cfe080478010cff
             code
                argcount  : 1
                nlocals   : 5
                stacksize : 10
                flags     : 3
                code
                   0x97007400000000000000000000006a010000000000000000a002000000
@@ -441,17 +503,17 @@
                   007d037d047c03640c6b0400000000722f7c04a00b000000000000000000
                   0000000000000000000000640e640fa6020000ab0200000000000000007d
                   047c02a009000000000000000000000000000000000000000064097c049b
                   00640d9d03a6010000ab01000000000000000001008c3b7c02a009000000
                   00000000000000000000000000000000006410a6010000ab010000000000
                   0000000100640064006400a6020000ab0200000000000000000100640053
                   002300310073047702780359007701010059000100010064005300
-                52           0 RESUME                   0
+                58           0 RESUME                   0
                
-                54           2 LOAD_GLOBAL              0 (os)
+                60           2 LOAD_GLOBAL              0 (os)
                             14 LOAD_ATTR                1 (path)
                             24 LOAD_METHOD              2 (abspath)
                             46 LOAD_GLOBAL              0 (os)
                             58 LOAD_ATTR                1 (path)
                             68 LOAD_METHOD              3 (dirname)
                             90 LOAD_GLOBAL              8 (sys)
                            102 LOAD_ATTR                5 (argv)
@@ -473,32 +535,32 @@
                            206 LOAD_FAST                0 (self)
                            208 LOAD_ATTR                7 (lang_id)
                            218 FORMAT_VALUE             0
                            220 LOAD_CONST               4 ('.py')
                            222 BUILD_STRING             7
                            224 STORE_FAST               1 (absfilename)
                
-                56         226 LOAD_GLOBAL             17 (NULL + open)
+                62         226 LOAD_GLOBAL             17 (NULL + open)
                            238 LOAD_FAST                1 (absfilename)
                            240 LOAD_CONST               5 ('w')
                            242 LOAD_CONST               6 ('utf8')
                            244 KW_NAMES                 7
                            246 PRECALL                  3
                            250 CALL                     3
                            260 BEFORE_WITH
                            262 STORE_FAST               2 (writer)
                
-                58         264 LOAD_FAST                2 (writer)
+                64         264 LOAD_FAST                2 (writer)
                            266 LOAD_METHOD              9 (write)
                            288 LOAD_CONST               8 ('texts = [\n')
                            290 PRECALL                  1
                            294 CALL                     1
                            304 POP_TOP
                
-                59         306 LOAD_FAST                2 (writer)
+                65         306 LOAD_FAST                2 (writer)
                            308 LOAD_METHOD              9 (write)
                            330 LOAD_CONST               9 ('    "')
                            332 LOAD_FAST                0 (self)
                            334 LOAD_CONST               1 (0)
                            336 BINARY_SUBSCR
                            346 FORMAT_VALUE             0
                            348 LOAD_CONST              10 ('", "')
@@ -513,57 +575,57 @@
                            382 FORMAT_VALUE             0
                            384 LOAD_CONST              13 ('",\n')
                            386 BUILD_STRING             7
                            388 PRECALL                  1
                            392 CALL                     1
                            402 POP_TOP
                
-                61         404 LOAD_FAST                0 (self)
+                67         404 LOAD_FAST                0 (self)
                            406 LOAD_METHOD             10 (items)
                            428 PRECALL                  0
                            432 CALL                     0
                            442 GET_ITER
                        >>  444 FOR_ITER                58 (to 562)
                            446 UNPACK_SEQUENCE          2
                            450 STORE_FAST               3 (i)
                            452 STORE_FAST               4 (text)
                
-                62         454 LOAD_FAST                3 (i)
+                68         454 LOAD_FAST                3 (i)
                            456 LOAD_CONST              12 (2)
                            458 COMPARE_OP               4 (>)
                            464 POP_JUMP_FORWARD_IF_FALSE    47 (to 560)
                
-                63         466 LOAD_FAST                4 (text)
+                69         466 LOAD_FAST                4 (text)
                            468 LOAD_METHOD             11 (replace)
                            490 LOAD_CONST              14 ('\n')
                            492 LOAD_CONST              15 ('\\n')
                            494 PRECALL                  2
                            498 CALL                     2
                            508 STORE_FAST               4 (text)
                
-                64         510 LOAD_FAST                2 (writer)
+                70         510 LOAD_FAST                2 (writer)
                            512 LOAD_METHOD              9 (write)
                            534 LOAD_CONST               9 ('    "')
                            536 LOAD_FAST                4 (text)
                            538 FORMAT_VALUE             0
                            540 LOAD_CONST              13 ('",\n')
                            542 BUILD_STRING             3
                            544 PRECALL                  1
                            548 CALL                     1
                            558 POP_TOP
                        >>  560 JUMP_BACKWARD           59 (to 444)
                
-                66     >>  562 LOAD_FAST                2 (writer)
+                72     >>  562 LOAD_FAST                2 (writer)
                            564 LOAD_METHOD              9 (write)
                            586 LOAD_CONST              16 (']')
                            588 PRECALL                  1
                            592 CALL                     1
                            602 POP_TOP
                
-                56         604 LOAD_CONST               0 (None)
+                62         604 LOAD_CONST               0 (None)
                            606 LOAD_CONST               0 (None)
                            608 LOAD_CONST               0 (None)
                            610 PRECALL                  2
                            614 CALL                     2
                            624 POP_TOP
                            626 LOAD_CONST               0 (None)
                            628 RETURN_VALUE
@@ -604,92 +666,92 @@
                   ']'
                names      ('os', 'path', 'abspath', 'dirname', 'sys', 'argv', 'sep', 'lang_id', 'open', 'write', 'items', 'replace')
                varnames   ('self', 'absfilename', 'writer', 'i', 'text')
                freevars   ()
                cellvars   ()
                filename   'C:\\Users\\symrb\\Documents\\dev\\python\\baopig\\baopig\\googletrans\\extension.py'
                name       'save'
-               firstlineno 52
+               firstlineno 58
                lnotab 0x0202e00226022a01620232010c012c0134022af6
             None
          names      ('__name__', '__module__', '__qualname__', '__init__', 'save')
          varnames   ()
          freevars   ()
          cellvars   ()
          filename   'C:\\Users\\symrb\\Documents\\dev\\python\\baopig\\baopig\\googletrans\\extension.py'
          name       'Dictionnary'
          firstlineno 9
-         lnotab 0x0a020629
+         lnotab 0x0a02062f
       'Dictionnary'
       code
          argcount  : 0
          nlocals   : 0
          stacksize : 3
          flags     : 0
          code
             0x970065005a0164005a02640184005a030200650464028400a6010000ab
             0100000000000000005a050200650464038400a6010000ab010000000000
             0000005a060200650464048400a6010000ab0100000000000000005a0764
             0584005a08640684005a09640784005a0a640884005a0b640984005a0c64
             0a84005a0d640b5300
-          69           0 RESUME                   0
+          75           0 RESUME                   0
                        2 LOAD_NAME                0 (__name__)
                        4 STORE_NAME               1 (__module__)
                        6 LOAD_CONST               0 ('LangManager')
                        8 STORE_NAME               2 (__qualname__)
          
-          71          10 LOAD_CONST               1 (<code object __init__, file "C:\Users\symrb\Documents\dev\python\baopig\baopig\googletrans\extension.py", line 71>)
+          77          10 LOAD_CONST               1 (<code object __init__, file "C:\Users\symrb\Documents\dev\python\baopig\baopig\googletrans\extension.py", line 77>)
                       12 MAKE_FUNCTION            0
                       14 STORE_NAME               3 (__init__)
          
-          84          16 PUSH_NULL
+          90          16 PUSH_NULL
                       18 LOAD_NAME                4 (property)
-                      20 LOAD_CONST               2 (<code object <lambda>, file "C:\Users\symrb\Documents\dev\python\baopig\baopig\googletrans\extension.py", line 84>)
+                      20 LOAD_CONST               2 (<code object <lambda>, file "C:\Users\symrb\Documents\dev\python\baopig\baopig\googletrans\extension.py", line 90>)
                       22 MAKE_FUNCTION            0
                       24 PRECALL                  1
                       28 CALL                     1
                       38 STORE_NAME               5 (is_connected_to_network)
          
-          85          40 PUSH_NULL
+          91          40 PUSH_NULL
                       42 LOAD_NAME                4 (property)
-                      44 LOAD_CONST               3 (<code object <lambda>, file "C:\Users\symrb\Documents\dev\python\baopig\baopig\googletrans\extension.py", line 85>)
+                      44 LOAD_CONST               3 (<code object <lambda>, file "C:\Users\symrb\Documents\dev\python\baopig\baopig\googletrans\extension.py", line 91>)
                       46 MAKE_FUNCTION            0
                       48 PRECALL                  1
                       52 CALL                     1
                       62 STORE_NAME               6 (language)
          
-          86          64 PUSH_NULL
+          92          64 PUSH_NULL
                       66 LOAD_NAME                4 (property)
-                      68 LOAD_CONST               4 (<code object <lambda>, file "C:\Users\symrb\Documents\dev\python\baopig\baopig\googletrans\extension.py", line 86>)
+                      68 LOAD_CONST               4 (<code object <lambda>, file "C:\Users\symrb\Documents\dev\python\baopig\baopig\googletrans\extension.py", line 92>)
                       70 MAKE_FUNCTION            0
                       72 PRECALL                  1
                       76 CALL                     1
                       86 STORE_NAME               7 (ref_language)
          
-          88          88 LOAD_CONST               5 (<code object get_text_from_id, file "C:\Users\symrb\Documents\dev\python\baopig\baopig\googletrans\extension.py", line 88>)
+          94          88 LOAD_CONST               5 (<code object get_text_from_id, file "C:\Users\symrb\Documents\dev\python\baopig\baopig\googletrans\extension.py", line 94>)
                       90 MAKE_FUNCTION            0
                       92 STORE_NAME               8 (get_text_from_id)
          
-          94          94 LOAD_CONST               6 (<code object remove_widget, file "C:\Users\symrb\Documents\dev\python\baopig\baopig\googletrans\extension.py", line 94>)
+         100          94 LOAD_CONST               6 (<code object remove_widget, file "C:\Users\symrb\Documents\dev\python\baopig\baopig\googletrans\extension.py", line 100>)
                       96 MAKE_FUNCTION            0
                       98 STORE_NAME               9 (remove_widget)
          
-          98         100 LOAD_CONST               7 (<code object set_connected, file "C:\Users\symrb\Documents\dev\python\baopig\baopig\googletrans\extension.py", line 98>)
+         104         100 LOAD_CONST               7 (<code object set_connected, file "C:\Users\symrb\Documents\dev\python\baopig\baopig\googletrans\extension.py", line 104>)
                      102 MAKE_FUNCTION            0
                      104 STORE_NAME              10 (set_connected)
          
-         114         106 LOAD_CONST               8 (<code object set_language, file "C:\Users\symrb\Documents\dev\python\baopig\baopig\googletrans\extension.py", line 114>)
+         120         106 LOAD_CONST               8 (<code object set_language, file "C:\Users\symrb\Documents\dev\python\baopig\baopig\googletrans\extension.py", line 120>)
                      108 MAKE_FUNCTION            0
                      110 STORE_NAME              11 (set_language)
          
-         138         112 LOAD_CONST               9 (<code object set_ref_language, file "C:\Users\symrb\Documents\dev\python\baopig\baopig\googletrans\extension.py", line 138>)
+         144         112 LOAD_CONST               9 (<code object set_ref_language, file "C:\Users\symrb\Documents\dev\python\baopig\baopig\googletrans\extension.py", line 144>)
                      114 MAKE_FUNCTION            0
                      116 STORE_NAME              12 (set_ref_language)
          
-         148         118 LOAD_CONST              10 (<code object set_ref_text, file "C:\Users\symrb\Documents\dev\python\baopig\baopig\googletrans\extension.py", line 148>)
+         154         118 LOAD_CONST              10 (<code object set_ref_text, file "C:\Users\symrb\Documents\dev\python\baopig\baopig\googletrans\extension.py", line 154>)
                      120 MAKE_FUNCTION            0
                      122 STORE_NAME              13 (set_ref_text)
                      124 LOAD_CONST              11 (None)
                      126 RETURN_VALUE
          consts
             'LangManager'
             code
@@ -702,51 +764,51 @@
                   00000000000000000000000000000000007c00a6010000ab010000000000
                   000000010069007c005f03000000000000000069007c005f040000000000
                   000000640078017c005f0500000000000000007c005f0600000000000000
                   0064017c005f0700000000000000007c00a0080000000000000000000000
                   0000000000000000006402a6010000ab01000000000000000001007c00a0
                   0800000000000000000000000000000000000000006403a6010000ab0100
                   00000000000000010064005300
-                71           0 RESUME                   0
+                77           0 RESUME                   0
                
-                73           2 LOAD_GLOBAL              0 (bp)
+                79           2 LOAD_GLOBAL              0 (bp)
                             14 LOAD_ATTR                1 (Communicative)
                             24 LOAD_METHOD              2 (__init__)
                             46 LOAD_FAST                0 (self)
                             48 PRECALL                  1
                             52 CALL                     1
                             62 POP_TOP
                
-                75          64 BUILD_MAP                0
+                81          64 BUILD_MAP                0
                             66 LOAD_FAST                0 (self)
                             68 STORE_ATTR               3 (_ref_texts)
                
-                76          78 BUILD_MAP                0
+                82          78 BUILD_MAP                0
                             80 LOAD_FAST                0 (self)
                             82 STORE_ATTR               4 (_textid_by_widget)
                
-                77          92 LOAD_CONST               0 (None)
+                83          92 LOAD_CONST               0 (None)
                             94 COPY                     1
                             96 LOAD_FAST                0 (self)
                             98 STORE_ATTR               5 (_ref_language)
                            108 LOAD_FAST                0 (self)
                            110 STORE_ATTR               6 (_language)
                
-                79         120 LOAD_CONST               1 (True)
+                85         120 LOAD_CONST               1 (True)
                            122 LOAD_FAST                0 (self)
                            124 STORE_ATTR               7 (_is_connected_to_network)
                
-                81         134 LOAD_FAST                0 (self)
+                87         134 LOAD_FAST                0 (self)
                            136 LOAD_METHOD              8 (create_signal)
                            158 LOAD_CONST               2 ('UPDATE_LANGUAGE')
                            160 PRECALL                  1
                            164 CALL                     1
                            174 POP_TOP
                
-                82         176 LOAD_FAST                0 (self)
+                88         176 LOAD_FAST                0 (self)
                            178 LOAD_METHOD              8 (create_signal)
                            200 LOAD_CONST               3 ('NEW_CONNECTION_STATE')
                            202 PRECALL                  1
                            206 CALL                     1
                            216 POP_TOP
                            218 LOAD_CONST               0 (None)
                            220 RETURN_VALUE
@@ -757,116 +819,116 @@
                   'NEW_CONNECTION_STATE'
                names      ('bp', 'Communicative', '__init__', '_ref_texts', '_textid_by_widget', '_ref_language', '_language', '_is_connected_to_network', 'create_signal')
                varnames   ('self',)
                freevars   ()
                cellvars   ()
                filename   'C:\\Users\\symrb\\Documents\\dev\\python\\baopig\\baopig\\googletrans\\extension.py'
                name       '__init__'
-               firstlineno 71
+               firstlineno 77
                lnotab 0x02023e020e010e011c020e022a01
             code
                argcount  : 1
                nlocals   : 1
                stacksize : 1
                flags     : 3
                code 0x97007c006a0000000000000000005300
-                84           0 RESUME                   0
+                90           0 RESUME                   0
                              2 LOAD_FAST                0 (self)
                              4 LOAD_ATTR                0 (_is_connected_to_network)
                             14 RETURN_VALUE
                consts
                   None
                names      ('_is_connected_to_network',)
                varnames   ('self',)
                freevars   ()
                cellvars   ()
                filename   'C:\\Users\\symrb\\Documents\\dev\\python\\baopig\\baopig\\googletrans\\extension.py'
                name       '<lambda>'
-               firstlineno 84
+               firstlineno 90
                lnotab 0x
             code
                argcount  : 1
                nlocals   : 1
                stacksize : 1
                flags     : 3
                code 0x97007c006a0000000000000000005300
-                85           0 RESUME                   0
+                91           0 RESUME                   0
                              2 LOAD_FAST                0 (self)
                              4 LOAD_ATTR                0 (_language)
                             14 RETURN_VALUE
                consts
                   None
                names      ('_language',)
                varnames   ('self',)
                freevars   ()
                cellvars   ()
                filename   'C:\\Users\\symrb\\Documents\\dev\\python\\baopig\\baopig\\googletrans\\extension.py'
                name       '<lambda>'
-               firstlineno 85
+               firstlineno 91
                lnotab 0x
             code
                argcount  : 1
                nlocals   : 1
                stacksize : 1
                flags     : 3
                code 0x97007c006a0000000000000000005300
-                86           0 RESUME                   0
+                92           0 RESUME                   0
                              2 LOAD_FAST                0 (self)
                              4 LOAD_ATTR                0 (_ref_language)
                             14 RETURN_VALUE
                consts
                   None
                names      ('_ref_language',)
                varnames   ('self',)
                freevars   ()
                cellvars   ()
                filename   'C:\\Users\\symrb\\Documents\\dev\\python\\baopig\\baopig\\googletrans\\extension.py'
                name       '<lambda>'
-               firstlineno 86
+               firstlineno 92
                lnotab 0x
             code
                argcount  : 2
                nlocals   : 2
                stacksize : 4
                flags     : 3
                code
                   0x970009007400000000000000000000007c006a01000000000000000019
                   0000000000000000007c0119000000000000000000530023007404000000
                   000000000000002400721b01007400000000000000000000007c006a0300
                   00000000000000190000000000000000007c011900000000000000000063
                   02590053007700780359007701
-                88           0 RESUME                   0
+                94           0 RESUME                   0
                
-                89           2 NOP
+                95           2 NOP
                
-                90           4 LOAD_GLOBAL              0 (dicts)
+                96           4 LOAD_GLOBAL              0 (dicts)
                             16 LOAD_FAST                0 (self)
                             18 LOAD_ATTR                1 (_language)
                             28 BINARY_SUBSCR
                             38 LOAD_FAST                1 (text_id)
                             40 BINARY_SUBSCR
                             50 RETURN_VALUE
                        >>   52 PUSH_EXC_INFO
                
-                91          54 LOAD_GLOBAL              4 (KeyError)
+                97          54 LOAD_GLOBAL              4 (KeyError)
                             66 CHECK_EXC_MATCH
                             68 POP_JUMP_FORWARD_IF_FALSE    27 (to 124)
                             70 POP_TOP
                
-                92          72 LOAD_GLOBAL              0 (dicts)
+                98          72 LOAD_GLOBAL              0 (dicts)
                             84 LOAD_FAST                0 (self)
                             86 LOAD_ATTR                3 (_ref_language)
                             96 BINARY_SUBSCR
                            106 LOAD_FAST                1 (text_id)
                            108 BINARY_SUBSCR
                            118 SWAP                     2
                            120 POP_EXCEPT
                            122 RETURN_VALUE
                
-                91     >>  124 RERAISE                  0
+                97     >>  124 RERAISE                  0
                        >>  126 COPY                     3
                            128 POP_EXCEPT
                            130 RERAISE                  1
                ExceptionTable:
                  4 to 48 -> 52 [0]
                  52 to 118 -> 126 [1] lasti
                  124 to 124 -> 126 [1] lasti
@@ -874,37 +936,37 @@
                   None
                names      ('dicts', '_language', 'KeyError', '_ref_language')
                varnames   ('self', 'text_id')
                freevars   ()
                cellvars   ()
                filename   'C:\\Users\\symrb\\Documents\\dev\\python\\baopig\\baopig\\googletrans\\extension.py'
                name       'get_text_from_id'
-               firstlineno 88
+               firstlineno 94
                lnotab 0x020102013201120134ff
             code
                argcount  : 2
                nlocals   : 2
                stacksize : 3
                flags     : 3
                code
                   0x97007c006a000000000000000000a00100000000000000000000000000
                   000000000000007c01a6010000ab01000000000000000001007c006a0200
                   00000000000000a00100000000000000000000000000000000000000007c
                   01a6010000ab010000000000000000010064005300
-                94           0 RESUME                   0
+               100           0 RESUME                   0
                
-                95           2 LOAD_FAST                0 (self)
+               101           2 LOAD_FAST                0 (self)
                              4 LOAD_ATTR                0 (_ref_texts)
                             14 LOAD_METHOD              1 (pop)
                             36 LOAD_FAST                1 (widget)
                             38 PRECALL                  1
                             42 CALL                     1
                             52 POP_TOP
                
-                96          54 LOAD_FAST                0 (self)
+               102          54 LOAD_FAST                0 (self)
                             56 LOAD_ATTR                2 (_textid_by_widget)
                             66 LOAD_METHOD              1 (pop)
                             88 LOAD_FAST                1 (widget)
                             90 PRECALL                  1
                             94 CALL                     1
                            104 POP_TOP
                            106 LOAD_CONST               0 (None)
@@ -913,65 +975,65 @@
                   None
                names      ('_ref_texts', 'pop', '_textid_by_widget')
                varnames   ('self', 'widget')
                freevars   ()
                cellvars   ()
                filename   'C:\\Users\\symrb\\Documents\\dev\\python\\baopig\\baopig\\googletrans\\extension.py'
                name       'remove_widget'
-               firstlineno 94
+               firstlineno 100
                lnotab 0x02013401
             code
                argcount  : 2
                nlocals   : 2
                stacksize : 3
                flags     : 3
                code
                   0x97007401000000000000000000007c01a6010000ab0100000000000000
                   007c006a0100000000000000006b02000000007202640053007c01722374
                   0400000000000000000000a0030000000000000000000000000000000000
                   000000a6000000ab000000000000000000720864017c005f040000000000
                   0000006e096400530064027c005f0400000000000000007c006a05000000
                   00000000006a060000000000000000a00700000000000000000000000000
                   00000000000000a6000000ab000000000000000000010064005300
-                98           0 RESUME                   0
+               104           0 RESUME                   0
                
-               100           2 LOAD_GLOBAL              1 (NULL + bool)
+               106           2 LOAD_GLOBAL              1 (NULL + bool)
                             14 LOAD_FAST                1 (connected)
                             16 PRECALL                  1
                             20 CALL                     1
                             30 LOAD_FAST                0 (self)
                             32 LOAD_ATTR                1 (is_connected_to_network)
                             42 COMPARE_OP               2 (==)
                             48 POP_JUMP_FORWARD_IF_FALSE     2 (to 54)
                
-               101          50 LOAD_CONST               0 (None)
+               107          50 LOAD_CONST               0 (None)
                             52 RETURN_VALUE
                
-               103     >>   54 LOAD_FAST                1 (connected)
+               109     >>   54 LOAD_FAST                1 (connected)
                             56 POP_JUMP_FORWARD_IF_FALSE    35 (to 128)
                
-               104          58 LOAD_GLOBAL              4 (translator)
+               110          58 LOAD_GLOBAL              4 (translator)
                             70 LOAD_METHOD              3 (test_connection)
                             92 PRECALL                  0
                             96 CALL                     0
                            106 POP_JUMP_FORWARD_IF_FALSE     8 (to 124)
                
-               105         108 LOAD_CONST               1 (True)
+               111         108 LOAD_CONST               1 (True)
                            110 LOAD_FAST                0 (self)
                            112 STORE_ATTR               4 (_is_connected_to_network)
                            122 JUMP_FORWARD             9 (to 142)
                
-               107     >>  124 LOAD_CONST               0 (None)
+               113     >>  124 LOAD_CONST               0 (None)
                            126 RETURN_VALUE
                
-               110     >>  128 LOAD_CONST               2 (False)
+               116     >>  128 LOAD_CONST               2 (False)
                            130 LOAD_FAST                0 (self)
                            132 STORE_ATTR               4 (_is_connected_to_network)
                
-               112     >>  142 LOAD_FAST                0 (self)
+               118     >>  142 LOAD_FAST                0 (self)
                            144 LOAD_ATTR                5 (signal)
                            154 LOAD_ATTR                6 (NEW_CONNECTION_STATE)
                            164 LOAD_METHOD              7 (emit)
                            186 PRECALL                  0
                            190 CALL                     0
                            200 POP_TOP
                            202 LOAD_CONST               0 (None)
@@ -982,15 +1044,15 @@
                   False
                names      ('bool', 'is_connected_to_network', 'translator', 'test_connection', '_is_connected_to_network', 'signal', 'NEW_CONNECTION_STATE', 'emit')
                varnames   ('self', 'connected')
                freevars   ()
                cellvars   ()
                filename   'C:\\Users\\symrb\\Documents\\dev\\python\\baopig\\baopig\\googletrans\\extension.py'
                name       'set_connected'
-               firstlineno 98
+               firstlineno 104
                lnotab 0x02023001040204013201100204030e02
             code
                argcount  : 2
                nlocals   : 4
                stacksize : 6
                flags     : 3
                code
@@ -1007,100 +1069,100 @@
                   00000000000000000000007c00a008000000000000000000000000000000
                   00000000007c026a090000000000000000a6010000ab0100000000000000
                   00a6010000ab01000000000000000001007c02a007000000000000000000
                   0000000000000000000000a6000000ab00000000000000000001008c447c
                   006a0a00000000000000006a0b0000000000000000a00c00000000000000
                   00000000000000000000000000a6000000ab000000000000000000010064
                   005300
-               114           0 RESUME                   0
+               120           0 RESUME                   0
                
-               116           2 LOAD_FAST                1 (lang_id)
+               122           2 LOAD_FAST                1 (lang_id)
                              4 LOAD_FAST                0 (self)
                              6 LOAD_ATTR                0 (_language)
                             16 COMPARE_OP               2 (==)
                             22 POP_JUMP_FORWARD_IF_FALSE     2 (to 28)
                
-               117          24 LOAD_CONST               0 (None)
+               123          24 LOAD_CONST               0 (None)
                             26 RETURN_VALUE
                
-               119     >>   28 LOAD_FAST                1 (lang_id)
+               125     >>   28 LOAD_FAST                1 (lang_id)
                             30 LOAD_GLOBAL              2 (dicts)
                             42 CONTAINS_OP              1
                             44 POP_JUMP_FORWARD_IF_FALSE    15 (to 76)
                
-               120          46 LOAD_GLOBAL              5 (NULL + Dictionnary)
+               126          46 LOAD_GLOBAL              5 (NULL + Dictionnary)
                             58 LOAD_FAST                1 (lang_id)
                             60 PRECALL                  1
                             64 CALL                     1
                             74 POP_TOP
                
-               122     >>   76 LOAD_FAST                1 (lang_id)
+               128     >>   76 LOAD_FAST                1 (lang_id)
                             78 LOAD_FAST                0 (self)
                             80 STORE_ATTR               0 (_language)
                
-               124          90 LOAD_FAST                0 (self)
+               130          90 LOAD_FAST                0 (self)
                             92 LOAD_ATTR                0 (_language)
                            102 LOAD_FAST                0 (self)
                            104 LOAD_ATTR                3 (_ref_language)
                            114 COMPARE_OP               2 (==)
                            120 POP_JUMP_FORWARD_IF_FALSE    73 (to 268)
                
-               126         122 LOAD_FAST                0 (self)
+               132         122 LOAD_FAST                0 (self)
                            124 LOAD_ATTR                4 (_ref_texts)
                            134 LOAD_METHOD              5 (items)
                            156 PRECALL                  0
                            160 CALL                     0
                            170 GET_ITER
                        >>  172 FOR_ITER                46 (to 266)
                            174 UNPACK_SEQUENCE          2
                            178 STORE_FAST               2 (widget)
                            180 STORE_FAST               3 (text)
                
-               127         182 LOAD_FAST                2 (widget)
+               133         182 LOAD_FAST                2 (widget)
                            184 LOAD_METHOD              6 (set_text)
                            206 LOAD_FAST                3 (text)
                            208 PRECALL                  1
                            212 CALL                     1
                            222 POP_TOP
                
-               128         224 LOAD_FAST                2 (widget)
+               134         224 LOAD_FAST                2 (widget)
                            226 LOAD_METHOD              7 (fit)
                            248 PRECALL                  0
                            252 CALL                     0
                            262 POP_TOP
                            264 JUMP_BACKWARD           47 (to 172)
                
-               126     >>  266 JUMP_FORWARD            75 (to 418)
+               132     >>  266 JUMP_FORWARD            75 (to 418)
                
-               132     >>  268 LOAD_FAST                0 (self)
+               138     >>  268 LOAD_FAST                0 (self)
                            270 LOAD_ATTR                4 (_ref_texts)
                            280 GET_ITER
                        >>  282 FOR_ITER                67 (to 418)
                            284 STORE_FAST               2 (widget)
                
-               133         286 LOAD_FAST                2 (widget)
+               139         286 LOAD_FAST                2 (widget)
                            288 LOAD_METHOD              6 (set_text)
                            310 LOAD_FAST                0 (self)
                            312 LOAD_METHOD              8 (get_text_from_id)
                            334 LOAD_FAST                2 (widget)
                            336 LOAD_ATTR                9 (text_id)
                            346 PRECALL                  1
                            350 CALL                     1
                            360 PRECALL                  1
                            364 CALL                     1
                            374 POP_TOP
                
-               134         376 LOAD_FAST                2 (widget)
+               140         376 LOAD_FAST                2 (widget)
                            378 LOAD_METHOD              7 (fit)
                            400 PRECALL                  0
                            404 CALL                     0
                            414 POP_TOP
                            416 JUMP_BACKWARD           68 (to 282)
                
-               136     >>  418 LOAD_FAST                0 (self)
+               142     >>  418 LOAD_FAST                0 (self)
                            420 LOAD_ATTR               10 (signal)
                            430 LOAD_ATTR               11 (UPDATE_LANGUAGE)
                            440 LOAD_METHOD             12 (emit)
                            462 PRECALL                  0
                            466 CALL                     0
                            476 POP_TOP
                            478 LOAD_CONST               0 (None)
@@ -1109,15 +1171,15 @@
                   None
                names      ('_language', 'dicts', 'Dictionnary', '_ref_language', '_ref_texts', 'items', 'set_text', 'fit', 'get_text_from_id', 'text_id', 'signal', 'UPDATE_LANGUAGE', 'emit')
                varnames   ('self', 'lang_id', 'widget', 'text')
                freevars   ()
                cellvars   ()
                filename   'C:\\Users\\symrb\\Documents\\dev\\python\\baopig\\baopig\\googletrans\\extension.py'
                name       'set_language'
-               firstlineno 114
+               firstlineno 120
                lnotab 0x02021601040212011e020e0220023c012a012afe020612015a012a02
             code
                argcount  : 2
                nlocals   : 2
                stacksize : 4
                flags     : 3
                code
@@ -1125,30 +1187,30 @@
                   0000009b009d02a6000000ab000000000000000000820174030000000000
                   00000000007c01740400000000000000000000a6020000ab020000000000
                   00000072137407000000000000000000007c01a6010000ab010000000000
                   00000064026b020000000073024a0082017c0178017c005f000000000000
                   0000007c005f0400000000000000007c01740a0000000000000000000076
                   017211740d000000000000000000007c01a6010000ab0100000000000000
                   0001006400530064005300
-               138           0 RESUME                   0
+               144           0 RESUME                   0
                
-               140           2 LOAD_FAST                0 (self)
+               146           2 LOAD_FAST                0 (self)
                              4 LOAD_ATTR                0 (_ref_language)
                             14 POP_JUMP_FORWARD_IF_NONE    18 (to 52)
                             16 LOAD_ASSERTION_ERROR
                             18 LOAD_CONST               1 ('The reference language is already set to ')
                             20 LOAD_FAST                0 (self)
                             22 LOAD_ATTR                0 (_ref_language)
                             32 FORMAT_VALUE             0
                             34 BUILD_STRING             2
                             36 PRECALL                  0
                             40 CALL                     0
                             50 RAISE_VARARGS            1
                
-               141     >>   52 LOAD_GLOBAL              3 (NULL + isinstance)
+               147     >>   52 LOAD_GLOBAL              3 (NULL + isinstance)
                             64 LOAD_FAST                1 (ref_lang_id)
                             66 LOAD_GLOBAL              4 (str)
                             78 PRECALL                  2
                             82 CALL                     2
                             92 POP_JUMP_FORWARD_IF_FALSE    19 (to 132)
                             94 LOAD_GLOBAL              7 (NULL + len)
                            106 LOAD_FAST                1 (ref_lang_id)
@@ -1156,47 +1218,47 @@
                            112 CALL                     1
                            122 LOAD_CONST               2 (2)
                            124 COMPARE_OP               2 (==)
                            130 POP_JUMP_FORWARD_IF_TRUE     2 (to 136)
                        >>  132 LOAD_ASSERTION_ERROR
                            134 RAISE_VARARGS            1
                
-               143     >>  136 LOAD_FAST                1 (ref_lang_id)
+               149     >>  136 LOAD_FAST                1 (ref_lang_id)
                            138 COPY                     1
                            140 LOAD_FAST                0 (self)
                            142 STORE_ATTR               0 (_ref_language)
                            152 LOAD_FAST                0 (self)
                            154 STORE_ATTR               4 (_language)
                
-               145         164 LOAD_FAST                1 (ref_lang_id)
+               151         164 LOAD_FAST                1 (ref_lang_id)
                            166 LOAD_GLOBAL             10 (dicts)
                            178 CONTAINS_OP              1
                            180 POP_JUMP_FORWARD_IF_FALSE    17 (to 216)
                
-               146         182 LOAD_GLOBAL             13 (NULL + Dictionnary)
+               152         182 LOAD_GLOBAL             13 (NULL + Dictionnary)
                            194 LOAD_FAST                1 (ref_lang_id)
                            196 PRECALL                  1
                            200 CALL                     1
                            210 POP_TOP
                            212 LOAD_CONST               0 (None)
                            214 RETURN_VALUE
                
-               145     >>  216 LOAD_CONST               0 (None)
+               151     >>  216 LOAD_CONST               0 (None)
                            218 RETURN_VALUE
                consts
                   None
                   'The reference language is already set to '
                   2
                names      ('_ref_language', 'isinstance', 'str', 'len', '_language', 'dicts', 'Dictionnary')
                varnames   ('self', 'ref_lang_id')
                freevars   ()
                cellvars   ()
                filename   'C:\\Users\\symrb\\Documents\\dev\\python\\baopig\\baopig\\googletrans\\extension.py'
                name       'set_ref_language'
-               firstlineno 138
+               firstlineno 144
                lnotab 0x0202320154021c02120122ff
             code
                argcount  : 3
                nlocals   : 4
                stacksize : 5
                flags     : 3
                code
@@ -1204,52 +1266,52 @@
                   0000000000000000007d037c037c006a0100000000000000007c013c0000
                   007c027c006a0200000000000000007c013c0000007c027c015f03000000
                   00000000007c01a00400000000000000000000000000000000000000007c
                   00a00500000000000000000000000000000000000000007c016a03000000
                   0000000000a6010000ab010000000000000000a6010000ab010000000000
                   00000001007c01a0060000000000000000000000000000000000000000a6
                   000000ab000000000000000000010064005300
-               148           0 RESUME                   0
+               154           0 RESUME                   0
                
-               150           2 LOAD_GLOBAL              0 (dicts)
+               156           2 LOAD_GLOBAL              0 (dicts)
                             14 LOAD_CONST               1 ('fr')
                             16 BINARY_SUBSCR
                             26 LOAD_FAST                2 (text_id)
                             28 BINARY_SUBSCR
                             38 STORE_FAST               3 (text)
                
-               151          40 LOAD_FAST                3 (text)
+               157          40 LOAD_FAST                3 (text)
                             42 LOAD_FAST                0 (self)
                             44 LOAD_ATTR                1 (_ref_texts)
                             54 LOAD_FAST                1 (widget)
                             56 STORE_SUBSCR
                
-               152          60 LOAD_FAST                2 (text_id)
+               158          60 LOAD_FAST                2 (text_id)
                             62 LOAD_FAST                0 (self)
                             64 LOAD_ATTR                2 (_textid_by_widget)
                             74 LOAD_FAST                1 (widget)
                             76 STORE_SUBSCR
                
-               153          80 LOAD_FAST                2 (text_id)
+               159          80 LOAD_FAST                2 (text_id)
                             82 LOAD_FAST                1 (widget)
                             84 STORE_ATTR               3 (text_id)
                
-               154          94 LOAD_FAST                1 (widget)
+               160          94 LOAD_FAST                1 (widget)
                             96 LOAD_METHOD              4 (set_text)
                            118 LOAD_FAST                0 (self)
                            120 LOAD_METHOD              5 (get_text_from_id)
                            142 LOAD_FAST                1 (widget)
                            144 LOAD_ATTR                3 (text_id)
                            154 PRECALL                  1
                            158 CALL                     1
                            168 PRECALL                  1
                            172 CALL                     1
                            182 POP_TOP
                
-               155         184 LOAD_FAST                1 (widget)
+               161         184 LOAD_FAST                1 (widget)
                            186 LOAD_METHOD              6 (fit)
                            208 PRECALL                  0
                            212 CALL                     0
                            222 POP_TOP
                            224 LOAD_CONST               0 (None)
                            226 RETURN_VALUE
                consts
@@ -1257,49 +1319,49 @@
                   'fr'
                names      ('dicts', '_ref_texts', '_textid_by_widget', 'text_id', 'set_text', 'get_text_from_id', 'fit')
                varnames   ('self', 'widget', 'text_id', 'text')
                freevars   ()
                cellvars   ()
                filename   'C:\\Users\\symrb\\Documents\\dev\\python\\baopig\\baopig\\googletrans\\extension.py'
                name       'set_ref_text'
-               firstlineno 148
+               firstlineno 154
                lnotab 0x02022601140114010e015a01
             None
          names      ('__name__', '__module__', '__qualname__', '__init__', 'property', 'is_connected_to_network', 'language', 'ref_language', 'get_text_from_id', 'remove_widget', 'set_connected', 'set_language', 'set_ref_language', 'set_ref_text')
          varnames   ()
          freevars   ()
          cellvars   ()
          filename   'C:\\Users\\symrb\\Documents\\dev\\python\\baopig\\baopig\\googletrans\\extension.py'
          name       'LangManager'
-         firstlineno 69
+         firstlineno 75
          lnotab 0x0a02060d1801180118020606060406100618060a
       'LangManager'
       code
          argcount  : 0
          nlocals   : 0
          stacksize : 2
          flags     : 0
          code
             0x8700970065005a0164005a02640184005a0388006601640284085a0488
             0078015a055300
                        0 MAKE_CELL                0 (__class__)
          
-         158           2 RESUME                   0
+         164           2 RESUME                   0
                        4 LOAD_NAME                0 (__name__)
                        6 STORE_NAME               1 (__module__)
                        8 LOAD_CONST               0 ('OptimizedTranslator')
                       10 STORE_NAME               2 (__qualname__)
          
-         160          12 LOAD_CONST               1 (<code object optimized_translate, file "C:\Users\symrb\Documents\dev\python\baopig\baopig\googletrans\extension.py", line 160>)
+         166          12 LOAD_CONST               1 (<code object optimized_translate, file "C:\Users\symrb\Documents\dev\python\baopig\baopig\googletrans\extension.py", line 166>)
                       14 MAKE_FUNCTION            0
                       16 STORE_NAME               3 (optimized_translate)
          
-         195          18 LOAD_CLOSURE             0 (__class__)
+         201          18 LOAD_CLOSURE             0 (__class__)
                       20 BUILD_TUPLE              1
-                      22 LOAD_CONST               2 (<code object test_connection, file "C:\Users\symrb\Documents\dev\python\baopig\baopig\googletrans\extension.py", line 195>)
+                      22 LOAD_CONST               2 (<code object test_connection, file "C:\Users\symrb\Documents\dev\python\baopig\baopig\googletrans\extension.py", line 201>)
                       24 MAKE_FUNCTION            8 (closure)
                       26 STORE_NAME               4 (test_connection)
                       28 LOAD_CLOSURE             0 (__class__)
                       30 COPY                     1
                       32 STORE_NAME               5 (__classcell__)
                       34 RETURN_VALUE
          consts
@@ -1338,157 +1400,157 @@
                   00000000000000000000000000000000000000640b84007c0b640c190000
                   000000000000004400a6000000ab000000000000000000a6010000ab0100
                   000000000000005300
                              0 MAKE_CELL                0 (self)
                              2 MAKE_CELL                2 (src)
                              4 MAKE_CELL                3 (dest)
                
-               160           6 RESUME                   0
+               166           6 RESUME                   0
                
-               162           8 LOAD_GLOBAL              1 (NULL + isinstance)
+               168           8 LOAD_GLOBAL              1 (NULL + isinstance)
                             20 LOAD_FAST                1 (text)
                             22 LOAD_GLOBAL              2 (list)
                             34 PRECALL                  2
                             38 CALL                     2
                             48 EXTENDED_ARG             1
                             50 POP_JUMP_FORWARD_IF_FALSE   256 (to 564)
                
-               164          52 LOAD_CONST               1 ('\n')
+               170          52 LOAD_CONST               1 ('\n')
                             54 STORE_FAST               4 (sep)
                
-               165          56 LOAD_CONST               2 ('')
+               171          56 LOAD_CONST               2 ('')
                             58 STORE_FAST               5 (sep_transition)
                
-               166          60 LOAD_CONST               3 ('')
+               172          60 LOAD_CONST               3 ('')
                             62 STORE_FAST               6 (sep_encoded)
                
-               167          64 LOAD_GLOBAL              5 (NULL + len)
+               173          64 LOAD_GLOBAL              5 (NULL + len)
                             76 LOAD_FAST                1 (text)
                             78 PRECALL                  1
                             82 CALL                     1
                             92 STORE_FAST               7 (ln)
                
-               168          94 LOAD_FAST                5 (sep_transition)
+               174          94 LOAD_FAST                5 (sep_transition)
                             96 LOAD_METHOD              3 (join)
                            118 LOAD_FAST                1 (text)
                            120 PRECALL                  1
                            124 CALL                     1
                            134 STORE_FAST               8 (joined)
                
-               169         136 LOAD_FAST                8 (joined)
+               175         136 LOAD_FAST                8 (joined)
                            138 LOAD_METHOD              4 (replace)
                            160 LOAD_FAST                4 (sep)
                            162 LOAD_FAST                6 (sep_encoded)
                            164 PRECALL                  2
                            168 CALL                     2
                            178 STORE_FAST               8 (joined)
                
-               170         180 LOAD_FAST                8 (joined)
+               176         180 LOAD_FAST                8 (joined)
                            182 LOAD_METHOD              4 (replace)
                            204 LOAD_FAST                5 (sep_transition)
                            206 LOAD_FAST                4 (sep)
                            208 PRECALL                  2
                            212 CALL                     2
                            222 STORE_FAST               8 (joined)
                
-               171         224 LOAD_DEREF               0 (self)
+               177         224 LOAD_DEREF               0 (self)
                            226 LOAD_METHOD              5 (optimized_translate)
                            248 LOAD_FAST                8 (joined)
                            250 LOAD_DEREF               3 (dest)
                            252 LOAD_DEREF               2 (src)
                            254 KW_NAMES                 4
                            256 PRECALL                  3
                            260 CALL                     3
                            270 STORE_FAST               9 (joined_translated)
                
-               172         272 LOAD_FAST                9 (joined_translated)
+               178         272 LOAD_FAST                9 (joined_translated)
                            274 LOAD_METHOD              4 (replace)
                            296 LOAD_FAST                4 (sep)
                            298 LOAD_FAST                5 (sep_transition)
                            300 PRECALL                  2
                            304 CALL                     2
                            314 STORE_FAST               9 (joined_translated)
                
-               173         316 LOAD_FAST                9 (joined_translated)
+               179         316 LOAD_FAST                9 (joined_translated)
                            318 LOAD_METHOD              4 (replace)
                            340 LOAD_FAST                6 (sep_encoded)
                            342 LOAD_FAST                4 (sep)
                            344 PRECALL                  2
                            348 CALL                     2
                            358 STORE_FAST               9 (joined_translated)
                
-               174         360 LOAD_FAST                9 (joined_translated)
+               180         360 LOAD_FAST                9 (joined_translated)
                            362 LOAD_METHOD              6 (split)
                            384 LOAD_FAST                5 (sep_transition)
                            386 PRECALL                  1
                            390 CALL                     1
                            400 STORE_FAST              10 (result)
                
-               175         402 LOAD_FAST                7 (ln)
+               181         402 LOAD_FAST                7 (ln)
                            404 LOAD_GLOBAL              5 (NULL + len)
                            416 LOAD_FAST               10 (result)
                            418 PRECALL                  1
                            422 CALL                     1
                            432 COMPARE_OP               2 (==)
                            438 POP_JUMP_FORWARD_IF_FALSE     2 (to 444)
                
-               176         440 LOAD_FAST               10 (result)
+               182         440 LOAD_FAST               10 (result)
                            442 RETURN_VALUE
                
-               178     >>  444 LOAD_GLOBAL             14 (bp)
+               184     >>  444 LOAD_GLOBAL             14 (bp)
                            456 LOAD_ATTR                8 (LOGGER)
                            466 LOAD_METHOD              9 (info)
                            488 LOAD_CONST               5 ('Translation optimization has failed')
                            490 PRECALL                  1
                            494 CALL                     1
                            504 POP_TOP
                
-               180         506 LOAD_GLOBAL             21 (NULL + tuple)
+               186         506 LOAD_GLOBAL             21 (NULL + tuple)
                            518 LOAD_CLOSURE             3 (dest)
                            520 LOAD_CLOSURE             0 (self)
                            522 LOAD_CLOSURE             2 (src)
                            524 BUILD_TUPLE              3
-                           526 LOAD_CONST               6 (<code object <genexpr>, file "C:\Users\symrb\Documents\dev\python\baopig\baopig\googletrans\extension.py", line 180>)
+                           526 LOAD_CONST               6 (<code object <genexpr>, file "C:\Users\symrb\Documents\dev\python\baopig\baopig\googletrans\extension.py", line 186>)
                            528 MAKE_FUNCTION            8 (closure)
                            530 LOAD_FAST                1 (text)
                            532 GET_ITER
                            534 PRECALL                  0
                            538 CALL                     0
                            548 PRECALL                  1
                            552 CALL                     1
                            562 RETURN_VALUE
                
-               182     >>  564 LOAD_FAST                1 (text)
+               188     >>  564 LOAD_FAST                1 (text)
                            566 POP_JUMP_FORWARD_IF_TRUE     2 (to 572)
                
-               183         568 LOAD_CONST               7 ('')
+               189         568 LOAD_CONST               7 ('')
                            570 RETURN_VALUE
                
-               185     >>  572 NOP
+               191     >>  572 NOP
                
-               186         574 LOAD_DEREF               0 (self)
+               192         574 LOAD_DEREF               0 (self)
                            576 LOAD_METHOD             11 (_translate)
                            598 LOAD_FAST                1 (text)
                            600 LOAD_DEREF               3 (dest)
                            602 LOAD_DEREF               2 (src)
                            604 LOAD_CONST               0 (None)
                            606 PRECALL                  4
                            610 CALL                     4
                            620 UNPACK_SEQUENCE          2
                            624 STORE_FAST              11 (data)
                            626 STORE_FAST              12 (response)
                            628 JUMP_FORWARD            57 (to 744)
                        >>  630 PUSH_EXC_INFO
                
-               188         632 LOAD_GLOBAL             24 (ConnectError)
+               194         632 LOAD_GLOBAL             24 (ConnectError)
                            644 CHECK_EXC_MATCH
                            646 POP_JUMP_FORWARD_IF_FALSE    44 (to 736)
                            648 POP_TOP
                
-               189         650 LOAD_GLOBAL             14 (bp)
+               195         650 LOAD_GLOBAL             14 (bp)
                            662 LOAD_ATTR                8 (LOGGER)
                            672 LOAD_METHOD             13 (warning)
                            694 LOAD_CONST               8 ("Couldn't translate ")
                            696 LOAD_FAST                1 (text)
                            698 FORMAT_VALUE             0
                            700 LOAD_CONST               9 (' from ')
                            702 LOAD_DEREF               2 (src)
@@ -1497,26 +1559,26 @@
                            708 LOAD_DEREF               3 (dest)
                            710 FORMAT_VALUE             0
                            712 BUILD_STRING             6
                            714 PRECALL                  1
                            718 CALL                     1
                            728 POP_TOP
                
-               190         730 POP_EXCEPT
+               196         730 POP_EXCEPT
                            732 LOAD_CONST               7 ('')
                            734 RETURN_VALUE
                
-               188     >>  736 RERAISE                  0
+               194     >>  736 RERAISE                  0
                        >>  738 COPY                     3
                            740 POP_EXCEPT
                            742 RERAISE                  1
                
-               193     >>  744 LOAD_CONST               7 ('')
+               199     >>  744 LOAD_CONST               7 ('')
                            746 LOAD_METHOD              3 (join)
-                           768 LOAD_CONST              11 (<code object <listcomp>, file "C:\Users\symrb\Documents\dev\python\baopig\baopig\googletrans\extension.py", line 193>)
+                           768 LOAD_CONST              11 (<code object <listcomp>, file "C:\Users\symrb\Documents\dev\python\baopig\baopig\googletrans\extension.py", line 199>)
                            770 MAKE_FUNCTION            0
                            772 LOAD_FAST               11 (data)
                            774 LOAD_CONST              12 (0)
                            776 BINARY_SUBSCR
                            786 GET_ITER
                            788 PRECALL                  0
                            792 CALL                     0
@@ -1541,15 +1603,15 @@
                      flags     : 51
                      code
                         0x95034b00010097007c005d1c7d018903a0000000000000000000000000
                         0000000000000000007c0189048902ac00a6030000ab0300000000000000
                         005600970101008c1d64015300
                                    0 COPY_FREE_VARS           3
                      
-                     180           2 RETURN_GENERATOR
+                     186           2 RETURN_GENERATOR
                                    4 POP_TOP
                                    6 RESUME                   0
                                    8 LOAD_FAST                0 (.0)
                              >>   10 FOR_ITER                28 (to 68)
                                   12 STORE_FAST               1 (t)
                                   14 LOAD_DEREF               3 (self)
                                   16 LOAD_METHOD              0 (optimized_translate)
@@ -1570,29 +1632,29 @@
                         None
                      names      ('optimized_translate',)
                      varnames   ('.0', 't')
                      freevars   ('dest', 'self', 'src')
                      cellvars   ()
                      filename   'C:\\Users\\symrb\\Documents\\dev\\python\\baopig\\baopig\\googletrans\\extension.py'
                      name       '<genexpr>'
-                     firstlineno 180
+                     firstlineno 186
                      lnotab 0x
                   ''
                   "Couldn't translate "
                   ' from '
                   ' to '
                   code
                      argcount  : 1
                      nlocals   : 2
                      stacksize : 4
                      flags     : 19
                      code
                         0x970067007c005d147d017c0164001900000000000000000072087c0164
                         00190000000000000000006e01640191028c155300
-                     193           0 RESUME                   0
+                     199           0 RESUME                   0
                                    2 BUILD_LIST               0
                                    4 LOAD_FAST                0 (.0)
                              >>    6 FOR_ITER                20 (to 48)
                                    8 STORE_FAST               1 (d)
                                   10 LOAD_FAST                1 (d)
                                   12 LOAD_CONST               0 (0)
                                   14 BINARY_SUBSCR
@@ -1610,24 +1672,24 @@
                         ''
                      names      ()
                      varnames   ('.0', 'd')
                      freevars   ()
                      cellvars   ()
                      filename   'C:\\Users\\symrb\\Documents\\dev\\python\\baopig\\baopig\\googletrans\\extension.py'
                      name       '<listcomp>'
-                     firstlineno 193
+                     firstlineno 199
                      lnotab 0x
                   0
                names      ('isinstance', 'list', 'len', 'join', 'replace', 'optimized_translate', 'split', 'bp', 'LOGGER', 'info', 'tuple', '_translate', 'ConnectError', 'warning')
                varnames   ('self', 'text', 'src', 'dest', 'sep', 'sep_transition', 'sep_encoded', 'ln', 'joined', 'joined_translated', 'result', 'data', 'response')
                freevars   ()
                cellvars   ('self', 'src', 'dest')
                filename   'C:\\Users\\symrb\\Documents\\dev\\python\\baopig\\baopig\\googletrans\\extension.py'
                name       'optimized_translate'
-               firstlineno 160
+               firstlineno 166
                lnotab
                   0x08022c020401040104011e012a012c012c0130012c012c012a01260104
                   023e023a020401040202013a021201500106fe0805
             code
                argcount  : 1
                nlocals   : 1
                stacksize : 6
@@ -1635,45 +1697,45 @@
                code
                   0x950197000900740100000000000000000000a6000000ab000000000000
                   000000a00100000000000000000000000000000000000000006401640264
                   036400ac04a6040000ab0400000000000000000100640553002300740400
                   0000000000000000002400720401005900640653007700780359007701
                              0 COPY_FREE_VARS           1
                
-               195           2 RESUME                   0
+               201           2 RESUME                   0
                
-               197           4 NOP
+               203           4 NOP
                
-               198           6 LOAD_GLOBAL              1 (NULL + super)
+               204           6 LOAD_GLOBAL              1 (NULL + super)
                             18 PRECALL                  0
                             22 CALL                     0
                             32 LOAD_METHOD              1 (_translate)
                             54 LOAD_CONST               1 ('Bonjour')
                             56 LOAD_CONST               2 ('fr')
                             58 LOAD_CONST               3 ('en')
                             60 LOAD_CONST               0 (None)
                             62 KW_NAMES                 4
                             64 PRECALL                  4
                             68 CALL                     4
                             78 POP_TOP
                
-               202          80 LOAD_CONST               5 (True)
+               208          80 LOAD_CONST               5 (True)
                             82 RETURN_VALUE
                        >>   84 PUSH_EXC_INFO
                
-               199          86 LOAD_GLOBAL              4 (ConnectError)
+               205          86 LOAD_GLOBAL              4 (ConnectError)
                             98 CHECK_EXC_MATCH
                            100 POP_JUMP_FORWARD_IF_FALSE     4 (to 110)
                            102 POP_TOP
                
-               200         104 POP_EXCEPT
+               206         104 POP_EXCEPT
                            106 LOAD_CONST               6 (False)
                            108 RETURN_VALUE
                
-               199     >>  110 RERAISE                  0
+               205     >>  110 RERAISE                  0
                        >>  112 COPY                     3
                            114 POP_EXCEPT
                            116 RERAISE                  1
                ExceptionTable:
                  6 to 78 -> 84 [0]
                  84 to 102 -> 112 [1] lasti
                  110 to 110 -> 112 [1] lasti
@@ -1687,26 +1749,26 @@
                   False
                names      ('super', '_translate', 'ConnectError')
                varnames   ('self',)
                freevars   ('__class__',)
                cellvars   ()
                filename   'C:\\Users\\symrb\\Documents\\dev\\python\\baopig\\baopig\\googletrans\\extension.py'
                name       'test_connection'
-               firstlineno 195
+               firstlineno 201
                lnotab 0x040202014a0406fd120106ff
          names      ('__name__', '__module__', '__qualname__', 'optimized_translate', 'test_connection', '__classcell__')
          varnames   ()
          freevars   ()
          cellvars   ('__class__',)
          filename   'C:\\Users\\symrb\\Documents\\dev\\python\\baopig\\baopig\\googletrans\\extension.py'
          name       'OptimizedTranslator'
-         firstlineno 158
+         firstlineno 164
          lnotab 0x0c020623
       'OptimizedTranslator'
    names      ('os', 'sys', 'importlib', 'httpcore', 'ConnectError', 'baopig', 'bp', 'client', 'Translator', 'dict', 'Dictionnary', 'Communicative', 'LangManager', 'OptimizedTranslator', 'dicts', 'lang_manager', 'translator')
    varnames   ()
    freevars   ()
    cellvars   ()
    filename   'C:\\Users\\symrb\\Documents\\dev\\python\\baopig\\baopig\\googletrans\\extension.py'
    name       '<module>'
    firstlineno 1
-   lnotab 0x00ff02010801080108010c0108010c031c3c26591c2f04011401
+   lnotab 0x00ff02010801080108010c0108010c031c4226591c2f04011401
```

## baopig/version/version.py

```diff
@@ -16,12 +16,12 @@
         return '{}.{}.{}'.format(*self) if len(self) == 3 else '{}.{}.{} - {}'.format(*self)
 
     major = property(lambda self: self[0])
     minor = property(lambda self: self[1])
     patch = property(lambda self: self[2])
 
 
-version = BaopigVersion(0, 20, 2)
+version = BaopigVersion(0, 20, 3)
 
 if __name__ == "__main__":
     # TODO : try to access baopig.version without creating application, threads...
     print("Hello, this is baopig version", version)
```

## baopig/version/__pycache__/version.cpython-311.pyc

### Python bytecode

```diff
@@ -1,9 +1,9 @@
 magic:    0xa70d0d0a
-moddate:  0xf2c84364 (Sat Apr 22 11:45:54 2023 UTC)
+moddate:  0xdcdf4364 (Sat Apr 22 13:23:40 2023 UTC)
 files sz: 931
 code
    argcount  : 0
    nlocals   : 0
    stacksize : 5
    flags     : 0
    code
@@ -11,27 +11,27 @@
       0102006501640264036404a6030000ab0300000000000000005a02650364
       056b0200000000720e0200650464066502a6020000ab0200000000000000
       0001006407530064075300
      0           0 RESUME                   0
    
      3           2 PUSH_NULL
                  4 LOAD_BUILD_CLASS
-                 6 LOAD_CONST               0 (<code object BaopigVersion, file "C:\Users\symrb\Documents\dev\python\baopig\baopig\version\version.py", line 3>)
+                 6 LOAD_CONST               0 (<code object BaopigVersion, file "C:\Users\symrb\Documents\dev\python\baopig\.\baopig\version\version.py", line 3>)
                  8 MAKE_FUNCTION            0
                 10 LOAD_CONST               1 ('BaopigVersion')
                 12 LOAD_NAME                0 (tuple)
                 14 PRECALL                  3
                 18 CALL                     3
                 28 STORE_NAME               1 (BaopigVersion)
    
     23          30 PUSH_NULL
                 32 LOAD_NAME                1 (BaopigVersion)
                 34 LOAD_CONST               2 (0)
                 36 LOAD_CONST               3 (20)
-                38 LOAD_CONST               4 (2)
+                38 LOAD_CONST               4 (3)
                 40 PRECALL                  3
                 44 CALL                     3
                 54 STORE_NAME               2 (version)
    
     25          56 LOAD_NAME                3 (__name__)
                 58 LOAD_CONST               5 ('__main__')
                 60 COMPARE_OP               2 (==)
@@ -72,45 +72,45 @@
            5          14 LOAD_CONST               2 (())
                       16 STORE_NAME               4 (__slots__)
          
            6          18 LOAD_CONST               3 (('major', 'minor', 'patch', 'backup'))
                       20 STORE_NAME               5 (fields)
          
            8          22 LOAD_CONST              11 ((None,))
-                      24 LOAD_CONST               5 (<code object __new__, file "C:\Users\symrb\Documents\dev\python\baopig\baopig\version\version.py", line 8>)
+                      24 LOAD_CONST               5 (<code object __new__, file "C:\Users\symrb\Documents\dev\python\baopig\.\baopig\version\version.py", line 8>)
                       26 MAKE_FUNCTION            1 (defaults)
                       28 STORE_NAME               6 (__new__)
          
-          11          30 LOAD_CONST               6 (<code object __repr__, file "C:\Users\symrb\Documents\dev\python\baopig\baopig\version\version.py", line 11>)
+          11          30 LOAD_CONST               6 (<code object __repr__, file "C:\Users\symrb\Documents\dev\python\baopig\.\baopig\version\version.py", line 11>)
                       32 MAKE_FUNCTION            0
                       34 STORE_NAME               7 (__repr__)
          
-          15          36 LOAD_CONST               7 (<code object __str__, file "C:\Users\symrb\Documents\dev\python\baopig\baopig\version\version.py", line 15>)
+          15          36 LOAD_CONST               7 (<code object __str__, file "C:\Users\symrb\Documents\dev\python\baopig\.\baopig\version\version.py", line 15>)
                       38 MAKE_FUNCTION            0
                       40 STORE_NAME               8 (__str__)
          
           18          42 PUSH_NULL
                       44 LOAD_NAME                9 (property)
-                      46 LOAD_CONST               8 (<code object <lambda>, file "C:\Users\symrb\Documents\dev\python\baopig\baopig\version\version.py", line 18>)
+                      46 LOAD_CONST               8 (<code object <lambda>, file "C:\Users\symrb\Documents\dev\python\baopig\.\baopig\version\version.py", line 18>)
                       48 MAKE_FUNCTION            0
                       50 PRECALL                  1
                       54 CALL                     1
                       64 STORE_NAME              10 (major)
          
           19          66 PUSH_NULL
                       68 LOAD_NAME                9 (property)
-                      70 LOAD_CONST               9 (<code object <lambda>, file "C:\Users\symrb\Documents\dev\python\baopig\baopig\version\version.py", line 19>)
+                      70 LOAD_CONST               9 (<code object <lambda>, file "C:\Users\symrb\Documents\dev\python\baopig\.\baopig\version\version.py", line 19>)
                       72 MAKE_FUNCTION            0
                       74 PRECALL                  1
                       78 CALL                     1
                       88 STORE_NAME              11 (minor)
          
           20          90 PUSH_NULL
                       92 LOAD_NAME                9 (property)
-                      94 LOAD_CONST              10 (<code object <lambda>, file "C:\Users\symrb\Documents\dev\python\baopig\baopig\version\version.py", line 20>)
+                      94 LOAD_CONST              10 (<code object <lambda>, file "C:\Users\symrb\Documents\dev\python\baopig\.\baopig\version\version.py", line 20>)
                       96 MAKE_FUNCTION            0
                       98 PRECALL                  1
                      102 CALL                     1
                      112 STORE_NAME              12 (patch)
                      114 LOAD_CONST               4 (None)
                      116 RETURN_VALUE
          consts
@@ -154,15 +154,15 @@
                consts
                   None
                   ()
                names      ('tuple', '__new__')
                varnames   ('cls', 'major', 'minor', 'patch', 'backup')
                freevars   ()
                cellvars   ()
-               filename   'C:\\Users\\symrb\\Documents\\dev\\python\\baopig\\baopig\\version\\version.py'
+               filename   'C:\\Users\\symrb\\Documents\\dev\\python\\baopig\\.\\baopig\\version\\version.py'
                name       '__new__'
                firstlineno 8
                lnotab 0x0201
             code
                argcount  : 1
                nlocals   : 2
                stacksize : 6
@@ -173,15 +173,15 @@
                   0000007d016402a002000000000000000000000000000000000000000074
                   07000000000000000000007c006a0400000000000000006a050000000000
                   000000a6010000ab0100000000000000006403a006000000000000000000
                   00000000000000000000007c01a6010000ab010000000000000000a60200
                   00ab0200000000000000005300
                 11           0 RESUME                   0
                
-                12           2 LOAD_CONST               1 (<code object <genexpr>, file "C:\Users\symrb\Documents\dev\python\baopig\baopig\version\version.py", line 12>)
+                12           2 LOAD_CONST               1 (<code object <genexpr>, file "C:\Users\symrb\Documents\dev\python\baopig\.\baopig\version\version.py", line 12>)
                              4 MAKE_FUNCTION            0
                              6 LOAD_GLOBAL              1 (NULL + zip)
                             18 LOAD_FAST                0 (self)
                             20 LOAD_ATTR                1 (fields)
                             30 LOAD_FAST                0 (self)
                             32 PRECALL                  2
                             36 CALL                     2
@@ -240,25 +240,25 @@
                      consts
                         '{}={}'
                         None
                      names      ('format',)
                      varnames   ('.0', 'fld', 'val')
                      freevars   ()
                      cellvars   ()
-                     filename   'C:\\Users\\symrb\\Documents\\dev\\python\\baopig\\baopig\\version\\version.py'
+                     filename   'C:\\Users\\symrb\\Documents\\dev\\python\\baopig\\.\\baopig\\version\\version.py'
                      name       '<genexpr>'
                      firstlineno 12
                      lnotab 0x
                   '{}({})'
                   ', '
                names      ('zip', 'fields', 'format', 'str', '__class__', '__name__', 'join')
                varnames   ('self', 'fields')
                freevars   ()
                cellvars   ()
-               filename   'C:\\Users\\symrb\\Documents\\dev\\python\\baopig\\baopig\\version\\version.py'
+               filename   'C:\\Users\\symrb\\Documents\\dev\\python\\baopig\\.\\baopig\\version\\version.py'
                name       '__repr__'
                firstlineno 11
                lnotab 0x02013e01
             code
                argcount  : 1
                nlocals   : 1
                stacksize : 3
@@ -293,15 +293,15 @@
                   3
                   '{}.{}.{}'
                   '{}.{}.{} - {}'
                names      ('len', 'format')
                varnames   ('self',)
                freevars   ()
                cellvars   ()
-               filename   'C:\\Users\\symrb\\Documents\\dev\\python\\baopig\\baopig\\version\\version.py'
+               filename   'C:\\Users\\symrb\\Documents\\dev\\python\\baopig\\.\\baopig\\version\\version.py'
                name       '__str__'
                firstlineno 15
                lnotab 0x0201
             code
                argcount  : 1
                nlocals   : 1
                stacksize : 2
@@ -315,15 +315,15 @@
                consts
                   None
                   0
                names      ()
                varnames   ('self',)
                freevars   ()
                cellvars   ()
-               filename   'C:\\Users\\symrb\\Documents\\dev\\python\\baopig\\baopig\\version\\version.py'
+               filename   'C:\\Users\\symrb\\Documents\\dev\\python\\baopig\\.\\baopig\\version\\version.py'
                name       '<lambda>'
                firstlineno 18
                lnotab 0x
             code
                argcount  : 1
                nlocals   : 1
                stacksize : 2
@@ -337,15 +337,15 @@
                consts
                   None
                   1
                names      ()
                varnames   ('self',)
                freevars   ()
                cellvars   ()
-               filename   'C:\\Users\\symrb\\Documents\\dev\\python\\baopig\\baopig\\version\\version.py'
+               filename   'C:\\Users\\symrb\\Documents\\dev\\python\\baopig\\.\\baopig\\version\\version.py'
                name       '<lambda>'
                firstlineno 19
                lnotab 0x
             code
                argcount  : 1
                nlocals   : 1
                stacksize : 2
@@ -359,35 +359,35 @@
                consts
                   None
                   2
                names      ()
                varnames   ('self',)
                freevars   ()
                cellvars   ()
-               filename   'C:\\Users\\symrb\\Documents\\dev\\python\\baopig\\baopig\\version\\version.py'
+               filename   'C:\\Users\\symrb\\Documents\\dev\\python\\baopig\\.\\baopig\\version\\version.py'
                name       '<lambda>'
                firstlineno 20
                lnotab 0x
             (None,)
          names      ('__name__', '__module__', '__qualname__', '__doc__', '__slots__', 'fields', '__new__', '__repr__', '__str__', 'property', 'major', 'minor', 'patch')
          varnames   ()
          freevars   ()
          cellvars   ()
-         filename   'C:\\Users\\symrb\\Documents\\dev\\python\\baopig\\baopig\\version\\version.py'
+         filename   'C:\\Users\\symrb\\Documents\\dev\\python\\baopig\\.\\baopig\\version\\version.py'
          name       'BaopigVersion'
          firstlineno 3
          lnotab 0x0a0104010401040208030604060318011801
       'BaopigVersion'
       0
       20
-      2
+      3
       '__main__'
       'Hello, this is baopig version'
       None
    names      ('tuple', 'BaopigVersion', 'version', '__name__', 'print')
    varnames   ()
    freevars   ()
    cellvars   ()
-   filename   'C:\\Users\\symrb\\Documents\\dev\\python\\baopig\\baopig\\version\\version.py'
+   filename   'C:\\Users\\symrb\\Documents\\dev\\python\\baopig\\.\\baopig\\version\\version.py'
    name       '<module>'
    firstlineno 1
    lnotab 0x00ff02031c141a020c021cfe
```

## Comparing `baopig-0.20.2.dist-info/LICENSE` & `baopig-0.20.3.dist-info/LICENSE`

 * *Files identical despite different names*

## Comparing `baopig-0.20.2.dist-info/METADATA` & `baopig-0.20.3.dist-info/METADATA`

 * *Files 1% similar despite different names*

```diff
@@ -1,10 +1,10 @@
 Metadata-Version: 2.1
 Name: baopig
-Version: 0.20.2
+Version: 0.20.3
 Summary: pygame gui
 Home-page: https://baopig.readthedocs.io/
 Author: Symeon Rougevin-Baville
 Author-email: dev.chresyr@gmail.com
 License: MIT
 Classifier: Intended Audience :: Developers
 Classifier: License :: OSI Approved :: MIT License
```

## Comparing `baopig-0.20.2.dist-info/RECORD` & `baopig-0.20.3.dist-info/RECORD`

 * *Files 2% similar despite different names*

```diff
@@ -1,13 +1,13 @@
 baopig/__init__.py,sha256=t2uh4SHnY_69CGZ3n7kbaT_5-INsSwjzSxolxvrNN7M,608
 baopig/communicative.py,sha256=4vT8P_P_2ZNt8AwsqaWffWy4o6vghJ3urrj9gkIICWA,3643
 baopig/documentation.py,sha256=YZVtnTOfgH4L7u8AfVIywaJE755bpDFpsW5jkrek5cQ,16525
 baopig/lines_counter.py,sha256=UcBTJwBQxJ_mHle-1w1h9B_cVs5LYXvdQyTk047jyWo,548
 baopig/__pycache__/__init__.cpython-310.pyc,sha256=hJjODRmGfzKR7QEnPU_LegS6ZqmFkbecj_k0yV70z2U,831
-baopig/__pycache__/__init__.cpython-311.pyc,sha256=n0l7fe2Fur5al70QUSWnc1l-boK4djN7j2Ut-xtS-E0,1151
+baopig/__pycache__/__init__.cpython-311.pyc,sha256=3lGWeIg9G2jXThKNSfCNDuOPMuGkq9HJgOpQ0pjHIyc,1151
 baopig/__pycache__/__init__.cpython-37.pyc,sha256=1ansnWF-3dACEQ92gACbcpaLgQLPbT4KdtPStD8dT78,866
 baopig/__pycache__/communicative.cpython-310.pyc,sha256=0zcxiochjDAdhLxSH-fRWtstgQ6MQBwzRjbcmWoZoTw,4334
 baopig/__pycache__/communicative.cpython-311.pyc,sha256=YAyp10vbL9_EJXkYcu1dxomnEFHEMMub3Ii5VWwIAeI,6953
 baopig/__pycache__/communicative.cpython-37.pyc,sha256=FsfYl8qXzIBB4fISd7UOEGDVNHGX70TVqgCnNCmx5Ac,6055
 baopig/__pycache__/documentation.cpython-310.pyc,sha256=WE3Z-59QnYQ80kBx5PEehT5vFnITiS31j6AxRRxTx1s,16336
 baopig/__pycache__/documentation.cpython-311.pyc,sha256=d1Ssq1w_CvLwyWzShdSe68VOXl75pyvFIsGySKLJ0UM,18292
 baopig/font/__init__.py,sha256=HMVvCTv2PMb_arg0v7rs7IaRohldwVXZYFaNGwCwUI8,24
@@ -48,28 +48,28 @@
 baopig/font/lib/JetBrainsMono-1.0.2/web/woff2/JetBrainsMono-Italic.woff2,sha256=a6erRLMrZ1UxAfoDTyWpCVbgK6a-O9qWJevK5YC7BFI,50936
 baopig/font/lib/JetBrainsMono-1.0.2/web/woff2/JetBrainsMono-Medium-Italic.woff2,sha256=e5CycNCL2ivorE0PUD_PlY1PDWOBnccCGK8zPoKHC0I,52928
 baopig/font/lib/JetBrainsMono-1.0.2/web/woff2/JetBrainsMono-Medium.woff2,sha256=XBuO6B8wybnzTqBT66hS8MCsPkjW73MFFq0hcbUAzdE,49592
 baopig/font/lib/JetBrainsMono-1.0.2/web/woff2/JetBrainsMono-Regular.woff2,sha256=7rmGzQFZFvj_OniUv3n8oyV3dhFy1lCk2XrcvVWZ7Ds,48700
 baopig/googletrans/__init__.py,sha256=DQOBhxXBLUo7eirqpyGjNK6gIflSPlFV2b3ImsXGa2g,413
 baopig/googletrans/client.py,sha256=Aios-7SWEXhYSQsaX4UhuSF2pGHRkqKUVoGUcKnJPLc,11622
 baopig/googletrans/constants.py,sha256=ZgRam-3-2w3RmmYhwXM69Nwn5Wx3Cc3xDptzXAYbGM4,11881
-baopig/googletrans/extension.py,sha256=o40Yl9-jQUMKDlBjh7NqS9KuQ6qsuPYwQC9SvgwNMwI,6508
+baopig/googletrans/extension.py,sha256=NyeDUlOvecT9wvYTrk6XYeFkIWL2Fr2GlwDWaaeLG1M,6781
 baopig/googletrans/gtoken.py,sha256=Vq23F2cKylRc7W0gNf4ticHV3I5tBiDi19S8R_nJO_8,7240
 baopig/googletrans/models.py,sha256=wJejA2QJr0QMnBmA9cIowCdvEQaxllR_FX5qYDq8FUE,1797
 baopig/googletrans/translatable.py,sha256=8cxz_w6oI-4T1w2XwJ0nb1wprmqsMigTMstY4GDL_K0,2163
 baopig/googletrans/urls.py,sha256=tKUbbC05UDGqQ8VgM65l1ECLwjolgVD3T5hAWJaqYtM,174
 baopig/googletrans/utils.py,sha256=v2TByek94Jnb3qvOwh2pGUJ_EAWIl2v8ne7FLikW1OA,1951
 baopig/googletrans/__pycache__/__init__.cpython-310.pyc,sha256=5S7AaS6hhCLTTqdU0pI7ds52zXzRlIakSFhqsPvftNs,682
 baopig/googletrans/__pycache__/__init__.cpython-311.pyc,sha256=UBXO3UkfAaHte6HsOpx5O1WmqkvEvEGctR9F_zkUUGw,822
 baopig/googletrans/__pycache__/client.cpython-310.pyc,sha256=jgV72J9DnB7taX3kGl02uNkm4aZ5fGvEYQBAAXa71gw,9616
 baopig/googletrans/__pycache__/client.cpython-311.pyc,sha256=xJ9l2nbZkybNvcWul7M-OZTViNMf2-KkS_d6DIQixEc,13590
 baopig/googletrans/__pycache__/constants.cpython-310.pyc,sha256=n439gXFLNNT7nB2xMNajtac07Y4DQl5Vsplqj3lOHUM,10152
 baopig/googletrans/__pycache__/constants.cpython-311.pyc,sha256=G0mUpARZYXcoNOqIOIZrvZ_wpxstIn1vmulGobJpCpk,12680
 baopig/googletrans/__pycache__/extension.cpython-310.pyc,sha256=14fWjNd-5jr8NhyRCwkLIEYkqlSCm6Nzaves8dptV_w,6220
-baopig/googletrans/__pycache__/extension.cpython-311.pyc,sha256=BKjSQujo4md-Q1-Q2lBiPfs1xl5wNFCX2Tk92L4wB4A,12270
+baopig/googletrans/__pycache__/extension.cpython-311.pyc,sha256=kPbPx0rvGXUHIEWSzojG_0B_wmNjLQj973NJJAy175s,12787
 baopig/googletrans/__pycache__/gtoken.cpython-310.pyc,sha256=ibpTNCxdLT7hFQ9xGzv5JVRP-pK19Wy5dxsx6N_kIL0,5423
 baopig/googletrans/__pycache__/gtoken.cpython-311.pyc,sha256=26xyLwfQFecfNTvpsn-3zRV8mNhbuDs9QYgysQ3T6TM,9846
 baopig/googletrans/__pycache__/models.cpython-310.pyc,sha256=ga4xpDoQlpMcpliKNIj_DjOo7bD1oSpi2sPA8AS_EEo,2490
 baopig/googletrans/__pycache__/models.cpython-311.pyc,sha256=jJRiOQ99qkVe6kSxizR-XleMpE5Xk1ycTWeb5pY-pu4,3533
 baopig/googletrans/__pycache__/translatable.cpython-310.pyc,sha256=GOrBHKcx3nkSPsD10GyGA3K7G7a5wK4DkQEe3eVHah0,3130
 baopig/googletrans/__pycache__/translatable.cpython-311.pyc,sha256=wSlNKkdjtL1SmaPe45HICHIxdYdGwzi9698BU5rj_8Y,5117
 baopig/googletrans/__pycache__/urls.cpython-310.pyc,sha256=XsAlhs9gUGH7GZGZVSQUJgj8whiTlNS5K3CfXV5kofo,321
@@ -250,17 +250,17 @@
 baopig/unit_tests/__pycache__/ut_sleep.cpython-311.pyc,sha256=9IsK69xKVmkyAR2CbTXopWWC0Vj7SRIndg1cQfi-5Ac,13507
 baopig/unit_tests/__pycache__/ut_text.cpython-310.pyc,sha256=Izd3N6trwDF_1o0O3msWBUUDBbfjphQ7Bh9DiROS-qI,3621
 baopig/unit_tests/__pycache__/ut_text.cpython-311.pyc,sha256=YOfvIZAZSaEmcCb4qxOybmWye-89s_lEVKR4Y8G6NFI,6753
 baopig/unit_tests/__pycache__/ut_textedit.cpython-310.pyc,sha256=Kb5XYTUGs1yP69qXaFwgbLqjXqI8V5AVtfiowqy4Mwo,1830
 baopig/unit_tests/__pycache__/ut_textedit.cpython-311.pyc,sha256=QGoRJDpfOUhFxL5d55cKdltmZp-r4zreIgYHWvhBU3M,3446
 baopig/unit_tests/__pycache__/ut_theme.cpython-310.pyc,sha256=Jd822wGf32M0nTwWRCSecbXojL_-Sk-Y-jt4qNKJFDU,2043
 baopig/unit_tests/__pycache__/ut_theme.cpython-311.pyc,sha256=5uTVze6gUU95lFO99ZXU6dvGquVDL5Xe8gIQqkFUYBE,3466
-baopig/version/version.py,sha256=p_vNeeBO48sQVj9DjIULBWN8BZwSeu6SPpnxDGBBgUM,931
+baopig/version/version.py,sha256=-8ODaQKDaHDoPUvKzSaxj9QoixyE78DzERESr05RLLU,931
 baopig/version/__pycache__/version.cpython-310.pyc,sha256=Rp0XTLPGzphYoaYVQXoqP_pfEh2wLtNCsS3tVJN1Lbk,1692
-baopig/version/__pycache__/version.cpython-311.pyc,sha256=btc3we2HFG9CiTI-gF3hOi4fQcLTihAZF1ZO0LbeM6M,2609
+baopig/version/__pycache__/version.cpython-311.pyc,sha256=siG7KXxNTYu7dx5o8oEM4JrhqSQgRn4yf4snp14EJMc,2611
 baopig/version/__pycache__/version.cpython-37.pyc,sha256=g23o3EB_00N3g1jhY4M6TwBov_bzg3MnZhZ2JPMLYHM,1642
 baopig/widgets/__init__.py,sha256=PeQrRjeytaGx2rd_C6ygb6wjiKoOQbDWtaHr9LvPtZg,767
 baopig/widgets/button.py,sha256=D7Q3wskW1gdq09Mj9EIuxYAtNbn3C9ejjnn-pN3-dFU,8232
 baopig/widgets/checkbox.py,sha256=VMsW42qIdGLCcD4KjPE3ytzqJvYs-ETzF1Y1Ku8Isfc,3102
 baopig/widgets/dialog.py,sha256=uJCa-Pr2dqaGhsHCuYIB03Dp8oaixFUmjapDfJuJRNk,5246
 baopig/widgets/entry.py,sha256=UODsZ2hPYKBY8QMPzOmiWGhTeF_p6bdsxJeRiTXRcuU,1609
 baopig/widgets/indicator.py,sha256=sEkysKLVNEQQPZgdnXd5KexBPDzUjQbKCYWT5Jiuuc8,3607
@@ -304,12 +304,12 @@
 baopig/widgets/__pycache__/slider.cpython-37.pyc,sha256=NhB3ncvsXTPaRXNm43xwc2DLV23RCaN6r1swBDjzwec,8011
 baopig/widgets/__pycache__/text.cpython-310.pyc,sha256=OhRohkmN_-EC-JXQsNr-WcCoeXSeOe-YxtdFBvnxdf4,24379
 baopig/widgets/__pycache__/text.cpython-311.pyc,sha256=y08KoLK9bQFsBECor7dDImLOvTLmYv06sG-1J5V9oC0,43877
 baopig/widgets/__pycache__/text.cpython-37.pyc,sha256=FIM-g85PDkaLQAHpojF_M88lkFpXG2kS_fwbvCsKCyo,27867
 baopig/widgets/__pycache__/textedit.cpython-310.pyc,sha256=D7KcLsLSPxQpLyaRf_BNHd7Px_jfPJVYcIXazq8FJHs,14346
 baopig/widgets/__pycache__/textedit.cpython-311.pyc,sha256=ACqhG1VRq7Ff_87p3QWyRZlx0IO8PNPLzqlNQEwa3Y4,32458
 baopig/widgets/__pycache__/textedit.cpython-37.pyc,sha256=Cia7Ci-9PVR2oUo4ObWEX7o5v3kULv-ZiTxbuH38JSA,13078
-baopig-0.20.2.dist-info/LICENSE,sha256=G6lZz1IZuCNLDTIxvk6dJWPWwozp2altzGHlF4NWUz4,1088
-baopig-0.20.2.dist-info/METADATA,sha256=x8ZNlu_w3Zh-HoJ54wGW44YwMpsAdgBO2jQGzxhi7A0,866
-baopig-0.20.2.dist-info/WHEEL,sha256=pkctZYzUS4AYVn6dJ-7367OJZivF2e8RA9b_ZBjif18,92
-baopig-0.20.2.dist-info/top_level.txt,sha256=soVidPUY0es6t4CoXpPdWPTwz8Y_4-NGZYPsvyET458,7
-baopig-0.20.2.dist-info/RECORD,,
+baopig-0.20.3.dist-info/LICENSE,sha256=G6lZz1IZuCNLDTIxvk6dJWPWwozp2altzGHlF4NWUz4,1088
+baopig-0.20.3.dist-info/METADATA,sha256=fI3B5hwxarqB9_pYPonl-TtQku30fD5zzbOS7Ojb_iY,866
+baopig-0.20.3.dist-info/WHEEL,sha256=pkctZYzUS4AYVn6dJ-7367OJZivF2e8RA9b_ZBjif18,92
+baopig-0.20.3.dist-info/top_level.txt,sha256=soVidPUY0es6t4CoXpPdWPTwz8Y_4-NGZYPsvyET458,7
+baopig-0.20.3.dist-info/RECORD,,
```

