# Comparing `tmp/baopig-0.20.4-py3-none-any.whl.zip` & `tmp/baopig-0.20.5-py3-none-any.whl.zip`

## zipinfo {}

```diff
@@ -1,14 +1,14 @@
-Zip file size: 2848249 bytes, number of entries: 315
--rw-rw-rw-  2.0 fat      608 b- defN 23-Apr-22 11:51 baopig/__init__.py
+Zip file size: 2848320 bytes, number of entries: 315
+-rw-rw-rw-  2.0 fat      682 b- defN 23-Apr-22 14:36 baopig/__init__.py
 -rw-rw-rw-  2.0 fat     3643 b- defN 22-Jul-12 21:25 baopig/communicative.py
 -rw-rw-rw-  2.0 fat    16525 b- defN 22-Jul-19 15:24 baopig/documentation.py
 -rw-rw-rw-  2.0 fat      548 b- defN 23-Feb-20 13:20 baopig/lines_counter.py
 -rw-rw-rw-  2.0 fat      831 b- defN 22-Jul-12 21:41 baopig/__pycache__/__init__.cpython-310.pyc
--rw-rw-rw-  2.0 fat     1151 b- defN 23-Apr-22 12:24 baopig/__pycache__/__init__.cpython-311.pyc
+-rw-rw-rw-  2.0 fat     1308 b- defN 23-Apr-22 14:38 baopig/__pycache__/__init__.cpython-311.pyc
 -rw-rw-rw-  2.0 fat      866 b- defN 22-Jun-10 11:59 baopig/__pycache__/__init__.cpython-37.pyc
 -rw-rw-rw-  2.0 fat     4334 b- defN 22-Jul-12 21:25 baopig/__pycache__/communicative.cpython-310.pyc
 -rw-rw-rw-  2.0 fat     6953 b- defN 23-Apr-14 15:58 baopig/__pycache__/communicative.cpython-311.pyc
 -rw-rw-rw-  2.0 fat     6055 b- defN 22-Jun-10 11:59 baopig/__pycache__/communicative.cpython-37.pyc
 -rw-rw-rw-  2.0 fat    16336 b- defN 22-Jul-19 15:24 baopig/__pycache__/documentation.cpython-310.pyc
 -rw-rw-rw-  2.0 fat    18292 b- defN 23-Apr-14 15:58 baopig/__pycache__/documentation.cpython-311.pyc
 -rw-rw-rw-  2.0 fat       24 b- defN 22-Jul-20 11:07 baopig/font/__init__.py
@@ -89,31 +89,31 @@
 -rw-rw-rw-  2.0 fat     7189 b- defN 22-Jun-10 11:59 baopig/io/__pycache__/keyboard.cpython-37.pyc
 -rw-rw-rw-  2.0 fat     3416 b- defN 22-Jul-21 12:50 baopig/io/__pycache__/logging.cpython-310.pyc
 -rw-rw-rw-  2.0 fat     6314 b- defN 23-Apr-14 15:58 baopig/io/__pycache__/logging.cpython-311.pyc
 -rw-rw-rw-  2.0 fat     3376 b- defN 22-Jun-10 11:59 baopig/io/__pycache__/logging.cpython-37.pyc
 -rw-rw-rw-  2.0 fat     7956 b- defN 22-Dec-18 21:13 baopig/io/__pycache__/mouse.cpython-310.pyc
 -rw-rw-rw-  2.0 fat    15307 b- defN 23-Apr-14 15:58 baopig/io/__pycache__/mouse.cpython-311.pyc
 -rw-rw-rw-  2.0 fat     9450 b- defN 22-Jun-10 11:59 baopig/io/__pycache__/mouse.cpython-37.pyc
--rw-rw-rw-  2.0 fat      596 b- defN 23-Apr-22 14:12 baopig/lib/__init__.py
+-rw-rw-rw-  2.0 fat      623 b- defN 23-Apr-22 14:32 baopig/lib/__init__.py
 -rw-rw-rw-  2.0 fat    14075 b- defN 22-Dec-04 18:48 baopig/lib/application.py
 -rw-rw-rw-  2.0 fat    16468 b- defN 23-Apr-21 14:28 baopig/lib/container.py
 -rw-rw-rw-  2.0 fat    18715 b- defN 22-Jul-21 19:32 baopig/lib/gridlayer.py
 -rw-rw-rw-  2.0 fat     2502 b- defN 22-Dec-13 12:20 baopig/lib/imagewidget.py
 -rw-rw-rw-  2.0 fat    10338 b- defN 22-Dec-13 12:16 baopig/lib/layer.py
 -rw-rw-rw-  2.0 fat     4172 b- defN 22-Jul-21 12:50 baopig/lib/layersmanager.py
 -rw-rw-rw-  2.0 fat     7037 b- defN 23-Jan-12 01:33 baopig/lib/scene.py
 -rw-rw-rw-  2.0 fat    10889 b- defN 22-Jul-21 19:31 baopig/lib/selections.py
 -rw-rw-rw-  2.0 fat     7360 b- defN 22-Dec-13 12:28 baopig/lib/shapes.py
 -rw-rw-rw-  2.0 fat    16552 b- defN 22-Jul-21 13:29 baopig/lib/style.py
 -rw-rw-rw-  2.0 fat     4162 b- defN 22-Jul-21 13:07 baopig/lib/utilities.py
 -rw-rw-rw-  2.0 fat    37125 b- defN 23-Jan-10 21:12 baopig/lib/widget.py
 -rw-rw-rw-  2.0 fat     9919 b- defN 23-Apr-22 14:10 baopig/lib/widget_supers.py
--rw-rw-rw-  2.0 fat     3300 b- defN 22-Jul-17 19:47 baopig/lib/zone.py
+-rw-rw-rw-  2.0 fat     3337 b- defN 23-Apr-22 14:36 baopig/lib/zone.py
 -rw-rw-rw-  2.0 fat     1022 b- defN 22-Jul-20 10:26 baopig/lib/__pycache__/__init__.cpython-310.pyc
--rw-rw-rw-  2.0 fat     1418 b- defN 23-Apr-22 14:11 baopig/lib/__pycache__/__init__.cpython-311.pyc
+-rw-rw-rw-  2.0 fat     1388 b- defN 23-Apr-22 14:32 baopig/lib/__pycache__/__init__.cpython-311.pyc
 -rw-rw-rw-  2.0 fat      996 b- defN 22-Jun-10 11:59 baopig/lib/__pycache__/__init__.cpython-37.pyc
 -rw-rw-rw-  2.0 fat    10025 b- defN 22-Dec-04 18:48 baopig/lib/__pycache__/application.cpython-310.pyc
 -rw-rw-rw-  2.0 fat    19363 b- defN 23-Apr-14 15:58 baopig/lib/__pycache__/application.cpython-311.pyc
 -rw-rw-rw-  2.0 fat    11173 b- defN 22-Jun-10 11:59 baopig/lib/__pycache__/application.cpython-37.pyc
 -rw-rw-rw-  2.0 fat    13868 b- defN 22-Dec-18 23:01 baopig/lib/__pycache__/container.cpython-310.pyc
 -rw-rw-rw-  2.0 fat    25435 b- defN 23-Apr-21 15:33 baopig/lib/__pycache__/container.cpython-311.pyc
 -rw-rw-rw-  2.0 fat    17854 b- defN 22-Jun-10 11:59 baopig/lib/__pycache__/container.cpython-37.pyc
@@ -145,15 +145,15 @@
 -rw-rw-rw-  2.0 fat    16139 b- defN 22-Jun-10 11:59 baopig/lib/__pycache__/utilities.cpython-37.pyc
 -rw-rw-rw-  2.0 fat    30683 b- defN 23-Jan-10 21:12 baopig/lib/__pycache__/widget.cpython-310.pyc
 -rw-rw-rw-  2.0 fat    57092 b- defN 23-Apr-14 15:58 baopig/lib/__pycache__/widget.cpython-311.pyc
 -rw-rw-rw-  2.0 fat    36355 b- defN 22-Jun-10 11:59 baopig/lib/__pycache__/widget.cpython-37.pyc
 -rw-rw-rw-  2.0 fat     8647 b- defN 23-Jan-12 01:33 baopig/lib/__pycache__/widget_supers.cpython-310.pyc
 -rw-rw-rw-  2.0 fat    16061 b- defN 23-Apr-22 14:10 baopig/lib/__pycache__/widget_supers.cpython-311.pyc
 -rw-rw-rw-  2.0 fat     3094 b- defN 22-Jul-17 19:50 baopig/lib/__pycache__/zone.cpython-310.pyc
--rw-rw-rw-  2.0 fat     6355 b- defN 23-Apr-14 15:58 baopig/lib/__pycache__/zone.cpython-311.pyc
+-rw-rw-rw-  2.0 fat     6410 b- defN 23-Apr-22 14:38 baopig/lib/__pycache__/zone.cpython-311.pyc
 -rw-rw-rw-  2.0 fat     3722 b- defN 22-Jun-10 11:59 baopig/lib/__pycache__/zone.cpython-37.pyc
 -rw-rw-rw-  2.0 fat     7489 b- defN 22-Jul-21 19:31 baopig/prefabs/colorchooserdialog.py
 -rw-rw-rw-  2.0 fat     5248 b- defN 22-Jul-21 12:53 baopig/prefabs/debugzone.py
 -rw-rw-rw-  2.0 fat     2177 b- defN 22-Dec-19 01:28 baopig/prefabs/presentationscene.py
 -rw-rw-rw-  2.0 fat     4847 b- defN 22-Dec-15 23:15 baopig/prefabs/testerscene.py
 -rw-rw-rw-  2.0 fat     1719 b- defN 22-Jul-20 17:38 baopig/prefabs/themes.py
 -rw-rw-rw-  2.0 fat     7273 b- defN 22-Jul-21 19:40 baopig/prefabs/__pycache__/colorchooserdialog.cpython-310.pyc
@@ -251,30 +251,30 @@
 -rw-rw-rw-  2.0 fat    13507 b- defN 23-Apr-22 11:43 baopig/unit_tests/__pycache__/ut_sleep.cpython-311.pyc
 -rw-rw-rw-  2.0 fat     3621 b- defN 22-Jul-21 20:14 baopig/unit_tests/__pycache__/ut_text.cpython-310.pyc
 -rw-rw-rw-  2.0 fat     6753 b- defN 23-Apr-22 11:43 baopig/unit_tests/__pycache__/ut_text.cpython-311.pyc
 -rw-rw-rw-  2.0 fat     1830 b- defN 22-Jul-21 20:14 baopig/unit_tests/__pycache__/ut_textedit.cpython-310.pyc
 -rw-rw-rw-  2.0 fat     3446 b- defN 23-Apr-22 11:43 baopig/unit_tests/__pycache__/ut_textedit.cpython-311.pyc
 -rw-rw-rw-  2.0 fat     2043 b- defN 22-Jul-21 19:40 baopig/unit_tests/__pycache__/ut_theme.cpython-310.pyc
 -rw-rw-rw-  2.0 fat     3466 b- defN 23-Apr-22 11:43 baopig/unit_tests/__pycache__/ut_theme.cpython-311.pyc
--rw-rw-rw-  2.0 fat      931 b- defN 23-Apr-22 14:15 baopig/version/version.py
+-rw-rw-rw-  2.0 fat      931 b- defN 23-Apr-22 14:36 baopig/version/version.py
 -rw-rw-rw-  2.0 fat     1692 b- defN 22-Dec-18 21:38 baopig/version/__pycache__/version.cpython-310.pyc
--rw-rw-rw-  2.0 fat     2611 b- defN 23-Apr-22 14:17 baopig/version/__pycache__/version.cpython-311.pyc
+-rw-rw-rw-  2.0 fat     2609 b- defN 23-Apr-22 14:38 baopig/version/__pycache__/version.cpython-311.pyc
 -rw-rw-rw-  2.0 fat     1642 b- defN 22-Jun-10 11:59 baopig/version/__pycache__/version.cpython-37.pyc
 -rw-rw-rw-  2.0 fat      767 b- defN 23-Jan-10 20:24 baopig/widgets/__init__.py
 -rw-rw-rw-  2.0 fat     8232 b- defN 23-Jan-10 19:59 baopig/widgets/button.py
 -rw-rw-rw-  2.0 fat     3102 b- defN 22-Jul-21 19:32 baopig/widgets/checkbox.py
 -rw-rw-rw-  2.0 fat     5246 b- defN 22-Jul-21 19:32 baopig/widgets/dialog.py
 -rw-rw-rw-  2.0 fat     1609 b- defN 22-Jul-20 17:43 baopig/widgets/entry.py
 -rw-rw-rw-  2.0 fat     3607 b- defN 23-Jan-10 20:40 baopig/widgets/indicator.py
 -rw-rw-rw-  2.0 fat     1041 b- defN 22-Jul-21 13:23 baopig/widgets/lineedit.py
 -rw-rw-rw-  2.0 fat     1608 b- defN 22-Jul-21 13:06 baopig/widgets/numentry.py
 -rw-rw-rw-  2.0 fat     1284 b- defN 22-Jul-21 13:06 baopig/widgets/progressbar.py
 -rw-rw-rw-  2.0 fat     6848 b- defN 22-Jul-20 10:31 baopig/widgets/scrollview.py
 -rw-rw-rw-  2.0 fat    10689 b- defN 22-Jul-19 16:37 baopig/widgets/slider.py
--rw-rw-rw-  2.0 fat    29570 b- defN 22-Jul-21 20:14 baopig/widgets/text.py
+-rw-rw-rw-  2.0 fat    29570 b- defN 23-Apr-22 14:31 baopig/widgets/text.py
 -rw-rw-rw-  2.0 fat    22533 b- defN 22-Jul-21 20:14 baopig/widgets/textedit.py
 -rw-rw-rw-  2.0 fat     1087 b- defN 23-Jan-10 20:24 baopig/widgets/__pycache__/__init__.cpython-310.pyc
 -rw-rw-rw-  2.0 fat     1417 b- defN 23-Apr-14 15:58 baopig/widgets/__pycache__/__init__.cpython-311.pyc
 -rw-rw-rw-  2.0 fat      810 b- defN 22-Jun-10 11:59 baopig/widgets/__pycache__/__init__.cpython-37.pyc
 -rw-rw-rw-  2.0 fat     8924 b- defN 23-Jan-10 19:59 baopig/widgets/__pycache__/button.cpython-310.pyc
 -rw-rw-rw-  2.0 fat    16245 b- defN 23-Apr-14 15:58 baopig/widgets/__pycache__/button.cpython-311.pyc
 -rw-rw-rw-  2.0 fat    10854 b- defN 22-Jun-10 11:59 baopig/widgets/__pycache__/button.cpython-37.pyc
@@ -300,18 +300,18 @@
 -rw-rw-rw-  2.0 fat     1527 b- defN 22-Jun-10 11:59 baopig/widgets/__pycache__/progressbar.cpython-37.pyc
 -rw-rw-rw-  2.0 fat     6846 b- defN 22-Jul-20 10:31 baopig/widgets/__pycache__/scrollview.cpython-310.pyc
 -rw-rw-rw-  2.0 fat    13258 b- defN 23-Apr-14 15:58 baopig/widgets/__pycache__/scrollview.cpython-311.pyc
 -rw-rw-rw-  2.0 fat     9558 b- defN 22-Jul-19 16:37 baopig/widgets/__pycache__/slider.cpython-310.pyc
 -rw-rw-rw-  2.0 fat    18086 b- defN 23-Apr-14 15:58 baopig/widgets/__pycache__/slider.cpython-311.pyc
 -rw-rw-rw-  2.0 fat     8011 b- defN 22-Jun-10 11:59 baopig/widgets/__pycache__/slider.cpython-37.pyc
 -rw-rw-rw-  2.0 fat    24379 b- defN 22-Jul-21 20:14 baopig/widgets/__pycache__/text.cpython-310.pyc
--rw-rw-rw-  2.0 fat    43877 b- defN 23-Apr-14 15:58 baopig/widgets/__pycache__/text.cpython-311.pyc
+-rw-rw-rw-  2.0 fat    43636 b- defN 23-Apr-22 14:32 baopig/widgets/__pycache__/text.cpython-311.pyc
 -rw-rw-rw-  2.0 fat    27867 b- defN 22-Jun-10 11:59 baopig/widgets/__pycache__/text.cpython-37.pyc
 -rw-rw-rw-  2.0 fat    14346 b- defN 22-Jul-21 20:14 baopig/widgets/__pycache__/textedit.cpython-310.pyc
 -rw-rw-rw-  2.0 fat    32458 b- defN 23-Apr-14 15:58 baopig/widgets/__pycache__/textedit.cpython-311.pyc
 -rw-rw-rw-  2.0 fat    13078 b- defN 22-Jun-10 11:59 baopig/widgets/__pycache__/textedit.cpython-37.pyc
--rw-rw-rw-  2.0 fat     1088 b- defN 23-Apr-22 14:17 baopig-0.20.4.dist-info/LICENSE
--rw-rw-rw-  2.0 fat      866 b- defN 23-Apr-22 14:17 baopig-0.20.4.dist-info/METADATA
--rw-rw-rw-  2.0 fat       92 b- defN 23-Apr-22 14:17 baopig-0.20.4.dist-info/WHEEL
--rw-rw-rw-  2.0 fat        7 b- defN 23-Apr-22 14:17 baopig-0.20.4.dist-info/top_level.txt
--rw-rw-r--  2.0 fat    32575 b- defN 23-Apr-22 14:17 baopig-0.20.4.dist-info/RECORD
-315 files, 5118612 bytes uncompressed, 2795071 bytes compressed:  45.4%
+-rw-rw-rw-  2.0 fat     1088 b- defN 23-Apr-22 14:38 baopig-0.20.5.dist-info/LICENSE
+-rw-rw-rw-  2.0 fat      866 b- defN 23-Apr-22 14:38 baopig-0.20.5.dist-info/METADATA
+-rw-rw-rw-  2.0 fat       92 b- defN 23-Apr-22 14:38 baopig-0.20.5.dist-info/WHEEL
+-rw-rw-rw-  2.0 fat        7 b- defN 23-Apr-22 14:38 baopig-0.20.5.dist-info/top_level.txt
+-rw-rw-r--  2.0 fat    32575 b- defN 23-Apr-22 14:38 baopig-0.20.5.dist-info/RECORD
+315 files, 5118689 bytes uncompressed, 2795142 bytes compressed:  45.4%
```

## zipnote {}

```diff
@@ -924,23 +924,23 @@
 
 Filename: baopig/widgets/__pycache__/textedit.cpython-311.pyc
 Comment: 
 
 Filename: baopig/widgets/__pycache__/textedit.cpython-37.pyc
 Comment: 
 
-Filename: baopig-0.20.4.dist-info/LICENSE
+Filename: baopig-0.20.5.dist-info/LICENSE
 Comment: 
 
-Filename: baopig-0.20.4.dist-info/METADATA
+Filename: baopig-0.20.5.dist-info/METADATA
 Comment: 
 
-Filename: baopig-0.20.4.dist-info/WHEEL
+Filename: baopig-0.20.5.dist-info/WHEEL
 Comment: 
 
-Filename: baopig-0.20.4.dist-info/top_level.txt
+Filename: baopig-0.20.5.dist-info/top_level.txt
 Comment: 
 
-Filename: baopig-0.20.4.dist-info/RECORD
+Filename: baopig-0.20.5.dist-info/RECORD
 Comment: 
 
 Zip file comment:
```

## baopig/__init__.py

```diff
@@ -8,22 +8,24 @@
 
 # print("baopig from WIP")
 
 # TODO : compilation executable
 from .version.version import version
 
 print(f"baopig {version}")
+print('WIP')
 from pygame import *
 from .pybao.issomething import *
 from .pybao.objectutilities import Object, PrefilledFunction, PackedFunctions
 
 from .io import *
 from .time import *
 from .lib import *
 from .widgets import *
+from .communicative import Communicative, Connection, Signal
 
 display = None  # protection for pygame.display
 
 __version__ = str(version)
 
 
 def debug_with_logging():
```

## baopig/__pycache__/__init__.cpython-311.pyc

### Python bytecode

```diff
@@ -1,22 +1,23 @@
 magic:    0xa70d0d0a
-moddate:  0x5eca4364 (Sat Apr 22 11:51:58 2023 UTC)
-files sz: 608
+moddate:  0xd8f04364 (Sat Apr 22 14:36:08 2023 UTC)
+files sz: 682
 code
    argcount  : 0
    nlocals   : 0
    stacksize : 4
    flags     : 0
    code
       0x970064005a00640164026c016d025a02010002006503640365029b009d
-      02a6010000ab0100000000000000000100640464056c045400640164056c
-      055400640164066c066d075a076d085a086d095a090100640164056c0a54
-      00640164056c0b5400640164056c0c5400640164056c0d540064075a0e02
-      00650f6502a6010000ab0100000000000000005a10640884005a11640753
-      00
+      02a6010000ab0100000000000000000100020065036404a6010000ab0100
+      000000000000000100640564066c045400640164066c055400640164076c
+      066d075a076d085a086d095a090100640164066c0a5400640164066c0b54
+      00640164066c0c5400640164066c0d5400640164086c0e6d0f5a0f6d105a
+      106d115a11010064095a12020065136502a6010000ab0100000000000000
+      005a14640a84005a1564095300
      0           0 RESUME                   0
    
      2           2 LOAD_CONST               0 ('\nWelcome to BaoPig\n\nBAOPIG : Boite A Outils Pour Interfaces Graphiques\n\n')
                  4 STORE_NAME               0 (__doc__)
    
     12           6 LOAD_CONST               1 (1)
                  8 LOAD_CONST               2 (('version',))
@@ -31,99 +32,119 @@
                 24 LOAD_NAME                2 (version)
                 26 FORMAT_VALUE             0
                 28 BUILD_STRING             2
                 30 PRECALL                  1
                 34 CALL                     1
                 44 POP_TOP
    
-    15          46 LOAD_CONST               4 (0)
-                48 LOAD_CONST               5 (('*',))
-                50 IMPORT_NAME              4 (pygame)
-                52 IMPORT_STAR
-   
-    16          54 LOAD_CONST               1 (1)
-                56 LOAD_CONST               5 (('*',))
-                58 IMPORT_NAME              5 (pybao.issomething)
-                60 IMPORT_STAR
-   
-    17          62 LOAD_CONST               1 (1)
-                64 LOAD_CONST               6 (('Object', 'PrefilledFunction', 'PackedFunctions'))
-                66 IMPORT_NAME              6 (pybao.objectutilities)
-                68 IMPORT_FROM              7 (Object)
-                70 STORE_NAME               7 (Object)
-                72 IMPORT_FROM              8 (PrefilledFunction)
-                74 STORE_NAME               8 (PrefilledFunction)
-                76 IMPORT_FROM              9 (PackedFunctions)
-                78 STORE_NAME               9 (PackedFunctions)
-                80 POP_TOP
-   
-    19          82 LOAD_CONST               1 (1)
-                84 LOAD_CONST               5 (('*',))
-                86 IMPORT_NAME             10 (io)
-                88 IMPORT_STAR
-   
-    20          90 LOAD_CONST               1 (1)
-                92 LOAD_CONST               5 (('*',))
-                94 IMPORT_NAME             11 (time)
-                96 IMPORT_STAR
-   
-    21          98 LOAD_CONST               1 (1)
-               100 LOAD_CONST               5 (('*',))
-               102 IMPORT_NAME             12 (lib)
-               104 IMPORT_STAR
-   
-    22         106 LOAD_CONST               1 (1)
-               108 LOAD_CONST               5 (('*',))
-               110 IMPORT_NAME             13 (widgets)
-               112 IMPORT_STAR
-   
-    24         114 LOAD_CONST               7 (None)
-               116 STORE_NAME              14 (display)
-   
-    26         118 PUSH_NULL
-               120 LOAD_NAME               15 (str)
-               122 LOAD_NAME                2 (version)
-               124 PRECALL                  1
-               128 CALL                     1
-               138 STORE_NAME              16 (__version__)
-   
-    29         140 LOAD_CONST               8 (<code object debug_with_logging, file "C:\Users\symrb\Documents\dev\python\baopig\baopig\__init__.py", line 29>)
-               142 MAKE_FUNCTION            0
-               144 STORE_NAME              17 (debug_with_logging)
-               146 LOAD_CONST               7 (None)
-               148 RETURN_VALUE
+    15          46 PUSH_NULL
+                48 LOAD_NAME                3 (print)
+                50 LOAD_CONST               4 ('WIP')
+                52 PRECALL                  1
+                56 CALL                     1
+                66 POP_TOP
+   
+    16          68 LOAD_CONST               5 (0)
+                70 LOAD_CONST               6 (('*',))
+                72 IMPORT_NAME              4 (pygame)
+                74 IMPORT_STAR
+   
+    17          76 LOAD_CONST               1 (1)
+                78 LOAD_CONST               6 (('*',))
+                80 IMPORT_NAME              5 (pybao.issomething)
+                82 IMPORT_STAR
+   
+    18          84 LOAD_CONST               1 (1)
+                86 LOAD_CONST               7 (('Object', 'PrefilledFunction', 'PackedFunctions'))
+                88 IMPORT_NAME              6 (pybao.objectutilities)
+                90 IMPORT_FROM              7 (Object)
+                92 STORE_NAME               7 (Object)
+                94 IMPORT_FROM              8 (PrefilledFunction)
+                96 STORE_NAME               8 (PrefilledFunction)
+                98 IMPORT_FROM              9 (PackedFunctions)
+               100 STORE_NAME               9 (PackedFunctions)
+               102 POP_TOP
+   
+    20         104 LOAD_CONST               1 (1)
+               106 LOAD_CONST               6 (('*',))
+               108 IMPORT_NAME             10 (io)
+               110 IMPORT_STAR
+   
+    21         112 LOAD_CONST               1 (1)
+               114 LOAD_CONST               6 (('*',))
+               116 IMPORT_NAME             11 (time)
+               118 IMPORT_STAR
+   
+    22         120 LOAD_CONST               1 (1)
+               122 LOAD_CONST               6 (('*',))
+               124 IMPORT_NAME             12 (lib)
+               126 IMPORT_STAR
+   
+    23         128 LOAD_CONST               1 (1)
+               130 LOAD_CONST               6 (('*',))
+               132 IMPORT_NAME             13 (widgets)
+               134 IMPORT_STAR
+   
+    24         136 LOAD_CONST               1 (1)
+               138 LOAD_CONST               8 (('Communicative', 'Connection', 'Signal'))
+               140 IMPORT_NAME             14 (communicative)
+               142 IMPORT_FROM             15 (Communicative)
+               144 STORE_NAME              15 (Communicative)
+               146 IMPORT_FROM             16 (Connection)
+               148 STORE_NAME              16 (Connection)
+               150 IMPORT_FROM             17 (Signal)
+               152 STORE_NAME              17 (Signal)
+               154 POP_TOP
+   
+    26         156 LOAD_CONST               9 (None)
+               158 STORE_NAME              18 (display)
+   
+    28         160 PUSH_NULL
+               162 LOAD_NAME               19 (str)
+               164 LOAD_NAME                2 (version)
+               166 PRECALL                  1
+               170 CALL                     1
+               180 STORE_NAME              20 (__version__)
+   
+    31         182 LOAD_CONST              10 (<code object debug_with_logging, file "C:\Users\symrb\Documents\dev\python\baopig\baopig\__init__.py", line 31>)
+               184 MAKE_FUNCTION            0
+               186 STORE_NAME              21 (debug_with_logging)
+               188 LOAD_CONST               9 (None)
+               190 RETURN_VALUE
    consts
       '\nWelcome to BaoPig\n\nBAOPIG : Boite A Outils Pour Interfaces Graphiques\n\n'
       1
       ('version',)
       'baopig '
+      'WIP'
       0
       ('*',)
       ('Object', 'PrefilledFunction', 'PackedFunctions')
+      ('Communicative', 'Connection', 'Signal')
       None
       code
          argcount  : 0
          nlocals   : 0
          stacksize : 3
          flags     : 3
          code
             0x9700740000000000000000000000a00100000000000000000000000000
             00000000000000a6000000ab000000000000000000010074000000000000
             00000000006a020000000000000000a00300000000000000000000000000
             000000000000007400000000000000000000006a040000000000000000a6
             010000ab010000000000000000010064005300
-          29           0 RESUME                   0
+          31           0 RESUME                   0
          
-          31           2 LOAD_GLOBAL              0 (LOGGER)
+          33           2 LOAD_GLOBAL              0 (LOGGER)
                       14 LOAD_METHOD              1 (add_debug_filehandler)
                       36 PRECALL                  0
                       40 CALL                     0
                       50 POP_TOP
          
-          32          52 LOAD_GLOBAL              0 (LOGGER)
+          34          52 LOAD_GLOBAL              0 (LOGGER)
                       64 LOAD_ATTR                2 (cons_handler)
                       74 LOAD_METHOD              3 (setLevel)
                       96 LOAD_GLOBAL              0 (LOGGER)
                      108 LOAD_ATTR                4 (DEBUG)
                      118 PRECALL                  1
                      122 CALL                     1
                      132 POP_TOP
@@ -133,17 +154,19 @@
             None
          names      ('LOGGER', 'add_debug_filehandler', 'cons_handler', 'setLevel', 'DEBUG')
          varnames   ()
          freevars   ()
          cellvars   ()
          filename   'C:\\Users\\symrb\\Documents\\dev\\python\\baopig\\baopig\\__init__.py'
          name       'debug_with_logging'
-         firstlineno 29
+         firstlineno 31
          lnotab 0x02023201
-   names      ('__doc__', 'version.version', 'version', 'print', 'pygame', 'pybao.issomething', 'pybao.objectutilities', 'Object', 'PrefilledFunction', 'PackedFunctions', 'io', 'time', 'lib', 'widgets', 'display', 'str', '__version__', 'debug_with_logging')
+   names      ('__doc__', 'version.version', 'version', 'print', 'pygame', 'pybao.issomething', 'pybao.objectutilities', 'Object', 'PrefilledFunction', 'PackedFunctions', 'io', 'time', 'lib', 'widgets', 'communicative', 'Communicative', 'Connection', 'Signal', 'display', 'str', '__version__', 'debug_with_logging')
    varnames   ()
    freevars   ()
    cellvars   ()
    filename   'C:\\Users\\symrb\\Documents\\dev\\python\\baopig\\baopig\\__init__.py'
    name       '<module>'
    firstlineno 1
-   lnotab 0x00ff0202040a0c021c01080108011402080108010801080204021603
+   lnotab
+      0x00ff0202040a0c021c0116010801080114020801080108010801140204
+      021603
```

## baopig/lib/__init__.py

```diff
@@ -1,9 +1,10 @@
 from .style import Theme
 from .utilities import *
+from .widget import Widget
 from .widget_supers import DraggableByMouse, Focusable, HoverableByMouse, LinkableByMouse, MaintainableByFocus, \
     RepetivelyAnimated, Runable, Validable
 from .imagewidget import Image
 from .shapes import Rectangle, Highlighter, Polygon, Line, Circle
 from .layer import Layer
 from .gridlayer import GridLayer
 from .layersmanager import LayersManager
```

## baopig/lib/zone.py

```diff
@@ -1,15 +1,14 @@
-
-
 import pygame
-from baopig.lib import Container, paint_lock, Widget
+from .utilities import paint_lock
+from .widget import Widget
+from .container import Container
 
 
 class Zone(Container):
-
     STYLE = Container.STYLE.substyle()
     STYLE.modify(
         width=100,
         height=100,
     )
 
     def divide(self, side, width):
```

## baopig/lib/__pycache__/__init__.cpython-311.pyc

### Python bytecode

```diff
@@ -1,24 +1,24 @@
 magic:    0xa70d0d0a
-moddate:  0x03eb4364 (Sat Apr 22 14:11:15 2023 UTC)
-files sz: 638
+moddate:  0xe2ef4364 (Sat Apr 22 14:32:02 2023 UTC)
+files sz: 623
 code
    argcount  : 0
    nlocals   : 0
    stacksize : 2
    flags     : 0
    code
       0x9700640064016c006d015a010100640064026c025400640064036c036d
-      045a046d055a050100640064046c066d075a076d085a086d095a096d0a5a
-      0a6d0b5a0b6d0c5a0c6d0d5a0d6d0e5a0e0100640064056c0f6d105a1001
-      00640064066c116d125a126d135a136d145a146d155a156d165a16010064
-      0064076c176d185a180100640064086c196d1a5a1a0100640064096c1b6d
-      1c5a1c01006400640a6c1d6d1e5a1e01006400640b6c1f6d205a206d215a
-      2101006400640c6c226d235a236d245a246d255a2501006400640d6c266d
-      275a2701006400640e6c286d295a290100640f5300
+      045a040100640064046c056d065a066d075a076d085a086d095a096d0a5a
+      0a6d0b5a0b6d0c5a0c6d0d5a0d0100640064056c0e6d0f5a0f0100640064
+      066c106d115a116d125a126d135a136d145a146d155a150100640064076c
+      166d175a170100640064086c186d195a190100640064096c1a6d1b5a1b01
+      006400640a6c1c6d1d5a1d01006400640b6c1e6d1f5a1f6d205a20010064
+      00640c6c216d225a226d235a236d245a2401006400640d6c256d265a2601
+      006400640e6c276d285a280100640f5300
      0           0 RESUME                   0
    
      1           2 LOAD_CONST               0 (1)
                  4 LOAD_CONST               1 (('Theme',))
                  6 IMPORT_NAME              0 (style)
                  8 IMPORT_FROM              1 (Theme)
                 10 STORE_NAME               1 (Theme)
@@ -26,148 +26,146 @@
    
      2          14 LOAD_CONST               0 (1)
                 16 LOAD_CONST               2 (('*',))
                 18 IMPORT_NAME              2 (utilities)
                 20 IMPORT_STAR
    
      3          22 LOAD_CONST               0 (1)
-                24 LOAD_CONST               3 (('Widget', 'Communicative'))
+                24 LOAD_CONST               3 (('Widget',))
                 26 IMPORT_NAME              3 (widget)
                 28 IMPORT_FROM              4 (Widget)
                 30 STORE_NAME               4 (Widget)
-                32 IMPORT_FROM              5 (Communicative)
-                34 STORE_NAME               5 (Communicative)
-                36 POP_TOP
-   
-     4          38 LOAD_CONST               0 (1)
-                40 LOAD_CONST               4 (('DraggableByMouse', 'Focusable', 'HoverableByMouse', 'LinkableByMouse', 'MaintainableByFocus', 'RepetivelyAnimated', 'Runable', 'Validable'))
-                42 IMPORT_NAME              6 (widget_supers)
-                44 IMPORT_FROM              7 (DraggableByMouse)
-                46 STORE_NAME               7 (DraggableByMouse)
-                48 IMPORT_FROM              8 (Focusable)
-                50 STORE_NAME               8 (Focusable)
-                52 IMPORT_FROM              9 (HoverableByMouse)
-                54 STORE_NAME               9 (HoverableByMouse)
-                56 IMPORT_FROM             10 (LinkableByMouse)
-                58 STORE_NAME              10 (LinkableByMouse)
-                60 IMPORT_FROM             11 (MaintainableByFocus)
-                62 STORE_NAME              11 (MaintainableByFocus)
-                64 IMPORT_FROM             12 (RepetivelyAnimated)
-                66 STORE_NAME              12 (RepetivelyAnimated)
-                68 IMPORT_FROM             13 (Runable)
-                70 STORE_NAME              13 (Runable)
-                72 IMPORT_FROM             14 (Validable)
-                74 STORE_NAME              14 (Validable)
-                76 POP_TOP
-   
-     6          78 LOAD_CONST               0 (1)
-                80 LOAD_CONST               5 (('Image',))
-                82 IMPORT_NAME             15 (imagewidget)
-                84 IMPORT_FROM             16 (Image)
-                86 STORE_NAME              16 (Image)
-                88 POP_TOP
-   
-     7          90 LOAD_CONST               0 (1)
-                92 LOAD_CONST               6 (('Rectangle', 'Highlighter', 'Polygon', 'Line', 'Circle'))
-                94 IMPORT_NAME             17 (shapes)
-                96 IMPORT_FROM             18 (Rectangle)
-                98 STORE_NAME              18 (Rectangle)
-               100 IMPORT_FROM             19 (Highlighter)
-               102 STORE_NAME              19 (Highlighter)
-               104 IMPORT_FROM             20 (Polygon)
-               106 STORE_NAME              20 (Polygon)
-               108 IMPORT_FROM             21 (Line)
-               110 STORE_NAME              21 (Line)
-               112 IMPORT_FROM             22 (Circle)
-               114 STORE_NAME              22 (Circle)
-               116 POP_TOP
-   
-     8         118 LOAD_CONST               0 (1)
-               120 LOAD_CONST               7 (('Layer',))
-               122 IMPORT_NAME             23 (layer)
-               124 IMPORT_FROM             24 (Layer)
-               126 STORE_NAME              24 (Layer)
-               128 POP_TOP
-   
-     9         130 LOAD_CONST               0 (1)
-               132 LOAD_CONST               8 (('GridLayer',))
-               134 IMPORT_NAME             25 (gridlayer)
-               136 IMPORT_FROM             26 (GridLayer)
-               138 STORE_NAME              26 (GridLayer)
-               140 POP_TOP
-   
-    10         142 LOAD_CONST               0 (1)
-               144 LOAD_CONST               9 (('LayersManager',))
-               146 IMPORT_NAME             27 (layersmanager)
-               148 IMPORT_FROM             28 (LayersManager)
-               150 STORE_NAME              28 (LayersManager)
-               152 POP_TOP
-   
-    11         154 LOAD_CONST               0 (1)
-               156 LOAD_CONST              10 (('Container',))
-               158 IMPORT_NAME             29 (container)
-               160 IMPORT_FROM             30 (Container)
-               162 STORE_NAME              30 (Container)
-               164 POP_TOP
-   
-    12         166 LOAD_CONST               0 (1)
-               168 LOAD_CONST              11 (('Zone', 'SubZone'))
-               170 IMPORT_NAME             31 (zone)
-               172 IMPORT_FROM             32 (Zone)
-               174 STORE_NAME              32 (Zone)
-               176 IMPORT_FROM             33 (SubZone)
-               178 STORE_NAME              33 (SubZone)
-               180 POP_TOP
-   
-    13         182 LOAD_CONST               0 (1)
-               184 LOAD_CONST              12 (('SelectableWidget', 'Selector', 'SelectionRect'))
-               186 IMPORT_NAME             34 (selections)
-               188 IMPORT_FROM             35 (SelectableWidget)
-               190 STORE_NAME              35 (SelectableWidget)
-               192 IMPORT_FROM             36 (Selector)
-               194 STORE_NAME              36 (Selector)
-               196 IMPORT_FROM             37 (SelectionRect)
-               198 STORE_NAME              37 (SelectionRect)
-               200 POP_TOP
-   
-    14         202 LOAD_CONST               0 (1)
-               204 LOAD_CONST              13 (('Scene',))
-               206 IMPORT_NAME             38 (scene)
-               208 IMPORT_FROM             39 (Scene)
-               210 STORE_NAME              39 (Scene)
-               212 POP_TOP
-   
-    15         214 LOAD_CONST               0 (1)
-               216 LOAD_CONST              14 (('Application',))
-               218 IMPORT_NAME             40 (application)
-               220 IMPORT_FROM             41 (Application)
-               222 STORE_NAME              41 (Application)
-               224 POP_TOP
-               226 LOAD_CONST              15 (None)
-               228 RETURN_VALUE
+                32 POP_TOP
+   
+     4          34 LOAD_CONST               0 (1)
+                36 LOAD_CONST               4 (('DraggableByMouse', 'Focusable', 'HoverableByMouse', 'LinkableByMouse', 'MaintainableByFocus', 'RepetivelyAnimated', 'Runable', 'Validable'))
+                38 IMPORT_NAME              5 (widget_supers)
+                40 IMPORT_FROM              6 (DraggableByMouse)
+                42 STORE_NAME               6 (DraggableByMouse)
+                44 IMPORT_FROM              7 (Focusable)
+                46 STORE_NAME               7 (Focusable)
+                48 IMPORT_FROM              8 (HoverableByMouse)
+                50 STORE_NAME               8 (HoverableByMouse)
+                52 IMPORT_FROM              9 (LinkableByMouse)
+                54 STORE_NAME               9 (LinkableByMouse)
+                56 IMPORT_FROM             10 (MaintainableByFocus)
+                58 STORE_NAME              10 (MaintainableByFocus)
+                60 IMPORT_FROM             11 (RepetivelyAnimated)
+                62 STORE_NAME              11 (RepetivelyAnimated)
+                64 IMPORT_FROM             12 (Runable)
+                66 STORE_NAME              12 (Runable)
+                68 IMPORT_FROM             13 (Validable)
+                70 STORE_NAME              13 (Validable)
+                72 POP_TOP
+   
+     6          74 LOAD_CONST               0 (1)
+                76 LOAD_CONST               5 (('Image',))
+                78 IMPORT_NAME             14 (imagewidget)
+                80 IMPORT_FROM             15 (Image)
+                82 STORE_NAME              15 (Image)
+                84 POP_TOP
+   
+     7          86 LOAD_CONST               0 (1)
+                88 LOAD_CONST               6 (('Rectangle', 'Highlighter', 'Polygon', 'Line', 'Circle'))
+                90 IMPORT_NAME             16 (shapes)
+                92 IMPORT_FROM             17 (Rectangle)
+                94 STORE_NAME              17 (Rectangle)
+                96 IMPORT_FROM             18 (Highlighter)
+                98 STORE_NAME              18 (Highlighter)
+               100 IMPORT_FROM             19 (Polygon)
+               102 STORE_NAME              19 (Polygon)
+               104 IMPORT_FROM             20 (Line)
+               106 STORE_NAME              20 (Line)
+               108 IMPORT_FROM             21 (Circle)
+               110 STORE_NAME              21 (Circle)
+               112 POP_TOP
+   
+     8         114 LOAD_CONST               0 (1)
+               116 LOAD_CONST               7 (('Layer',))
+               118 IMPORT_NAME             22 (layer)
+               120 IMPORT_FROM             23 (Layer)
+               122 STORE_NAME              23 (Layer)
+               124 POP_TOP
+   
+     9         126 LOAD_CONST               0 (1)
+               128 LOAD_CONST               8 (('GridLayer',))
+               130 IMPORT_NAME             24 (gridlayer)
+               132 IMPORT_FROM             25 (GridLayer)
+               134 STORE_NAME              25 (GridLayer)
+               136 POP_TOP
+   
+    10         138 LOAD_CONST               0 (1)
+               140 LOAD_CONST               9 (('LayersManager',))
+               142 IMPORT_NAME             26 (layersmanager)
+               144 IMPORT_FROM             27 (LayersManager)
+               146 STORE_NAME              27 (LayersManager)
+               148 POP_TOP
+   
+    11         150 LOAD_CONST               0 (1)
+               152 LOAD_CONST              10 (('Container',))
+               154 IMPORT_NAME             28 (container)
+               156 IMPORT_FROM             29 (Container)
+               158 STORE_NAME              29 (Container)
+               160 POP_TOP
+   
+    12         162 LOAD_CONST               0 (1)
+               164 LOAD_CONST              11 (('Zone', 'SubZone'))
+               166 IMPORT_NAME             30 (zone)
+               168 IMPORT_FROM             31 (Zone)
+               170 STORE_NAME              31 (Zone)
+               172 IMPORT_FROM             32 (SubZone)
+               174 STORE_NAME              32 (SubZone)
+               176 POP_TOP
+   
+    13         178 LOAD_CONST               0 (1)
+               180 LOAD_CONST              12 (('SelectableWidget', 'Selector', 'SelectionRect'))
+               182 IMPORT_NAME             33 (selections)
+               184 IMPORT_FROM             34 (SelectableWidget)
+               186 STORE_NAME              34 (SelectableWidget)
+               188 IMPORT_FROM             35 (Selector)
+               190 STORE_NAME              35 (Selector)
+               192 IMPORT_FROM             36 (SelectionRect)
+               194 STORE_NAME              36 (SelectionRect)
+               196 POP_TOP
+   
+    14         198 LOAD_CONST               0 (1)
+               200 LOAD_CONST              13 (('Scene',))
+               202 IMPORT_NAME             37 (scene)
+               204 IMPORT_FROM             38 (Scene)
+               206 STORE_NAME              38 (Scene)
+               208 POP_TOP
+   
+    15         210 LOAD_CONST               0 (1)
+               212 LOAD_CONST              14 (('Application',))
+               214 IMPORT_NAME             39 (application)
+               216 IMPORT_FROM             40 (Application)
+               218 STORE_NAME              40 (Application)
+               220 POP_TOP
+               222 LOAD_CONST              15 (None)
+               224 RETURN_VALUE
    consts
       1
       ('Theme',)
       ('*',)
-      ('Widget', 'Communicative')
+      ('Widget',)
       ('DraggableByMouse', 'Focusable', 'HoverableByMouse', 'LinkableByMouse', 'MaintainableByFocus', 'RepetivelyAnimated', 'Runable', 'Validable')
       ('Image',)
       ('Rectangle', 'Highlighter', 'Polygon', 'Line', 'Circle')
       ('Layer',)
       ('GridLayer',)
       ('LayersManager',)
       ('Container',)
       ('Zone', 'SubZone')
       ('SelectableWidget', 'Selector', 'SelectionRect')
       ('Scene',)
       ('Application',)
       None
-   names      ('style', 'Theme', 'utilities', 'widget', 'Widget', 'Communicative', 'widget_supers', 'DraggableByMouse', 'Focusable', 'HoverableByMouse', 'LinkableByMouse', 'MaintainableByFocus', 'RepetivelyAnimated', 'Runable', 'Validable', 'imagewidget', 'Image', 'shapes', 'Rectangle', 'Highlighter', 'Polygon', 'Line', 'Circle', 'layer', 'Layer', 'gridlayer', 'GridLayer', 'layersmanager', 'LayersManager', 'container', 'Container', 'zone', 'Zone', 'SubZone', 'selections', 'SelectableWidget', 'Selector', 'SelectionRect', 'scene', 'Scene', 'application', 'Application')
+   names      ('style', 'Theme', 'utilities', 'widget', 'Widget', 'widget_supers', 'DraggableByMouse', 'Focusable', 'HoverableByMouse', 'LinkableByMouse', 'MaintainableByFocus', 'RepetivelyAnimated', 'Runable', 'Validable', 'imagewidget', 'Image', 'shapes', 'Rectangle', 'Highlighter', 'Polygon', 'Line', 'Circle', 'layer', 'Layer', 'gridlayer', 'GridLayer', 'layersmanager', 'LayersManager', 'container', 'Container', 'zone', 'Zone', 'SubZone', 'selections', 'SelectableWidget', 'Selector', 'SelectionRect', 'scene', 'Scene', 'application', 'Application')
    varnames   ()
    freevars   ()
    cellvars   ()
    filename   'C:\\Users\\symrb\\Documents\\dev\\python\\baopig\\baopig\\lib\\__init__.py'
    name       '<module>'
    firstlineno 1
    lnotab
-      0x00ff02010c010801100128020c011c010c010c010c010c01100114010c
+      0x00ff02010c0108010c0128020c011c010c010c010c010c01100114010c
       01
```

## baopig/lib/__pycache__/zone.cpython-311.pyc

### Python bytecode

```diff
@@ -1,63 +1,76 @@
 magic:    0xa70d0d0a
-moddate:  0x4167d462 (Sun Jul 17 19:47:13 2022 UTC)
-files sz: 3300
+moddate:  0xd8f04364 (Sat Apr 22 14:36:08 2023 UTC)
+files sz: 3337
 code
    argcount  : 0
    nlocals   : 0
    stacksize : 5
    flags     : 0
    code
-      0x9700640064016c005a00640064026c016d025a026d035a036d045a0401
-      00020047006403840064046502a6030000ab0300000000000000005a0502
-      0047006405840064066505a6030000ab0300000000000000005a06640153
-      00
+      0x9700640064016c005a00640264036c016d025a020100640264046c036d
+      045a040100640264056c056d065a060100020047006406840064076506a6
+      030000ab0300000000000000005a07020047006408840064096507a60300
+      00ab0300000000000000005a0864015300
      0           0 RESUME                   0
    
-     3           2 LOAD_CONST               0 (0)
+     1           2 LOAD_CONST               0 (0)
                  4 LOAD_CONST               1 (None)
                  6 IMPORT_NAME              0 (pygame)
                  8 STORE_NAME               0 (pygame)
    
-     4          10 LOAD_CONST               0 (0)
-                12 LOAD_CONST               2 (('Container', 'paint_lock', 'Widget'))
-                14 IMPORT_NAME              1 (baopig.lib)
-                16 IMPORT_FROM              2 (Container)
-                18 STORE_NAME               2 (Container)
-                20 IMPORT_FROM              3 (paint_lock)
-                22 STORE_NAME               3 (paint_lock)
-                24 IMPORT_FROM              4 (Widget)
-                26 STORE_NAME               4 (Widget)
-                28 POP_TOP
+     2          10 LOAD_CONST               2 (1)
+                12 LOAD_CONST               3 (('paint_lock',))
+                14 IMPORT_NAME              1 (utilities)
+                16 IMPORT_FROM              2 (paint_lock)
+                18 STORE_NAME               2 (paint_lock)
+                20 POP_TOP
    
-     7          30 PUSH_NULL
-                32 LOAD_BUILD_CLASS
-                34 LOAD_CONST               3 (<code object Zone, file "C:\Users\symrb\Documents\dev\python\baopig\baopig\lib\zone.py", line 7>)
-                36 MAKE_FUNCTION            0
-                38 LOAD_CONST               4 ('Zone')
-                40 LOAD_NAME                2 (Container)
-                42 PRECALL                  3
-                46 CALL                     3
-                56 STORE_NAME               5 (Zone)
+     3          22 LOAD_CONST               2 (1)
+                24 LOAD_CONST               4 (('Widget',))
+                26 IMPORT_NAME              3 (widget)
+                28 IMPORT_FROM              4 (Widget)
+                30 STORE_NAME               4 (Widget)
+                32 POP_TOP
    
-    28          58 PUSH_NULL
-                60 LOAD_BUILD_CLASS
-                62 LOAD_CONST               5 (<code object SubZone, file "C:\Users\symrb\Documents\dev\python\baopig\baopig\lib\zone.py", line 28>)
-                64 MAKE_FUNCTION            0
-                66 LOAD_CONST               6 ('SubZone')
-                68 LOAD_NAME                5 (Zone)
-                70 PRECALL                  3
-                74 CALL                     3
-                84 STORE_NAME               6 (SubZone)
-                86 LOAD_CONST               1 (None)
-                88 RETURN_VALUE
+     4          34 LOAD_CONST               2 (1)
+                36 LOAD_CONST               5 (('Container',))
+                38 IMPORT_NAME              5 (container)
+                40 IMPORT_FROM              6 (Container)
+                42 STORE_NAME               6 (Container)
+                44 POP_TOP
+   
+     7          46 PUSH_NULL
+                48 LOAD_BUILD_CLASS
+                50 LOAD_CONST               6 (<code object Zone, file "C:\Users\symrb\Documents\dev\python\baopig\baopig\lib\zone.py", line 7>)
+                52 MAKE_FUNCTION            0
+                54 LOAD_CONST               7 ('Zone')
+                56 LOAD_NAME                6 (Container)
+                58 PRECALL                  3
+                62 CALL                     3
+                72 STORE_NAME               7 (Zone)
+   
+    27          74 PUSH_NULL
+                76 LOAD_BUILD_CLASS
+                78 LOAD_CONST               8 (<code object SubZone, file "C:\Users\symrb\Documents\dev\python\baopig\baopig\lib\zone.py", line 27>)
+                80 MAKE_FUNCTION            0
+                82 LOAD_CONST               9 ('SubZone')
+                84 LOAD_NAME                7 (Zone)
+                86 PRECALL                  3
+                90 CALL                     3
+               100 STORE_NAME               8 (SubZone)
+               102 LOAD_CONST               1 (None)
+               104 RETURN_VALUE
    consts
       0
       None
-      ('Container', 'paint_lock', 'Widget')
+      1
+      ('paint_lock',)
+      ('Widget',)
+      ('Container',)
       code
          argcount  : 0
          nlocals   : 0
          stacksize : 4
          flags     : 0
          code
             0x970065005a0164005a0265036a040000000000000000a0050000000000
@@ -66,34 +79,34 @@
             02a6020000ab0200000000000000000100640384005a0764045300
            7           0 RESUME                   0
                        2 LOAD_NAME                0 (__name__)
                        4 STORE_NAME               1 (__module__)
                        6 LOAD_CONST               0 ('Zone')
                        8 STORE_NAME               2 (__qualname__)
          
-           9          10 LOAD_NAME                3 (Container)
+           8          10 LOAD_NAME                3 (Container)
                       12 LOAD_ATTR                4 (STYLE)
                       22 LOAD_METHOD              5 (substyle)
                       44 PRECALL                  0
                       48 CALL                     0
                       58 STORE_NAME               4 (STYLE)
          
-          10          60 LOAD_NAME                4 (STYLE)
+           9          60 LOAD_NAME                4 (STYLE)
                       62 LOAD_METHOD              6 (modify)
          
-          11          84 LOAD_CONST               1 (100)
+          10          84 LOAD_CONST               1 (100)
          
-          12          86 LOAD_CONST               1 (100)
+          11          86 LOAD_CONST               1 (100)
          
-          10          88 KW_NAMES                 2
+           9          88 KW_NAMES                 2
                       90 PRECALL                  2
                       94 CALL                     2
                      104 POP_TOP
          
-          15         106 LOAD_CONST               3 (<code object divide, file "C:\Users\symrb\Documents\dev\python\baopig\baopig\lib\zone.py", line 15>)
+          14         106 LOAD_CONST               3 (<code object divide, file "C:\Users\symrb\Documents\dev\python\baopig\baopig\lib\zone.py", line 14>)
                      108 MAKE_FUNCTION            0
                      110 STORE_NAME               7 (divide)
                      112 LOAD_CONST               4 (None)
                      114 RETURN_VALUE
          consts
             'Zone'
             100
@@ -107,121 +120,121 @@
                   0x97007c0164016b0200000000725c7c027c006a0000000000000000005f
                   0100000000000000007c006a00000000000000000078016a020000000000
                   0000007c027a17000063025f0200000000000000007c006a000000000000
                   0000006a02000000000000000064026b0100000000720f74070000000000
                   00000000006403a6010000ab010000000000000000820174090000000000
                   00000000007c027c006a0000000000000000006a05000000000000000066
                   02a6010000ab0100000000000000007d036e02640053007c035300
-                15           0 RESUME                   0
+                14           0 RESUME                   0
                
-                17           2 LOAD_FAST                1 (side)
+                16           2 LOAD_FAST                1 (side)
                              4 LOAD_CONST               1 ('left')
                              6 COMPARE_OP               2 (==)
                             12 POP_JUMP_FORWARD_IF_FALSE    92 (to 198)
                
-                18          14 LOAD_FAST                2 (width)
+                17          14 LOAD_FAST                2 (width)
                             16 LOAD_FAST                0 (self)
                             18 LOAD_ATTR                0 (rect)
                             28 STORE_ATTR               1 (left)
                
-                19          38 LOAD_FAST                0 (self)
+                18          38 LOAD_FAST                0 (self)
                             40 LOAD_ATTR                0 (rect)
                             50 COPY                     1
                             52 LOAD_ATTR                2 (w)
                             62 LOAD_FAST                2 (width)
                             64 BINARY_OP               23 (-=)
                             68 SWAP                     2
                             70 STORE_ATTR               2 (w)
                
-                20          80 LOAD_FAST                0 (self)
+                19          80 LOAD_FAST                0 (self)
                             82 LOAD_ATTR                0 (rect)
                             92 LOAD_ATTR                2 (w)
                            102 LOAD_CONST               2 (0)
                            104 COMPARE_OP               1 (<=)
                            110 POP_JUMP_FORWARD_IF_FALSE    15 (to 142)
                
-                21         112 LOAD_GLOBAL              7 (NULL + ValueError)
+                20         112 LOAD_GLOBAL              7 (NULL + ValueError)
                            124 LOAD_CONST               3 ("the new zone shouldn't completly override the central zone")
                            126 PRECALL                  1
                            130 CALL                     1
                            140 RAISE_VARARGS            1
                
-                22     >>  142 LOAD_GLOBAL              9 (NULL + Zone)
+                21     >>  142 LOAD_GLOBAL              9 (NULL + Zone)
                            154 LOAD_FAST                2 (width)
                            156 LOAD_FAST                0 (self)
                            158 LOAD_ATTR                0 (rect)
                            168 LOAD_ATTR                5 (h)
                            178 BUILD_TUPLE              2
                            180 PRECALL                  1
                            184 CALL                     1
                            194 STORE_FAST               3 (zone)
                            196 JUMP_FORWARD             2 (to 202)
                
-                24     >>  198 LOAD_CONST               0 (None)
+                23     >>  198 LOAD_CONST               0 (None)
                            200 RETURN_VALUE
                
-                25     >>  202 LOAD_FAST                3 (zone)
+                24     >>  202 LOAD_FAST                3 (zone)
                            204 RETURN_VALUE
                consts
                   None
                   'left'
                   0
                   "the new zone shouldn't completly override the central zone"
                names      ('rect', 'left', 'w', 'ValueError', 'Zone', 'h')
                varnames   ('self', 'side', 'width', 'zone')
                freevars   ()
                cellvars   ()
                filename   'C:\\Users\\symrb\\Documents\\dev\\python\\baopig\\baopig\\lib\\zone.py'
                name       'divide'
-               firstlineno 15
+               firstlineno 14
                lnotab 0x02020c0118012a0120011e0138020401
             None
          names      ('__name__', '__module__', '__qualname__', 'Container', 'STYLE', 'substyle', 'modify', 'divide')
          varnames   ()
          freevars   ()
          cellvars   ()
          filename   'C:\\Users\\symrb\\Documents\\dev\\python\\baopig\\baopig\\lib\\zone.py'
          name       'Zone'
          firstlineno 7
-         lnotab 0x0a0232011801020102fe1205
+         lnotab 0x0a0132011801020102fe1205
       'Zone'
       code
          argcount  : 0
          nlocals   : 0
          stacksize : 1
          flags     : 0
          code
             0x970065005a0164005a0264015a03640284005a04640384005a05640484
             005a06640584005a07640684005a0864075300
-          28           0 RESUME                   0
+          27           0 RESUME                   0
                        2 LOAD_NAME                0 (__name__)
                        4 STORE_NAME               1 (__module__)
                        6 LOAD_CONST               0 ('SubZone')
                        8 STORE_NAME               2 (__qualname__)
          
-          30          10 LOAD_CONST               1 ('A SuzZone is an optimized Zone, its surface is a subsurface of its parent (cannot have transparency)')
+          29          10 LOAD_CONST               1 ('A SuzZone is an optimized Zone, its surface is a subsurface of its parent (cannot have transparency)')
                       12 STORE_NAME               3 (__doc__)
          
-          32          14 LOAD_CONST               2 (<code object __init__, file "C:\Users\symrb\Documents\dev\python\baopig\baopig\lib\zone.py", line 32>)
+          31          14 LOAD_CONST               2 (<code object __init__, file "C:\Users\symrb\Documents\dev\python\baopig\baopig\lib\zone.py", line 31>)
                       16 MAKE_FUNCTION            0
                       18 STORE_NAME               4 (__init__)
          
-          44          20 LOAD_CONST               3 (<code object _update_subsurface, file "C:\Users\symrb\Documents\dev\python\baopig\baopig\lib\zone.py", line 44>)
+          43          20 LOAD_CONST               3 (<code object _update_subsurface, file "C:\Users\symrb\Documents\dev\python\baopig\baopig\lib\zone.py", line 43>)
                       22 MAKE_FUNCTION            0
                       24 STORE_NAME               5 (_update_subsurface)
          
-          54          26 LOAD_CONST               4 (<code object _flip, file "C:\Users\symrb\Documents\dev\python\baopig\baopig\lib\zone.py", line 54>)
+          53          26 LOAD_CONST               4 (<code object _flip, file "C:\Users\symrb\Documents\dev\python\baopig\baopig\lib\zone.py", line 53>)
                       28 MAKE_FUNCTION            0
                       30 STORE_NAME               6 (_flip)
          
-          72          32 LOAD_CONST               5 (<code object _update_surface_from_resize, file "C:\Users\symrb\Documents\dev\python\baopig\baopig\lib\zone.py", line 72>)
+          71          32 LOAD_CONST               5 (<code object _update_surface_from_resize, file "C:\Users\symrb\Documents\dev\python\baopig\baopig\lib\zone.py", line 71>)
                       34 MAKE_FUNCTION            0
                       36 STORE_NAME               7 (_update_surface_from_resize)
          
-          82          38 LOAD_CONST               6 (<code object _warn_parent, file "C:\Users\symrb\Documents\dev\python\baopig\baopig\lib\zone.py", line 82>)
+          81          38 LOAD_CONST               6 (<code object _warn_parent, file "C:\Users\symrb\Documents\dev\python\baopig\baopig\lib\zone.py", line 81>)
                       40 MAKE_FUNCTION            0
                       42 STORE_NAME               8 (_warn_parent)
                       44 LOAD_CONST               7 (None)
                       46 RETURN_VALUE
          consts
             'SubZone'
             'A SuzZone is an optimized Zone, its surface is a subsurface of its parent (cannot have transparency)'
@@ -243,30 +256,30 @@
                   006401a6010000ab010000000000000000820177007803590077017c006a
                   0200000000000000006a0d00000000000000006a0e0000000000000000a0
                   0f00000000000000000000000000000000000000007c006a100000000000
                   0000007c00ac02a6020000ab02000000000000000001007c006a0d000000
                   00000000006a110000000000000000a00f00000000000000000000000000
                   000000000000007c006a1000000000000000007c00ac02a6020000ab0200
                   00000000000000010064005300
-                32           0 RESUME                   0
+                31           0 RESUME                   0
                
-                34           2 LOAD_GLOBAL              1 (NULL + Zone)
+                33           2 LOAD_GLOBAL              1 (NULL + Zone)
                             14 LOAD_ATTR                1 (__init__)
                             24 LOAD_FAST                0 (self)
                             26 LOAD_FAST                1 (parent)
                             28 BUILD_TUPLE              2
                             30 BUILD_MAP                0
                             32 LOAD_FAST                2 (kwargs)
                             34 DICT_MERGE               1
                             36 CALL_FUNCTION_EX         1
                             38 POP_TOP
                
-                35          40 NOP
+                34          40 NOP
                
-                36          42 LOAD_FAST                0 (self)
+                35          42 LOAD_FAST                0 (self)
                             44 LOAD_ATTR                2 (parent)
                             54 LOAD_ATTR                3 (surface)
                             64 LOAD_METHOD              4 (subsurface)
                             86 LOAD_FAST                0 (self)
                             88 LOAD_ATTR                5 (rect)
                             98 LOAD_ATTR                6 (topleft)
                            108 LOAD_FAST                0 (self)
@@ -276,56 +289,56 @@
                            134 PRECALL                  1
                            138 CALL                     1
                            148 LOAD_FAST                0 (self)
                            150 STORE_ATTR               8 (_surface)
                            160 JUMP_FORWARD            67 (to 296)
                        >>  162 PUSH_EXC_INFO
                
-                37         164 LOAD_GLOBAL             18 (ValueError)
+                36         164 LOAD_GLOBAL             18 (ValueError)
                            176 CHECK_EXC_MATCH
                            178 POP_JUMP_FORWARD_IF_FALSE    54 (to 288)
                            180 POP_TOP
                
-                38         182 LOAD_FAST                0 (self)
+                37         182 LOAD_FAST                0 (self)
                            184 LOAD_ATTR                2 (parent)
                            194 LOAD_ATTR               10 (auto_rect)
                            204 LOAD_METHOD             11 (contains)
                            226 LOAD_FAST                0 (self)
                            228 LOAD_ATTR                5 (rect)
                            238 PRECALL                  1
                            242 CALL                     1
                            252 POP_JUMP_FORWARD_IF_FALSE     2 (to 258)
                            254 LOAD_ASSERTION_ERROR
                            256 RAISE_VARARGS            1
                
-                39     >>  258 LOAD_GLOBAL             25 (NULL + PermissionError)
+                38     >>  258 LOAD_GLOBAL             25 (NULL + PermissionError)
                            270 LOAD_CONST               1 ('A SubZone must fit inside its parent')
                            272 PRECALL                  1
                            276 CALL                     1
                            286 RAISE_VARARGS            1
                
-                37     >>  288 RERAISE                  0
+                36     >>  288 RERAISE                  0
                        >>  290 COPY                     3
                            292 POP_EXCEPT
                            294 RERAISE                  1
                
-                41     >>  296 LOAD_FAST                0 (self)
+                40     >>  296 LOAD_FAST                0 (self)
                            298 LOAD_ATTR                2 (parent)
                            308 LOAD_ATTR               13 (signal)
                            318 LOAD_ATTR               14 (NEW_SURFACE)
                            328 LOAD_METHOD             15 (connect)
                            350 LOAD_FAST                0 (self)
                            352 LOAD_ATTR               16 (_update_subsurface)
                            362 LOAD_FAST                0 (self)
                            364 KW_NAMES                 2
                            366 PRECALL                  2
                            370 CALL                     2
                            380 POP_TOP
                
-                42         382 LOAD_FAST                0 (self)
+                41         382 LOAD_FAST                0 (self)
                            384 LOAD_ATTR               13 (signal)
                            394 LOAD_ATTR               17 (MOTION)
                            404 LOAD_METHOD             15 (connect)
                            426 LOAD_FAST                0 (self)
                            428 LOAD_ATTR               16 (_update_subsurface)
                            438 LOAD_FAST                0 (self)
                            440 KW_NAMES                 2
@@ -343,15 +356,15 @@
                   ('owner',)
                names      ('Zone', '__init__', 'parent', 'surface', 'subsurface', 'rect', 'topleft', 'size', '_surface', 'ValueError', 'auto_rect', 'contains', 'PermissionError', 'signal', 'NEW_SURFACE', 'connect', '_update_subsurface', 'MOTION')
                varnames   ('self', 'parent', 'kwargs')
                freevars   ()
                cellvars   ()
                filename   'C:\\Users\\symrb\\Documents\\dev\\python\\baopig\\baopig\\lib\\zone.py'
                name       '__init__'
-               firstlineno 32
+               firstlineno 31
                lnotab 0x0202260102017a0112014c011efe08045601
             code
                argcount  : 1
                nlocals   : 1
                stacksize : 10
                flags     : 3
                code
@@ -369,23 +382,23 @@
                   0000007419000000000000000000006a0d00000000000000007c006a0600
                   00000000000000a6010000ab010000000000000000a00e00000000000000
                   000000000000000000000000007c006a0300000000000000006a0a000000
                   0000000000a6010000ab010000000000000000a6010000ab010000000000
                   000000a6020000ab020000000000000000010059006e0477007803590077
                   01640064006400a6020000ab020000000000000000010064005300230031
                   0073047702780359007701010059000100010064005300
-                44           0 RESUME                   0
+                43           0 RESUME                   0
                
-                46           2 LOAD_GLOBAL              0 (paint_lock)
+                45           2 LOAD_GLOBAL              0 (paint_lock)
                             14 BEFORE_WITH
                             16 POP_TOP
                
-                47          18 NOP
+                46          18 NOP
                
-                48          20 LOAD_GLOBAL              3 (NULL + Widget)
+                47          20 LOAD_GLOBAL              3 (NULL + Widget)
                             32 LOAD_ATTR                2 (set_surface)
                             42 LOAD_FAST                0 (self)
                             44 LOAD_FAST                0 (self)
                             46 LOAD_ATTR                3 (parent)
                             56 LOAD_ATTR                4 (surface)
                             66 LOAD_METHOD              5 (subsurface)
                             88 LOAD_FAST                0 (self)
@@ -399,66 +412,66 @@
                            140 CALL                     1
                            150 PRECALL                  2
                            154 CALL                     2
                            164 POP_TOP
                            166 JUMP_FORWARD           156 (to 480)
                        >>  168 PUSH_EXC_INFO
                
-                49         170 LOAD_GLOBAL             18 (ValueError)
+                48         170 LOAD_GLOBAL             18 (ValueError)
                            182 CHECK_EXC_MATCH
                            184 POP_JUMP_FORWARD_IF_FALSE   143 (to 472)
                            186 POP_TOP
                
-                50         188 LOAD_FAST                0 (self)
+                49         188 LOAD_FAST                0 (self)
                            190 LOAD_ATTR                3 (parent)
                            200 LOAD_ATTR               10 (auto_rect)
                            210 LOAD_METHOD             11 (contains)
                            232 LOAD_FAST                0 (self)
                            234 LOAD_ATTR                6 (rect)
                            244 PRECALL                  1
                            248 CALL                     1
                            258 POP_JUMP_FORWARD_IF_FALSE     2 (to 264)
                            260 LOAD_ASSERTION_ERROR
                            262 RAISE_VARARGS            1
                
-                51     >>  264 LOAD_GLOBAL              3 (NULL + Widget)
+                50     >>  264 LOAD_GLOBAL              3 (NULL + Widget)
                            276 LOAD_ATTR                2 (set_surface)
                            286 LOAD_FAST                0 (self)
                            288 LOAD_FAST                0 (self)
                            290 LOAD_ATTR                3 (parent)
                            300 LOAD_ATTR                4 (surface)
                            310 LOAD_METHOD              5 (subsurface)
                
-                52         332 LOAD_GLOBAL             25 (NULL + pygame)
+                51         332 LOAD_GLOBAL             25 (NULL + pygame)
                            344 LOAD_ATTR               13 (Rect)
                            354 LOAD_FAST                0 (self)
                            356 LOAD_ATTR                6 (rect)
                            366 PRECALL                  1
                            370 CALL                     1
                            380 LOAD_METHOD             14 (clip)
                            402 LOAD_FAST                0 (self)
                            404 LOAD_ATTR                3 (parent)
                            414 LOAD_ATTR               10 (auto_rect)
                            424 PRECALL                  1
                            428 CALL                     1
                
-                51         438 PRECALL                  1
+                50         438 PRECALL                  1
                            442 CALL                     1
                            452 PRECALL                  2
                            456 CALL                     2
                            466 POP_TOP
                            468 POP_EXCEPT
                            470 JUMP_FORWARD             4 (to 480)
                
-                49     >>  472 RERAISE                  0
+                48     >>  472 RERAISE                  0
                        >>  474 COPY                     3
                            476 POP_EXCEPT
                            478 RERAISE                  1
                
-                46     >>  480 LOAD_CONST               0 (None)
+                45     >>  480 LOAD_CONST               0 (None)
                            482 LOAD_CONST               0 (None)
                            484 LOAD_CONST               0 (None)
                            486 PRECALL                  2
                            490 CALL                     2
                            500 POP_TOP
                            502 LOAD_CONST               0 (None)
                            504 RETURN_VALUE
@@ -489,15 +502,15 @@
                   None
                names      ('paint_lock', 'Widget', 'set_surface', 'parent', 'surface', 'subsurface', 'rect', 'topleft', 'size', 'ValueError', 'auto_rect', 'contains', 'pygame', 'Rect', 'clip')
                varnames   ('self',)
                freevars   ()
                cellvars   ()
                filename   'C:\\Users\\symrb\\Documents\\dev\\python\\baopig\\baopig\\lib\\zone.py'
                name       '_update_subsurface'
-               firstlineno 44
+               firstlineno 43
                lnotab 0x020210010201960112014c0144016aff22fe08fd
             code
                argcount  : 1
                nlocals   : 1
                stacksize : 6
                flags     : 3
                code
@@ -511,55 +524,55 @@
                   0000007c006a0300000000000000006a0a00000000000000007c006a0800
                   000000000000006a0a00000000000000007a0000007c006a030000000000
                   0000006a0b00000000000000007c006a0800000000000000006a0b000000
                   00000000007a00000066027c006a0800000000000000006a0c0000000000
                   0000007a000000ac02a6010000ab01000000000000000001006401640164
                   01a6020000ab020000000000000000010064015300230031007304770278
                   0359007701010059000100010064015300
-                54           0 RESUME                   0
+                53           0 RESUME                   0
                
-                57           2 LOAD_FAST                0 (self)
+                56           2 LOAD_FAST                0 (self)
                              4 LOAD_ATTR                0 (is_hidden)
                             14 POP_JUMP_FORWARD_IF_FALSE     2 (to 20)
                
-                58          16 LOAD_CONST               1 (None)
+                57          16 LOAD_CONST               1 (None)
                             18 RETURN_VALUE
                
-                60     >>   20 LOAD_GLOBAL              2 (paint_lock)
+                59     >>   20 LOAD_GLOBAL              2 (paint_lock)
                             32 BEFORE_WITH
                             34 POP_TOP
                
-                62          36 LOAD_FAST                0 (self)
+                61          36 LOAD_FAST                0 (self)
                             38 LOAD_METHOD              2 (_flip_without_update)
                             60 PRECALL                  0
                             64 CALL                     0
                             74 POP_TOP
                
-                65          76 LOAD_FAST                0 (self)
+                64          76 LOAD_FAST                0 (self)
                             78 LOAD_ATTR                3 (parent)
                             88 LOAD_FAST                0 (self)
                             90 LOAD_ATTR                4 (scene)
                            100 IS_OP                    0
                            102 POP_JUMP_FORWARD_IF_FALSE    37 (to 178)
                
-                66         104 LOAD_GLOBAL             10 (pygame)
+                65         104 LOAD_GLOBAL             10 (pygame)
                            116 LOAD_ATTR                6 (display)
                            126 LOAD_METHOD              7 (update)
                            148 LOAD_FAST                0 (self)
                            150 LOAD_ATTR                8 (hitbox)
                            160 PRECALL                  1
                            164 CALL                     1
                            174 POP_TOP
                            176 JUMP_FORWARD            88 (to 354)
                
-                68     >>  178 LOAD_FAST                0 (self)
+                67     >>  178 LOAD_FAST                0 (self)
                            180 LOAD_ATTR                3 (parent)
                            190 LOAD_METHOD              9 (send_display_request)
                
-                69         212 LOAD_FAST                0 (self)
+                68         212 LOAD_FAST                0 (self)
                            214 LOAD_ATTR                3 (parent)
                            224 LOAD_ATTR               10 (left)
                            234 LOAD_FAST                0 (self)
                            236 LOAD_ATTR                8 (hitbox)
                            246 LOAD_ATTR               10 (left)
                            256 BINARY_OP                0 (+)
                            260 LOAD_FAST                0 (self)
@@ -571,20 +584,20 @@
                            304 BINARY_OP                0 (+)
                            308 BUILD_TUPLE              2
                            310 LOAD_FAST                0 (self)
                            312 LOAD_ATTR                8 (hitbox)
                            322 LOAD_ATTR               12 (size)
                            332 BINARY_OP                0 (+)
                
-                68         336 KW_NAMES                 2
+                67         336 KW_NAMES                 2
                            338 PRECALL                  1
                            342 CALL                     1
                            352 POP_TOP
                
-                60     >>  354 LOAD_CONST               1 (None)
+                59     >>  354 LOAD_CONST               1 (None)
                            356 LOAD_CONST               1 (None)
                            358 LOAD_CONST               1 (None)
                            360 PRECALL                  2
                            364 CALL                     2
                            374 POP_TOP
                            376 LOAD_CONST               1 (None)
                            378 RETURN_VALUE
@@ -611,15 +624,15 @@
                   ('rect',)
                names      ('is_hidden', 'paint_lock', '_flip_without_update', 'parent', 'scene', 'pygame', 'display', 'update', 'hitbox', 'send_display_request', 'left', 'top', 'size')
                varnames   ('self',)
                freevars   ()
                cellvars   ()
                filename   'C:\\Users\\symrb\\Documents\\dev\\python\\baopig\\baopig\\lib\\zone.py'
                name       '_flip'
-               firstlineno 54
+               firstlineno 53
                lnotab 0x02030e010402100228031c014a0222017cff12f8
             code
                argcount  : 2
                nlocals   : 2
                stacksize : 8
                flags     : 3
                code
@@ -632,23 +645,23 @@
                   006a090000000000000000a00a0000000000000000000000000000000000
                   0000007c006a060000000000000000a6010000ab01000000000000000072
                   024a0082017417000000000000000000006401a6010000ab010000000000
                   000000820177007803590077017c00a00c00000000000000000000000000
                   00000000000000a6000000ab0000000000000000000100640064006400a6
                   020000ab0200000000000000000100640053002300310073047702780359
                   007701010059000100010064005300
-                72           0 RESUME                   0
+                71           0 RESUME                   0
                
-                74           2 LOAD_GLOBAL              0 (paint_lock)
+                73           2 LOAD_GLOBAL              0 (paint_lock)
                             14 BEFORE_WITH
                             16 POP_TOP
                
-                75          18 NOP
+                74          18 NOP
                
-                76          20 LOAD_GLOBAL              3 (NULL + Widget)
+                75          20 LOAD_GLOBAL              3 (NULL + Widget)
                             32 LOAD_ATTR                2 (set_surface)
                             42 LOAD_FAST                0 (self)
                             44 LOAD_FAST                0 (self)
                             46 LOAD_ATTR                3 (parent)
                             56 LOAD_ATTR                4 (surface)
                             66 LOAD_METHOD              5 (subsurface)
                             88 LOAD_FAST                0 (self)
@@ -660,49 +673,49 @@
                            120 CALL                     1
                            130 PRECALL                  2
                            134 CALL                     2
                            144 POP_TOP
                            146 JUMP_FORWARD            67 (to 282)
                        >>  148 PUSH_EXC_INFO
                
-                77         150 LOAD_GLOBAL             16 (ValueError)
+                76         150 LOAD_GLOBAL             16 (ValueError)
                            162 CHECK_EXC_MATCH
                            164 POP_JUMP_FORWARD_IF_FALSE    54 (to 274)
                            166 POP_TOP
                
-                78         168 LOAD_FAST                0 (self)
+                77         168 LOAD_FAST                0 (self)
                            170 LOAD_ATTR                3 (parent)
                            180 LOAD_ATTR                9 (auto_rect)
                            190 LOAD_METHOD             10 (contains)
                            212 LOAD_FAST                0 (self)
                            214 LOAD_ATTR                6 (rect)
                            224 PRECALL                  1
                            228 CALL                     1
                            238 POP_JUMP_FORWARD_IF_FALSE     2 (to 244)
                            240 LOAD_ASSERTION_ERROR
                            242 RAISE_VARARGS            1
                
-                79     >>  244 LOAD_GLOBAL             23 (NULL + PermissionError)
+                78     >>  244 LOAD_GLOBAL             23 (NULL + PermissionError)
                            256 LOAD_CONST               1 ('A SubZone must fit inside its parent')
                            258 PRECALL                  1
                            262 CALL                     1
                            272 RAISE_VARARGS            1
                
-                77     >>  274 RERAISE                  0
+                76     >>  274 RERAISE                  0
                        >>  276 COPY                     3
                            278 POP_EXCEPT
                            280 RERAISE                  1
                
-                80     >>  282 LOAD_FAST                0 (self)
+                79     >>  282 LOAD_FAST                0 (self)
                            284 LOAD_METHOD             12 (_flip_without_update)
                            306 PRECALL                  0
                            310 CALL                     0
                            320 POP_TOP
                
-                74         322 LOAD_CONST               0 (None)
+                73         322 LOAD_CONST               0 (None)
                            324 LOAD_CONST               0 (None)
                            326 LOAD_CONST               0 (None)
                            328 PRECALL                  2
                            332 CALL                     2
                            342 POP_TOP
                            344 LOAD_CONST               0 (None)
                            346 RETURN_VALUE
@@ -732,15 +745,15 @@
                   'A SubZone must fit inside its parent'
                names      ('paint_lock', 'Widget', 'set_surface', 'parent', 'surface', 'subsurface', 'rect', 'topleft', 'ValueError', 'auto_rect', 'contains', 'PermissionError', '_flip_without_update')
                varnames   ('self', 'asked_size')
                freevars   ()
                cellvars   ()
                filename   'C:\\Users\\symrb\\Documents\\dev\\python\\baopig\\baopig\\lib\\zone.py'
                name       '_update_surface_from_resize'
-               firstlineno 72
+               firstlineno 71
                lnotab 0x020210010201820112014c011efe080328fa
             code
                argcount  : 2
                nlocals   : 2
                stacksize : 6
                flags     : 3
                code
@@ -750,17 +763,17 @@
                   000000000000007c0164036404850219000000000000000000a6010000ab
                   0100000000000000007a0000007d017c006a0400000000000000007c006a
                   05000000000000000075007221740c000000000000000000006a07000000
                   0000000000a00800000000000000000000000000000000000000007c01a6
                   010000ab0100000000000000000100640453007c006a0400000000000000
                   00a00900000000000000000000000000000000000000007c01a6010000ab
                   010000000000000000010064045300
-                82           0 RESUME                   0
+                81           0 RESUME                   0
                
-                85           2 LOAD_FAST                0 (self)
+                84           2 LOAD_FAST                0 (self)
                              4 LOAD_ATTR                0 (rect)
                             14 LOAD_ATTR                1 (left)
                             24 LOAD_FAST                1 (rect)
                             26 LOAD_CONST               1 (0)
                             28 BINARY_SUBSCR
                             38 BINARY_OP                0 (+)
                             42 LOAD_FAST                0 (self)
@@ -778,32 +791,32 @@
                            102 BUILD_SLICE              2
                            104 BINARY_SUBSCR
                            114 PRECALL                  1
                            118 CALL                     1
                            128 BINARY_OP                0 (+)
                            132 STORE_FAST               1 (rect)
                
-                88         134 LOAD_FAST                0 (self)
+                87         134 LOAD_FAST                0 (self)
                            136 LOAD_ATTR                4 (parent)
                            146 LOAD_FAST                0 (self)
                            148 LOAD_ATTR                5 (scene)
                            158 IS_OP                    0
                            160 POP_JUMP_FORWARD_IF_FALSE    33 (to 228)
                
-                89         162 LOAD_GLOBAL             12 (pygame)
+                88         162 LOAD_GLOBAL             12 (pygame)
                            174 LOAD_ATTR                7 (display)
                            184 LOAD_METHOD              8 (update)
                            206 LOAD_FAST                1 (rect)
                            208 PRECALL                  1
                            212 CALL                     1
                            222 POP_TOP
                            224 LOAD_CONST               4 (None)
                            226 RETURN_VALUE
                
-                91     >>  228 LOAD_FAST                0 (self)
+                90     >>  228 LOAD_FAST                0 (self)
                            230 LOAD_ATTR                4 (parent)
                            240 LOAD_METHOD              9 (_warn_parent)
                            262 LOAD_FAST                1 (rect)
                            264 PRECALL                  1
                            268 CALL                     1
                            278 POP_TOP
                            280 LOAD_CONST               4 (None)
@@ -816,27 +829,27 @@
                   None
                names      ('rect', 'left', 'top', 'tuple', 'parent', 'scene', 'pygame', 'display', 'update', '_warn_parent')
                varnames   ('self', 'rect')
                freevars   ()
                cellvars   ()
                filename   'C:\\Users\\symrb\\Documents\\dev\\python\\baopig\\baopig\\lib\\zone.py'
                name       '_warn_parent'
-               firstlineno 82
+               firstlineno 81
                lnotab 0x020384031c014202
             None
          names      ('__name__', '__module__', '__qualname__', '__doc__', '__init__', '_update_subsurface', '_flip', '_update_surface_from_resize', '_warn_parent')
          varnames   ()
          freevars   ()
          cellvars   ()
          filename   'C:\\Users\\symrb\\Documents\\dev\\python\\baopig\\baopig\\lib\\zone.py'
          name       'SubZone'
-         firstlineno 28
+         firstlineno 27
          lnotab 0x0a020402060c060a0612060a
       'SubZone'
-   names      ('pygame', 'baopig.lib', 'Container', 'paint_lock', 'Widget', 'Zone', 'SubZone')
+   names      ('pygame', 'utilities', 'paint_lock', 'widget', 'Widget', 'container', 'Container', 'Zone', 'SubZone')
    varnames   ()
    freevars   ()
    cellvars   ()
    filename   'C:\\Users\\symrb\\Documents\\dev\\python\\baopig\\baopig\\lib\\zone.py'
    name       '<module>'
    firstlineno 1
-   lnotab 0x00ff0203080114031c15
+   lnotab 0x00ff020108010c010c010c031c14
```

## baopig/version/version.py

```diff
@@ -16,12 +16,12 @@
         return '{}.{}.{}'.format(*self) if len(self) == 3 else '{}.{}.{} - {}'.format(*self)
 
     major = property(lambda self: self[0])
     minor = property(lambda self: self[1])
     patch = property(lambda self: self[2])
 
 
-version = BaopigVersion(0, 20, 4)
+version = BaopigVersion(0, 20, 5)
 
 if __name__ == "__main__":
     # TODO : try to access baopig.version without creating application, threads...
     print("Hello, this is baopig version", version)
```

## baopig/version/__pycache__/version.cpython-311.pyc

### Python bytecode

```diff
@@ -1,9 +1,9 @@
 magic:    0xa70d0d0a
-moddate:  0xf2eb4364 (Sat Apr 22 14:15:14 2023 UTC)
+moddate:  0x03f14364 (Sat Apr 22 14:36:51 2023 UTC)
 files sz: 931
 code
    argcount  : 0
    nlocals   : 0
    stacksize : 5
    flags     : 0
    code
@@ -11,27 +11,27 @@
       0102006501640264036404a6030000ab0300000000000000005a02650364
       056b0200000000720e0200650464066502a6020000ab0200000000000000
       0001006407530064075300
      0           0 RESUME                   0
    
      3           2 PUSH_NULL
                  4 LOAD_BUILD_CLASS
-                 6 LOAD_CONST               0 (<code object BaopigVersion, file "C:\Users\symrb\Documents\dev\python\baopig\.\baopig\version\version.py", line 3>)
+                 6 LOAD_CONST               0 (<code object BaopigVersion, file "C:\Users\symrb\Documents\dev\python\baopig\baopig\version\version.py", line 3>)
                  8 MAKE_FUNCTION            0
                 10 LOAD_CONST               1 ('BaopigVersion')
                 12 LOAD_NAME                0 (tuple)
                 14 PRECALL                  3
                 18 CALL                     3
                 28 STORE_NAME               1 (BaopigVersion)
    
     23          30 PUSH_NULL
                 32 LOAD_NAME                1 (BaopigVersion)
                 34 LOAD_CONST               2 (0)
                 36 LOAD_CONST               3 (20)
-                38 LOAD_CONST               4 (4)
+                38 LOAD_CONST               4 (5)
                 40 PRECALL                  3
                 44 CALL                     3
                 54 STORE_NAME               2 (version)
    
     25          56 LOAD_NAME                3 (__name__)
                 58 LOAD_CONST               5 ('__main__')
                 60 COMPARE_OP               2 (==)
@@ -72,45 +72,45 @@
            5          14 LOAD_CONST               2 (())
                       16 STORE_NAME               4 (__slots__)
          
            6          18 LOAD_CONST               3 (('major', 'minor', 'patch', 'backup'))
                       20 STORE_NAME               5 (fields)
          
            8          22 LOAD_CONST              11 ((None,))
-                      24 LOAD_CONST               5 (<code object __new__, file "C:\Users\symrb\Documents\dev\python\baopig\.\baopig\version\version.py", line 8>)
+                      24 LOAD_CONST               5 (<code object __new__, file "C:\Users\symrb\Documents\dev\python\baopig\baopig\version\version.py", line 8>)
                       26 MAKE_FUNCTION            1 (defaults)
                       28 STORE_NAME               6 (__new__)
          
-          11          30 LOAD_CONST               6 (<code object __repr__, file "C:\Users\symrb\Documents\dev\python\baopig\.\baopig\version\version.py", line 11>)
+          11          30 LOAD_CONST               6 (<code object __repr__, file "C:\Users\symrb\Documents\dev\python\baopig\baopig\version\version.py", line 11>)
                       32 MAKE_FUNCTION            0
                       34 STORE_NAME               7 (__repr__)
          
-          15          36 LOAD_CONST               7 (<code object __str__, file "C:\Users\symrb\Documents\dev\python\baopig\.\baopig\version\version.py", line 15>)
+          15          36 LOAD_CONST               7 (<code object __str__, file "C:\Users\symrb\Documents\dev\python\baopig\baopig\version\version.py", line 15>)
                       38 MAKE_FUNCTION            0
                       40 STORE_NAME               8 (__str__)
          
           18          42 PUSH_NULL
                       44 LOAD_NAME                9 (property)
-                      46 LOAD_CONST               8 (<code object <lambda>, file "C:\Users\symrb\Documents\dev\python\baopig\.\baopig\version\version.py", line 18>)
+                      46 LOAD_CONST               8 (<code object <lambda>, file "C:\Users\symrb\Documents\dev\python\baopig\baopig\version\version.py", line 18>)
                       48 MAKE_FUNCTION            0
                       50 PRECALL                  1
                       54 CALL                     1
                       64 STORE_NAME              10 (major)
          
           19          66 PUSH_NULL
                       68 LOAD_NAME                9 (property)
-                      70 LOAD_CONST               9 (<code object <lambda>, file "C:\Users\symrb\Documents\dev\python\baopig\.\baopig\version\version.py", line 19>)
+                      70 LOAD_CONST               9 (<code object <lambda>, file "C:\Users\symrb\Documents\dev\python\baopig\baopig\version\version.py", line 19>)
                       72 MAKE_FUNCTION            0
                       74 PRECALL                  1
                       78 CALL                     1
                       88 STORE_NAME              11 (minor)
          
           20          90 PUSH_NULL
                       92 LOAD_NAME                9 (property)
-                      94 LOAD_CONST              10 (<code object <lambda>, file "C:\Users\symrb\Documents\dev\python\baopig\.\baopig\version\version.py", line 20>)
+                      94 LOAD_CONST              10 (<code object <lambda>, file "C:\Users\symrb\Documents\dev\python\baopig\baopig\version\version.py", line 20>)
                       96 MAKE_FUNCTION            0
                       98 PRECALL                  1
                      102 CALL                     1
                      112 STORE_NAME              12 (patch)
                      114 LOAD_CONST               4 (None)
                      116 RETURN_VALUE
          consts
@@ -154,15 +154,15 @@
                consts
                   None
                   ()
                names      ('tuple', '__new__')
                varnames   ('cls', 'major', 'minor', 'patch', 'backup')
                freevars   ()
                cellvars   ()
-               filename   'C:\\Users\\symrb\\Documents\\dev\\python\\baopig\\.\\baopig\\version\\version.py'
+               filename   'C:\\Users\\symrb\\Documents\\dev\\python\\baopig\\baopig\\version\\version.py'
                name       '__new__'
                firstlineno 8
                lnotab 0x0201
             code
                argcount  : 1
                nlocals   : 2
                stacksize : 6
@@ -173,15 +173,15 @@
                   0000007d016402a002000000000000000000000000000000000000000074
                   07000000000000000000007c006a0400000000000000006a050000000000
                   000000a6010000ab0100000000000000006403a006000000000000000000
                   00000000000000000000007c01a6010000ab010000000000000000a60200
                   00ab0200000000000000005300
                 11           0 RESUME                   0
                
-                12           2 LOAD_CONST               1 (<code object <genexpr>, file "C:\Users\symrb\Documents\dev\python\baopig\.\baopig\version\version.py", line 12>)
+                12           2 LOAD_CONST               1 (<code object <genexpr>, file "C:\Users\symrb\Documents\dev\python\baopig\baopig\version\version.py", line 12>)
                              4 MAKE_FUNCTION            0
                              6 LOAD_GLOBAL              1 (NULL + zip)
                             18 LOAD_FAST                0 (self)
                             20 LOAD_ATTR                1 (fields)
                             30 LOAD_FAST                0 (self)
                             32 PRECALL                  2
                             36 CALL                     2
@@ -240,25 +240,25 @@
                      consts
                         '{}={}'
                         None
                      names      ('format',)
                      varnames   ('.0', 'fld', 'val')
                      freevars   ()
                      cellvars   ()
-                     filename   'C:\\Users\\symrb\\Documents\\dev\\python\\baopig\\.\\baopig\\version\\version.py'
+                     filename   'C:\\Users\\symrb\\Documents\\dev\\python\\baopig\\baopig\\version\\version.py'
                      name       '<genexpr>'
                      firstlineno 12
                      lnotab 0x
                   '{}({})'
                   ', '
                names      ('zip', 'fields', 'format', 'str', '__class__', '__name__', 'join')
                varnames   ('self', 'fields')
                freevars   ()
                cellvars   ()
-               filename   'C:\\Users\\symrb\\Documents\\dev\\python\\baopig\\.\\baopig\\version\\version.py'
+               filename   'C:\\Users\\symrb\\Documents\\dev\\python\\baopig\\baopig\\version\\version.py'
                name       '__repr__'
                firstlineno 11
                lnotab 0x02013e01
             code
                argcount  : 1
                nlocals   : 1
                stacksize : 3
@@ -293,15 +293,15 @@
                   3
                   '{}.{}.{}'
                   '{}.{}.{} - {}'
                names      ('len', 'format')
                varnames   ('self',)
                freevars   ()
                cellvars   ()
-               filename   'C:\\Users\\symrb\\Documents\\dev\\python\\baopig\\.\\baopig\\version\\version.py'
+               filename   'C:\\Users\\symrb\\Documents\\dev\\python\\baopig\\baopig\\version\\version.py'
                name       '__str__'
                firstlineno 15
                lnotab 0x0201
             code
                argcount  : 1
                nlocals   : 1
                stacksize : 2
@@ -315,15 +315,15 @@
                consts
                   None
                   0
                names      ()
                varnames   ('self',)
                freevars   ()
                cellvars   ()
-               filename   'C:\\Users\\symrb\\Documents\\dev\\python\\baopig\\.\\baopig\\version\\version.py'
+               filename   'C:\\Users\\symrb\\Documents\\dev\\python\\baopig\\baopig\\version\\version.py'
                name       '<lambda>'
                firstlineno 18
                lnotab 0x
             code
                argcount  : 1
                nlocals   : 1
                stacksize : 2
@@ -337,15 +337,15 @@
                consts
                   None
                   1
                names      ()
                varnames   ('self',)
                freevars   ()
                cellvars   ()
-               filename   'C:\\Users\\symrb\\Documents\\dev\\python\\baopig\\.\\baopig\\version\\version.py'
+               filename   'C:\\Users\\symrb\\Documents\\dev\\python\\baopig\\baopig\\version\\version.py'
                name       '<lambda>'
                firstlineno 19
                lnotab 0x
             code
                argcount  : 1
                nlocals   : 1
                stacksize : 2
@@ -359,35 +359,35 @@
                consts
                   None
                   2
                names      ()
                varnames   ('self',)
                freevars   ()
                cellvars   ()
-               filename   'C:\\Users\\symrb\\Documents\\dev\\python\\baopig\\.\\baopig\\version\\version.py'
+               filename   'C:\\Users\\symrb\\Documents\\dev\\python\\baopig\\baopig\\version\\version.py'
                name       '<lambda>'
                firstlineno 20
                lnotab 0x
             (None,)
          names      ('__name__', '__module__', '__qualname__', '__doc__', '__slots__', 'fields', '__new__', '__repr__', '__str__', 'property', 'major', 'minor', 'patch')
          varnames   ()
          freevars   ()
          cellvars   ()
-         filename   'C:\\Users\\symrb\\Documents\\dev\\python\\baopig\\.\\baopig\\version\\version.py'
+         filename   'C:\\Users\\symrb\\Documents\\dev\\python\\baopig\\baopig\\version\\version.py'
          name       'BaopigVersion'
          firstlineno 3
          lnotab 0x0a0104010401040208030604060318011801
       'BaopigVersion'
       0
       20
-      4
+      5
       '__main__'
       'Hello, this is baopig version'
       None
    names      ('tuple', 'BaopigVersion', 'version', '__name__', 'print')
    varnames   ()
    freevars   ()
    cellvars   ()
-   filename   'C:\\Users\\symrb\\Documents\\dev\\python\\baopig\\.\\baopig\\version\\version.py'
+   filename   'C:\\Users\\symrb\\Documents\\dev\\python\\baopig\\baopig\\version\\version.py'
    name       '<module>'
    firstlineno 1
    lnotab 0x00ff02031c141a020c021cfe
```

## baopig/widgets/__pycache__/text.cpython-311.pyc

### Python bytecode

```diff
@@ -1,9 +1,9 @@
 magic:    0xa70d0d0a
-moddate:  0xa2b3d962 (Thu Jul 21 20:14:26 2022 UTC)
+moddate:  0xceef4364 (Sat Apr 22 14:31:42 2023 UTC)
 files sz: 29570
 code
    argcount  : 0
    nlocals   : 0
    stacksize : 6
    flags     : 0
    code
```

## Comparing `baopig-0.20.4.dist-info/LICENSE` & `baopig-0.20.5.dist-info/LICENSE`

 * *Files identical despite different names*

## Comparing `baopig-0.20.4.dist-info/METADATA` & `baopig-0.20.5.dist-info/METADATA`

 * *Files 1% similar despite different names*

```diff
@@ -1,10 +1,10 @@
 Metadata-Version: 2.1
 Name: baopig
-Version: 0.20.4
+Version: 0.20.5
 Summary: pygame gui
 Home-page: https://baopig.readthedocs.io/
 Author: Symeon Rougevin-Baville
 Author-email: dev.chresyr@gmail.com
 License: MIT
 Classifier: Intended Audience :: Developers
 Classifier: License :: OSI Approved :: MIT License
```

## Comparing `baopig-0.20.4.dist-info/RECORD` & `baopig-0.20.5.dist-info/RECORD`

 * *Files 1% similar despite different names*

```diff
@@ -1,13 +1,13 @@
-baopig/__init__.py,sha256=t2uh4SHnY_69CGZ3n7kbaT_5-INsSwjzSxolxvrNN7M,608
+baopig/__init__.py,sha256=ZpXpRQEpatP62k6xrR7yS9TAdmWUJqDVrHt_R62PFF4,682
 baopig/communicative.py,sha256=4vT8P_P_2ZNt8AwsqaWffWy4o6vghJ3urrj9gkIICWA,3643
 baopig/documentation.py,sha256=YZVtnTOfgH4L7u8AfVIywaJE755bpDFpsW5jkrek5cQ,16525
 baopig/lines_counter.py,sha256=UcBTJwBQxJ_mHle-1w1h9B_cVs5LYXvdQyTk047jyWo,548
 baopig/__pycache__/__init__.cpython-310.pyc,sha256=hJjODRmGfzKR7QEnPU_LegS6ZqmFkbecj_k0yV70z2U,831
-baopig/__pycache__/__init__.cpython-311.pyc,sha256=3lGWeIg9G2jXThKNSfCNDuOPMuGkq9HJgOpQ0pjHIyc,1151
+baopig/__pycache__/__init__.cpython-311.pyc,sha256=ZI6Te9ncRCabghVa5liVrTMExT0bzbu1-IoWhwGfVEE,1308
 baopig/__pycache__/__init__.cpython-37.pyc,sha256=1ansnWF-3dACEQ92gACbcpaLgQLPbT4KdtPStD8dT78,866
 baopig/__pycache__/communicative.cpython-310.pyc,sha256=0zcxiochjDAdhLxSH-fRWtstgQ6MQBwzRjbcmWoZoTw,4334
 baopig/__pycache__/communicative.cpython-311.pyc,sha256=YAyp10vbL9_EJXkYcu1dxomnEFHEMMub3Ii5VWwIAeI,6953
 baopig/__pycache__/communicative.cpython-37.pyc,sha256=FsfYl8qXzIBB4fISd7UOEGDVNHGX70TVqgCnNCmx5Ac,6055
 baopig/__pycache__/documentation.cpython-310.pyc,sha256=WE3Z-59QnYQ80kBx5PEehT5vFnITiS31j6AxRRxTx1s,16336
 baopig/__pycache__/documentation.cpython-311.pyc,sha256=d1Ssq1w_CvLwyWzShdSe68VOXl75pyvFIsGySKLJ0UM,18292
 baopig/font/__init__.py,sha256=HMVvCTv2PMb_arg0v7rs7IaRohldwVXZYFaNGwCwUI8,24
@@ -88,31 +88,31 @@
 baopig/io/__pycache__/keyboard.cpython-37.pyc,sha256=DLpaiZhujZ9G_DtjRX6YfryVep-5ccc5Hk7ImMK-Dks,7189
 baopig/io/__pycache__/logging.cpython-310.pyc,sha256=79S-YGeUaXu81fCAZr4UUA8dy8-okGNl1ycB30crxtM,3416
 baopig/io/__pycache__/logging.cpython-311.pyc,sha256=INAkhL5VZWsMAsU_zOcy2niifIlvkBHvozwtgHi8ldA,6314
 baopig/io/__pycache__/logging.cpython-37.pyc,sha256=0apV2UPLFBH1OkNU7kWYnAY-2tW3rShDpRSFlDj6UtQ,3376
 baopig/io/__pycache__/mouse.cpython-310.pyc,sha256=OMkB7t88yMt4ku6J0VXpRYsknY6JslUEi5unWG7GhF0,7956
 baopig/io/__pycache__/mouse.cpython-311.pyc,sha256=gP9aEEbscsyzy7BA2G7V19hbx5ke86uhU8tAxbKg99U,15307
 baopig/io/__pycache__/mouse.cpython-37.pyc,sha256=6QybLrsrImVBpnh9YCb1dapDUNhz4y9Lf_4LvfJrhQA,9450
-baopig/lib/__init__.py,sha256=lPf5jSg4gxGecm44nfUOomrdJipEu2C8UHX5jGZ7GLc,596
+baopig/lib/__init__.py,sha256=z9i029KfyWBTem8AxGfkypPMO6aak1KucUI6ygY0iuk,623
 baopig/lib/application.py,sha256=prGTgjq4OJ1H2JcAx42Gnz_QZ-f8i7zaqW-mlTtp29A,14075
 baopig/lib/container.py,sha256=VwHW6C6p4RohLPHH1YD_OdIe7sukT1_tZa4vCz-j3Es,16468
 baopig/lib/gridlayer.py,sha256=A5YqZtz56i-9AGJjIU-1ukhbRqvTjzfa86pIxu5u04Q,18715
 baopig/lib/imagewidget.py,sha256=QKfSJo4R3fsYgNgnenGYlsBnX8JvxiiaapYhLmmzCfk,2502
 baopig/lib/layer.py,sha256=mx_gcQjZ_4uFQu9w6k8M55zYIJVPIiV8SKSmWcM9AQY,10338
 baopig/lib/layersmanager.py,sha256=qmZxVn5_0Sj1OJ8JmDJfDi7FM4ydNA4kcwqCoHHyxcQ,4172
 baopig/lib/scene.py,sha256=uYybMC2uNh-6cXlQd3yP0SsqFTCEsUWJpK0V6AHEFLM,7037
 baopig/lib/selections.py,sha256=5orInDZ4vWj7LLodlqgyfhXqtwvwLxcoauZNTfoT6s0,10889
 baopig/lib/shapes.py,sha256=wMVdMoWu6vQ1hxJ2HH9JO9tHBWemNeBLbAbFGchrbeQ,7360
 baopig/lib/style.py,sha256=keDYALWSKO2D3wdPDOmgQMwIb0tpNYboCfMs49kNhfU,16552
 baopig/lib/utilities.py,sha256=t6hq2G8BVL4e2ml9YkrmiFT1MkNaZc2ioGhJ9_BzpAI,4162
 baopig/lib/widget.py,sha256=rCdIzMaRrQXQh_w-C3-crC-iXt_uhcd2sTKlvoDafxk,37125
 baopig/lib/widget_supers.py,sha256=HGtkyeeG07N0Ux0hx-dD4WZJy3zHV8pp0eRqNfLd23A,9919
-baopig/lib/zone.py,sha256=i3m_-5JbdRkQ_zOwHUoCfZv5TeBMUC_5yIdyfgNV2j8,3300
+baopig/lib/zone.py,sha256=5HOl1noG_3VfskX033dj-8HRnuYsDqWXDykeGdCuR4Y,3337
 baopig/lib/__pycache__/__init__.cpython-310.pyc,sha256=bwkBpR3K5cQLEtjcxWvn7Eo4Gpq8fwgofGC1Nz2bCAo,1022
-baopig/lib/__pycache__/__init__.cpython-311.pyc,sha256=Rt6FQVsfBsAfRMsokRy8Rhqy3n-e7t7Zr09Kc7LI4H0,1418
+baopig/lib/__pycache__/__init__.cpython-311.pyc,sha256=a79p9rlRFfeJbB626y8IrPNozfY_nM1POK7UbWD-rec,1388
 baopig/lib/__pycache__/__init__.cpython-37.pyc,sha256=UFHkDz3gqx-YZr_AgX4fU5o2v0qmcYNRDS8hQvvDwKw,996
 baopig/lib/__pycache__/application.cpython-310.pyc,sha256=mUYtq9moPq3csEQi--t_mRBW-MbUiBXA7sbG62hW8Nk,10025
 baopig/lib/__pycache__/application.cpython-311.pyc,sha256=joewM1eHUVcYq6vdkknkMjGNMIzQOI4MLY8ipuiYGa8,19363
 baopig/lib/__pycache__/application.cpython-37.pyc,sha256=FaFtKhczKjVQzmpMQ8Wa1R2FmCzx0d1s60Vds2bCMtE,11173
 baopig/lib/__pycache__/container.cpython-310.pyc,sha256=LzNkbl_-VqPBC4J93ElOqIdJ_DRWjvHE10cRQPBLwzI,13868
 baopig/lib/__pycache__/container.cpython-311.pyc,sha256=KoyYLzWiPlsefuDZUHg3dHgANU9uuxXP_GHc6GbFjXw,25435
 baopig/lib/__pycache__/container.cpython-37.pyc,sha256=RAPlBe9JL_uJwDwxMT2zl4VrJZKACWHwKt9-PJG6tTQ,17854
@@ -144,15 +144,15 @@
 baopig/lib/__pycache__/utilities.cpython-37.pyc,sha256=RBVbBPfYzj1Uzp-yYvd09e1dOQ4BsDKFDt9_o_Ok9sk,16139
 baopig/lib/__pycache__/widget.cpython-310.pyc,sha256=tczMn_oQc5MK-fizAxEZBvxgOMfVb3S1JZC5KII56LM,30683
 baopig/lib/__pycache__/widget.cpython-311.pyc,sha256=61x2zKTwxmOjClMrYoR5eKnIB7YLTGBB4psLl4k2Z6Q,57092
 baopig/lib/__pycache__/widget.cpython-37.pyc,sha256=UGGfvYZWBzLeytZm86HGJ3mxjFtaCD5brN9SlduELa0,36355
 baopig/lib/__pycache__/widget_supers.cpython-310.pyc,sha256=WGm9nZbLBU1IVNJAyCvE-yBkpTrFLFTlPudgJjdCVa4,8647
 baopig/lib/__pycache__/widget_supers.cpython-311.pyc,sha256=NVOuwFoX43B05Cq49Rz06R3Aat1TyEOd5qFi9fmDwQ4,16061
 baopig/lib/__pycache__/zone.cpython-310.pyc,sha256=scAXcJVqrQ3c-lOH7Oq38GKwYTa47c7769mICY2Wuus,3094
-baopig/lib/__pycache__/zone.cpython-311.pyc,sha256=eN3yp7eYkP9JVs46ORv3yQMF8c32AbjUjyNhmDXXMx0,6355
+baopig/lib/__pycache__/zone.cpython-311.pyc,sha256=yDHOy7I81uudFmMY0kFaDlGye5uKOkYRAImT8bO-t3k,6410
 baopig/lib/__pycache__/zone.cpython-37.pyc,sha256=M31S58SrSbqqrvHzRK6KztFemUXO8UBi-36Kriy9qAQ,3722
 baopig/prefabs/colorchooserdialog.py,sha256=FpSzWUNOS1lRiwT-7S3K-w8BDVq5FUPKAiozmO1j57Y,7489
 baopig/prefabs/debugzone.py,sha256=pWuJnPSPH7iFf-2wvULBZfnOhvJS6cfYzW6rj7HVTx8,5248
 baopig/prefabs/presentationscene.py,sha256=iZZeGOGjV-Ii4JrrrYEtpIABly3ay6G9KtHgSt2K7WU,2177
 baopig/prefabs/testerscene.py,sha256=nznLRxlND-vlBEUVhr2vC1peOTPVDsLdnVoJR7I-q4Y,4847
 baopig/prefabs/themes.py,sha256=hgzV2YdOcuIbLSB21IRKluF1Lm5FrUbik-9VM2zCaF4,1719
 baopig/prefabs/__pycache__/colorchooserdialog.cpython-310.pyc,sha256=RqGx_52i-vxsWKjHzll8PSgDK7l9yA7rYARgBPvuiQ0,7273
@@ -250,17 +250,17 @@
 baopig/unit_tests/__pycache__/ut_sleep.cpython-311.pyc,sha256=9IsK69xKVmkyAR2CbTXopWWC0Vj7SRIndg1cQfi-5Ac,13507
 baopig/unit_tests/__pycache__/ut_text.cpython-310.pyc,sha256=Izd3N6trwDF_1o0O3msWBUUDBbfjphQ7Bh9DiROS-qI,3621
 baopig/unit_tests/__pycache__/ut_text.cpython-311.pyc,sha256=YOfvIZAZSaEmcCb4qxOybmWye-89s_lEVKR4Y8G6NFI,6753
 baopig/unit_tests/__pycache__/ut_textedit.cpython-310.pyc,sha256=Kb5XYTUGs1yP69qXaFwgbLqjXqI8V5AVtfiowqy4Mwo,1830
 baopig/unit_tests/__pycache__/ut_textedit.cpython-311.pyc,sha256=QGoRJDpfOUhFxL5d55cKdltmZp-r4zreIgYHWvhBU3M,3446
 baopig/unit_tests/__pycache__/ut_theme.cpython-310.pyc,sha256=Jd822wGf32M0nTwWRCSecbXojL_-Sk-Y-jt4qNKJFDU,2043
 baopig/unit_tests/__pycache__/ut_theme.cpython-311.pyc,sha256=5uTVze6gUU95lFO99ZXU6dvGquVDL5Xe8gIQqkFUYBE,3466
-baopig/version/version.py,sha256=RRxaDsx2M9VMGh2CEKs0W03_iC9x_cS-FdJxiJDKa7E,931
+baopig/version/version.py,sha256=Fzrev2Dp7N9nDNlVDQISF1Xjy2s_JzSI7jq2SFMdl0Y,931
 baopig/version/__pycache__/version.cpython-310.pyc,sha256=Rp0XTLPGzphYoaYVQXoqP_pfEh2wLtNCsS3tVJN1Lbk,1692
-baopig/version/__pycache__/version.cpython-311.pyc,sha256=1DUdeaVxWFQH58-laGK_9UTYt4M1-aaBbU8ykWACZCI,2611
+baopig/version/__pycache__/version.cpython-311.pyc,sha256=-jWGDTydy5zfzDzHNz4G6lD8xFBa-0rYYuJZ92SlWM4,2609
 baopig/version/__pycache__/version.cpython-37.pyc,sha256=g23o3EB_00N3g1jhY4M6TwBov_bzg3MnZhZ2JPMLYHM,1642
 baopig/widgets/__init__.py,sha256=PeQrRjeytaGx2rd_C6ygb6wjiKoOQbDWtaHr9LvPtZg,767
 baopig/widgets/button.py,sha256=D7Q3wskW1gdq09Mj9EIuxYAtNbn3C9ejjnn-pN3-dFU,8232
 baopig/widgets/checkbox.py,sha256=VMsW42qIdGLCcD4KjPE3ytzqJvYs-ETzF1Y1Ku8Isfc,3102
 baopig/widgets/dialog.py,sha256=uJCa-Pr2dqaGhsHCuYIB03Dp8oaixFUmjapDfJuJRNk,5246
 baopig/widgets/entry.py,sha256=UODsZ2hPYKBY8QMPzOmiWGhTeF_p6bdsxJeRiTXRcuU,1609
 baopig/widgets/indicator.py,sha256=sEkysKLVNEQQPZgdnXd5KexBPDzUjQbKCYWT5Jiuuc8,3607
@@ -299,17 +299,17 @@
 baopig/widgets/__pycache__/progressbar.cpython-37.pyc,sha256=9hyN2De6o5KNn9NR3breaizGaH_gYv4WbTmdfMSax1A,1527
 baopig/widgets/__pycache__/scrollview.cpython-310.pyc,sha256=HOEVwrK5OR4yAliQCwughQBd3QN8PuRftyLmhe4aK7s,6846
 baopig/widgets/__pycache__/scrollview.cpython-311.pyc,sha256=2LBsip3HHAQ1OiRQyDt8AtNLLBcvFQDQXHvZpCmNCZk,13258
 baopig/widgets/__pycache__/slider.cpython-310.pyc,sha256=pWsuWyOImJCXogXDIbEotKlT8WKJHAPyLM8yswrQGqM,9558
 baopig/widgets/__pycache__/slider.cpython-311.pyc,sha256=WcJUh3ELinmz9oQqKeSY9KSOZCbFRtg4LeQHmxPnR8k,18086
 baopig/widgets/__pycache__/slider.cpython-37.pyc,sha256=NhB3ncvsXTPaRXNm43xwc2DLV23RCaN6r1swBDjzwec,8011
 baopig/widgets/__pycache__/text.cpython-310.pyc,sha256=OhRohkmN_-EC-JXQsNr-WcCoeXSeOe-YxtdFBvnxdf4,24379
-baopig/widgets/__pycache__/text.cpython-311.pyc,sha256=y08KoLK9bQFsBECor7dDImLOvTLmYv06sG-1J5V9oC0,43877
+baopig/widgets/__pycache__/text.cpython-311.pyc,sha256=CuVZVd1trFnzxhfe6EJjKhytnOexBxfWmPagrRVR8vE,43636
 baopig/widgets/__pycache__/text.cpython-37.pyc,sha256=FIM-g85PDkaLQAHpojF_M88lkFpXG2kS_fwbvCsKCyo,27867
 baopig/widgets/__pycache__/textedit.cpython-310.pyc,sha256=D7KcLsLSPxQpLyaRf_BNHd7Px_jfPJVYcIXazq8FJHs,14346
 baopig/widgets/__pycache__/textedit.cpython-311.pyc,sha256=ACqhG1VRq7Ff_87p3QWyRZlx0IO8PNPLzqlNQEwa3Y4,32458
 baopig/widgets/__pycache__/textedit.cpython-37.pyc,sha256=Cia7Ci-9PVR2oUo4ObWEX7o5v3kULv-ZiTxbuH38JSA,13078
-baopig-0.20.4.dist-info/LICENSE,sha256=G6lZz1IZuCNLDTIxvk6dJWPWwozp2altzGHlF4NWUz4,1088
-baopig-0.20.4.dist-info/METADATA,sha256=ug_SKuum0rxMLo6KeAhhJ-E5o8aJ8FLwjph_eNygO_M,866
-baopig-0.20.4.dist-info/WHEEL,sha256=pkctZYzUS4AYVn6dJ-7367OJZivF2e8RA9b_ZBjif18,92
-baopig-0.20.4.dist-info/top_level.txt,sha256=soVidPUY0es6t4CoXpPdWPTwz8Y_4-NGZYPsvyET458,7
-baopig-0.20.4.dist-info/RECORD,,
+baopig-0.20.5.dist-info/LICENSE,sha256=G6lZz1IZuCNLDTIxvk6dJWPWwozp2altzGHlF4NWUz4,1088
+baopig-0.20.5.dist-info/METADATA,sha256=eocbJGzx2kkq9nCAfBMI1bbmFJGiHpPS9FbGosP5BSk,866
+baopig-0.20.5.dist-info/WHEEL,sha256=pkctZYzUS4AYVn6dJ-7367OJZivF2e8RA9b_ZBjif18,92
+baopig-0.20.5.dist-info/top_level.txt,sha256=soVidPUY0es6t4CoXpPdWPTwz8Y_4-NGZYPsvyET458,7
+baopig-0.20.5.dist-info/RECORD,,
```

